Workbook

Sheet ENERO
Q1: MES
B2: REPORTE DE AVANCE | Q2: ENERO
B3: Fecha: 29/06/2022 | F3: Version: 01 | J3: GP-F-23
Q4: FEBRERO
B5: Código Orden de servicio | D5: 90578295 | Q5: MARZO
Q6: JUNIO
B7: Mes a reportar | D7: ENERO | Q7: JULIO
Q8: AGOSTO
B9: Fecha reporte | D9: 46053 | Q9: SEPTIEMBRE
Q10: OCTUBRE
B11: Clasificación del servicio | I11: Reporte mes por servicio | K11: Reporte acumulado por servicio | Q11: NOVIEMBRE
B12: Ítem general | C12: ítem actividad | D12: Descripción de la actividad | E12: Profesional a cargo | F12: Soporte | G12: Medio de entrega | H12: Días contratados | I12: Días | J12: % avance | K12: Días | L12: % avance | Q12: DICIEMBRE
B13: 3 | C13: 3.6 | D13: Generar Modelo analítico del yacimiento integrando la información disponible en un software específico | E13: Christian Mauricio Pardo Carranza | F13: Se generó modelo analítico del yacimiento para para revisión de auditoría 2025 de reservas y recursos contingentes. | G13: \\10.100.25.60\sya\GEC\Ariari\67. ENTREGAS DE CARGO\ING. DE PORTAFOLIO\CMPC\Christian Pardo\ENTREGABLES 2026\01. ENERO | H13: 11 | I13: 3 | J13: =IFERROR(I13/H13,0) -> 0.27272727 | K13: =+I13 -> 3 | L13: =IFERROR(K13/H13,0) -> 0.27272727
B14: 3 | C14: 3.13 | D14: Generar base de datos de producción (OFM o la que se requiera) | F14: Se generó base de datos de OFM para análisis histórico de producción para revisión de auditoría 2025 de reservas y recursos contingentes. | G14: \\10.100.25.60\sya\GEC\Ariari\67. ENTREGAS DE CARGO\ING. DE PORTAFOLIO\CMPC\Christian Pardo\ENTREGABLES 2026\01. ENERO | H14: 12 | I14: 3 | J14: =IFERROR(I14/H14,0) -> 0.25 | K14: =+I14 -> 3 | L14: =IFERROR(K14/H14,0) -> 0.25
B15: 3 | C15: 3.14 | D15: Generar Distribución de Producción por sub- unidades (allocation) | F15: Se generó distribución de producción por sub-unidades para revisión de auditoría 2025 de reservas y recursos contingentes. | G15: \\10.100.25.60\sya\GEC\Ariari\67. ENTREGAS DE CARGO\ING. DE PORTAFOLIO\CMPC\Christian Pardo\ENTREGABLES 2026\01. ENERO | H15: 11 | I15: 4 | J15: =IFERROR(I15/H15,0) -> 0.36363636 | K15: =+I15 -> 4 | L15: =IFERROR(K15/H15,0) -> 0.36363636
B16: 3 | C16: 3.16 | D16: Análisis de Declinaciones por pozo y/o subunidad | F16: Se analizó declinación de pozos para revisión de auditoría 2025 de reservas y recursos contingentes. | G16: \\10.100.25.60\sya\GEC\Ariari\67. ENTREGAS DE CARGO\ING. DE PORTAFOLIO\CMPC\Christian Pardo\ENTREGABLES 2026\01. ENERO | H16: 11 | I16: 4 | J16: =IFERROR(I16/H16,0) -> 0.36363636 | K16: =+I16 -> 4 | L16: =IFERROR(K16/H16,0) -> 0.36363636
B17: 3 | C17: 3.17 | D17: Analizar data histórica de producción, productividad y daño por pozo | F17: Se analizó data histórica de producción para revisión de auditoría 2025 de reservas y recursos contingentes. | G17: \\10.100.25.60\sya\GEC\Ariari\67. ENTREGAS DE CARGO\ING. DE PORTAFOLIO\CMPC\Christian Pardo\ENTREGABLES 2026\01. ENERO | H17: 11 | I17: 4 | J17: =IFERROR(I17/H17,0) -> 0.36363636 | K17: =+I17 -> 4 | L17: =IFERROR(K17/H17,0) -> 0.36363636
B18: 3 | C18: 3.18 | D18: Generar perfiles de Producción por pozos para pozos existente en escenarios Bajo, Medio y Alto | F18: Se calcularon los perfiles para cada uno de los escenarios bajo, base y alto para revisión de auditoría 2025 de reservas y recursos contingentes. | G18: \\10.100.25.60\sya\GEC\Ariari\67. ENTREGAS DE CARGO\ING. DE PORTAFOLIO\CMPC\Christian Pardo\ENTREGABLES 2026\01. ENERO | H18: 11 | I18: 4 | J18: =IFERROR(I18/H18,0) -> 0.36363636 | K18: =+I18 -> 4 | L18: =IFERROR(K18/H18,0) -> 0.36363636
B19: 5 | C19: 5.2 | D19: Generación de oportunidades de intervención a Pozos | F19: Se generaron oportunidades de intervención a pozos para proyecto ET-2. | G19: \\10.100.25.60\sya\GEC\Ariari\67. ENTREGAS DE CARGO\ING. DE PORTAFOLIO\CMPC\Christian Pardo\ENTREGABLES 2026\01. ENERO | H19: 11 | I19: 4 | J19: =IFERROR(I19/H19,0) -> 0.36363636 | K19: =+I19 -> 4 | L19: =IFERROR(K19/H19,0) -> 0.36363636
B20: 8 | C20: 8.2 | D20: Carga de datos, procesamiento de datos, Análisis Estadístico descriptivo considerando hipótesis desde la teoría, y análisis descriptivo considerando hipótesis generadas desde la misma data (pasos 1, 2 y 3 teoría CRISP-DM). | F20: Se realizó archivo con perfiles visión certificador de campo pachaquiaro para análisis de robustez. Se realizó balance de incorporación de reservas para el bloque Apiay-ariari. Se revisó P-50 por pozo para meta de producción. Se realizó balance de agua para P-50 JD. Se cargó en PBI volúmenes certificados. Se cargo factor geológico en tablero 2.6. Se inició con RWA para seguimiento a secundaria. Se realizó reporte de producción e inyección semanal. Se inició con entrega de cargo ingeniero de portafolio y reservas. Se inició con entrega de cargo ingeniero de implementación y aseguramiento I&A. Se inició con informe técnico anual ITA 2025. Se inició con justificación de reservas 1P. | G20: \\10.100.25.60\sya\GEC\Ariari\67. ENTREGAS DE CARGO\ING. DE PORTAFOLIO\CMPC\Christian Pardo\ENTREGABLES 2026\01. ENERO | H20: 12 | I20: 4 | J20: =IFERROR(I20/H20,0) -> 0.33333333 | K20: =+I20 -> 4 | L20: =IFERROR(K20/H20,0) -> 0.33333333
B21: 3 | C21: 3.6 | D21: Generar Modelo analítico del yacimiento integrando la información disponible en un software específico | E21: Nubia Solanlly Reyes Ávila | F21: Modelo Analítico - Perfiles de Producción - Informe del modelo | G21: Digital | H21: 9 | I21: 3 | J21: =IFERROR(I21/H21,0) -> 0.33333333 | K21: =+I21 -> 3 | L21: =IFERROR(K21/H21,0) -> 0.33333333
B22: 3 | C22: 3.12 | D22: Generar Modelo de Presiones partiendo de las pruebas previamente validadas e interpretadas | F22: Base de Datos | G22: Digital | H22: 8 | I22: 2 | J22: =IFERROR(I22/H22,0) -> 0.25 | K22: =+I22 -> 2 | L22: =IFERROR(K22/H22,0) -> 0.25
B23: 3 | C23: 3.13 | D23: Generar base de datos de producción (OFM o la que se requiera) | F23: Base de Datos | G23: Digital | H23: 8 | I23: 3 | J23: =IFERROR(I23/H23,0) -> 0.375 | K23: =+I23 -> 3 | L23: =IFERROR(K23/H23,0) -> 0.375
B24: 3 | C24: 3.14 | D24: Generar Distribución de Producción por sub- unidades (allocation) | F24: Base de Datos | G24: Digital | H24: 8 | I24: 2 | J24: =IFERROR(I24/H24,0) -> 0.25 | K24: =+I24 -> 2 | L24: =IFERROR(K24/H24,0) -> 0.25
B25: 3 | C25: 3.16 | D25: Análisis de Declinaciones por pozo y/o subunidad | F25: Base de Datos - Perfiles Generados - Informe del análisis | G25: Digital | H25: 9 | I25: 3 | J25: =IFERROR(I25/H25,0) -> 0.33333333 | K25: =+I25 -> 3 | L25: =IFERROR(K25/H25,0) -> 0.33333333
B26: 3 | C26: 3.17 | D26: Analizar data histórica de producción, productividad y daño por pozo | F26: Base de Datos - Informe de la Evaluación | G26: Digital | H26: 8 | I26: 3 | J26: =IFERROR(I26/H26,0) -> 0.375 | K26: =+I26 -> 3 | L26: =IFERROR(K26/H26,0) -> 0.375
B27: 3 | C27: 3.18 | D27: Generar perfiles de Producción por pozos para pozos existente en escenarios Bajo, Medio y Alto | F27: Base de Datos - Informe de la Evaluación | G27: Digital | H27: 8 | I27: 3 | J27: =IFERROR(I27/H27,0) -> 0.375 | K27: =+I27 -> 3 | L27: =IFERROR(K27/H27,0) -> 0.375
B28: 5 | C28: 5.1 | D28: Generar bases de datos de Eventos de pozos | F28: Base de Datos | G28: Digital | H28: 8 | I28: 2 | J28: =IFERROR(I28/H28,0) -> 0.25 | K28: =+I28 -> 2 | L28: =IFERROR(K28/H28,0) -> 0.25
B29: 5 | C29: 5.2 | D29: Generación de oportunidades de intervención a Pozos | F29: Base de Datos - Informe de la Evaluación | G29: Digital | H29: 8 | I29: 3 | J29: =IFERROR(I29/H29,0) -> 0.375 | K29: =+I29 -> 3 | L29: =IFERROR(K29/H29,0) -> 0.375
B30: 5 | C30: 5.9 | D30: Realizar el seguimiento de producción/ inyección de pozos intervenidos con base en los comportamientos de producción previo y posterior a la intervención | F30: Base de Datos - Informe de la Evaluación | G30: Digital | H30: 8 | I30: 3 | J30: =IFERROR(I30/H30,0) -> 0.375 | K30: =+I30 -> 3 | L30: =IFERROR(K30/H30,0) -> 0.375
B31: 8 | C31: 8.2 | D31: Carga de datos, procesamiento de datos, Análisis Estadístico descriptivo considerando hipótesis desde la teoría, y análisis descriptivo considerando hipótesis generadas desde la misma data (pasos 1, 2 y 3 teoría CRISP-DM). | F31: Informe, con estadísticas descriptivas, histogramas, pruebas de ajuste, etc. | G31: Digital | H31: 8 | I31: 3 | J31: =IFERROR(I31/H31,0) -> 0.375 | K31: =+I31 -> 3 | L31: =IFERROR(K31/H31,0) -> 0.375
B32: 2 | C32: 2.2 | D32: Generación Modelo Petrofísico | E32: Maria Alejandra Mojica Arciniegas | F32: Modelo petrofisica Suria IFT | G32: Digital | H32: 11 | I32: 7 | J32: =IFERROR(I32/H32,0) -> 0.63636364 | K32: =+I32 -> 7 | L32: =IFERROR(K32/H32,0) -> 0.63636364
B33: 2 | C33: 2.3 | D33: Definir Contactos de Fluidos, Arena neta, Net pay, por pozo y por zona | F33: Modelo petrofisico Suria K1-Poro_Perm | G33: Digital | H33: 11 | I33: 6 | J33: =IFERROR(I33/H33,0) -> 0.54545455 | K33: =+I33 -> 6 | L33: =IFERROR(K33/H33,0) -> 0.54545455
B34: 2 | C34: 2.4 | D34: Realizar inventario y análisis de información petrofísica | F34: Analisis / interpretacion registros pozo LBN5 | G34: Digital | H34: 12 | I34: 4 | J34: =IFERROR(I34/H34,0) -> 0.33333333 | K34: =+I34 -> 4 | L34: =IFERROR(K34/H34,0) -> 0.33333333
B35: 2 | C35: 2.5 | D35: Realizar caracterización Scal (interpretación) | F35: - | G35: - | H35: 11 | I35: 0 | J35: =IFERROR(I35/H35,0) -> 0 | K35: =+I35 -> 0 | L35: =IFERROR(K35/H35,0) -> 0
B36: 2 | C36: 2.6 | D36: Realizar la digitalización de registros, normalización de curvas, edición y corrección de curvas | F36: - | G36: - | H36: 11 | I36: 0 | J36: =IFERROR(I36/H36,0) -> 0 | K36: =+I36 -> 0 | L36: =IFERROR(K36/H36,0) -> 0
B37: 2 | C37: 2.9 | D37: Generar tipos de roca / unidades de flujo por yacimiento y/o campo | F37: Analisis de K_H de pozos de correlacion para pozo Villavicencio | G37: Digital | H37: 11 | I37: 4 | J37: =IFERROR(I37/H37,0) -> 0.36363636 | K37: =+I37 -> 4 | L37: =IFERROR(K37/H37,0) -> 0.36363636
B38: 2 | C38: 2.10 | D38: Generar base de datos petrofísicos | F38: Evaluacion informacion formacion T1 campo Apiay | G38: Digital | H38: 11 | I38: 4 | J38: =IFERROR(I38/H38,0) -> 0.36363636 | K38: =+I38 -> 4 | L38: =IFERROR(K38/H38,0) -> 0.36363636
B39: 2 | C39: 2.11 | D39: Generación de Modelos de Física de Rocas | F39: Modelo TR K1_Suria | G39: Digital | H39: 12 | I39: 5 | J39: =IFERROR(I39/H39,0) -> 0.41666667 | K39: =+I39 -> 5 | L39: =IFERROR(K39/H39,0) -> 0.41666667
B40: 3 | C40: 3.6 | D40: Generar Modelo analítico del yacimiento integrando la información disponible en un software específico | E40: Jaime José Martínez Vertel | F40: Construcción de modelo en Sahara con la información del activo Apiay - Ariari exportado desde Petrel | G40: Comparativo Saharas.xlsx | H40: 10 | I40: 4 | J40: =IFERROR(I40/H40,0) -> 0.4 | K40: =+I40 -> 4 | L40: =IFERROR(K40/H40,0) -> 0.4
B41: 3 | C41: 3.13 | D41: Generar base de datos de producción (OFM o la que se requiera) | F41: Base de Datos | G41: Digital | H41: 10 | I41: 3 | J41: =IFERROR(I41/H41,0) -> 0.3 | K41: =+I41 -> 3 | L41: =IFERROR(K41/H41,0) -> 0.3
B42: 3 | C42: 3.14 | D42: Generar Distribución de Producción por sub- unidades (allocation) | F42: Base de Datos | G42: Digital | H42: 10 | I42: 3 | J42: =IFERROR(I42/H42,0) -> 0.3 | K42: =+I42 -> 3 | L42: =IFERROR(K42/H42,0) -> 0.3
B43: 3 | C43: 3.16 | D43: Análisis de Declinaciones por pozo y/o subunidad | F43: Vintage de producción de la unidad T2 en el campo Suria | G43: Metodología Perfiles Crudo .xlsx | H43: 10 | I43: 3 | J43: =IFERROR(I43/H43,0) -> 0.3 | K43: =+I43 -> 3 | L43: =IFERROR(K43/H43,0) -> 0.3
B44: 3 | C44: 3.17 | D44: Analizar data histórica de producción, productividad y daño por pozo | F44: Curva Característica Suria T2 | G44: 9. Septiembre - Curva Características T2 Suria 1.xlsx | H44: 10 | I44: 4 | J44: =IFERROR(I44/H44,0) -> 0.4 | K44: =+I44 -> 4 | L44: =IFERROR(K44/H44,0) -> 0.4
B45: 3 | C45: 3.18 | D45: Generar perfiles de Producción por pozos para pozos existente en escenarios Bajo, Medio y Alto | F45: Perfiles de pozos de gas con nuevo cronograma, perfiles proyecto integrado Pachaquiaro - Polux. | G45: https://ecopetrol.sharepoint.com/:u:/r/sites/YACIMIENTOS-APIAY/Documentos%20compartidos/General/DOCUMENTOS%20SOPORTE/PDI/2025/Pruebas%20NO%20TOCAR!!!!%20NO%20ELIMINAR!!!/TABLERO%203%20ESCENARIOS%20CONSOLIDADOS/PDI%202025%203%20ESCENARIOS%20+%20RESERVAS%202025%20+%20AUD%202024%20+%20VT%20ECP%20V2%20+%20ALLOCATION.pbix?csf=1&web=1&e=BDckdf ; https://ecopetrol.sharepoint.com/:x:/r/sites/YACIMIENTOS-APIAY/Documentos%20compartidos/General/PROYECTOS/GAS%20-%20%20Zocay/2025/Perfiles/PDT%2022%20agosto%202025/Perfiles%20gas%20PilExp%2004092025.xlsx?d=wb1cb16f6130548d181b9c3bead053120&csf=1&web=1&e=35bzkM | H45: 10 | I45: 4 | J45: =IFERROR(I45/H45,0) -> 0.4 | K45: =+I45 -> 4 | L45: =IFERROR(K45/H45,0) -> 0.4
B46: 5 | C46: 5.2 | D46: Generación de oportunidades de intervención a Pozos | F46: Base de datos | G46: Digital | H46: 10 | I46: 3 | J46: =IFERROR(I46/H46,0) -> 0.3 | K46: =+I46 -> 3 | L46: =IFERROR(K46/H46,0) -> 0.3
B47: 5 | C47: 5.9 | D47: Realizar el seguimiento de producción/ inyección de pozos intervenidos con base en los comportamientos de producción previo y posterior a la intervención | F47: Seguimiento a las intervenciones realizadas en el campo Pachaquiaro en proyecto de Sahara del activo, así como a los pozos del campo Suria con estimulaciones y/o fracturamiento. | G47: https://ecopetrol.sharepoint.com/:u:/r/sites/YACIMIENTOS-APIAY/Documentos%20compartidos/General/PROYECTOS/PACHAQUIARO/2025/Escenarios%20Abr%202025/Escenario%201/Pachaquiaro_Caso_1_Abr2025_Exportable.arps?csf=1&web=1&e=1Gmqki | H47: 10 | I47: 3 | J47: =IFERROR(I47/H47,0) -> 0.3 | K47: =+I47 -> 3 | L47: =IFERROR(K47/H47,0) -> 0.3
B48: 8 | C48: 8.2 | D48: Carga de datos, procesamiento de datos, Análisis Estadístico descriptivo considerando hipótesis desde la teoría, y análisis descriptivo considerando hipótesis generadas desde la misma data (pasos 1, 2 y 3 teoría CRISP-DM). | F48: Informe, con estadísticas descriptivas, histogramas, pruebas de ajuste, etc. | G48: Digital | H48: 10 | I48: 3 | J48: =IFERROR(I48/H48,0) -> 0.3 | K48: =+I48 -> 3 | L48: =IFERROR(K48/H48,0) -> 0.3
B49: 1 | C49: 1.1 | D49: Generar Modelo Estático del yacimiento integrando la información disponible | E49: Diana Marcela Caceres Salinas | F49: Soporte PLTs e ILTs y sistemáticas multidisciplinarias. | G49: PD E:\c3040586\Documents\I&A\Petrel\Proyecto_Sept_2025_I&A | H49: 15 | I49: 7 | J49: =IFERROR(I49/H49,0) -> 0.46666667 | K49: =+I49 -> 7 | L49: =IFERROR(K49/H49,0) -> 0.46666667
B50: 1 | C50: 1.2 | D50: Generación Bases de Datos de Pozos (Registros, Topes e información disponible) | F50: Apoyo y seguimiento a Cambio menor de MHM vigente y actualización MHM 2025. | G50: Teams: YACIMIENTOS GDA/ General/PROYECTOS/MODELO HIDROGEOLOGICO 2025 | H50: 15 | I50: 4 | J50: =IFERROR(I50/H50,0) -> 0.26666667 | K50: =+I50 -> 4 | L50: =IFERROR(K50/H50,0) -> 0.26666667
B51: 1 | C51: 1.3 | D51: Interpretación Sísmica | F51: Revisión caudales objetivos, pozos circular 1. | G51: PD E:\c3040586\Documents\I&A\Petrel\Proyecto_Sept_2025_I&A | H51: 15 | I51: 4 | J51: =IFERROR(I51/H51,0) -> 0.26666667 | K51: =+I51 -> 4 | L51: =IFERROR(K51/H51,0) -> 0.26666667
B52: 1 | C52: 1.12 | D52: Generación de mapas de facies | F52: Apoyo a justificación de Workovers, KOM, formas ministeriales, soporte en puesta en profundidad de cañoneos, shift de registros, diseño de cañoneos y estimulaciones. | G52: PD E:\c3040586\Documents\I&A\Petrel\Proyecto_Sept_2025_I&A | H52: 15 | I52: 4 | J52: =IFERROR(I52/H52,0) -> 0.26666667 | K52: =+I52 -> 4 | L52: =IFERROR(K52/H52,0) -> 0.26666667
B53: 1 | C53: 1.17 | D53: Calculo probabilístico de Volúmenes In situ. | F53: Mapas de PWF, H2S. | G53: PD E:\c3040586\Documents\I&A\Petrel\Proyecto_Sept_2025_I&A | H53: 15 | I53: 4 | J53: =IFERROR(I53/H53,0) -> 0.26666667 | K53: =+I53 -> 4 | L53: =IFERROR(K53/H53,0) -> 0.26666667
B54: 2 | C54: 2.3 | D54: Definir Contactos de Fluidos, Arena neta, Net pay, por pozo y por zona | F54: Soporte construcción de tableros WF. Factor de conectividad, factor geológico | G54: Teams: I&A GDA/ General/Geología, mapas e imágenes/ Tableros WF | H54: 15 | I54: 7 | J54: =IFERROR(I54/H54,0) -> 0.46666667 | K54: =+I54 -> 7 | L54: =IFERROR(K54/H54,0) -> 0.46666667
B55: 3 | C55: 3.6 | D55: Generar Modelo analítico del yacimiento integrando la información disponible en un software específico | E55: Paola Andrea Gomez Cabrera | F55: Se realizó cargue de pruebas de produccion, tasas de inyección, pruebas de ILT en la BD de Sahara CAN01, CAN71 adicionalmente se realiza el seguimiento a las optimizaciones, y Wo en ejecucion CAN262, conversion CA23. | G55: \\10.100.25.60\sya\gec\Castilla\39. Proyecto_Inyeccion_de_Agua\SAHARA) y en las notas de wellmeeting | H55: 9 | I55: 3 | J55: =IFERROR(I55/H55,0) -> 0.33333333 | K55: =+I55 -> 3 | L55: =IFERROR(K55/H55,0) -> 0.33333333
B56: 3 | C56: 3.13 | D56: Generar base de datos de producción (OFM o la que se requiera) | F56: Se realizó la base de datos de seguimiento a patrones de Centro Norte con datos del tablero de producción prorrateada el cual es alimentado con base en la producción por formas y pruebas de producción de AVM. | G56: DTWF CASTILLA-Tablero Castilla y \\10.100.25.60\sya\gec\Castilla\39. Proyecto_Inyeccion_de_Agua\SAHARA | H56: 18 | I56: 6 | J56: =IFERROR(I56/H56,0) -> 0.33333333 | K56: =+I56 -> 6 | L56: =IFERROR(K56/H56,0) -> 0.33333333
B57: 3 | C57: 3.14 | D57: Generar Distribución de Producción por sub- unidades (allocation) | F57: Para esta actividad se genera distribución vertical por unidad para los inyectores asociados a la Zona Centro Norte. La distribución se encuentra actualizada a la fecha con los últimos valores de ILT para cada inyector. La evidencia se encuentra en la Base de Datos SAHARA. | G57: \\10.100.25.60\sya\gec\Castilla\39. Proyecto_Inyeccion_de_Agua\SAHARA | H57: 6 | I57: 2 | J57: =IFERROR(I57/H57,0) -> 0.33333333 | K57: =+I57 -> 2 | L57: =IFERROR(K57/H57,0) -> 0.33333333
B58: 3 | C58: 3.16 | D58: Análisis de Declinaciones por pozo y/o subunidad | F58: De acuerdo con el seguimiento a la producción e inyección, se realizó el seguimiento a los patrones CAN05, CAN01, CAN454, CAN71,y CAN462. | G58: https://teams.microsoft.com/l/channel/19%3A0KSR0Sqd9sL27-AWAKb2UFAmZ-fupgWBuEQNEHUYOIY1%40thread.tacv2/Documentos?groupId=ba918c77-3768-4ebd-affe-4ef992094119&tenantId=a4305987-cf78-4f93-9d64-bf18af65397b | H58: 18 | I58: 6 | J58: =IFERROR(I58/H58,0) -> 0.33333333 | K58: =+I58 -> 6 | L58: =IFERROR(K58/H58,0) -> 0.33333333
B59: 3 | C59: 3.17 | D59: Analizar data histórica de producción, productividad y daño por pozo | F59: se realiza relaciones y comparaciones con los datos de producción e inyección de la zona Centro Norte cargada en la base de datos de Sahara. Ver mayor ampliación en GP-F-25 | G59: \\10.100.25.60\sya\gec\Castilla\39. Proyecto_Inyeccion_de_Agua\SAHARA\BD Sahara | H59: 9 | I59: 3 | J59: =IFERROR(I59/H59,0) -> 0.33333333 | K59: =+I59 -> 3 | L59: =IFERROR(K59/H59,0) -> 0.33333333
B60: 3 | C60: 3.18 | D60: Generar perfiles de Producción por pozos para pozos existente en escenarios Bajo, Medio y Alto | F60: Para este ítem para el mes de enero se realizó los perfiles generados para los pozos candidatos a (RDG) rediseño y Workover (WO) )CAN73 y CA374 los cuales quedan registrados en la ruta del equipo de taller de producción GDT | G60: GDT Plus (El V.A.R.) - General - Todos los documentos y https://ecopetrol.sharepoint.com/sites/CastillaWOs2022/Documentos%20compartidos/Forms/AllItems.aspx | H60: 9 | I60: 3 | J60: =IFERROR(I60/H60,0) -> 0.33333333 | K60: =+I60 -> 3 | L60: =IFERROR(K60/H60,0) -> 0.33333333
B61: 5 | C61: 5.2 | D61: Generación de oportunidades de intervención a Pozos | F61: Con el equipo multidiciplinario se realiza un análisis de los pozos encontrando bajas eficiencias y declinaciones presentadas de los pozos de la zona Centro Norte concluyendo las oportunidades de intervención en la medida que se puedan realizar las oportunidades en los pozos candidatos, lo cual queda consignado en el WM. Se realizo analisis de de pozos inyectores con respecto a la petrofisica y se monitoreo acciones tomadas en los 23 patrones de la zona | G61: https://wellmeeting.ecopetrol.com.co/home | H61: 6 | I61: 2 | J61: =IFERROR(I61/H61,0) -> 0.33333333 | K61: =+I61 -> 2 | L61: =IFERROR(K61/H61,0) -> 0.33333333
B62: 5 | C62: 5.9 | D62: Realizar el seguimiento de producción/ inyección de pozos intervenidos con base en los comportamientos de producción previo y posterior a la intervención | F62: Se realizo el seguimiento de producción/ inyección de pozos a cargo (23 patrones de inyección) con base en los comportamientos de producción e inyección | G62: https://teams.microsoft.com/l/channel/19%3A0KSR0Sqd9sL27-AWAKb2UFAmZ-fupgWBuEQNEHUYOIY1%40thread.tacv2/Documentos?groupId=ba918c77-3768-4ebd-affe-4ef992094119&tenantId=a4305987-cf78-4f93-9d64-bf18af65397b | H62: 9 | I62: 3 | J62: =IFERROR(I62/H62,0) -> 0.33333333 | K62: =+I62 -> 3 | L62: =IFERROR(K62/H62,0) -> 0.33333333
B63: 8 | C63: 8.2 | D63: Carga de datos, procesamiento de datos, Análisis Estadístico descriptivo considerando hipótesis desde la teoría, y análisis descriptivo considerando hipótesis generadas desde la misma data (pasos 1, 2 y 3 teoría CRISP-DM). | F63: Para este ítem se realizó carga de datos de ILT en la BD de Sahara. Se realizó la actualización de volumetrías del pozo CAN01 y CAN71. | G63: \\10.100.25.60\sya\gec\Castilla\39. Proyecto_Inyeccion_de_Agua\SAHARA) y en las notas de wellmeeting | H63: 6 | I63: 2 | J63: =IFERROR(I63/H63,0) -> 0.33333333 | K63: =+I63 -> 2 | L63: =IFERROR(K63/H63,0) -> 0.33333333
B64: 3 | C64: 3.6 | D64: Generar Modelo analítico del yacimiento integrando la información disponible en un software específico | E64: Jose Gabriel Nassar Diaz | F64: Modelo Analítico - Perfiles de Producción - Informe del modelo | G64: \\10.100.25.60\sya\gec\JOSE GABRIEL NASSAR - PORTAFOLIO CASTILLA\0. ENTREGABLES | H64: 10 | I64: 3 | J64: =IFERROR(I64/H64,0) -> 0.3 | K64: =+I64 -> 3 | L64: =IFERROR(K64/H64,0) -> 0.3
B65: 3 | C65: 3.13 | D65: Generar base de datos de producción (OFM o la que se requiera) | F65: - Recepción, corridas de recalculate groups, batch manager y export de información de Plan 2 enviadas por certificador. - Carga en tableros de información Plan 2 enviada por certificador y revisión y comparación de volúmenes. Respuestas a certificador con actividades y pronósticos faltantes. | G65: \\10.100.25.60\sya\gec\JOSE GABRIEL NASSAR - PORTAFOLIO CASTILLA\0. ENTREGABLES | H65: 10 | I65: 4 | J65: =IFERROR(I65/H65,0) -> 0.4 | K65: =+I65 -> 4 | L65: =IFERROR(K65/H65,0) -> 0.4
B66: 3 | C66: 3.14 | D66: Generar Distribución de Producción por sub- unidades (allocation) | F66: - Corrida de fechas de pronósticos acordados con certificador, de acuerdo con cartilla aprobada por el corporativo. - Generación de escenario con cierres a WOR 230 a partir de pronósticos acordados con el certificador. - Generación de script de carga de pronósticos y carga en plan Sandbox. | G66: \\10.100.25.60\sya\gec\JOSE GABRIEL NASSAR - PORTAFOLIO CASTILLA\0. ENTREGABLES | H66: 10 | I66: 4 | J66: =IFERROR(I66/H66,0) -> 0.4 | K66: =+I66 -> 4 | L66: =IFERROR(K66/H66,0) -> 0.4
B67: 3 | C67: 3.16 | D67: Análisis de Declinaciones por pozo y/o subunidad | F67: - Verificación de información de pronósticos y conteo cargado en herramienta de financiera Planning Space. | G67: \\10.100.25.60\sya\gec\JOSE GABRIEL NASSAR - PORTAFOLIO CASTILLA\0. ENTREGABLES | H67: 10 | I67: 3 | J67: =IFERROR(I67/H67,0) -> 0.3 | K67: =+I67 -> 3 | L67: =IFERROR(K67/H67,0) -> 0.3
B68: 3 | C68: 3.17 | D68: Analizar data histórica de producción, productividad y daño por pozo | F68: - Realización de conteo de pozos productores, inyectores, CLIA y disposal. - Generación de script de carga de conteo y carga en Plan Sandbox. | G68: \\10.100.25.60\sya\gec\JOSE GABRIEL NASSAR - PORTAFOLIO CASTILLA\0. ENTREGABLES | H68: 10 | I68: 3 | J68: =IFERROR(I68/H68,0) -> 0.3 | K68: =+I68 -> 3 | L68: =IFERROR(K68/H68,0) -> 0.3
B69: 3 | C69: 3.18 | D69: Generar perfiles de Producción por pozos para pozos existente en escenarios Bajo, Medio y Alto | F69: Base de Datos - Informe de la Evaluación | G69: \\10.100.25.60\sya\gec\JOSE GABRIEL NASSAR - PORTAFOLIO CASTILLA\0. ENTREGABLES | H69: 10 | I69: 3 | J69: =IFERROR(I69/H69,0) -> 0.3 | K69: =+I69 -> 3 | L69: =IFERROR(K69/H69,0) -> 0.3
B70: 5 | C70: 5.2 | D70: Generación de oportunidades de intervención a Pozos | F70: - Actualización de archivo Type of Work Plan 2 y Plan 3 para compartir con certificador. | G70: \\10.100.25.60\sya\gec\JOSE GABRIEL NASSAR - PORTAFOLIO CASTILLA\0. ENTREGABLES | H70: 10 | I70: 3 | J70: =IFERROR(I70/H70,0) -> 0.3 | K70: =+I70 -> 3 | L70: =IFERROR(K70/H70,0) -> 0.3
B71: 5 | C71: 5.9 | D71: Realizar el seguimiento de producción/ inyección de pozos intervenidos con base en los comportamientos de producción previo y posterior a la intervención | F71: - Realización de balance de agua con corrientes Winj, Wvertimiento, Wirrigation, Wdisposal para enviar a certificador con el objetivo de cerrar Plan 3 de certificación. - Análisis y anticipación de riesgos en proceso de certificación de reservas. | G71: \\10.100.25.60\sya\gec\JOSE GABRIEL NASSAR - PORTAFOLIO CASTILLA\0. ENTREGABLES | H71: 10 | I71: 4 | J71: =IFERROR(I71/H71,0) -> 0.4 | K71: =+I71 -> 4 | L71: =IFERROR(K71/H71,0) -> 0.4
B72: 8 | C72: 8.2 | D72: Carga de datos, procesamiento de datos, Análisis Estadístico descriptivo considerando hipótesis desde la teoría, y análisis descriptivo considerando hipótesis generadas desde la misma data (pasos 1, 2 y 3 teoría CRISP-DM). | F72: Informe, con estadísticas descriptivas, histogramas, pruebas de ajuste, etc. | G72: \\10.100.25.60\sya\gec\JOSE GABRIEL NASSAR - PORTAFOLIO CASTILLA\0. ENTREGABLES | H72: 10 | I72: 3 | J72: =IFERROR(I72/H72,0) -> 0.3 | K72: =+I72 -> 3 | L72: =IFERROR(K72/H72,0) -> 0.3
B73: 3 | C73: 3.3 | D73: Realice el plan de desarrollo del campo y los pronosticos:la prediccion se basaría en el plan de desarrollo de campo, la ubicación de perforaciones de relleno, el analisis de los patrones, la optimizacion de inyeccion de agua, las tasas de inyeccion óptima y el proceso de recuperacion terciaria (quimica y terminca). Realizar evaluaciones economicas y evaluaciones de cada proceso y presentar la mejor solucion optima. | E73: Carlos Rafael Olmos Carval | F73: Se consolidaron los Qobj, arenas, mandriles y presiones en cabeza de la zona Centro Norte en el archivo Qobj.xlsx. | G73: Qobj.xlsx | H73: 10 | I73: 4 | J73: =IFERROR(I73/H73,0) -> 0.4 | K73: =+I73 -> 4 | L73: =IFERROR(K73/H73,0) -> 0.4
B74: 3 | C74: 3.17 | D74: Analizar data histórica de producción, productividad y daño por pozo | F74: Se construyeron y enviaron las plantillas para el cargue trimestral por campo para la actualización de molinos de viento. | G74: W:\39. Proyecto_Inyeccion_de_Agua\Planillas Power BI\6. Molinos de Viento\3.Actualizaciones\Cargue por campo\2025\9.Diciembre | H74: 10 | I74: 4 | J74: =IFERROR(I74/H74,0) -> 0.4 | K74: =+I74 -> 4 | L74: =IFERROR(K74/H74,0) -> 0.4
B75: 3 | C75: 3.18 | D75: Generar perfiles de Producción por pozos para pozos existente en escenarios Bajo, Medio y Alto | F75: Se realizo la construcción de los archivos .TXT que actualizan la base de datos de molinos de vientos para cada uno de los proyectos del activo. | G75: W:\39. Proyecto_Inyeccion_de_Agua\Planillas Power BI\6. Molinos de Viento\3. Actualizaciones\Cargue Proyectos\Real\2025\Diciembre\TXT | H75: 10 | I75: 4 | J75: =IFERROR(I75/H75,0) -> 0.4 | K75: =+I75 -> 4 | L75: =IFERROR(K75/H75,0) -> 0.4
B76: 5 | C76: 5.2 | D76: Generación de oportunidades de intervención a Pozos | F76: Se ajusto el tablero de capacidad de flujo de Castilla, realizándole cambios de forma necesarios para poder ser publicado en la web del equipo de Monitoreo VRO. | G76: Capacidad_de_flujo_Castilla_WF_Dic2025.pbix | H76: 10 | I76: 3 | J76: =IFERROR(I76/H76,0) -> 0.3 | K76: =+I76 -> 3 | L76: =IFERROR(K76/H76,0) -> 0.3
B77: 5 | C77: 5.9 | D77: Realizar el seguimiento de producción/ inyección de pozos intervenidos con base en los comportamientos de producción previo y posterior a la intervención | F77: Se construyeron las diapositivas de seguimiento de revisión de pozos inyectores y productores de la zona Centro Norte con los datos de producción prorrateada de Octubre. Estas llevan gráficos de control, mapas de Pwf, RAP y Utilidad. | G77: Seguimiento P&I Dic 2025 Zona Centro Norte (Diciembre).pptx | H77: 10 | I77: 3 | J77: =IFERROR(I77/H77,0) -> 0.3 | K77: =+I77 -> 3 | L77: =IFERROR(K77/H77,0) -> 0.3
B78: 8 | C78: 8.2 | D78: Carga de datos, procesamiento de datos, Análisis Estadístico descriptivo considerando hipótesis desde la teoría, y análisis descriptivo considerando hipótesis generadas desde la misma data (pasos 1, 2 y 3 teoría CRISP-DM). | F78: Se actualizo y ajusto el tablero 2.3_Monitoreo_Secundaria_VRO_Sep_2025. | G78: 2.3_Monitoreo_Secundaria_VRO_Sep_2025.pbix | H78: 10 | I78: 3 | J78: =IFERROR(I78/H78,0) -> 0.3 | K78: =+I78 -> 3 | L78: =IFERROR(K78/H78,0) -> 0.3
B79: 8 | C79: 8.3 | D79: Construcción de modelo matemático utilizando las técnicas pertinentes de Ciencia de Datos (e.g. Programación Matemática / Optimización / Investigación de Operaciones, Modelamiento Probabilístico, Machine Learning, etc.), con dominio de conocimiento petrotécnico. Si el modelo es supervisado y no paramétrico, se debe generar el sustento y razonamiento respectivo, arquitectura, calibración de parámetros adecuado, pruebas de validación, generalización, desempeño, etc. La fase de modelamiento debe incluir el razonamiento del modelo y como se relaciona con los modelos petrotécnicos convencionales o actuales, en que difiere y cuál es su innovación en términos de analítica de datos. Lo anterior no indica que tenga que ser un modelo o metodología nueva – e.g. puede ser la aplicación de un modelo existente como el Capacitance Resistance Model (CRM). Etapa 4 y 5 de la metodología CRISP-DM). Los supuestos se deben descomponer en dos: i) del dominio petrotécnico (si la inferencia / deducción es válida, e.g. en el caso del modelo CRM la inferencia procede si la etapa de llenado se ha superado, etc.) y ii) matemáticos / estadísticos, e.g. si se requiere estacionariedad, el error debe ser Gaussiano, etc. | F79: Se realizo revisión y actualización del tablero P50. Se actualizaron los perfiles P50 correspondientes al trienio 2025-2027. Se trabajo en los perfiles de producción de petróleo, agua y agua inyectada. | G79: P50 CASTILLA_2024_V19.pbix | H79: 10 | I79: 3 | J79: =IFERROR(I79/H79,0) -> 0.3 | K79: =+I79 -> 3 | L79: =IFERROR(K79/H79,0) -> 0.3
B80: 8 | C80: 8.4 | D80: Análisis de resultados y análisis Estadístico - descriptivo de los resultados obtenidos, así como de las pruebas implementadas. Ejemplificación de la interpretación de resultados y auto-critica de los mismos. Mapeo de conclusiones, recomendaciones y validación de los objetivos con enfoque de valor. Es clave generar nociones para que los resultados puedan ser bien utilizados y/o asociados con otras metodologías. Si procede, se debe validar los resultados con los expertos o dolientes respectivos. Etapa 5 de la metodología CRISP-DM. | F80: Se apoyo con el diligenciamiento de las actas de las reuniones de la zona centro norte en la herramienta WellMeeting, donde se establecen los diagnósticos y acciones a llevar a cabo en cada uno de los pozos analizados en los espacios. | G80: WELLMEETING | H80: 10 | I80: 3 | J80: =IFERROR(I80/H80,0) -> 0.3 | K80: =+I80 -> 3 | L80: =IFERROR(K80/H80,0) -> 0.3
B81: 8 | C81: 8.5 | D81: Programación del modelo matemático en las herramientas que se considere más adecuada, e.g. R, Python, SAS, C++, Java, Matlab, Visual, etc. Los scripts deben respetar los planteamientos y consideraciones contenidas en el informe, debe contener buenas prácticas de programación (e.g. comentarios, identación (anglicismo de “identation”), separación por métodos o funciones, etc. – el programa no necesariamente debe estar orientado a objetos y otros paradigmas, e.g. la programación funcional podría ser altamente recomendable). | F81: Se realizó el seguimiento a las optimizaciones, rediseños y WO a ejecutar. La información quedó asegurada en el archivo “Matriz priorizacion incrementos“ y "Priorizacion de acciones GDT_RD-WO-WS" | G81: \\10.100.25.60\sya\gec\Castilla\39. Proyecto_Inyeccion_de_Agua\SAHARA) y en las notas de wellmeeting | H81: 10 | I81: 3 | J81: =IFERROR(I81/H81,0) -> 0.3 | K81: =+I81 -> 3 | L81: =IFERROR(K81/H81,0) -> 0.3
B82: 3 | C82: 3.6 | D82: Generar Modelo analítico del yacimiento integrando la información disponible en un software específico | E82: Cesar Eliecer Rodriguez Camelo | F82: Se realizó el seguimiento a las optimizaciones, rediseños y WO a ejecutar. La información quedó asegurada en el archivo “Matriz priorizacion incrementos“ y "Priorizacion de acciones GDT_RD-WO-WS" | G82: \\10.100.25.60\sya\gec\Castilla\39. Proyecto_Inyeccion_de_Agua\SAHARA) y en las notas de wellmeeting | H82: 10 | I82: 4 | J82: =IFERROR(I82/H82,0) -> 0.4 | K82: =+I82 -> 4 | L82: =IFERROR(K82/H82,0) -> 0.4
B83: 3 | C83: 3.13 | D83: Generar base de datos de producción (OFM o la que se requiera) | F83: En la herramienta Sahara oficial con corte a Ene/2025, se corrigió y actualizó estado de capa y factores de alocacion pozos CA21, CA222st, CA257. Cargue de data de producción y Presiones dinamicas actualizadas a Feb/26 de zona centro sur. Corrección de topes y registro para CA338 | G83: \\10.100.25.60\sya\gec\Castilla\39. Proyecto_Inyeccion_de_Agua\SAHARA | H83: 10 | I83: 4 | J83: =IFERROR(I83/H83,0) -> 0.4 | K83: =+I83 -> 4 | L83: =IFERROR(K83/H83,0) -> 0.4
B84: 3 | C84: 3.14 | D84: Generar Distribución de Producción por sub- unidades (allocation) | F84: Por solicitud de la líder, se diligenciaron los siguientes archivos con la información actualizada del estado de los pozos productores e inyectores del área que tengo en monitoreo: Candidatos rediseños, Rediseños Ejecutados en 2026 por zona. actualización de EM, propiedades petrofísicas y factores de alocación para los diferentes pozos en la BD de SAHARA | G84: DTWF CASTILLA - Tablero Castilla Fan Edition - Todos los documentos \\10.100.25.60\sya\gec\Castilla\39. Proyecto_Inyeccion_de_Agua\SAHARA\BD Sahara | H84: 10 | I84: 4 | J84: =IFERROR(I84/H84,0) -> 0.4 | K84: =+I84 -> 4 | L84: =IFERROR(K84/H84,0) -> 0.4
B85: 3 | C85: 3.16 | D85: Análisis de Declinaciones por pozo y/o subunidad | F85: De acuerdo con el seguimiento a la producción e inyección, se realizó el seguimiento a las optimizaciones realizadas en el mes de diciembre de 2025 y enero, febrero de 2026 de acuerdo con el BSW, pruebas de producción y toma de niveles. | G85: \\10.100.25.60\sya\gec\Castilla\39. Proyecto_Inyeccion_de_Agua\SAHARA\BD Sahara | H85: 10 | I85: 2 | J85: =IFERROR(I85/H85,0) -> 0.2 | K85: =+I85 -> 2 | L85: =IFERROR(K85/H85,0) -> 0.2
B86: 3 | C86: 3.17 | D86: Analizar data histórica de producción, productividad y daño por pozo | F86: Se llevaron a mesa los pozos CA360H con la finalidad de aprobar oportunidades de WOP. Visualizados pozos con oportunidad de RDG: CA184, CA340, CA119 y CA152H. Ver mayor ampliación en GP-F-25 | G86: https://wellmeeting.ecopetrol.com.co/login | H86: 10 | I86: 3 | J86: =IFERROR(I86/H86,0) -> 0.3 | K86: =+I86 -> 3 | L86: =IFERROR(K86/H86,0) -> 0.3
B87: 3 | C87: 3.18 | D87: Generar perfiles de Producción por pozos para pozos existente en escenarios Bajo, Medio y Alto | F87: Se aseguraron los diagnósticos y acciones en wellmeeting por motivos de las revisiones con el equipo multidisciplinario y revisión interna. Ver mayor ampliación en GP-F-25 | G87: https://wellmeeting.ecopetrol.com.co/login GDT Plus (El V.A.R.) - General - Todos los documentos | H87: 10 | I87: 2 | J87: =IFERROR(I87/H87,0) -> 0.2 | K87: =+I87 -> 2 | L87: =IFERROR(K87/H87,0) -> 0.2
B88: 5 | C88: 5.2 | D88: Generación de oportunidades de intervención a Pozos | F88: De acuerdo con los rediseños propuestos en el plan de cierre de brechas, se obtuvo una lista de 5 pozos que se requieren optimizar, se irán priorizando de acuerdo con el presupuesto aprobado: CA255, CA309, CA372:K2, CA62, CA187. Se define el apagado de CA593. | G88: teams (Sistemática WF y Gestión de la Básica y en la BD SAHARA (\\10.100.25.60\sya\gec\Castilla\39. Proyecto_Inyeccion_de_Agua\SAHARA) | H88: 10 | I88: 4 | J88: =IFERROR(I88/H88,0) -> 0.4 | K88: =+I88 -> 4 | L88: =IFERROR(K88/H88,0) -> 0.4
B89: 5 | C89: 5.9 | D89: Realizar el seguimiento de producción/ inyección de pozos intervenidos con base en los comportamientos de producción previo y posterior a la intervención | F89: Se realizo el seguimiento de producción/ inyección de pozos a cargo (18 patrones de inyección) con base en los comportamientos de producción e inyección entre ellos el ingreso de nuevo inyector CA21. Seguimiento escenarios de CA16 nuevo pozo de conversion. | G89: TEAMS del equipo I&A Castilla (Sistemática WF): https://ecopetrol.sharepoint.com/sites/DTWFCASTILLA/Documentos%20compartidos/Forms/AllItems.aspx?OR=Teams%2DHL&CT=1722020892543&clickparams=eyJBcHBOYW1lIjoiVGVhbXMtRGVza3RvcCIsIkFwcFZlcnNpb24iOiI0OS8yNDA2MjcyNDgxNCIsIkhhc0ZlZGVyYXRlZFVzZXIiOmZhbHNlfQ%3D%3D&id=%2Fsites%2FDTWFCASTILLA%2FDocumentos%20compartidos%2FGeneral&viewid=9ba680aa%2D7c76%2D4823%2Dbaac%2Dba7ef8ef6f87 | H89: 10 | I89: 4 | J89: =IFERROR(I89/H89,0) -> 0.4 | K89: =+I89 -> 4 | L89: =IFERROR(K89/H89,0) -> 0.4
B90: 8 | C90: 8.2 | D90: Carga de datos, procesamiento de datos, Análisis Estadístico descriptivo considerando hipótesis desde la teoría, y análisis descriptivo considerando hipótesis generadas desde la misma data (pasos 1, 2 y 3 teoría CRISP-DM). | F90: En cuanto a la herramienta OFM se realizó el cargue de la producción, inyección y pruebas del mes de Diciembre/2025. La información quedó asegurada en el proyecto 05. Proyecto OFM\Archivos Excel\Cargue OFM\2025 | G90: La información quedó asegurada en el proyecto 131. \\10.100.25.60\sya\gec\05. Proyecto OFM\Archivos Excel\Cargue OFM\2025 | H90: 10 | I90: 3 | J90: =IFERROR(I90/H90,0) -> 0.3 | K90: =+I90 -> 3 | L90: =IFERROR(K90/H90,0) -> 0.3
B91: 3 | C91: 3.6 | D91: Generar Modelo analítico del yacimiento integrando la información disponible en un software específico | E91: Ana María Castellanos Barreto | F91: Modelo Analítico - Perfiles de Producción - Informe del modelo | G91: \\10.100.25.60\sya\gec | H91: 10 | I91: 4 | J91: =IFERROR(I91/H91,0) -> 0.4 | K91: =+I91 -> 4 | L91: =IFERROR(K91/H91,0) -> 0.4
B92: 3 | C92: 3.13 | D92: Generar base de datos de producción (OFM o la que se requiera) | F92: Base de Datos | G92: \\10.100.25.60\sya\gec | H92: 10 | I92: 3 | J92: =IFERROR(I92/H92,0) -> 0.3 | K92: =+I92 -> 3 | L92: =IFERROR(K92/H92,0) -> 0.3
B93: 3 | C93: 3.14 | D93: Generar Distribución de Producción por sub- unidades (allocation) | F93: Base de Datos | G93: \\10.100.25.60\sya\gec | H93: 10 | I93: 3 | J93: =IFERROR(I93/H93,0) -> 0.3 | K93: =+I93 -> 3 | L93: =IFERROR(K93/H93,0) -> 0.3
B94: 3 | C94: 3.16 | D94: Análisis de Declinaciones por pozo y/o subunidad | F94: Base de Datos - Perfiles Generados - Informe del análisis | G94: https://ecopetrol.sharepoint.com/sites/BDSaharaCastilla/Documentos%20compartidos/Forms/AllItems.aspx?id=%2Fsites%2FBDSaharaCastilla%2FDocumentos%20compartidos%2FBD%20Sahara&viewid=a035cf74%2D0100%2D4f66%2Da914%2D651dfeb02341 | H94: 10 | I94: 3 | J94: =IFERROR(I94/H94,0) -> 0.3 | K94: =+I94 -> 3 | L94: =IFERROR(K94/H94,0) -> 0.3
B95: 3 | C95: 3.17 | D95: Analizar data histórica de producción, productividad y daño por pozo | F95: Base de Datos - Informe de la Evaluación | G95: \\10.100.25.60\sya\gec | H95: 10 | I95: 3 | J95: =IFERROR(I95/H95,0) -> 0.3 | K95: =+I95 -> 3 | L95: =IFERROR(K95/H95,0) -> 0.3
B96: 3 | C96: 3.18 | D96: Generar perfiles de Producción por pozos para pozos existente en escenarios Bajo, Medio y Alto | F96: Base de Datos - Informe de la Evaluación | G96: \\10.100.25.60\sya\gec Sahara/ Tableros de diagnostico | H96: 10 | I96: 4 | J96: =IFERROR(I96/H96,0) -> 0.4 | K96: =+I96 -> 4 | L96: =IFERROR(K96/H96,0) -> 0.4
B97: 5 | C97: 5.2 | D97: Generación de oportunidades de intervención a Pozos | F97: Base de Datos - Informe de la Evaluación | G97: https://wellmeeting.ecopetrol.com.co/home https://ecopetrol.sharepoint.com/sites/CastillaWOs2022/Documentos%20compartidos/Forms/AllItems.aspx | H97: 10 | I97: 3 | J97: =IFERROR(I97/H97,0) -> 0.3 | K97: =+I97 -> 3 | L97: =IFERROR(K97/H97,0) -> 0.3
B98: 5 | C98: 5.9 | D98: Realizar el seguimiento de producción/ inyección de pozos intervenidos con base en los comportamientos de producción previo y posterior a la intervención | F98: Base de Datos - Informe de la Evaluación | G98: 2025-04-21 Sahara VyP Castilla.zip https://ecopetrol.sharepoint.com/sites/BDSaharaCastilla/Documentos%20compartidos/Forms/AllItems.aspx?id=%2Fsites%2FBDSaharaCastilla%2FDocumentos%20compartidos%2FPresentaciones%20soporte%20sesiones%2F2025&viewid=a035cf74%2D0100%2D4f66%2Da914%2D651dfeb02341 | H98: 10 | I98: 3 | J98: =IFERROR(I98/H98,0) -> 0.3 | K98: =+I98 -> 3 | L98: =IFERROR(K98/H98,0) -> 0.3
B99: 8 | C99: 8.2 | D99: Carga de datos, procesamiento de datos, Análisis Estadístico descriptivo considerando hipótesis desde la teoría, y análisis descriptivo considerando hipótesis generadas desde la misma data (pasos 1, 2 y 3 teoría CRISP-DM). | F99: Informe, con estadísticas descriptivas, histogramas, pruebas de ajuste, etc. | G99: https://app.powerbi.com/singleSignOn?ru=https%3A%2F%2Fapp.powerbi.com%2Fgroups%2Fe5641789-d59d-4f86-b857-9812c65a1a04%2Freports%2Fdff68870-b9fb-4308-960e-6c4f8c41c79d%2FReportSection974a4271511adef5c478%3FnoSignUpCheck%3D1 | H99: 10 | I99: 4 | J99: =IFERROR(I99/H99,0) -> 0.4 | K99: =+I99 -> 4 | L99: =IFERROR(K99/H99,0) -> 0.4
B100: 1 | C100: 1.2 | D100: Generación Bases de Datos de Pozos (Registros, Topes e información disponible) | E100: Gloria Fernanda Vidal González | F100: Base de Datos | G100: Digital:M:\39. Proyecto_Inyeccion_de_Agua\Geologia_seguimiento a la inyeccion | H100: 8 | I100: 2 | J100: =IFERROR(I100/H100,0) -> 0.25 | K100: =+I100 -> 2 | L100: =IFERROR(K100/H100,0) -> 0.25
...

Sheet FEBRERO
Q1: MES
B2: REPORTE DE AVANCE | Q2: ENERO
B3: Fecha: 29/06/2022 | F3: Version: 01 | J3: GP-F-23
Q4: FEBRERO
B5: Código Orden de servicio | D5: 90578295 | Q5: MARZO
Q6: JUNIO
B7: Mes a reportar | D7: FEBRERO | Q7: JULIO
Q8: AGOSTO
B9: Fecha reporte | D9: 46081 | Q9: SEPTIEMBRE
Q10: OCTUBRE
B11: Clasificación del servicio | I11: Reporte mes por servicio | K11: Reporte acumulado por servicio | Q11: NOVIEMBRE
B12: Ítem general | C12: ítem actividad | D12: Descripción de la actividad | E12: Profesional a cargo | F12: Soporte | G12: Medio de entrega | H12: Días contratados | I12: Días | J12: % avance | K12: Días | L12: % avance | Q12: DICIEMBRE
B13: 3 | C13: 3.6 | D13: Generar Modelo analítico del yacimiento integrando la información disponible en un software específico | E13: Christian Mauricio Pardo Carranza | F13: Se generó modelo analítico del yacimiento en Sahara para seguimiento de producción y variables operacionales: Se cargó producciones y diferidas. Se cargó análisis fisicoquímicos. Actualización de estado de pozos. Actualización estados mecánicos. Generación de líneas base. Se cargó PLT y ILT. Se cargó PWF y parámetros. Se cargó pruebas de producción. | G13: \\10.100.25.60\sya\GEC\Ariari\67. ENTREGAS DE CARGO\I&A GDA\2026\3. CMPC\02. FEBRERO | H13: 11 | I13: 3 | J13: =IFERROR(I13/H13,0) -> 0.27272727 | K13: =+I13+ENERO!K13 -> 6 | L13: =IFERROR(K13/H13,0) -> 0.54545455
B14: 3 | C14: 3.13 | D14: Generar base de datos de producción (OFM o la que se requiera) | F14: Se generó base de datos de OFM para análisis histórico de producción para: Cálculo de EUR por pozo. Cargue de producciones Sahara y PBI. | G14: \\10.100.25.60\sya\GEC\Ariari\67. ENTREGAS DE CARGO\I&A GDA\2026\3. CMPC\02. FEBRERO | H14: 12 | I14: 3 | J14: =IFERROR(I14/H14,0) -> 0.25 | K14: =+I14+ENERO!K14 -> 6 | L14: =IFERROR(K14/H14,0) -> 0.5
B15: 3 | C15: 3.14 | D15: Generar Distribución de Producción por sub- unidades (allocation) | F15: Se generó distribución de producción por sub-unidades para: Cargue de producciones Sahara y PBI. | G15: \\10.100.25.60\sya\GEC\Ariari\67. ENTREGAS DE CARGO\I&A GDA\2026\3. CMPC\02. FEBRERO | H15: 11 | I15: 4 | J15: =IFERROR(I15/H15,0) -> 0.36363636 | K15: =+I15+ENERO!K15 -> 8 | L15: =IFERROR(K15/H15,0) -> 0.72727273
B16: 3 | C16: 3.16 | D16: Análisis de Declinaciones por pozo y/o subunidad | F16: Se analizó declinación de pozos para: Cálculo de líneas base pozos M-11. Archivo de Excel con proyecciones de Gas. Archivo de Excel con volúmenes del proyecto ET-1 y ET-4.1 para evaluación financiera. | G16: \\10.100.25.60\sya\GEC\Ariari\67. ENTREGAS DE CARGO\I&A GDA\2026\3. CMPC\02. FEBRERO | H16: 11 | I16: 4 | J16: =IFERROR(I16/H16,0) -> 0.36363636 | K16: =+I16+ENERO!K16 -> 8 | L16: =IFERROR(K16/H16,0) -> 0.72727273
B17: 3 | C17: 3.17 | D17: Analizar data histórica de producción, productividad y daño por pozo | F17: Se analizó data histórica de producción para: Cargue de producciones Sahara y PBI. Cálculo de EUR por pozo. Archivo de Excel con proyecciones de Gas. Archivo de Excel con volúmenes del proyecto ET-1 y ET-4.1 para evaluación financiera. | G17: \\10.100.25.60\sya\GEC\Ariari\67. ENTREGAS DE CARGO\I&A GDA\2026\3. CMPC\02. FEBRERO | H17: 11 | I17: 4 | J17: =IFERROR(I17/H17,0) -> 0.36363636 | K17: =+I17+ENERO!K17 -> 8 | L17: =IFERROR(K17/H17,0) -> 0.72727273
B18: 3 | C18: 3.18 | D18: Generar perfiles de Producción por pozos para pozos existente en escenarios Bajo, Medio y Alto | F18: Se calcularon los perfiles para cada uno de los escenarios bajo, base y alto para: Archivo de Excel con proyecciones de Gas. Archivo de Excel con volúmenes del proyecto ET-1 y ET-4.1 para evaluación financiera. | G18: \\10.100.25.60\sya\GEC\Ariari\67. ENTREGAS DE CARGO\I&A GDA\2026\3. CMPC\02. FEBRERO | H18: 11 | I18: 4 | J18: =IFERROR(I18/H18,0) -> 0.36363636 | K18: =+I18+ENERO!K18 -> 8 | L18: =IFERROR(K18/H18,0) -> 0.72727273
B19: 5 | C19: 5.2 | D19: Generación de oportunidades de intervención a Pozos | F19: Se generaron oportunidades de intervención a pozos para: Maduración del proyecto ET-2. Reactivaciones por WSV. | G19: \\10.100.25.60\sya\GEC\Ariari\67. ENTREGAS DE CARGO\I&A GDA\2026\3. CMPC\02. FEBRERO | H19: 11 | I19: 4 | J19: =IFERROR(I19/H19,0) -> 0.36363636 | K19: =+I19+ENERO!K19 -> 8 | L19: =IFERROR(K19/H19,0) -> 0.72727273
B20: 8 | C20: 8.2 | D20: Carga de datos, procesamiento de datos, Análisis Estadístico descriptivo considerando hipótesis desde la teoría, y análisis descriptivo considerando hipótesis generadas desde la misma data (pasos 1, 2 y 3 teoría CRISP-DM). | F20: Se realizó actualización de informe ITA para el proyecto Modulo 12. Se cargó factor geológico y conectividades tablero 2.6. Se generó proyección de vertimiento para los campos Apiay y Suria con base en perfiles PDI 1. Se revisaron caudales de pozos del proyecto ET-4.2 de básica e incremental de P-50. Se realizó justificación de reservas 1P. Se realizó justificación de recursos contingentes. Se realizó reporte semanal. Se realizó informe de seguimiento a ruta WO y WSV. Se consolidó información para proyecto Maxpro. Se realizó entrega de cargo ingeniero de portafolio. Se realizó actualización en informe de recursos contingentes pozos excluidos de reservas M-12. Se realizó archivo con perfiles de básica para ICO protección de la básica con base en PDI 1. Se cargó P-50 y Real en PBI para comparación mes a mes de P-50 y AUD 2025 con respecto al real. | G20: \\10.100.25.60\sya\GEC\Ariari\67. ENTREGAS DE CARGO\I&A GDA\2026\3. CMPC\02. FEBRERO | H20: 12 | I20: 4 | J20: =IFERROR(I20/H20,0) -> 0.33333333 | K20: =+I20+ENERO!K20 -> 8 | L20: =IFERROR(K20/H20,0) -> 0.66666667
B21: 3 | C21: 3.6 | D21: Generar Modelo analítico del yacimiento integrando la información disponible en un software específico | E21: Nubia Solanlly Reyes Ávila | F21: Modelo Analítico - Perfiles de Producción - Informe del modelo | G21: Digital | H21: 9 | I21: 3 | J21: =IFERROR(I21/H21,0) -> 0.33333333 | K21: =+I21+ENERO!K21 -> 6 | L21: =IFERROR(K21/H21,0) -> 0.66666667
B22: 3 | C22: 3.12 | D22: Generar Modelo de Presiones partiendo de las pruebas previamente validadas e interpretadas | F22: Base de Datos | G22: Digital | H22: 8 | I22: 3 | J22: =IFERROR(I22/H22,0) -> 0.375 | K22: =+I22+ENERO!K22 -> 5 | L22: =IFERROR(K22/H22,0) -> 0.625
B23: 3 | C23: 3.13 | D23: Generar base de datos de producción (OFM o la que se requiera) | F23: Base de Datos | G23: Digital | H23: 8 | I23: 2 | J23: =IFERROR(I23/H23,0) -> 0.25 | K23: =+I23+ENERO!K23 -> 5 | L23: =IFERROR(K23/H23,0) -> 0.625
B24: 3 | C24: 3.14 | D24: Generar Distribución de Producción por sub- unidades (allocation) | F24: Base de Datos | G24: Digital | H24: 8 | I24: 3 | J24: =IFERROR(I24/H24,0) -> 0.375 | K24: =+I24+ENERO!K24 -> 5 | L24: =IFERROR(K24/H24,0) -> 0.625
B25: 3 | C25: 3.16 | D25: Análisis de Declinaciones por pozo y/o subunidad | F25: Base de Datos - Perfiles Generados - Informe del análisis | G25: Digital | H25: 9 | I25: 3 | J25: =IFERROR(I25/H25,0) -> 0.33333333 | K25: =+I25+ENERO!K25 -> 6 | L25: =IFERROR(K25/H25,0) -> 0.66666667
B26: 3 | C26: 3.17 | D26: Analizar data histórica de producción, productividad y daño por pozo | F26: Base de Datos - Informe de la Evaluación | G26: Digital | H26: 8 | I26: 2 | J26: =IFERROR(I26/H26,0) -> 0.25 | K26: =+I26+ENERO!K26 -> 5 | L26: =IFERROR(K26/H26,0) -> 0.625
B27: 3 | C27: 3.18 | D27: Generar perfiles de Producción por pozos para pozos existente en escenarios Bajo, Medio y Alto | F27: Base de Datos - Informe de la Evaluación | G27: Digital | H27: 8 | I27: 3 | J27: =IFERROR(I27/H27,0) -> 0.375 | K27: =+I27+ENERO!K27 -> 6 | L27: =IFERROR(K27/H27,0) -> 0.75
B28: 5 | C28: 5.1 | D28: Generar bases de datos de Eventos de pozos | F28: Base de Datos | G28: Digital | H28: 8 | I28: 3 | J28: =IFERROR(I28/H28,0) -> 0.375 | K28: =+I28+ENERO!K28 -> 5 | L28: =IFERROR(K28/H28,0) -> 0.625
B29: 5 | C29: 5.2 | D29: Generación de oportunidades de intervención a Pozos | F29: Base de Datos - Informe de la Evaluación | G29: Digital | H29: 8 | I29: 2 | J29: =IFERROR(I29/H29,0) -> 0.25 | K29: =+I29+ENERO!K29 -> 5 | L29: =IFERROR(K29/H29,0) -> 0.625
B30: 5 | C30: 5.9 | D30: Realizar el seguimiento de producción/ inyección de pozos intervenidos con base en los comportamientos de producción previo y posterior a la intervención | F30: Base de Datos - Informe de la Evaluación | G30: Digital | H30: 8 | I30: 3 | J30: =IFERROR(I30/H30,0) -> 0.375 | K30: =+I30+ENERO!K30 -> 6 | L30: =IFERROR(K30/H30,0) -> 0.75
B31: 8 | C31: 8.2 | D31: Carga de datos, procesamiento de datos, Análisis Estadístico descriptivo considerando hipótesis desde la teoría, y análisis descriptivo considerando hipótesis generadas desde la misma data (pasos 1, 2 y 3 teoría CRISP-DM). | F31: Informe, con estadísticas descriptivas, histogramas, pruebas de ajuste, etc. | G31: Digital | H31: 8 | I31: 3 | J31: =IFERROR(I31/H31,0) -> 0.375 | K31: =+I31+ENERO!K31 -> 6 | L31: =IFERROR(K31/H31,0) -> 0.75
B32: 2 | C32: 2.2 | D32: Generación Modelo Petrofísico | E32: Maria Alejandra Mojica Arciniegas | F32: Modelo petrofisico Suria | G32: Digital | H32: 11 | I32: 4 | J32: =IFERROR(I32/H32,0) -> 0.36363636 | K32: =+I32+ENERO!K32 -> 11 | L32: =IFERROR(K32/H32,0) -> 1
B33: 2 | C33: 2.3 | D33: Definir Contactos de Fluidos, Arena neta, Net pay, por pozo y por zona | F33: Pozos WO-Etapa 2 | G33: Digital | H33: 11 | I33: 5 | J33: =IFERROR(I33/H33,0) -> 0.45454545 | K33: =+I33+ENERO!K33 -> 11 | L33: =IFERROR(K33/H33,0) -> 1
B34: 2 | C34: 2.4 | D34: Realizar inventario y análisis de información petrofísica | F34: Modelo petrofisico T1 | G34: Digital | H34: 12 | I34: 8 | J34: =IFERROR(I34/H34,0) -> 0.66666667 | K34: =+I34+ENERO!K34 -> 12 | L34: =IFERROR(K34/H34,0) -> 1
B35: 2 | C35: 2.5 | D35: Realizar caracterización Scal (interpretación) | F35: Modelo petrofisico Suria - T1 | G35: Digital | H35: 11 | I35: 5 | J35: =IFERROR(I35/H35,0) -> 0.45454545 | K35: =+I35+ENERO!K35 -> 5 | L35: =IFERROR(K35/H35,0) -> 0.45454545
B36: 2 | C36: 2.6 | D36: Realizar la digitalización de registros, normalización de curvas, edición y corrección de curvas | F36: Modelo petrofisica T1 | G36: Digital | H36: 11 | I36: 2 | J36: =IFERROR(I36/H36,0) -> 0.18181818 | K36: =+I36+ENERO!K36 -> 2 | L36: =IFERROR(K36/H36,0) -> 0.18181818
B37: 2 | C37: 2.9 | D37: Generar tipos de roca / unidades de flujo por yacimiento y/o campo | F37: Soporte equipo corto plazo | G37: Digital | H37: 11 | I37: 2 | J37: =IFERROR(I37/H37,0) -> 0.18181818 | K37: =+I37+ENERO!K37 -> 6 | L37: =IFERROR(K37/H37,0) -> 0.54545455
B38: 2 | C38: 2.10 | D38: Generar base de datos petrofísicos | F38: Informe ITA campos del activo Apiay -Ariari | G38: Digital | H38: 11 | I38: 2 | J38: =IFERROR(I38/H38,0) -> 0.18181818 | K38: =+I38+ENERO!K38 -> 6 | L38: =IFERROR(K38/H38,0) -> 0.54545455
B39: 2 | C39: 2.11 | D39: Generación de Modelos de Física de Rocas | F39: Informe IRR campos del activo Apiay -Ariari | G39: Digital | H39: 12 | I39: 2 | J39: =IFERROR(I39/H39,0) -> 0.16666667 | K39: =+I39+ENERO!K39 -> 7 | L39: =IFERROR(K39/H39,0) -> 0.58333333
B40: 3 | C40: 3.6 | D40: Generar Modelo analítico del yacimiento integrando la información disponible en un software específico | E40: Jaime José Martínez Vertel | F40: Construcción de modelo en Sahara con la información del activo Apiay - Ariari exportado desde Petrel | G40: Comparativo Saharas.xlsx | H40: 10 | I40: 4 | J40: =IFERROR(I40/H40,0) -> 0.4 | K40: =+I40+ENERO!K40 -> 8 | L40: =IFERROR(K40/H40,0) -> 0.8
B41: 3 | C41: 3.13 | D41: Generar base de datos de producción (OFM o la que se requiera) | F41: Base de Datos | G41: Digital | H41: 10 | I41: 3 | J41: =IFERROR(I41/H41,0) -> 0.3 | K41: =+I41+ENERO!K41 -> 6 | L41: =IFERROR(K41/H41,0) -> 0.6
B42: 3 | C42: 3.14 | D42: Generar Distribución de Producción por sub- unidades (allocation) | F42: Base de Datos | G42: Digital | H42: 10 | I42: 3 | J42: =IFERROR(I42/H42,0) -> 0.3 | K42: =+I42+ENERO!K42 -> 6 | L42: =IFERROR(K42/H42,0) -> 0.6
B43: 3 | C43: 3.16 | D43: Análisis de Declinaciones por pozo y/o subunidad | F43: Vintage de producción de la unidad T2 en el campo Suria | G43: Metodología Perfiles Crudo .xlsx | H43: 10 | I43: 3 | J43: =IFERROR(I43/H43,0) -> 0.3 | K43: =+I43+ENERO!K43 -> 6 | L43: =IFERROR(K43/H43,0) -> 0.6
B44: 3 | C44: 3.17 | D44: Analizar data histórica de producción, productividad y daño por pozo | F44: Curva Característica Suria T2 | G44: 9. Septiembre - Curva Características T2 Suria 1.xlsx | H44: 10 | I44: 4 | J44: =IFERROR(I44/H44,0) -> 0.4 | K44: =+I44+ENERO!K44 -> 8 | L44: =IFERROR(K44/H44,0) -> 0.8
B45: 3 | C45: 3.18 | D45: Generar perfiles de Producción por pozos para pozos existente en escenarios Bajo, Medio y Alto | F45: Perfiles de pozos de gas con nuevo cronograma, perfiles proyecto integrado Pachaquiaro - Polux. | G45: https://ecopetrol.sharepoint.com/:u:/r/sites/YACIMIENTOS-APIAY/Documentos%20compartidos/General/DOCUMENTOS%20SOPORTE/PDI/2025/Pruebas%20NO%20TOCAR!!!!%20NO%20ELIMINAR!!!/TABLERO%203%20ESCENARIOS%20CONSOLIDADOS/PDI%202025%203%20ESCENARIOS%20+%20RESERVAS%202025%20+%20AUD%202024%20+%20VT%20ECP%20V2%20+%20ALLOCATION.pbix?csf=1&web=1&e=BDckdf ; https://ecopetrol.sharepoint.com/:x:/r/sites/YACIMIENTOS-APIAY/Documentos%20compartidos/General/PROYECTOS/GAS%20-%20%20Zocay/2025/Perfiles/PDT%2022%20agosto%202025/Perfiles%20gas%20PilExp%2004092025.xlsx?d=wb1cb16f6130548d181b9c3bead053120&csf=1&web=1&e=35bzkM | H45: 10 | I45: 4 | J45: =IFERROR(I45/H45,0) -> 0.4 | K45: =+I45+ENERO!K45 -> 8 | L45: =IFERROR(K45/H45,0) -> 0.8
B46: 5 | C46: 5.2 | D46: Generación de oportunidades de intervención a Pozos | F46: Análisis de reservas, producción real reportada vs pronósticos certificados en la Auditoría 2025 para el activo Apiay-Ariari | G46: Información confidencial, cargada en los sitios oficiales destinados para tal fin. | H46: 10 | I46: 3 | J46: =IFERROR(I46/H46,0) -> 0.3 | K46: =+I46+ENERO!K46 -> 6 | L46: =IFERROR(K46/H46,0) -> 0.6
B47: 5 | C47: 5.9 | D47: Realizar el seguimiento de producción/ inyección de pozos intervenidos con base en los comportamientos de producción previo y posterior a la intervención | F47: Seguimiento a las intervenciones realizadas en el campo Pachaquiaro en proyecto de Sahara del activo, así como a los pozos del campo Suria con estimulaciones y/o fracturamiento. | G47: https://ecopetrol.sharepoint.com/:u:/r/sites/YACIMIENTOS-APIAY/Documentos%20compartidos/General/PROYECTOS/PACHAQUIARO/2025/Escenarios%20Abr%202025/Escenario%201/Pachaquiaro_Caso_1_Abr2025_Exportable.arps?csf=1&web=1&e=1Gmqki | H47: 10 | I47: 3 | J47: =IFERROR(I47/H47,0) -> 0.3 | K47: =+I47+ENERO!K47 -> 6 | L47: =IFERROR(K47/H47,0) -> 0.6
B48: 8 | C48: 8.2 | D48: Carga de datos, procesamiento de datos, Análisis Estadístico descriptivo considerando hipótesis desde la teoría, y análisis descriptivo considerando hipótesis generadas desde la misma data (pasos 1, 2 y 3 teoría CRISP-DM). | F48: Informe, con estadísticas descriptivas, histogramas, pruebas de ajuste, etc. | G48: Digital | H48: 10 | I48: 3 | J48: =IFERROR(I48/H48,0) -> 0.3 | K48: =+I48+ENERO!K48 -> 6 | L48: =IFERROR(K48/H48,0) -> 0.6
B49: 1 | C49: 1.1 | D49: Generar Modelo Estático del yacimiento integrando la información disponible | E49: Diana Marcela Caceres Salinas | F49: Soporte PLTs e ILTs y sistemáticas multidisciplinarias. | G49: PD E:\c3040586\Documents\I&A\Petrel\Proyecto_Sept_2025_I&A | H49: 15 | I49: 3 | J49: =IFERROR(I49/H49,0) -> 0.2 | K49: =+I49+ENERO!K49 -> 10 | L49: =IFERROR(K49/H49,0) -> 0.66666667
B50: 1 | C50: 1.2 | D50: Generación Bases de Datos de Pozos (Registros, Topes e información disponible) | F50: Revisión patrones de inyección desbalanceados. | G50: Teams: I&A GDA/ General/Geología, mapas e imágenes/ Análisis Suria Sur | H50: 15 | I50: 7 | J50: =IFERROR(I50/H50,0) -> 0.46666667 | K50: =+I50+ENERO!K50 -> 11 | L50: =IFERROR(K50/H50,0) -> 0.73333333
B51: 1 | C51: 1.3 | D51: Interpretación Sísmica | F51: Construcción IRR 2025 | G51: Teams: YACIMIENTOS GDA/ General/DOCUMENTOS SOPORTE/ ANH/INFORME IRR/2026 | H51: 15 | I51: 7 | J51: =IFERROR(I51/H51,0) -> 0.46666667 | K51: =+I51+ENERO!K51 -> 11 | L51: =IFERROR(K51/H51,0) -> 0.73333333
B52: 1 | C52: 1.12 | D52: Generación de mapas de facies | F52: Apoyo a justificación de Workovers, KOM, formas ministeriales, soporte en puesta en profundidad de cañoneos, shift de registros, diseño de cañoneos y estimulaciones. | G52: PD E:\c3040586\Documents\I&A\Petrel\Proyecto_Sept_2025_I&A | H52: 15 | I52: 5 | J52: =IFERROR(I52/H52,0) -> 0.33333333 | K52: =+I52+ENERO!K52 -> 9 | L52: =IFERROR(K52/H52,0) -> 0.6
B53: 1 | C53: 1.17 | D53: Calculo probabilístico de Volúmenes In situ. | F53: Mapas de PWF, H2S. | G53: PD E:\c3040586\Documents\I&A\Petrel\Proyecto_Sept_2025_I&A | H53: 15 | I53: 5 | J53: =IFERROR(I53/H53,0) -> 0.33333333 | K53: =+I53+ENERO!K53 -> 9 | L53: =IFERROR(K53/H53,0) -> 0.6
B54: 2 | C54: 2.3 | D54: Definir Contactos de Fluidos, Arena neta, Net pay, por pozo y por zona | F54: Soporte construcción de tableros WF. Factor de conectividad, factor geológico | G54: Teams: I&A GDA/ General/Geología, mapas e imágenes/ Tableros WF | H54: 15 | I54: 3 | J54: =IFERROR(I54/H54,0) -> 0.2 | K54: =+I54+ENERO!K54 -> 10 | L54: =IFERROR(K54/H54,0) -> 0.66666667
B55: 3 | C55: 3.6 | D55: Generar Modelo analítico del yacimiento integrando la información disponible en un software específico | E55: Paola Andrea Gomez Cabrera | F55: Se realizó cargue de pruebas de produccion, tasas de inyección, pruebas de ILT en la BD de Sahara CAN61, CAN05 adicionalmente se realiza el seguimiento a las optimizaciones CAN256, CAN412, CAN26, CAN72, CAN373, 1 WO CAN262 y una intervención a inyector CAN74. | G55: \\10.100.25.60\sya\gec\Castilla\39. Proyecto_Inyeccion_de_Agua\SAHARA) y en las notas de wellmeeting | H55: 9 | I55: 3 | J55: =IFERROR(I55/H55,0) -> 0.33333333 | K55: =+I55+ENERO!K55 -> 6 | L55: =IFERROR(K55/H55,0) -> 0.66666667
B56: 3 | C56: 3.13 | D56: Generar base de datos de producción (OFM o la que se requiera) | F56: Se realizó la base de datos de seguimiento a patrones de Centro Norte con datos del tablero de producción prorrateada el cual es alimentado con base en la producción por formas y pruebas de producción de AVM. | G56: DTWF CASTILLA-Tablero Castilla y \\10.100.25.60\sya\gec\Castilla\39. Proyecto_Inyeccion_de_Agua\SAHARA | H56: 18 | I56: 6 | J56: =IFERROR(I56/H56,0) -> 0.33333333 | K56: =+I56+ENERO!K56 -> 12 | L56: =IFERROR(K56/H56,0) -> 0.66666667
B57: 3 | C57: 3.14 | D57: Generar Distribución de Producción por sub- unidades (allocation) | F57: Para esta actividad se genera distribución vertical por unidad para los inyectores asociados a la Zona Centro Norte. La distribución se encuentra actualizada a la fecha con los últimos valores de ILT para cada inyector. La evidencia se encuentra en la Base de Datos SAHARA. | G57: \\10.100.25.60\sya\gec\Castilla\39. Proyecto_Inyeccion_de_Agua\SAHARA | H57: 6 | I57: 2 | J57: =IFERROR(I57/H57,0) -> 0.33333333 | K57: =+I57+ENERO!K57 -> 4 | L57: =IFERROR(K57/H57,0) -> 0.66666667
B58: 3 | C58: 3.16 | D58: Análisis de Declinaciones por pozo y/o subunidad | F58: De acuerdo con el seguimiento a la producción e inyección, se realizó el seguimiento a los patrones CAN22, CAN71, CAN74, CAN60 y CAN700. | G58: https://teams.microsoft.com/l/channel/19%3A0KSR0Sqd9sL27-AWAKb2UFAmZ-fupgWBuEQNEHUYOIY1%40thread.tacv2/Documentos?groupId=ba918c77-3768-4ebd-affe-4ef992094119&tenantId=a4305987-cf78-4f93-9d64-bf18af65397b | H58: 18 | I58: 6 | J58: =IFERROR(I58/H58,0) -> 0.33333333 | K58: =+I58+ENERO!K58 -> 12 | L58: =IFERROR(K58/H58,0) -> 0.66666667
B59: 3 | C59: 3.17 | D59: Analizar data histórica de producción, productividad y daño por pozo | F59: se realiza relaciones y comparaciones con los datos de producción e inyección de la zona Centro Norte cargada en la base de datos de Sahara. Ver mayor ampliación en GP-F-25, asi como justificacion de la brecha de P50 | G59: \\10.100.25.60\sya\gec\Castilla\39. Proyecto_Inyeccion_de_Agua\SAHARA\BD Sahara | H59: 9 | I59: 3 | J59: =IFERROR(I59/H59,0) -> 0.33333333 | K59: =+I59+ENERO!K59 -> 6 | L59: =IFERROR(K59/H59,0) -> 0.66666667
B60: 3 | C60: 3.18 | D60: Generar perfiles de Producción por pozos para pozos existente en escenarios Bajo, Medio y Alto | F60: Para este ítem para el mes de febrero se realizó los perfiles generados para los pozos candidatos a (RDG) rediseño y Workover (WO) CAN133 y CAN404 los cuales quedan registrados en la ruta del equipo de taller de producción GDT | G60: GDT Plus (El V.A.R.) - General - Todos los documentos y https://ecopetrol.sharepoint.com/sites/CastillaWOs2022/Documentos%20compartidos/Forms/AllItems.aspx | H60: 9 | I60: 3 | J60: =IFERROR(I60/H60,0) -> 0.33333333 | K60: =+I60+ENERO!K60 -> 6 | L60: =IFERROR(K60/H60,0) -> 0.66666667
B61: 5 | C61: 5.2 | D61: Generación de oportunidades de intervención a Pozos | F61: Con el equipo multidiciplinario se realiza un análisis de los pozos encontrando bajas eficiencias y declinaciones presentadas de los pozos de la zona Centro Norte concluyendo las oportunidades de intervención en la medida que se puedan realizar las oportunidades en los pozos candidatos, lo cual queda consignado en el WM. Se realizo analisis de de pozos inyectores con respecto a la petrofisica y se monitoreo acciones tomadas en los 23 patrones de la zona | G61: https://wellmeeting.ecopetrol.com.co/home | H61: 6 | I61: 2 | J61: =IFERROR(I61/H61,0) -> 0.33333333 | K61: =+I61+ENERO!K61 -> 4 | L61: =IFERROR(K61/H61,0) -> 0.66666667
B62: 5 | C62: 5.9 | D62: Realizar el seguimiento de producción/ inyección de pozos intervenidos con base en los comportamientos de producción previo y posterior a la intervención | F62: Se realizo el seguimiento de producción/ inyección de pozos a cargo (23 patrones de inyección) con base en los comportamientos de producción e inyección, se cargan en la BD de Sahara para realizar el cargue de las líneas base de producción CAN21 y CAN373 | G62: https://teams.microsoft.com/l/channel/19%3A0KSR0Sqd9sL27-AWAKb2UFAmZ-fupgWBuEQNEHUYOIY1%40thread.tacv2/Documentos?groupId=ba918c77-3768-4ebd-affe-4ef992094119&tenantId=a4305987-cf78-4f93-9d64-bf18af65397b | H62: 9 | I62: 3 | J62: =IFERROR(I62/H62,0) -> 0.33333333 | K62: =+I62+ENERO!K62 -> 6 | L62: =IFERROR(K62/H62,0) -> 0.66666667
B63: 8 | C63: 8.2 | D63: Carga de datos, procesamiento de datos, Análisis Estadístico descriptivo considerando hipótesis desde la teoría, y análisis descriptivo considerando hipótesis generadas desde la misma data (pasos 1, 2 y 3 teoría CRISP-DM). | F63: Para este ítem se realizó carga de datos de ILT en la BD de Sahara. Se realizó la actualización de volumetrías del pozo CAN125. | G63: \\10.100.25.60\sya\gec\Castilla\39. Proyecto_Inyeccion_de_Agua\SAHARA) y en las notas de wellmeeting | H63: 6 | I63: 2 | J63: =IFERROR(I63/H63,0) -> 0.33333333 | K63: =+I63+ENERO!K63 -> 4 | L63: =IFERROR(K63/H63,0) -> 0.66666667
B64: 3 | C64: 3.6 | D64: Generar Modelo analítico del yacimiento integrando la información disponible en un software específico | E64: Jose Gabriel Nassar Diaz | F64: Modelo Analítico - Perfiles de Producción - Informe del modelo | G64: \\10.100.25.60\sya\gec\JOSE GABRIEL NASSAR - PORTAFOLIO CASTILLA\0. ENTREGABLES | H64: 10 | I64: 3 | J64: =IFERROR(I64/H64,0) -> 0.3 | K64: =+I64+ENERO!K64 -> 6 | L64: =IFERROR(K64/H64,0) -> 0.6
B65: 3 | C65: 3.13 | D65: Generar base de datos de producción (OFM o la que se requiera) | F65: - Soporte en generación de informes a entes oficiales: ITA e IRR. | G65: \\10.100.25.60\sya\gec\JOSE GABRIEL NASSAR - PORTAFOLIO CASTILLA\0. ENTREGABLES | H65: 10 | I65: 3 | J65: =IFERROR(I65/H65,0) -> 0.3 | K65: =+I65+ENERO!K65 -> 7 | L65: =IFERROR(K65/H65,0) -> 0.7
B66: 3 | C66: 3.14 | D66: Generar Distribución de Producción por sub- unidades (allocation) | F66: - Corrida de fechas de pronósticos acordados con certificador, de acuerdo con cartilla aprobada por el corporativo. - Generación de escenario con cierres a WOR 230 a partir de pronósticos acordados con el certificador. - Generación de script de carga de pronósticos y carga en plan Sandbox. | G66: \\10.100.25.60\sya\gec\JOSE GABRIEL NASSAR - PORTAFOLIO CASTILLA\0. ENTREGABLES | H66: 10 | I66: 3 | J66: =IFERROR(I66/H66,0) -> 0.3 | K66: =+I66+ENERO!K66 -> 7 | L66: =IFERROR(K66/H66,0) -> 0.7
B67: 3 | C67: 3.16 | D67: Análisis de Declinaciones por pozo y/o subunidad | F67: - Verificación de información de pronósticos y conteo cargado en herramienta de financiera Planning Space. | G67: \\10.100.25.60\sya\gec\JOSE GABRIEL NASSAR - PORTAFOLIO CASTILLA\0. ENTREGABLES | H67: 10 | I67: 4 | J67: =IFERROR(I67/H67,0) -> 0.4 | K67: =+I67+ENERO!K67 -> 7 | L67: =IFERROR(K67/H67,0) -> 0.7
B68: 3 | C68: 3.17 | D68: Analizar data histórica de producción, productividad y daño por pozo | F68: - Realización de conteo de pozos productores, inyectores, CLIA y disposal. - Generación de script de carga de conteo y carga en Plan Sandbox. | G68: \\10.100.25.60\sya\gec\JOSE GABRIEL NASSAR - PORTAFOLIO CASTILLA\0. ENTREGABLES | H68: 10 | I68: 3 | J68: =IFERROR(I68/H68,0) -> 0.3 | K68: =+I68+ENERO!K68 -> 6 | L68: =IFERROR(K68/H68,0) -> 0.6
B69: 3 | C69: 3.18 | D69: Generar perfiles de Producción por pozos para pozos existente en escenarios Bajo, Medio y Alto | F69: Base de Datos - Informe de la Evaluación | G69: \\10.100.25.60\sya\gec\JOSE GABRIEL NASSAR - PORTAFOLIO CASTILLA\0. ENTREGABLES | H69: 10 | I69: 4 | J69: =IFERROR(I69/H69,0) -> 0.4 | K69: =+I69+ENERO!K69 -> 7 | L69: =IFERROR(K69/H69,0) -> 0.7
B70: 5 | C70: 5.2 | D70: Generación de oportunidades de intervención a Pozos | F70: - Explicación de variaciones en las reservas 2024 vs 2025. | G70: \\10.100.25.60\sya\gec\JOSE GABRIEL NASSAR - PORTAFOLIO CASTILLA\0. ENTREGABLES | H70: 10 | I70: 4 | J70: =IFERROR(I70/H70,0) -> 0.4 | K70: =+I70+ENERO!K70 -> 7 | L70: =IFERROR(K70/H70,0) -> 0.7
B71: 5 | C71: 5.9 | D71: Realizar el seguimiento de producción/ inyección de pozos intervenidos con base en los comportamientos de producción previo y posterior a la intervención | F71: - Socialización de escenearios PDI aprobados y certificación con equipo Largo Plazo y Corto Plazo. - Análisis y anticipación de riesgos en proceso de certificación de reservas. | G71: \\10.100.25.60\sya\gec\JOSE GABRIEL NASSAR - PORTAFOLIO CASTILLA\0. ENTREGABLES | H71: 10 | I71: 3 | J71: =IFERROR(I71/H71,0) -> 0.3 | K71: =+I71+ENERO!K71 -> 7 | L71: =IFERROR(K71/H71,0) -> 0.7
B72: 8 | C72: 8.2 | D72: Carga de datos, procesamiento de datos, Análisis Estadístico descriptivo considerando hipótesis desde la teoría, y análisis descriptivo considerando hipótesis generadas desde la misma data (pasos 1, 2 y 3 teoría CRISP-DM). | F72: Informe, con estadísticas descriptivas, histogramas, pruebas de ajuste, etc. | G72: \\10.100.25.60\sya\gec\JOSE GABRIEL NASSAR - PORTAFOLIO CASTILLA\0. ENTREGABLES | H72: 10 | I72: 3 | J72: =IFERROR(I72/H72,0) -> 0.3 | K72: =+I72+ENERO!K72 -> 6 | L72: =IFERROR(K72/H72,0) -> 0.6
B73: 3 | C73: 3.3 | D73: Realice el plan de desarrollo del campo y los pronosticos:la prediccion se basaría en el plan de desarrollo de campo, la ubicación de perforaciones de relleno, el analisis de los patrones, la optimizacion de inyeccion de agua, las tasas de inyeccion óptima y el proceso de recuperacion terciaria (quimica y terminca). Realizar evaluaciones economicas y evaluaciones de cada proceso y presentar la mejor solucion optima. | E73: Carlos Rafael Olmos Carval | F73: Se consolidaron los Qobj, arenas, mandriles y presiones en cabeza de la zona Centro Norte en el archivo Qobj.xlsx. | G73: Qobj.xlsx | H73: 10 | I73: 3 | J73: =IFERROR(I73/H73,0) -> 0.3 | K73: =+I73+ENERO!K73 -> 7 | L73: =IFERROR(K73/H73,0) -> 0.7
B74: 3 | C74: 3.17 | D74: Analizar data histórica de producción, productividad y daño por pozo | F74: Se construyo documento con los perfiles real, fcst y FID para los 3 fluidos del proyecto WF N/S. | G74: PERFILES WF NS.xlsx | H74: 10 | I74: 3 | J74: =IFERROR(I74/H74,0) -> 0.3 | K74: =+I74+ENERO!K74 -> 7 | L74: =IFERROR(K74/H74,0) -> 0.7
B75: 3 | C75: 3.18 | D75: Generar perfiles de Producción por pozos para pozos existente en escenarios Bajo, Medio y Alto | F75: Se realizo la construcción de los archivos .TXT que actualizan la base de datos de molinos de vientos para cada uno de los proyectos del activo. | G75: W:\39. Proyecto_Inyeccion_de_Agua\Planillas Power BI\6. Molinos de Viento\3. Actualizaciones\Cargue Proyectos\Real\2026\Enero\TXT | H75: 10 | I75: 3 | J75: =IFERROR(I75/H75,0) -> 0.3 | K75: =+I75+ENERO!K75 -> 7 | L75: =IFERROR(K75/H75,0) -> 0.7
B76: 5 | C76: 5.2 | D76: Generación de oportunidades de intervención a Pozos | F76: Se ajusto el tablero de capacidad de flujo de Castilla, realizándole cambios de forma necesarios para poder ser publicado en la web del equipo de Monitoreo VRO. | G76: Capacidad_de_flujo_Castilla_WF_Dic2025.pbix | H76: 10 | I76: 4 | J76: =IFERROR(I76/H76,0) -> 0.4 | K76: =+I76+ENERO!K76 -> 7 | L76: =IFERROR(K76/H76,0) -> 0.7
B77: 5 | C77: 5.9 | D77: Realizar el seguimiento de producción/ inyección de pozos intervenidos con base en los comportamientos de producción previo y posterior a la intervención | F77: Se construyeron las diapositivas de seguimiento de revisión de pozos inyectores y productores de la zona Centro Norte con los datos de producción prorrateada de Enero. Estas llevan gráficos de control, mapas de Pwf, RAP y Utilidad. | G77: Seguimiento P&I Ene 2025 Zona Centro Norte (Enero).pptx | H77: 10 | I77: 4 | J77: =IFERROR(I77/H77,0) -> 0.4 | K77: =+I77+ENERO!K77 -> 7 | L77: =IFERROR(K77/H77,0) -> 0.7
B78: 8 | C78: 8.2 | D78: Carga de datos, procesamiento de datos, Análisis Estadístico descriptivo considerando hipótesis desde la teoría, y análisis descriptivo considerando hipótesis generadas desde la misma data (pasos 1, 2 y 3 teoría CRISP-DM). | F78: Se actualizo y ajusto el tablero 2.3_Monitoreo_Secundaria_VRO_Ene_2026. | G78: 2.3_Monitoreo_Secundaria_VRO_Ene_2026.pbix | H78: 10 | I78: 4 | J78: =IFERROR(I78/H78,0) -> 0.4 | K78: =+I78+ENERO!K78 -> 7 | L78: =IFERROR(K78/H78,0) -> 0.7
B79: 8 | C79: 8.3 | D79: Construcción de modelo matemático utilizando las técnicas pertinentes de Ciencia de Datos (e.g. Programación Matemática / Optimización / Investigación de Operaciones, Modelamiento Probabilístico, Machine Learning, etc.), con dominio de conocimiento petrotécnico. Si el modelo es supervisado y no paramétrico, se debe generar el sustento y razonamiento respectivo, arquitectura, calibración de parámetros adecuado, pruebas de validación, generalización, desempeño, etc. La fase de modelamiento debe incluir el razonamiento del modelo y como se relaciona con los modelos petrotécnicos convencionales o actuales, en que difiere y cuál es su innovación en términos de analítica de datos. Lo anterior no indica que tenga que ser un modelo o metodología nueva – e.g. puede ser la aplicación de un modelo existente como el Capacitance Resistance Model (CRM). Etapa 4 y 5 de la metodología CRISP-DM). Los supuestos se deben descomponer en dos: i) del dominio petrotécnico (si la inferencia / deducción es válida, e.g. en el caso del modelo CRM la inferencia procede si la etapa de llenado se ha superado, etc.) y ii) matemáticos / estadísticos, e.g. si se requiere estacionariedad, el error debe ser Gaussiano, etc. | F79: Se realizo revisión y actualización del tablero P50. Se actualizaron los perfiles P50 correspondientes al trienio 2025-2027. Se trabajo en los perfiles de producción de petróleo, agua y agua inyectada. | G79: P50 CASTILLA_2024_V19.pbix | H79: 10 | I79: 3 | J79: =IFERROR(I79/H79,0) -> 0.3 | K79: =+I79+ENERO!K79 -> 6 | L79: =IFERROR(K79/H79,0) -> 0.6
B80: 8 | C80: 8.4 | D80: Análisis de resultados y análisis Estadístico - descriptivo de los resultados obtenidos, así como de las pruebas implementadas. Ejemplificación de la interpretación de resultados y auto-critica de los mismos. Mapeo de conclusiones, recomendaciones y validación de los objetivos con enfoque de valor. Es clave generar nociones para que los resultados puedan ser bien utilizados y/o asociados con otras metodologías. Si procede, se debe validar los resultados con los expertos o dolientes respectivos. Etapa 5 de la metodología CRISP-DM. | F80: Se apoyo con el diligenciamiento de las actas de las reuniones de la zona centro norte en la herramienta WellMeeting, donde se establecen los diagnósticos y acciones a llevar a cabo en cada uno de los pozos analizados en los espacios. | G80: WELLMEETING | H80: 10 | I80: 3 | J80: =IFERROR(I80/H80,0) -> 0.3 | K80: =+I80+ENERO!K80 -> 6 | L80: =IFERROR(K80/H80,0) -> 0.6
B81: 8 | C81: 8.5 | D81: Programación del modelo matemático en las herramientas que se considere más adecuada, e.g. R, Python, SAS, C++, Java, Matlab, Visual, etc. Los scripts deben respetar los planteamientos y consideraciones contenidas en el informe, debe contener buenas prácticas de programación (e.g. comentarios, identación (anglicismo de “identation”), separación por métodos o funciones, etc. – el programa no necesariamente debe estar orientado a objetos y otros paradigmas, e.g. la programación funcional podría ser altamente recomendable). | F81: Se realizó el seguimiento a las optimizaciones, rediseños y WO a ejecutar. La información quedó asegurada en el archivo “Matriz priorizacion incrementos“ y "Priorizacion de acciones GDT_RD-WO-WS" | G81: \\10.100.25.60\sya\gec\Castilla\39. Proyecto_Inyeccion_de_Agua\SAHARA) y en las notas de wellmeeting | H81: 10 | I81: 3 | J81: =IFERROR(I81/H81,0) -> 0.3 | K81: =+I81+ENERO!K81 -> 6 | L81: =IFERROR(K81/H81,0) -> 0.6
B82: 3 | C82: 3.6 | D82: Generar Modelo analítico del yacimiento integrando la información disponible en un software específico | E82: Cesar Eliecer Rodriguez Camelo | F82: Se realizó el seguimiento a las optimizaciones, rediseños y WO a ejecutar. La información quedó asegurada en el archivo “Matriz priorizacion incrementos“ y "Priorizacion de acciones GDT_RD-WO-WS" | G82: \\10.100.25.60\sya\gec\Castilla\39. Proyecto_Inyeccion_de_Agua\SAHARA) y en las notas de wellmeeting | H82: 10 | I82: 3 | J82: =IFERROR(I82/H82,0) -> 0.3 | K82: =+I82+ENERO!K82 -> 7 | L82: =IFERROR(K82/H82,0) -> 0.7
B83: 3 | C83: 3.13 | D83: Generar base de datos de producción (OFM o la que se requiera) | F83: En la herramienta Sahara oficial con corte a Ene/2025, se corrigió y actualizó estado de capa y factores de alocacion pozos CA21, CA222st, CA257. Cargue de data de producción y Presiones dinamicas actualizadas a Feb/26 de zona centro sur. Corrección de topes y registro para CA338 | G83: \\10.100.25.60\sya\gec\Castilla\39. Proyecto_Inyeccion_de_Agua\SAHARA | H83: 10 | I83: 3 | J83: =IFERROR(I83/H83,0) -> 0.3 | K83: =+I83+ENERO!K83 -> 7 | L83: =IFERROR(K83/H83,0) -> 0.7
B84: 3 | C84: 3.14 | D84: Generar Distribución de Producción por sub- unidades (allocation) | F84: Por solicitud de la líder, se diligenciaron los siguientes archivos con la información actualizada del estado de los pozos productores e inyectores del área que tengo en monitoreo: Candidatos rediseños, Rediseños Ejecutados en 2026 por zona. actualización de EM, propiedades petrofísicas y factores de alocación para los diferentes pozos en la BD de SAHARA | G84: DTWF CASTILLA - Tablero Castilla Fan Edition - Todos los documentos \\10.100.25.60\sya\gec\Castilla\39. Proyecto_Inyeccion_de_Agua\SAHARA\BD Sahara | H84: 10 | I84: 3 | J84: =IFERROR(I84/H84,0) -> 0.3 | K84: =+I84+ENERO!K84 -> 7 | L84: =IFERROR(K84/H84,0) -> 0.7
B85: 3 | C85: 3.16 | D85: Análisis de Declinaciones por pozo y/o subunidad | F85: De acuerdo con el seguimiento a la producción e inyección, se realizó el seguimiento a las optimizaciones realizadas en el mes de diciembre de 2025 y enero, febrero de 2026 de acuerdo con el BSW, pruebas de producción y toma de niveles. | G85: \\10.100.25.60\sya\gec\Castilla\39. Proyecto_Inyeccion_de_Agua\SAHARA\BD Sahara | H85: 10 | I85: 4 | J85: =IFERROR(I85/H85,0) -> 0.4 | K85: =+I85+ENERO!K85 -> 6 | L85: =IFERROR(K85/H85,0) -> 0.6
B86: 3 | C86: 3.17 | D86: Analizar data histórica de producción, productividad y daño por pozo | F86: Se llevaron a mesa los pozos CA360H con la finalidad de aprobar oportunidades de WOP. Visualizados pozos con oportunidad de RDG: CA184, CA340, CA119 y CA152H. Ver mayor ampliación en GP-F-25 | G86: https://wellmeeting.ecopetrol.com.co/login | H86: 10 | I86: 3 | J86: =IFERROR(I86/H86,0) -> 0.3 | K86: =+I86+ENERO!K86 -> 6 | L86: =IFERROR(K86/H86,0) -> 0.6
B87: 3 | C87: 3.18 | D87: Generar perfiles de Producción por pozos para pozos existente en escenarios Bajo, Medio y Alto | F87: Se aseguraron los diagnósticos y acciones en wellmeeting por motivos de las revisiones con el equipo multidisciplinario y revisión interna. Ver mayor ampliación en GP-F-25 | G87: https://wellmeeting.ecopetrol.com.co/login GDT Plus (El V.A.R.) - General - Todos los documentos | H87: 10 | I87: 4 | J87: =IFERROR(I87/H87,0) -> 0.4 | K87: =+I87+ENERO!K87 -> 6 | L87: =IFERROR(K87/H87,0) -> 0.6
B88: 5 | C88: 5.2 | D88: Generación de oportunidades de intervención a Pozos | F88: De acuerdo con los rediseños propuestos en el plan de cierre de brechas, se obtuvo una lista de 5 pozos que se requieren optimizar, se irán priorizando de acuerdo con el presupuesto aprobado: CA255, CA309, CA372:K2, CA62, CA187. Se define el apagado de CA593. | G88: teams (Sistemática WF y Gestión de la Básica y en la BD SAHARA (\\10.100.25.60\sya\gec\Castilla\39. Proyecto_Inyeccion_de_Agua\SAHARA) | H88: 10 | I88: 3 | J88: =IFERROR(I88/H88,0) -> 0.3 | K88: =+I88+ENERO!K88 -> 7 | L88: =IFERROR(K88/H88,0) -> 0.7
B89: 5 | C89: 5.9 | D89: Realizar el seguimiento de producción/ inyección de pozos intervenidos con base en los comportamientos de producción previo y posterior a la intervención | F89: Se realizo el seguimiento de producción/ inyección de pozos a cargo (18 patrones de inyección) con base en los comportamientos de producción e inyección entre ellos el ingreso de nuevo inyector CA21. Seguimiento escenarios de CA16 nuevo pozo de conversion. | G89: TEAMS del equipo I&A Castilla (Sistemática WF): https://ecopetrol.sharepoint.com/sites/DTWFCASTILLA/Documentos%20compartidos/Forms/AllItems.aspx?OR=Teams%2DHL&CT=1722020892543&clickparams=eyJBcHBOYW1lIjoiVGVhbXMtRGVza3RvcCIsIkFwcFZlcnNpb24iOiI0OS8yNDA2MjcyNDgxNCIsIkhhc0ZlZGVyYXRlZFVzZXIiOmZhbHNlfQ%3D%3D&id=%2Fsites%2FDTWFCASTILLA%2FDocumentos%20compartidos%2FGeneral&viewid=9ba680aa%2D7c76%2D4823%2Dbaac%2Dba7ef8ef6f87 | H89: 10 | I89: 3 | J89: =IFERROR(I89/H89,0) -> 0.3 | K89: =+I89+ENERO!K89 -> 7 | L89: =IFERROR(K89/H89,0) -> 0.7
B90: 8 | C90: 8.2 | D90: Carga de datos, procesamiento de datos, Análisis Estadístico descriptivo considerando hipótesis desde la teoría, y análisis descriptivo considerando hipótesis generadas desde la misma data (pasos 1, 2 y 3 teoría CRISP-DM). | F90: En cuanto a la herramienta OFM se realizó el cargue de la producción, inyección y pruebas del mes de Diciembre/2025. La información quedó asegurada en el proyecto 05. Proyecto OFM\Archivos Excel\Cargue OFM\2025 | G90: La información quedó asegurada en el proyecto 131. \\10.100.25.60\sya\gec\05. Proyecto OFM\Archivos Excel\Cargue OFM\2025 | H90: 10 | I90: 4 | J90: =IFERROR(I90/H90,0) -> 0.4 | K90: =+I90+ENERO!K90 -> 7 | L90: =IFERROR(K90/H90,0) -> 0.7
B91: 3 | C91: 3.6 | D91: Generar Modelo analítico del yacimiento integrando la información disponible en un software específico | E91: Ana María Castellanos Barreto | F91: Modelo Analítico - Perfiles de Producción - Informe del modelo | G91: \\10.100.25.60\sya\gec | H91: 10 | I91: 4 | J91: =IFERROR(I91/H91,0) -> 0.4 | K91: =+I91+ENERO!K91 -> 8 | L91: =IFERROR(K91/H91,0) -> 0.8
B92: 3 | C92: 3.13 | D92: Generar base de datos de producción (OFM o la que se requiera) | F92: Base de Datos | G92: \\10.100.25.60\sya\gec | H92: 10 | I92: 3 | J92: =IFERROR(I92/H92,0) -> 0.3 | K92: =+I92+ENERO!K92 -> 6 | L92: =IFERROR(K92/H92,0) -> 0.6
B93: 3 | C93: 3.14 | D93: Generar Distribución de Producción por sub- unidades (allocation) | F93: Base de Datos | G93: \\10.100.25.60\sya\gec | H93: 10 | I93: 3 | J93: =IFERROR(I93/H93,0) -> 0.3 | K93: =+I93+ENERO!K93 -> 6 | L93: =IFERROR(K93/H93,0) -> 0.6
B94: 3 | C94: 3.16 | D94: Análisis de Declinaciones por pozo y/o subunidad | F94: Base de Datos - Perfiles Generados - Informe del análisis | G94: https://ecopetrol.sharepoint.com/sites/BDSaharaCastilla/Documentos%20compartidos/Forms/AllItems.aspx?id=%2Fsites%2FBDSaharaCastilla%2FDocumentos%20compartidos%2FBD%20Sahara&viewid=a035cf74%2D0100%2D4f66%2Da914%2D651dfeb02341 | H94: 10 | I94: 3 | J94: =IFERROR(I94/H94,0) -> 0.3 | K94: =+I94+ENERO!K94 -> 6 | L94: =IFERROR(K94/H94,0) -> 0.6
B95: 3 | C95: 3.17 | D95: Analizar data histórica de producción, productividad y daño por pozo | F95: Base de Datos - Informe de la Evaluación | G95: \\10.100.25.60\sya\gec | H95: 10 | I95: 3 | J95: =IFERROR(I95/H95,0) -> 0.3 | K95: =+I95+ENERO!K95 -> 6 | L95: =IFERROR(K95/H95,0) -> 0.6
B96: 3 | C96: 3.18 | D96: Generar perfiles de Producción por pozos para pozos existente en escenarios Bajo, Medio y Alto | F96: Base de Datos - Informe de la Evaluación | G96: \\10.100.25.60\sya\gec Sahara/ Tableros de diagnostico | H96: 10 | I96: 4 | J96: =IFERROR(I96/H96,0) -> 0.4 | K96: =+I96+ENERO!K96 -> 8 | L96: =IFERROR(K96/H96,0) -> 0.8
B97: 5 | C97: 5.2 | D97: Generación de oportunidades de intervención a Pozos | F97: Base de Datos - Informe de la Evaluación | G97: https://wellmeeting.ecopetrol.com.co/home https://ecopetrol.sharepoint.com/sites/CastillaWOs2022/Documentos%20compartidos/Forms/AllItems.aspx | H97: 10 | I97: 3 | J97: =IFERROR(I97/H97,0) -> 0.3 | K97: =+I97+ENERO!K97 -> 6 | L97: =IFERROR(K97/H97,0) -> 0.6
B98: 5 | C98: 5.9 | D98: Realizar el seguimiento de producción/ inyección de pozos intervenidos con base en los comportamientos de producción previo y posterior a la intervención | F98: Base de Datos - Informe de la Evaluación | G98: 2025-04-21 Sahara VyP Castilla.zip https://ecopetrol.sharepoint.com/sites/BDSaharaCastilla/Documentos%20compartidos/Forms/AllItems.aspx?id=%2Fsites%2FBDSaharaCastilla%2FDocumentos%20compartidos%2FPresentaciones%20soporte%20sesiones%2F2025&viewid=a035cf74%2D0100%2D4f66%2Da914%2D651dfeb02341 | H98: 10 | I98: 3 | J98: =IFERROR(I98/H98,0) -> 0.3 | K98: =+I98+ENERO!K98 -> 6 | L98: =IFERROR(K98/H98,0) -> 0.6
B99: 8 | C99: 8.2 | D99: Carga de datos, procesamiento de datos, Análisis Estadístico descriptivo considerando hipótesis desde la teoría, y análisis descriptivo considerando hipótesis generadas desde la misma data (pasos 1, 2 y 3 teoría CRISP-DM). | F99: Informe, con estadísticas descriptivas, histogramas, pruebas de ajuste, etc. | G99: https://app.powerbi.com/singleSignOn?ru=https%3A%2F%2Fapp.powerbi.com%2Fgroups%2Fe5641789-d59d-4f86-b857-9812c65a1a04%2Freports%2Fdff68870-b9fb-4308-960e-6c4f8c41c79d%2FReportSection974a4271511adef5c478%3FnoSignUpCheck%3D1 | H99: 10 | I99: 4 | J99: =IFERROR(I99/H99,0) -> 0.4 | K99: =+I99+ENERO!K99 -> 8 | L99: =IFERROR(K99/H99,0) -> 0.8
B100: 1 | C100: 1.2 | D100: Generación Bases de Datos de Pozos (Registros, Topes e información disponible) | E100: Gloria Fernanda Vidal González | F100: Base de Datos | G100: Digital:M:\39. Proyecto_Inyeccion_de_Agua\Geologia_seguimiento a la inyeccion | H100: 8 | I100: 3 | J100: =IFERROR(I100/H100,0) -> 0.375 | K100: =+I100+ENERO!K100 -> 5 | L100: =IFERROR(K100/H100,0) -> 0.625
...
