Workbook

Sheet ENERO
Q1: MES
B2: REPORTE DE AVANCE | Q2: ENERO
B3: Fecha: 29/06/2022 | F3: Version: 01 | J3: GP-F-23
Q4: FEBRERO
B5: Código Orden de servicio | D5: 90599924 | Q5: MARZO
Q6: ABRIL
B7: Mes a reportar | D7: ENERO | Q7: JULIO
Q8: AGOSTO
B9: Fecha reporte | D9: 46052 | Q9: SEPTIEMBRE
Q10: OCTUBRE
B11: Clasificación del servicio | I11: Reporte mes por servicio | K11: Reporte acumulado por servicio | Q11: NOVIEMBRE
B12: Ítem general | C12: ítem actividad | D12: Descripción de la actividad | E12: Profesional a cargo | F12: Soporte | G12: Medio de entrega | H12: Días contratados | I12: Días | J12: % avance | K12: Días | L12: % avance | Q12: DICIEMBRE
B13: 3 | C13: 3.17 | D13: Analizar data histórica de producción, productividad y daño por pozo | E13: Franklin Alejandro Botero Rivera | F13: Base de Datos Modelo de Balance Informe del modelo | G13: Digital, dbase de datos interna https://ecopetrol.sharepoint.com/sites/CastillaWOs2022/Documentos%20compartidos/Forms/AllItems.aspx?id=%2Fsites%2FCastillaWOs2022%2FDocumentos%20compartidos%2FJustificaciones&viewid=9ecb22f4%2D2d68%2D4a78%2Db78d%2Df5ff342528b5&noAuthRedirect=1 | H13: 33 | I13: 2 | J13: =IFERROR(I13/H13,0) -> 0.060606061 | K13: =I13 -> 2 | L13: =IFERROR(K13/H13,0) -> 0.060606061
B14: 5 | C14: 5.2 | D14: Generación de oportunidades de intervención a Pozos | F14: Base de Datos - Informe de la Evaluación | G14: Digital, Email a todos los de castilla-sharepoint, desarrollo ing, planeacion https://ecopetrol.sharepoint.com/sites/CastillaWOs2022/Documentos%20compartidos/Forms/AllItems.aspx?id=%2Fsites%2FCastillaWOs2022%2FDocumentos%20compartidos%2FJustificaciones&viewid=9ecb22f4%2D2d68%2D4a78%2Db78d%2Df5ff342528b5&noAuthRedirect=1 | H14: 32 | I14: 3 | J14: =IFERROR(I14/H14,0) -> 0.09375 | K14: =I14 -> 3 | L14: =IFERROR(K14/H14,0) -> 0.09375
B15: 5 | C15: 5.5 | D15: Adelantar la evaluación e interpretación de datos enfocada a candidatización de actividades de reacondicionamiento y optimización de productividad en los activos | F15: Base de Datos Informe de la Evaluación | G15: Digital, base de datos interna https://ecopetrol.sharepoint.com/sites/comunidadesdepracticaECP/EstimPozos/GDFE/Forms/AllItems.aspx?csf=1&web=1&e=Mm2usV&cid=a85ef813%2Dc5d9%2D4601%2Dbdf8%2Ddd5fa9d6a721&FolderCTID=0x01200095C6E94CFEA613409C4EA4FF99FD008C&id=%2Fsites%2FcomunidadesdepracticaECP%2FEstimPozos%2FGDFE%2FBarriles%2F2024&viewid=71ccfd21%2D31af%2D497c%2Dbcc1%2D9e157842de62 | H15: 32 | I15: 3 | J15: =IFERROR(I15/H15,0) -> 0.09375 | K15: =I15 -> 3 | L15: =IFERROR(K15/H15,0) -> 0.09375
B16: 5 | C16: 5.6 | D16: Generar los análisis asociados a candidatización de pozos para optimización de la producción empleando simulación numérica (análisis nodal) de productividad de pozos | F16: Base de Datos Informe de la Evaluación | G16: Digita Nodal IFDMl https://ifdm-ecp.co/auth/login | H16: 32 | I16: 1 | J16: =IFERROR(I16/H16,0) -> 0.03125 | K16: =I16 -> 1 | L16: =IFERROR(K16/H16,0) -> 0.03125
B17: 5 | C17: 5.7 | D17: Generar reportes de soporte en la ejecución de trabajos ejecutados, tales como estimulaciones, fracturamientos hidráulicos, recañoneos, entre otros. | F17: Base de Datos Informe de la Evaluación | G17: Digital, PJR post jobs reports en repositorio https://ecopetrol.sharepoint.com/sites/comunidadesdepracticaECP/EstimPozos/GDFE/Forms/AllItems.aspx?csf=1&web=1&e=Mm2usV&cid=a85ef813%2Dc5d9%2D4601%2Dbdf8%2Ddd5fa9d6a721&FolderCTID=0x01200095C6E94CFEA613409C4EA4FF99FD008C&id=%2Fsites%2FcomunidadesdepracticaECP%2FEstimPozos%2FGDFE%2FBarriles%2F2024&viewid=71ccfd21%2D31af%2D497c%2Dbcc1%2D9e157842de62 | H17: 32 | I17: 2 | J17: =IFERROR(I17/H17,0) -> 0.0625 | K17: =I17 -> 2 | L17: =IFERROR(K17/H17,0) -> 0.0625
B18: 5 | C18: 5.8 | D18: Generar reportes de evaluación de los tratamientos de estimulación y optimización de producción implementados en la vigencia respectiva | F18: Base de Datos Informe de la Evaluación | G18: Digital PJR post jobs analisis en repositorio https://ecopetrol.sharepoint.com/sites/comunidadesdepracticaECP/EstimPozos/GDFE/Forms/AllItems.aspx?csf=1&web=1&e=Mm2usV&cid=a85ef813%2Dc5d9%2D4601%2Dbdf8%2Ddd5fa9d6a721&FolderCTID=0x01200095C6E94CFEA613409C4EA4FF99FD008C&id=%2Fsites%2FcomunidadesdepracticaECP%2FEstimPozos%2FGDFE%2FBarriles%2F2024&viewid=71ccfd21%2D31af%2D497c%2Dbcc1%2D9e157842de62 | H18: 32 | I18: 2 | J18: =IFERROR(I18/H18,0) -> 0.0625 | K18: =I18 -> 2 | L18: =IFERROR(K18/H18,0) -> 0.0625
B19: 5 | C19: 5.9 | D19: Realizar el seguimiento de producción/ inyección de pozos intervenidos con base en los comportamientos de producción previo y posterior a la intervención | F19: Base de Datos Informe de la Evaluación | G19: Digital, MER (grupo de productividad) https://ecopetrol.sharepoint.com/sites/comunidadesdepracticaECP/EstimPozos/GDFE/Forms/AllItems.aspx?csf=1&web=1&e=Mm2usV&cid=a85ef813%2Dc5d9%2D4601%2Dbdf8%2Ddd5fa9d6a721&FolderCTID=0x01200095C6E94CFEA613409C4EA4FF99FD008C&id=%2Fsites%2FcomunidadesdepracticaECP%2FEstimPozos%2FGDFE%2FBarriles&viewid=71ccfd21%2D31af%2D497c%2Dbcc1%2D9e157842de62 | H19: 32 | I19: 2 | J19: =IFERROR(I19/H19,0) -> 0.0625 | K19: =I19 -> 2 | L19: =IFERROR(K19/H19,0) -> 0.0625
B20: 3 | C20: 3.17 | D20: Analizar data histórica de producción, productividad y daño por pozo | E20: Maria Alejandra Giraldo Muñoz | F20: Análisis de delta de presión en ingreso de nanofluidos en pozos productores del campo Apiay y Suria de la gerencia GDA | G20: C:\Users\C1017211\OneDrive - Ecopetrol S.A\Documentos | H20: 32 | I20: 3 | J20: =IFERROR(I20/H20,0) -> 0.09375 | K20: =I20 -> 3 | L20: =IFERROR(K20/H20,0) -> 0.09375
B21: 5 | C21: 5.2 | D21: Generación de oportunidades de intervención a Pozos | F21: Consolidación de plan de operaciones de estimulación y fractura para el año 2026, con el fin de determinar la actividad proyectada en pro de sostener la productividad de la compañía | G21: C:\Users\C1017211\OneDrive - Ecopetrol S.A\Documentos\CP Estimulación de Pozos - GDFE\Barriles\2026 | H21: 32 | I21: 3 | J21: =IFERROR(I21/H21,0) -> 0.09375 | K21: =I21 -> 3 | L21: =IFERROR(K21/H21,0) -> 0.09375
B22: 5 | C22: 5.5 | D22: Adelantar la evaluación e interpretación de pozos ac | F22: Revisión de candidatización de pozos en las genrecias GCL, GDA y GCH y caracterización de daño y estimulación matricial en VRO | G22: https://ecopetrol.sharepoint.com/sites/comunidadesdepracticaECP/EstimPozos/GDFE | H22: 32 | I22: 3 | J22: =IFERROR(I22/H22,0) -> 0.09375 | K22: =I22 -> 3 | L22: =IFERROR(K22/H22,0) -> 0.09375
B23: 5 | C23: 5.6 | D23: Generar los análisis asociados a candidatización de pozos para optimización de la producción empleando simulación numérica (análisis nodal) de productividad de pozos | F23: Confirmación de operaciones y trenes de evaluación Revisión de data para análisis nodal de los pozos de la campaña MaxPro a implementar en el año 2026 | G23: C:\Users\C1017211\OneDrive - Ecopetrol S.A\Documentos\CP Estimulación de Pozos - GDFE | H23: 32 | I23: 1 | J23: =IFERROR(I23/H23,0) -> 0.03125 | K23: =I23 -> 1 | L23: =IFERROR(K23/H23,0) -> 0.03125
B24: 5 | C24: 5.7 | D24: Generar reportes de soporte en la ejecución de trabajos ejecutados, tales como estimulaciones, fracturamientos hidráulicos, recañoneos, entre otros. | F24: Revisión y consolidación de programas operativos de estimulación matricial, con sus respectivos informes de laboratorio y aseguramiento de operación | G24: C:\Users\C1017211\OneDrive - Ecopetrol S.A\Documentos\CP Estimulación de Pozos - GDFE | H24: 32 | I24: 2 | J24: =IFERROR(I24/H24,0) -> 0.0625 | K24: =I24 -> 2 | L24: =IFERROR(K24/H24,0) -> 0.0625
B25: 5 | C25: 5.8 | D25: Generar reportes de evaluación de los tratamientos de estimulación y optimización de producción implementados en la vigencia respectiva | F25: Revisión y consolidación de reportes finales de intervenciones de estimulación matricial y fracturamiento hidráulico de pozos en las gerencias GCL, GDA y GCH | G25: C:\Users\C1017211\OneDrive - Ecopetrol S.A\Documentos\CP Estimulación de Pozos - GDFE | H25: 32 | I25: 2 | J25: =IFERROR(I25/H25,0) -> 0.0625 | K25: =I25 -> 2 | L25: =IFERROR(K25/H25,0) -> 0.0625
B26: 5 | C26: 5.9 | D26: Realizar el seguimiento de producción/ inyección de pozos intervenidos con base en los comportamientos de producción previo y posterior a la intervención | F26: Seguimiento y actualización de la producción incremental de los pozos estimulados y/o fracturados en las gerencias GLC, GDA, GCH para la vigencia 2025 en el archivo Campaña MER 2026. | G26: "C:\Users\C1017211\OneDrive - Ecopetrol S.A\Documentos\CP Estimulación de Pozos - GDFE\Barriles\2026\Campaña_MER_2026.xlsm" | H26: 33 | I26: 1 | J26: =IFERROR(I26/H26,0) -> 0.03030303 | K26: =I26 -> 1 | L26: =IFERROR(K26/H26,0) -> 0.03030303
B27: 5 | C27: 5.1 | D27: Generar bases de datos de Eventos de pozos | E27: Javier Enrique Guerrero Arrieta | F27: - | G27: - | H27: 15 | I27: 0 | J27: =IFERROR(I27/H27,0) -> 0 | K27: =I27 -> 0 | L27: =IFERROR(K27/H27,0) -> 0
B28: 5 | C28: 5.2 | D28: Generación de oportunidades de intervención a Pozos | F28: Base de Datos - Informe de la Evaluación | G28: Digital | H28: 15 | I28: 5 | J28: =IFERROR(I28/H28,0) -> 0.33333333 | K28: =I28 -> 5 | L28: =IFERROR(K28/H28,0) -> 0.33333333
B29: 5 | C29: 5.3 | D29: Estimar restricciones de Presión y tasas para la generacion | F29: - | G29: - | H29: 15 | I29: 0 | J29: =IFERROR(I29/H29,0) -> 0 | K29: =I29 -> 0 | L29: =IFERROR(K29/H29,0) -> 0
B30: 5 | C30: 5.4 | D30: Generar modelo de Pozos | F30: - | G30: - | H30: 15 | I30: 0 | J30: =IFERROR(I30/H30,0) -> 0 | K30: =I30 -> 0 | L30: =IFERROR(K30/H30,0) -> 0
B31: 5 | C31: 5.5 | D31: Adelantar la evaluación e interpretación de datos | F31: Base de Datos - Informe de la Evaluación | G31: Digital | H31: 15 | I31: 7 | J31: =IFERROR(I31/H31,0) -> 0.46666667 | K31: =I31 -> 7 | L31: =IFERROR(K31/H31,0) -> 0.46666667
B32: 5 | C32: 5.6 | D32: Generar los análisis asociados a candidatización de pozos para optimización de la producción empleando simulación numérica (análisis nodal) de productividad de pozos | F32: Base de Datos - Informe de la Evaluación | G32: Digital | H32: 15 | I32: 3 | J32: =IFERROR(I32/H32,0) -> 0.2 | K32: =I32 -> 3 | L32: =IFERROR(K32/H32,0) -> 0.2
B33: 5 | C33: 5.7 | D33: Generar reportes de soporte en la ejecución de trabajos ejecutados, tales como estimulaciones, fracturamientos hidráulicos, recañoneos, entre otros. | F33: - | G33: - | H33: 15 | I33: 0 | J33: =IFERROR(I33/H33,0) -> 0 | K33: =I33 -> 0 | L33: =IFERROR(K33/H33,0) -> 0
B34: 5 | C34: 5.8 | D34: Generar reportes de evaluación de los tratamientos de estimulación y optimización de producción implementados en la vigencia respectiva | F34: - | G34: - | H34: 15 | I34: 0 | J34: =IFERROR(I34/H34,0) -> 0 | K34: =I34 -> 0 | L34: =IFERROR(K34/H34,0) -> 0
B35: 5 | C35: 5.9 | D35: Realizar el seguimiento de producción/ inyección de pozos intervenidos con base en los comportamientos de producción previo y posterior a la intervención | F35: - | G35: - | H35: 15 | I35: 0 | J35: =IFERROR(I35/H35,0) -> 0 | K35: =I35 -> 0 | L35: =IFERROR(K35/H35,0) -> 0
B36: 5 | C36: 5.10 | D36: Adelantar en análisis y evaluación de datos enfocada a la ejecución de estudios de daño de formación | F36: - | G36: - | H36: 15 | I36: 0 | J36: =IFERROR(I36/H36,0) -> 0 | K36: =I36 -> 0 | L36: =IFERROR(K36/H36,0) -> 0
B37: 5 | C37: 5.11 | D37: Generar los análisis asociados a la ejecución de estudios de daño de formación empleando simulación numérica (análisis nodal y single well model, análisis de aguas, análisis de crudos, entre otros) | F37: - | G37: - | H37: 15 | I37: 0 | J37: =IFERROR(I37/H37,0) -> 0 | K37: =I37 -> 0 | L37: =IFERROR(K37/H37,0) -> 0
B38: 7 | C38: 7.1 | D38: Evaluar el estatus de las facilidades (Operatividad) y | F38: - | G38: - | H38: 15 | I38: 0 | J38: =IFERROR(I38/H38,0) -> 0 | K38: =I38 -> 0 | L38: =IFERROR(K38/H38,0) -> 0
B39: 7 | C39: 7.2 | D39: Evaluar la Integridad de las facilidades existentes | F39: - | G39: - | H39: 15 | I39: 0 | J39: =IFERROR(I39/H39,0) -> 0 | K39: =I39 -> 0 | L39: =IFERROR(K39/H39,0) -> 0
... B41: 8 | C41: 8.4 | D41: Análisis de resultados y análisis Estadístico - descriptivo de | F41: - | G41: - | H41: 15 | I41: 0 | J41: =IFERROR(I41/H41,0) -> 0 | K41: =I41 -> 0 | L41: =IFERROR(K41/H41,0) -> 0
B42: 3 | C42: 3.10 | D42: Control de calidad del dato adquirido para valorar representatividad de la prueba en cuestión. De ser válidas, levantamiento de información de entrada para análisis e interpretación (registros de desviación, estado mecánico de cada pozo, caliper/bit size ("), espesor neto (pies TVD), porosidad media (phi), Sw, PVT, producciones asociadas, corte de agua, salinidades, mapa estructural, etc. | E42: Daniela Molina Landinez | F42: Inventario - Informe de | G42: Digital | H42: 37 | I42: 1 | J42: =IFERROR(I42/H42,0) -> 0.027027027 | K42: =I42 -> 1 | L42: =IFERROR(K42/H42,0) -> 0.027027027
B43: 3 | C43: 3.16 | D43: Análisis de Declinaciones por pozo y/o subunidad | F43: Base de Datos - Perfiles | G43: Digital | H43: 37 | I43: 2 | J43: =IFERROR(I43/H43,0) -> 0.054054054 | K43: =I43 -> 2 | L43: =IFERROR(K43/H43,0) -> 0.054054054
B44: 3 | C44: 3.17 | D44: Analizar data histórica de producción, productividad y daño por pozo | F44: Base de Datos - Informe de | G44: Digital | H44: 37 | I44: 2 | J44: =IFERROR(I44/H44,0) -> 0.054054054 | K44: =I44 -> 2 | L44: =IFERROR(K44/H44,0) -> 0.054054054
B45: 3 | C45: 3.18 | D45: Generar perfiles de Producción por pozos para pozos existente en escenarios Bajo, Medio y Alto | F45: Base de Datos - Informe de | G45: Digital | H45: 38 | I45: 4 | J45: =IFERROR(I45/H45,0) -> 0.10526316 | K45: =I45 -> 4 | L45: =IFERROR(K45/H45,0) -> 0.10526316
B46: 5 | C46: 5.9 | D46: Realizar el seguimiento de producción/ inyección de pozos intervenidos con base en los comportamientos de producción previo y posterior a la intervención | F46: Base de Datos - Informe d | G46: Digital | H46: 38 | I46: 3 | J46: =IFERROR(I46/H46,0) -> 0.078947368 | K46: =I46 -> 3 | L46: =IFERROR(K46/H46,0) -> 0.078947368
B47: 5 | C47: 5.10 | D47: Adelantar en análisis y evaluación de datos enfocada a la ejecución de estudios de daño de formación | F47: Base de Datos - Informe d | G47: Digital | H47: 38 | I47: 3 | J47: =IFERROR(I47/H47,0) -> 0.078947368 | K47: =I47 -> 3 | L47: =IFERROR(K47/H47,0) -> 0.078947368
B48: 3 | C48: 3.10 | D48: Control de calidad del dato adquirido para valorar representatividad de la prueba en cuestión. De ser válidas, levantamiento de información de entrada para análisis e interpretación (registros de desviación, estado mecánico de cada pozo, caliper/bit size ("), espesor neto (pies TVD), porosidad media (phi), Sw, PVT, producciones asociadas, corte de agua, salinidades, mapa estructural, etc. | E48: Alexandra Katherine Londoño Camacho | F48: Inventario - Informe de | G48: Digital | H48: 38 | I48: 5 | J48: =IFERROR(I48/H48,0) -> 0.13157895 | K48: =I48 -> 5 | L48: =IFERROR(K48/H48,0) -> 0.13157895
B49: 3 | C49: 3.16 | D49: Análisis de Declinaciones por pozo y/o subunidad | F49: Base de Datos - Perfiles | G49: Digital | H49: 38 | I49: 2 | J49: =IFERROR(I49/H49,0) -> 0.052631579 | K49: =I49 -> 2 | L49: =IFERROR(K49/H49,0) -> 0.052631579
B50: 3 | C50: 3.17 | D50: Analizar data histórica de producción, productividad y daño por pozo | F50: Base de Datos - Informe de | G50: Digital | H50: 38 | I50: 1 | J50: =IFERROR(I50/H50,0) -> 0.026315789 | K50: =I50 -> 1 | L50: =IFERROR(K50/H50,0) -> 0.026315789
B51: 3 | C51: 3.18 | D51: Generar perfiles de Producción por pozos para pozos existente en escenarios Bajo, Medio y Alto | F51: Base de Datos - Informe de | G51: Digital | H51: 37 | I51: 1 | J51: =IFERROR(I51/H51,0) -> 0.027027027 | K51: =I51 -> 1 | L51: =IFERROR(K51/H51,0) -> 0.027027027
B52: 5 | C52: 5.9 | D52: Realizar el seguimiento de producción/ inyección de pozos intervenidos con base en los comportamientos de producción previo y posterior a la intervención | F52: Base de Datos - Informe d | G52: Digital | H52: 37 | I52: 1 | J52: =IFERROR(I52/H52,0) -> 0.027027027 | K52: =I52 -> 1 | L52: =IFERROR(K52/H52,0) -> 0.027027027
B53: 5 | C53: 5.10 | D53: Adelantar en análisis y evaluación de datos enfocada a la ejecución de estudios de daño de formación | F53: Base de Datos - Informe d | G53: Digital | H53: 37 | I53: 5 | J53: =IFERROR(I53/H53,0) -> 0.13513514 | K53: =I53 -> 5 | L53: =IFERROR(K53/H53,0) -> 0.13513514
B54: 3 | C54: 3.10 | D54: Control de calidad del dato adquirido para valorar representatividad de la prueba en cuestión. De ser válidas, levantamiento de información de entrada para análisis e interpretación (registros de desviación, estado mecánico de cada pozo, caliper/bit size ("), espesor neto (pies TVD), porosidad media (phi), Sw, PVT, producciones asociadas, corte de agua, salinidades, mapa estructural, etc. | E54: Por confirmar | F54: - | G54: - | H54: =[1]ENERO!G54 -> 0 | I54: 0 | J54: =IFERROR(I54/H54,0) -> 0 | K54: =I54+[1]NOVIEMBRE!J54 -> 0 | L54: =IFERROR(K54/H54,0) -> 0
B55: 3 | C55: 3.17 | D55: Analizar data histórica de producción, productividad y daño por pozo | F55: - | G55: - | H55: =[1]ENERO!G55 -> 0 | I55: 0 | J55: =IFERROR(I55/H55,0) -> 0 | K55: =I55+[1]NOVIEMBRE!J55 -> 0 | L55: =IFERROR(K55/H55,0) -> 0
B56: 5 | C56: 5.1 | D56: Generar bases de datos de Eventos de pozos | F56: - | G56: - | H56: =[1]ENERO!G56 -> 0 | I56: 0 | J56: =IFERROR(I56/H56,0) -> 0 | K56: =I56+[1]NOVIEMBRE!J56 -> 0 | L56: =IFERROR(K56/H56,0) -> 0
B57: 5 | C57: 5.7 | D57: Generar reportes de soporte en la ejecución de trabajos ejecutados, tales como estimulaciones, fracturamientos hidráulicos, recañoneos, entre otros. | F57: - | G57: - | H57: =[1]ENERO!G57 -> 0 | I57: 0 | J57: =IFERROR(I57/H57,0) -> 0 | K57: =I57+[1]NOVIEMBRE!J57 -> 0 | L57: =IFERROR(K57/H57,0) -> 0
B58: 5 | C58: 5.11 | D58: Generar los análisis asociados a la ejecución de estudios de daño de formación empleando simulación numérica (análisis nodal y single well model, análisis de aguas, análisis de crudos, entre otros) | F58: - | G58: - | H58: =[1]ENERO!G58 -> 0 | I58: 0 | J58: =IFERROR(I58/H58,0) -> 0 | K58: =I58+[1]NOVIEMBRE!J58 -> 0 | L58: =IFERROR(K58/H58,0) -> 0
B59: 3 | C59: 3.11 | D59: Análisis e interpretación de datos de pruebas de presión-producción (DSTs, PBU, Pruebas Extendidas Producción, Gradientes Estáticos- Dinámicos PT, etc.) o de presión inyección (Inyectividad, SRT, FOT) aplicadas ya sea en tiempo real, memorizadas o con sarta temporal DST. Integración Probador Formación - Registros Open Hole. | E59: Lenin Cordoba Rivas | F59: Informe del análisis por pozo o prueba | G59: Digital | H59: 225 | I59: 15 | J59: =IFERROR(I59/H59,0) -> 0.066666667 | K59: =I59 -> 15 | L59: =IFERROR(K59/H59,0) -> 0.066666667
B60: 1 | C60: 1.2 | D60: Generación Bases de Datos de Pozos (Registros, Topes e información disponible). | E60: Jesus Ernesto Coqueco Vargas | F60: Base de datos en Excel. Organización de carpetas en la nube (onedrive) | G60: Todos los conceptos, interpretaciones, análisis y estudios son enviados a través de Correo electrónico a las diferentes áreas interesadas y son guardados en la siguiente carpeta de OneDrive Dominio Ecopetrol perteneciente al Lider Técnico Alexander Castro: https://ecopetrol-my.sharepoint.com/:f:/r/personal/alexander_castroch_ecopetrol_com_co/Documents/ALEX/Registros?csf=1&web=1&e=tP4gfr | H60: 15 | I60: 1 | J60: =IFERROR(I60/H60,0) -> 0.066666667 | K60: =I60 -> 1 | L60: =IFERROR(K60/H60,0) -> 0.066666667
B61: 3 | C61: 3.8 | D61: Validación y estudio de presiones (Pre-Test) adquiridos a través de probadores de formación. | F61: Presentación con concepto técnico | G61: Todos los conceptos, interpretaciones, análisis y estudios son enviados a través de Correo electrónico a las diferentes áreas interesadas y son guardados en la siguiente carpeta de OneDrive Dominio Ecopetrol perteneciente al Lider Técnico Alexander Castro: https://ecopetrol-my.sharepoint.com/:f:/r/personal/alexander_castroch_ecopetrol_com_co/Documents/ALEX/Registros?csf=1&web=1&e=tP4gfr | H61: 15 | I61: 1 | J61: =IFERROR(I61/H61,0) -> 0.066666667 | K61: =I61 -> 1 | L61: =IFERROR(K61/H61,0) -> 0.066666667
B62: 3 | C62: 3.9 | D62: Inventario y acceso a raw data de cada prueba de presión-producción o de presión inyección asociada incluyendo sensores involucrados (main+backup) así como job log de cada prueba donde se especifique, a parte de la secuencia operativa, fecha exacta de inicio de prueba (ddmm-yy hh:mm:ss), tipo de sensores empleados, profundidad de lectura tanto MD/TVD. | F62: Base de datos en Excel. Organización de carpetas en la nube (onedrive) | G62: Todos los conceptos, interpretaciones, análisis y estudios son enviados a través de Correo electrónico a las diferentes áreas interesadas y son guardados en la siguiente carpeta de OneDrive Dominio Ecopetrol perteneciente al Lider Técnico Alexander Castro: https://ecopetrol-my.sharepoint.com/:f:/r/personal/alexander_castroch_ecopetrol_com_co/Documents/ALEX/Registros?csf=1&web=1&e=tP4gfr | H62: 30 | I62: 2 | J62: =IFERROR(I62/H62,0) -> 0.066666667 | K62: =I62 -> 2 | L62: =IFERROR(K62/H62,0) -> 0.066666667
B63: 3 | C63: 3.11 | D63: Análisis e interpretación de datos de pruebas de presión-producción (DSTs, PBU, Pruebas Extendidas Producción, Gradientes Estáticos- Dinámicos PT, etc.) o de presión inyección (Inyectividad, SRT, FOT) aplicadas ya sea en tiempo real, memorizadas o con sarta temporal DST. Integración Probador Formación - Registros Open Hole. | F63: Presentación con concepto técnico y presentación via teams ante el personal interesado | G63: Todos los conceptos, interpretaciones, análisis y estudios son enviados a través de Correo electrónico a las diferentes áreas interesadas y son guardados en la siguiente carpeta de OneDrive Dominio Ecopetrol perteneciente al Lider Técnico Alexander Castro: https://ecopetrol-my.sharepoint.com/:f:/r/personal/alexander_castroch_ecopetrol_com_co/Documents/ALEX/Registros?csf=1&web=1&e=tP4gfr | H63: 35 | I63: 2 | J63: =IFERROR(I63/H63,0) -> 0.057142857 | K63: =I63 -> 2 | L63: =IFERROR(K63/H63,0) -> 0.057142857
B64: 3 | C64: 3.12 | D64: Generar Modelo de Presiones partiendo de las pruebas previamente validadas e interpretadas | F64: Modelo del sector | G64: Todos los conceptos, interpretaciones, análisis y estudios son enviados a través de Correo electrónico a las diferentes áreas interesadas y son guardados en la siguiente carpeta de OneDrive Dominio Ecopetrol perteneciente al Lider Técnico Alexander Castro: https://ecopetrol-my.sharepoint.com/:f:/r/personal/alexander_castroch_ecopetrol_com_co/Documents/ALEX/Registros?csf=1&web=1&e=tP4gfr | H64: 30 | I64: 2 | J64: =IFERROR(I64/H64,0) -> 0.066666667 | K64: =I64 -> 2 | L64: =IFERROR(K64/H64,0) -> 0.066666667
B65: 5 | C65: 5.5 | D65: Adelantar la evaluación e interpretación de datos enfocada a candidatización de actividades de reacondicionamiento y optimización de productividad en los activos | F65: Base de Datos Informe de la Evaluación | G65: Todos los conceptos, interpretaciones, análisis y estudios son enviados a través de Correo electrónico a las diferentes áreas interesadas y son guardados en la siguiente carpeta de OneDrive Dominio Ecopetrol perteneciente al Lider Técnico Alexander Castro: https://ecopetrol-my.sharepoint.com/:f:/r/personal/alexander_castroch_ecopetrol_com_co/Documents/ALEX/Registros?csf=1&web=1&e=tP4gfr | H65: 30 | I65: 2 | J65: =IFERROR(I65/H65,0) -> 0.066666667 | K65: =I65 -> 2 | L65: =IFERROR(K65/H65,0) -> 0.066666667
B66: 5 | C66: 5.6 | D66: Generar los análisis asociados a candidatización de pozos para optimización de la producción empleando simulación numérica (análisis nodal) de productividad de pozos | F66: Base de Datos Informe de la Evaluación | G66: Todos los conceptos, interpretaciones, análisis y estudios son enviados a través de Correo electrónico a las diferentes áreas interesadas y son guardados en la siguiente carpeta de OneDrive Dominio Ecopetrol perteneciente al Lider Técnico Alexander Castro: https://ecopetrol-my.sharepoint.com/:f:/r/personal/alexander_castroch_ecopetrol_com_co/Documents/ALEX/Registros?csf=1&web=1&e=tP4gfr | H66: 35 | I66: 3 | J66: =IFERROR(I66/H66,0) -> 0.085714286 | K66: =I66 -> 3 | L66: =IFERROR(K66/H66,0) -> 0.085714286
B67: 5 | C67: 5.7 | D67: Generar reportes de soporte en la ejecución de trabajos ejecutados, tales como estimulaciones, fracturamientos hidráulicos, recañoneos, entre otros. | F67: Base de Datos, presentaciones, informes con conceptos técnicos | G67: Todos los conceptos, interpretaciones, análisis y estudios son enviados a través de Correo electrónico a las diferentes áreas interesadas y son guardados en la siguiente carpeta de OneDrive Dominio Ecopetrol perteneciente al Lider Técnico Alexander Castro: https://ecopetrol-my.sharepoint.com/:f:/r/personal/alexander_castroch_ecopetrol_com_co/Documents/ALEX/Registros?csf=1&web=1&e=tP4gfr | H67: 35 | I67: 2 | J67: =IFERROR(I67/H67,0) -> 0.057142857 | K67: =I67 -> 2 | L67: =IFERROR(K67/H67,0) -> 0.057142857
H68: =+CONCATENATE("TOTAL A ",D7) -> TOTAL A ENERO | K68: TOTAL ACUMULADO
H69: =+SUM(H13:H67) -> 1575 | I69: =+SUM(I13:I67) -> 105 | J69: =IFERROR(I69/H69,0) -> 0.066666667 | K69: =+SUM(K13:K67) -> 105 | L69: =IFERROR(K69/H69,0) -> 0.066666667
B71: Observaciones: | D71: 3,1 3,16 3,17 3,18 5,9 5,10 Junior (DM) Ajustes de sector model en REVEAL para escenarios de eficiencia de tratamientos de nano para control de arena en los pozos de Vigía sur. Inicio de recopilación y organización de información para generar un sector model en REVEAL para generar un análisis del pozo K2 GC562_9_BP01, tuvo un problema de arenamiento y necesita comprensión del efecto de la generación y transporte de arena. Se prepara presentación para definir el objetivo y alcance del análisis K2 GC562_9_BP01 Sanding Incident con ECP America Soporte en reuniones sistemáticas multidisciplinarias jueves de piloto en el campo GCH.
D72: 3.17 5.2 5.5 5.6 5.7 5.8 5.9 Senior (MG): Se reportan 15 días del mes de enero, con incio de contrato el día 16 de enero de 2026 y # Contrato 90599924
D73: 5,1 5,2 5,3 5,4 5,5 5,6 5,7 5,8 5,9 5,1 5,11 7,1 7,2 7,3 8,4 Senior (JG):
D74: 3,10 3,16 3,17 3,18 5,9 5,1 Junior (DM):
D75: 3,10 3,16 3,17 3,18 5,9 5,1 Junior (AL):
D76: 3.10 3.17 5.1 5.7 5.11 Senior ():
D77: 3.11 Junior (LC): Inicio de contrato laboral desde el 16 de enero. Por motivos de la descativación de cuenta realizada en diciembre, fue necesario habilitar accesos a cuentas de red, correos, teams,onedrive, etc. Este proceso fue un poco confuso y tomó alrededor de una semana.
D78: 1.2 3.8 3.9 3.11 3.12 5.5 5.6 5.7 Senior (JC): * Se realizó evaluación de 3 registros de calidad de cemento, en diferentes campos de diferentes vicepresidencias (CASTILLA, CASABE, PIEDEMONTE), usando el software Emeraude y aplicativo propio diseñado en Python. * Se discutió a través de reuniones virtuales las intervenciones a diferentes pozos, en los campos CASTILLA, LLANITO, APIAY, entre otros. Se brindaron las recomendaciones técnicas pertinentes. * Se prestó apoyo en la realización de los Templates en el Software Emeraude versión 5.60.01, para agilizar el proceso de cargue de los pozos. Se logró una reducción significativa en los tiempos de respuesta gracias al uso de dichos templates. * La implementación de código de uso libre en Python permitió superar desafíos en el análisis de datos y la interpretación de registros, contribuyendo de manera clave al cumplimiento de los objetivos propuestos. * Todos los conceptos, interpretaciones, análisis y estudios son enviados a través de Correo electrónico a las diferentes áreas interesadas y son guardados en la siguiente carpeta de OneDrive Dominio Ecopetrol perteneciente al Líder Técnico Alexander Castro. En el formato GP-F-25 (Sección 2, descripción y/o resultados) se detalla pozo a pozo la ubicación de los archivos dentro de la nube: https://ecopetrol-my.sharepoint.com/:f:/r/personal/alexander_castroch_ecopetrol_com_co/Documents/ALEX/Registros?csf=1&web=1&e=tP4gfr
B79: ¿Se presentó algún aspecto o situación que afecte la ejecución y calidad de los entregables? (Marque con una X)
B81: PROFESIONAL
B82: SI | D82: Describa en este espacio su observación
B83: NO | C83: X
B84: ¿Se presentó algún aspecto o situación que afecte la ejecución y calidad de los entregables? (Marque con una X)
B86: INTERVENTOR O LIDER
B87: SI | D87: Describa en este espacio su observación
B88: NO
B91: Italo Bahamon
B92: Revisa: | H92: Interventor: | I92: Richard Disney Zabala Romero
A124: MES
A125: ENERO
A126: FEBRERO
A127: MARZO
A128: ABRIL
A129: MAYO
A130: JUNIO
A131: JULIO
A132: AGOSTO
A133: SEPTIEMBRE
A134: OCTUBRE
A135: NOVIEMBRE
A136: DICIEMBRE

Sheet FEBRERO
Q1: MES
B2: REPORTE DE AVANCE | Q2: ENERO
B3: Fecha: 29/06/2022 | F3: Version: 01 | J3: GP-F-23
Q4: FEBRERO
B5: Código Orden de servicio | D5: 90599924 | Q5: MARZO
Q6: ABRIL
B7: Mes a reportar | D7: FEBRERO | Q7: JULIO
Q8: AGOSTO
B9: Fecha reporte | D9: 46081 | Q9: SEPTIEMBRE
Q10: OCTUBRE
B11: Clasificación del servicio | I11: Reporte mes por servicio | K11: Reporte acumulado por servicio | Q11: NOVIEMBRE
B12: Ítem general | C12: ítem actividad | D12: Descripción de la actividad | E12: Profesional a cargo | F12: Soporte | G12: Medio de entrega | H12: Días contratados | I12: Días | J12: % avance | K12: Días | L12: % avance | Q12: DICIEMBRE
B13: 3 | C13: 3.17 | D13: Analizar data histórica de producción, productividad y daño por pozo | E13: Franklin Alejandro Botero Rivera | F13: Base de Datos - Informe de la Evaluación | G13: Digital, dbase de datos interna https://ecopetrol.sharepoint.com/sites/CastillaWOs2022/Documentos%20compartidos/Forms/AllItems.aspx?id=%2Fsites%2FCastillaWOs2022%2FDocumentos%20compartidos%2FJustificaciones&viewid=9ecb22f4%2D2d68%2D4a78%2Db78d%2Df5ff342528b5&noAuthRedirect=1 | H13: 33 | I13: 5 | J13: =IFERROR(I13/H13,0) -> 0.15151515 | K13: =I13+ENERO!K13 -> 7 | L13: =IFERROR(K13/H13,0) -> 0.21212121
B14: 5 | C14: 5.2 | D14: Generación de oportunidades de intervención a Pozos | F14: Base de Datos - Informe de la Evaluación | G14: Digital, Email a todos los de castilla-sharepoint, desarrollo ing, planeacion https://ecopetrol.sharepoint.com/sites/CastillaWOs2022/Documentos%20compartidos/Forms/AllItems.aspx?id=%2Fsites%2FCastillaWOs2022%2FDocumentos%20compartidos%2FJustificaciones&viewid=9ecb22f4%2D2d68%2D4a78%2Db78d%2Df5ff342528b5&noAuthRedirect=1 | H14: 32 | I14: 5 | J14: =IFERROR(I14/H14,0) -> 0.15625 | K14: =I14+ENERO!K14 -> 8 | L14: =IFERROR(K14/H14,0) -> 0.25
B15: 5 | C15: 5.5 | D15: Adelantar la evaluación e interpretación de datos enfocada a candidatización de actividades de reacondicionamiento y optimización de productividad en los activos | F15: Base de Datos - Informe de la Evaluación | G15: Digital, base de datos interna https://ecopetrol.sharepoint.com/sites/comunidadesdepracticaECP/EstimPozos/GDFE/Forms/AllItems.aspx?csf=1&web=1&e=Mm2usV&cid=a85ef813%2Dc5d9%2D4601%2Dbdf8%2Ddd5fa9d6a721&FolderCTID=0x01200095C6E94CFEA613409C4EA4FF99FD008C&id=%2Fsites%2FcomunidadesdepracticaECP%2FEstimPozos%2FGDFE%2FBarriles%2F2024&viewid=71ccfd21%2D31af%2D497c%2Dbcc1%2D9e157842de62 | H15: 32 | I15: 6 | J15: =IFERROR(I15/H15,0) -> 0.1875 | K15: =I15+ENERO!K15 -> 9 | L15: =IFERROR(K15/H15,0) -> 0.28125
B16: 5 | C16: 5.6 | D16: Generar los análisis asociados a candidatización de pozos para optimización de la producción empleando simulación numérica (análisis nodal) de productividad de pozos | F16: Base de Datos - Informe de la Evaluación | G16: Digita Nodal IFDMl https://ifdm-ecp.co/auth/login | H16: 32 | I16: 2 | J16: =IFERROR(I16/H16,0) -> 0.0625 | K16: =I16+ENERO!K16 -> 3 | L16: =IFERROR(K16/H16,0) -> 0.09375
B17: 5 | C17: 5.7 | D17: Generar reportes de soporte en la ejecución de trabajos ejecutados, tales como estimulaciones, fracturamientos hidráulicos, recañoneos, entre otros. | F17: Base de Datos - Informe de la Evaluación | G17: Digital, PJR post jobs reports en repositorio https://ecopetrol.sharepoint.com/sites/comunidadesdepracticaECP/EstimPozos/GDFE/Forms/AllItems.aspx?csf=1&web=1&e=Mm2usV&cid=a85ef813%2Dc5d9%2D4601%2Dbdf8%2Ddd5fa9d6a721&FolderCTID=0x01200095C6E94CFEA613409C4EA4FF99FD008C&id=%2Fsites%2FcomunidadesdepracticaECP%2FEstimPozos%2FGDFE%2FBarriles%2F2024&viewid=71ccfd21%2D31af%2D497c%2Dbcc1%2D9e157842de62 | H17: 32 | I17: 4 | J17: =IFERROR(I17/H17,0) -> 0.125 | K17: =I17+ENERO!K17 -> 6 | L17: =IFERROR(K17/H17,0) -> 0.1875
B18: 5 | C18: 5.8 | D18: Generar reportes de evaluación de los tratamientos de estimulación y optimización de producción implementados en la vigencia respectiva | F18: Base de Datos - Informe de la Evaluación | G18: Digital PJR post jobs analisis en repositorio https://ecopetrol.sharepoint.com/sites/comunidadesdepracticaECP/EstimPozos/GDFE/Forms/AllItems.aspx?csf=1&web=1&e=Mm2usV&cid=a85ef813%2Dc5d9%2D4601%2Dbdf8%2Ddd5fa9d6a721&FolderCTID=0x01200095C6E94CFEA613409C4EA4FF99FD008C&id=%2Fsites%2FcomunidadesdepracticaECP%2FEstimPozos%2FGDFE%2FBarriles%2F2024&viewid=71ccfd21%2D31af%2D497c%2Dbcc1%2D9e157842de62 | H18: 32 | I18: 4 | J18: =IFERROR(I18/H18,0) -> 0.125 | K18: =I18+ENERO!K18 -> 6 | L18: =IFERROR(K18/H18,0) -> 0.1875
B19: 5 | C19: 5.9 | D19: Realizar el seguimiento de producción/ inyección de pozos intervenidos con base en los comportamientos de producción previo y posterior a la intervención | F19: Base de Datos - Informe de la Evaluación | G19: Digital, MER (grupo de productividad) https://ecopetrol.sharepoint.com/sites/comunidadesdepracticaECP/EstimPozos/GDFE/Forms/AllItems.aspx?csf=1&web=1&e=Mm2usV&cid=a85ef813%2Dc5d9%2D4601%2Dbdf8%2Ddd5fa9d6a721&FolderCTID=0x01200095C6E94CFEA613409C4EA4FF99FD008C&id=%2Fsites%2FcomunidadesdepracticaECP%2FEstimPozos%2FGDFE%2FBarriles&viewid=71ccfd21%2D31af%2D497c%2Dbcc1%2D9e157842de62 | H19: 32 | I19: 4 | J19: =IFERROR(I19/H19,0) -> 0.125 | K19: =I19+ENERO!K19 -> 6 | L19: =IFERROR(K19/H19,0) -> 0.1875
B20: 3 | C20: 3.17 | D20: Analizar data histórica de producción, productividad y daño por pozo | E20: Maria Alejandra Giraldo Muñoz | F20: Finalización de presentación de lecciones aprendidas para GDA 2025, Y análisis de inyectividad en K para el campo Chichimene | G20: C:\Users\C1017211\OneDrive - Ecopetrol S.A\Documentos\CP Estimulación de Pozos - GDFE\Barriles\2026\Lecciones Aprendidas GAA 2025 | H20: 32 | I20: 6 | J20: =IFERROR(I20/H20,0) -> 0.1875 | K20: =I20+ENERO!K20 -> 9 | L20: =IFERROR(K20/H20,0) -> 0.28125
B21: 5 | C21: 5.2 | D21: Generación de oportunidades de intervención a Pozos | F21: Consolidación final de plan de operaciones de estimulación y fractura para el año 2026 y certificación MRT, y participación activa en campaña de cierre de brechas en en campo Akacias | G21: C:\Users\C1017211\OneDrive - Ecopetrol S.A\Documentos\CP Estimulación de Pozos - GDFE\Barriles\2026 | H21: 32 | I21: 4 | J21: =IFERROR(I21/H21,0) -> 0.125 | K21: =I21+ENERO!K21 -> 7 | L21: =IFERROR(K21/H21,0) -> 0.21875
B22: 5 | C22: 5.5 | D22: Adelantar la evaluación e interpretación de pozos ac | F22: Revisión de candidatización de pozos en las genrecias GCL, GDA y GCH y caracterización de daño y estimulación matricial en VRO | G22: https://ecopetrol.sharepoint.com/sites/comunidadesdepracticaECP/EstimPozos/GDFE | H22: 32 | I22: 4 | J22: =IFERROR(I22/H22,0) -> 0.125 | K22: =I22+ENERO!K22 -> 7 | L22: =IFERROR(K22/H22,0) -> 0.21875
B23: 5 | C23: 5.6 | D23: Generar los análisis asociados a candidatización de pozos para optimización de la producción empleando simulación numérica (análisis nodal) de productividad de pozos | F23: Confirmación de operaciones y trenes de evaluación Consolidación de escenarios financieros variando costos y productividad de pozos de campaña MaxPro | G23: C:\Users\C1017211\OneDrive - Ecopetrol S.A\Documentos\CP Estimulación de Pozos - GDFE | H23: 32 | I23: 4 | J23: =IFERROR(I23/H23,0) -> 0.125 | K23: =I23+ENERO!K23 -> 5 | L23: =IFERROR(K23/H23,0) -> 0.15625
B24: 5 | C24: 5.7 | D24: Generar reportes de soporte en la ejecución de trabajos ejecutados, tales como estimulaciones, fracturamientos hidráulicos, recañoneos, entre otros. | F24: Revisión y consolidación de programas operativos de estimulación matricial, con sus respectivos informes de laboratorio y aseguramiento de operación | G24: C:\Users\C1017211\OneDrive - Ecopetrol S.A\Documentos\CP Estimulación de Pozos - GDFE | H24: 32 | I24: 4 | J24: =IFERROR(I24/H24,0) -> 0.125 | K24: =I24+ENERO!K24 -> 6 | L24: =IFERROR(K24/H24,0) -> 0.1875
B25: 5 | C25: 5.8 | D25: Generar reportes de evaluación de los tratamientos de estimulación y optimización de producción implementados en la vigencia respectiva | F25: Revisión y consolidación de reportes finales de intervenciones de estimulación matricial y fracturamiento hidráulico de pozos en las gerencias GCL, GDA y GCH y consolidación de archivo SRT para documento PJR | G25: C:\Users\C1017211\OneDrive - Ecopetrol S.A\Documentos\CP Estimulación de Pozos - GDFE | H25: 32 | I25: 4 | J25: =IFERROR(I25/H25,0) -> 0.125 | K25: =I25+ENERO!K25 -> 6 | L25: =IFERROR(K25/H25,0) -> 0.1875
B26: 5 | C26: 5.9 | D26: Realizar el seguimiento de producción/ inyección de pozos intervenidos con base en los comportamientos de producción previo y posterior a la intervención | F26: Seguimiento y actualización de la producción incremental de los pozos estimulados y/o fracturados en las gerencias GLC, GDA, GCH para la actualización del archivo Campaña MER 2026. | G26: "C:\Users\C1017211\OneDrive - Ecopetrol S.A\Documentos\CP Estimulación de Pozos - GDFE\Barriles\2026\Campaña_MER_2026.xlsm" | H26: 33 | I26: 4 | J26: =IFERROR(I26/H26,0) -> 0.12121212 | K26: =I26+ENERO!K26 -> 5 | L26: =IFERROR(K26/H26,0) -> 0.15151515
B27: 5 | C27: 5.1 | D27: Generar bases de datos de Eventos de pozos | E27: Javier Enrique Guerrero Arrieta | F27: Base de Datos | G27: Digital | H27: 15 | I27: 5 | J27: =IFERROR(I27/H27,0) -> 0.33333333 | K27: =I27+ENERO!K27 -> 5 | L27: =IFERROR(K27/H27,0) -> 0.33333333
B28: 5 | C28: 5.2 | D28: Generación de oportunidades de intervención a Pozos | F28: - | G28: - | H28: 15 | I28: 0 | J28: =IFERROR(I28/H28,0) -> 0 | K28: =I28+ENERO!K28 -> 5 | L28: =IFERROR(K28/H28,0) -> 0.33333333
B29: 5 | C29: 5.3 | D29: Estimar restricciones de Presión y tasas para la generacion | F29: Base de Datos - Informe de la Evaluación | G29: Digital | H29: 15 | I29: 7 | J29: =IFERROR(I29/H29,0) -> 0.46666667 | K29: =I29+ENERO!K29 -> 7 | L29: =IFERROR(K29/H29,0) -> 0.46666667
B30: 5 | C30: 5.4 | D30: Generar modelo de Pozos | F30: Base de Datos - Informe de la Evaluación | G30: Digital | H30: 15 | I30: 6 | J30: =IFERROR(I30/H30,0) -> 0.4 | K30: =I30+ENERO!K30 -> 6 | L30: =IFERROR(K30/H30,0) -> 0.4
B31: 5 | C31: 5.5 | D31: Adelantar la evaluación e interpretación de datos | F31: Base de Datos - Informe de la Evaluación | G31: Digital | H31: 15 | I31: 3 | J31: =IFERROR(I31/H31,0) -> 0.2 | K31: =I31+ENERO!K31 -> 10 | L31: =IFERROR(K31/H31,0) -> 0.66666667
B32: 5 | C32: 5.6 | D32: Generar los análisis asociados a candidatización de pozos para optimización de la producción empleando simulación numérica (análisis nodal) de productividad de pozos | F32: Base de Datos - Informe de la Evaluación | G32: Digital | H32: 15 | I32: 7 | J32: =IFERROR(I32/H32,0) -> 0.46666667 | K32: =I32+ENERO!K32 -> 10 | L32: =IFERROR(K32/H32,0) -> 0.66666667
B33: 5 | C33: 5.7 | D33: Generar reportes de soporte en la ejecución de trabajos ejecutados, tales como estimulaciones, fracturamientos hidráulicos, recañoneos, entre otros. | F33: - | G33: - | H33: 15 | I33: 0 | J33: =IFERROR(I33/H33,0) -> 0 | K33: =I33+ENERO!K33 -> 0 | L33: =IFERROR(K33/H33,0) -> 0
B34: 5 | C34: 5.8 | D34: Generar reportes de evaluación de los tratamientos de estimulación y optimización de producción implementados en la vigencia respectiva | F34: - | G34: - | H34: 15 | I34: 0 | J34: =IFERROR(I34/H34,0) -> 0 | K34: =I34+ENERO!K34 -> 0 | L34: =IFERROR(K34/H34,0) -> 0
B35: 5 | C35: 5.9 | D35: Realizar el seguimiento de producción/ inyección de pozos intervenidos con base en los comportamientos de producción previo y posterior a la intervención | F35: - | G35: - | H35: 15 | I35: 0 | J35: =IFERROR(I35/H35,0) -> 0 | K35: =I35+ENERO!K35 -> 0 | L35: =IFERROR(K35/H35,0) -> 0
B36: 5 | C36: 5.10 | D36: Adelantar en análisis y evaluación de datos enfocada a la ejecución de estudios de daño de formación | F36: - | G36: - | H36: 15 | I36: 0 | J36: =IFERROR(I36/H36,0) -> 0 | K36: =I36+ENERO!K36 -> 0 | L36: =IFERROR(K36/H36,0) -> 0
B37: 5 | C37: 5.11 | D37: Generar los análisis asociados a la ejecución de estudios de daño de formación empleando simulación numérica (análisis nodal y single well model, análisis de aguas, análisis de crudos, entre otros) | F37: - | G37: - | H37: 15 | I37: 0 | J37: =IFERROR(I37/H37,0) -> 0 | K37: =I37+ENERO!K37 -> 0 | L37: =IFERROR(K37/H37,0) -> 0
B38: 7 | C38: 7.1 | D38: Evaluar el estatus de las facilidades (Operatividad) y | F38: - | G38: - | H38: 15 | I38: 0 | J38: =IFERROR(I38/H38,0) -> 0 | K38: =I38+ENERO!K38 -> 0 | L38: =IFERROR(K38/H38,0) -> 0
B39: 7 | C39: 7.2 | D39: Evaluar la Integridad de las facilidades existentes | F39: Informe de la Evaluación | G39: Digital | H39: 15 | I39: 2 | J39: =IFERROR(I39/H39,0) -> 0.13333333 | K39: =I39+ENERO!K39 -> 2 | L39: =IFERROR(K39/H39,0) -> 0.13333333
... B41: 8 | C41: 8.4 | D41: Análisis de resultados y análisis Estadístico - descriptivo de | F41: - | G41: - | H41: 15 | I41: 0 | J41: =IFERROR(I41/H41,0) -> 0 | K41: =I41+ENERO!K41 -> 0 | L41: =IFERROR(K41/H41,0) -> 0
B42: 3 | C42: 3.10 | D42: Control de calidad del dato adquirido para valorar representatividad de la prueba en cuestión. De ser válidas, levantamiento de información de entrada para análisis e interpretación (registros de desviación, estado mecánico de cada pozo, caliper/bit size ("), espesor neto (pies TVD), porosidad media (phi), Sw, PVT, producciones asociadas, corte de agua, salinidades, mapa estructural, etc. | E42: Daniela Molina Landinez | F42: Inventario - Informe de | G42: Digital | H42: 37 | I42: 5 | J42: =IFERROR(I42/H42,0) -> 0.13513514 | K42: =I42+ENERO!K42 -> 6 | L42: =IFERROR(K42/H42,0) -> 0.16216216
B43: 3 | C43: 3.16 | D43: Análisis de Declinaciones por pozo y/o subunidad | F43: Base de Datos - Perfiles | G43: Digital | H43: 37 | I43: 6 | J43: =IFERROR(I43/H43,0) -> 0.16216216 | K43: =I43+ENERO!K43 -> 8 | L43: =IFERROR(K43/H43,0) -> 0.21621622
B44: 3 | C44: 3.17 | D44: Analizar data histórica de producción, productividad y daño por pozo | F44: Base de Datos - Informe de | G44: Digital | H44: 37 | I44: 8 | J44: =IFERROR(I44/H44,0) -> 0.21621622 | K44: =I44+ENERO!K44 -> 10 | L44: =IFERROR(K44/H44,0) -> 0.27027027
B45: 3 | C45: 3.18 | D45: Generar perfiles de Producción por pozos para pozos existente en escenarios Bajo, Medio y Alto | F45: Base de Datos - Informe de | G45: Digital | H45: 38 | I45: 6 | J45: =IFERROR(I45/H45,0) -> 0.15789474 | K45: =I45+ENERO!K45 -> 10 | L45: =IFERROR(K45/H45,0) -> 0.26315789
B46: 5 | C46: 5.9 | D46: Realizar el seguimiento de producción/ inyección de pozos intervenidos con base en los comportamientos de producción previo y posterior a la intervención | F46: Base de Datos - Informe d | G46: Digital | H46: 38 | I46: 3 | J46: =IFERROR(I46/H46,0) -> 0.078947368 | K46: =I46+ENERO!K46 -> 6 | L46: =IFERROR(K46/H46,0) -> 0.15789474
B47: 5 | C47: 5.10 | D47: Adelantar en análisis y evaluación de datos enfocada a la ejecución de estudios de daño de formación | F47: Base de Datos - Informe d | G47: Digital | H47: 38 | I47: 2 | J47: =IFERROR(I47/H47,0) -> 0.052631579 | K47: =I47+ENERO!K47 -> 5 | L47: =IFERROR(K47/H47,0) -> 0.13157895
B48: 3 | C48: 3.10 | D48: Control de calidad del dato adquirido para valorar representatividad de la prueba en cuestión. De ser válidas, levantamiento de información de entrada para análisis e interpretación (registros de desviación, estado mecánico de cada pozo, caliper/bit size ("), espesor neto (pies TVD), porosidad media (phi), Sw, PVT, producciones asociadas, corte de agua, salinidades, mapa estructural, etc. | E48: Alexandra Katherine Londoño Camacho | F48: Inventario - Informe de | G48: Digital | H48: 38 | I48: 5 | J48: =IFERROR(I48/H48,0) -> 0.13157895 | K48: =I48+ENERO!K48 -> 10 | L48: =IFERROR(K48/H48,0) -> 0.26315789
B49: 3 | C49: 3.16 | D49: Análisis de Declinaciones por pozo y/o subunidad | F49: Base de Datos - Perfiles | G49: Digital | H49: 38 | I49: 7 | J49: =IFERROR(I49/H49,0) -> 0.18421053 | K49: =I49+ENERO!K49 -> 9 | L49: =IFERROR(K49/H49,0) -> 0.23684211
B50: 3 | C50: 3.17 | D50: Analizar data histórica de producción, productividad y daño por pozo | F50: Base de Datos - Informe de | G50: Digital | H50: 38 | I50: 5 | J50: =IFERROR(I50/H50,0) -> 0.13157895 | K50: =I50+ENERO!K50 -> 6 | L50: =IFERROR(K50/H50,0) -> 0.15789474
B51: 3 | C51: 3.18 | D51: Generar perfiles de Producción por pozos para pozos existente en escenarios Bajo, Medio y Alto | F51: Base de Datos - Informe de | G51: Digital | H51: 37 | I51: 3 | J51: =IFERROR(I51/H51,0) -> 0.081081081 | K51: =I51+ENERO!K51 -> 4 | L51: =IFERROR(K51/H51,0) -> 0.10810811
B52: 5 | C52: 5.9 | D52: Realizar el seguimiento de producción/ inyección de pozos intervenidos con base en los comportamientos de producción previo y posterior a la intervención | F52: Base de Datos - Informe d | G52: Digital | H52: 37 | I52: 2 | J52: =IFERROR(I52/H52,0) -> 0.054054054 | K52: =I52+ENERO!K52 -> 3 | L52: =IFERROR(K52/H52,0) -> 0.081081081
B53: 5 | C53: 5.10 | D53: Adelantar en análisis y evaluación de datos enfocada a la ejecución de estudios de daño de formación | F53: Base de Datos - Informe d | G53: Digital | H53: 37 | I53: 8 | J53: =IFERROR(I53/H53,0) -> 0.21621622 | K53: =I53+ENERO!K53 -> 13 | L53: =IFERROR(K53/H53,0) -> 0.35135135
B54: 3 | C54: 3.10 | D54: Control de calidad del dato adquirido para valorar representatividad de la prueba en cuestión. De ser válidas, levantamiento de información de entrada para análisis e interpretación (registros de desviación, estado mecánico de cada pozo, caliper/bit size ("), espesor neto (pies TVD), porosidad media (phi), Sw, PVT, producciones asociadas, corte de agua, salinidades, mapa estructural, etc. | E54: Lenin Cordoba Rivas | F54: Base de datos en sitio compartido | G54: Digital | H54: 39 | I54: 6 | J54: =IFERROR(I54/H54,0) -> 0.15384615 | K54: =I54+ENERO!K54 -> 6 | L54: =IFERROR(K54/H54,0) -> 0.15384615
B55: 3 | C55: 3.17 | D55: Analizar data histórica de producción, productividad y daño por pozo | F55: Base de Datos Modelo por pozo | G55: Digital | H55: 39 | I55: 3 | J55: =IFERROR(I55/H55,0) -> 0.076923077 | K55: =I55+ENERO!K55 -> 3 | L55: =IFERROR(K55/H55,0) -> 0.076923077
B56: 5 | C56: 5.1 | D56: Generar bases de datos de Eventos de pozos | F56: Base de Datos en sitio compartido | G56: Digital | H56: 40 | I56: 3 | J56: =IFERROR(I56/H56,0) -> 0.075 | K56: =I56+ENERO!K56 -> 3 | L56: =IFERROR(K56/H56,0) -> 0.075
B57: 5 | C57: 5.7 | D57: Generar reportes de soporte en la ejecución de trabajos ejecutados, tales como estimulaciones, fracturamientos hidráulicos, recañoneos, entre otros. | F57: Conceptos y/o presentaciones de interpretaciones de pruebas y registros de pozos | G57: Digital | H57: 40 | I57: 4 | J57: =IFERROR(I57/H57,0) -> 0.1 | K57: =I57+ENERO!K57 -> 4 | L57: =IFERROR(K57/H57,0) -> 0.1
B58: 5 | C58: 5.11 | D58: Generar los análisis asociados a la ejecución de estudios de daño de formación empleando simulación numérica (análisis nodal y single well model, análisis de aguas, análisis de crudos, entre otros) | F58: Base de Datos Informe de la Evaluación | G58: Digital | H58: 40 | I58: 2 | J58: =IFERROR(I58/H58,0) -> 0.05 | K58: =I58+ENERO!K58 -> 2 | L58: =IFERROR(K58/H58,0) -> 0.05
B59: 3 | C59: 3.11 | D59: Análisis e interpretación de datos de pruebas de presión-producción (DSTs, PBU, Pruebas Extendidas Producción, Gradientes Estáticos- Dinámicos PT, etc.) o de presión inyección (Inyectividad, SRT, FOT) aplicadas ya sea en tiempo real, memorizadas o con sarta temporal DST. Integración Probador Formación - Registros Open Hole. | E59: Lenin Córdoba Rivas / Luis Chimones | F59: Informe del análisis por pozo o prueba | G59: Digital | H59: 225 | I59: 30 | J59: =IFERROR(I59/H59,0) -> 0.13333333 | K59: =I59+ENERO!K59 -> 45 | L59: =IFERROR(K59/H59,0) -> 0.2
B60: 1 | C60: 1.2 | D60: Generación Bases de Datos de Pozos (Registros, Topes e información disponible). | E60: Jesus Ernesto Coqueco Vargas | F60: Base de datos en Excel. Organización de carpetas en la nube (onedrive) | G60: Todos los conceptos, interpretaciones, análisis y estudios son enviados a través de Correo electrónico a las diferentes áreas interesadas y son guardados en la siguiente carpeta de OneDrive Dominio Ecopetrol perteneciente al Lider Técnico Alexander Castro: https://ecopetrol-my.sharepoint.com/:f:/r/personal/alexander_castroch_ecopetrol_com_co/Documents/ALEX/Registros?csf=1&web=1&e=tP4gfr | H60: 15 | I60: 2 | J60: =IFERROR(I60/H60,0) -> 0.13333333 | K60: =I60+ENERO!K60 -> 3 | L60: =IFERROR(K60/H60,0) -> 0.2
B61: 3 | C61: 3.8 | D61: Validación y estudio de presiones (Pre-Test) adquiridos a través de probadores de formación. | F61: Presentación con concepto técnico | G61: Todos los conceptos, interpretaciones, análisis y estudios son enviados a través de Correo electrónico a las diferentes áreas interesadas y son guardados en la siguiente carpeta de OneDrive Dominio Ecopetrol perteneciente al Lider Técnico Alexander Castro: https://ecopetrol-my.sharepoint.com/:f:/r/personal/alexander_castroch_ecopetrol_com_co/Documents/ALEX/Registros?csf=1&web=1&e=tP4gfr | H61: 15 | I61: 3 | J61: =IFERROR(I61/H61,0) -> 0.2 | K61: =I61+ENERO!K61 -> 4 | L61: =IFERROR(K61/H61,0) -> 0.26666667
B62: 3 | C62: 3.9 | D62: Inventario y acceso a raw data de cada prueba de presión-producción o de presión inyección asociada incluyendo sensores involucrados (main+backup) así como job log de cada prueba donde se especifique, a parte de la secuencia operativa, fecha exacta de inicio de prueba (ddmm-yy hh:mm:ss), tipo de sensores empleados, profundidad de lectura tanto MD/TVD. | F62: Base de datos en Excel. Organización de carpetas en la nube (onedrive) | G62: Todos los conceptos, interpretaciones, análisis y estudios son enviados a través de Correo electrónico a las diferentes áreas interesadas y son guardados en la siguiente carpeta de OneDrive Dominio Ecopetrol perteneciente al Lider Técnico Alexander Castro: https://ecopetrol-my.sharepoint.com/:f:/r/personal/alexander_castroch_ecopetrol_com_co/Documents/ALEX/Registros?csf=1&web=1&e=tP4gfr | H62: 30 | I62: 5 | J62: =IFERROR(I62/H62,0) -> 0.16666667 | K62: =I62+ENERO!K62 -> 7 | L62: =IFERROR(K62/H62,0) -> 0.23333333
B63: 3 | C63: 3.11 | D63: Análisis e interpretación de datos de pruebas de presión-producción (DSTs, PBU, Pruebas Extendidas Producción, Gradientes Estáticos- Dinámicos PT, etc.) o de presión inyección (Inyectividad, SRT, FOT) aplicadas ya sea en tiempo real, memorizadas o con sarta temporal DST. Integración Probador Formación - Registros Open Hole. | F63: Presentación con concepto técnico y presentación via teams ante el personal interesado | G63: Todos los conceptos, interpretaciones, análisis y estudios son enviados a través de Correo electrónico a las diferentes áreas interesadas y son guardados en la siguiente carpeta de OneDrive Dominio Ecopetrol perteneciente al Lider Técnico Alexander Castro: https://ecopetrol-my.sharepoint.com/:f:/r/personal/alexander_castroch_ecopetrol_com_co/Documents/ALEX/Registros?csf=1&web=1&e=tP4gfr | H63: 35 | I63: 5 | J63: =IFERROR(I63/H63,0) -> 0.14285714 | K63: =I63+ENERO!K63 -> 7 | L63: =IFERROR(K63/H63,0) -> 0.2
B64: 3 | C64: 3.12 | D64: Generar Modelo de Presiones partiendo de las pruebas previamente validadas e interpretadas | F64: Modelo del sector | G64: Todos los conceptos, interpretaciones, análisis y estudios son enviados a través de Correo electrónico a las diferentes áreas interesadas y son guardados en la siguiente carpeta de OneDrive Dominio Ecopetrol perteneciente al Lider Técnico Alexander Castro: https://ecopetrol-my.sharepoint.com/:f:/r/personal/alexander_castroch_ecopetrol_com_co/Documents/ALEX/Registros?csf=1&web=1&e=tP4gfr | H64: 30 | I64: 4 | J64: =IFERROR(I64/H64,0) -> 0.13333333 | K64: =I64+ENERO!K64 -> 6 | L64: =IFERROR(K64/H64,0) -> 0.2
B65: 5 | C65: 5.5 | D65: Adelantar la evaluación e interpretación de datos enfocada a candidatización de actividades de reacondicionamiento y optimización de productividad en los activos | F65: Base de Datos Informe de la Evaluación | G65: Todos los conceptos, interpretaciones, análisis y estudios son enviados a través de Correo electrónico a las diferentes áreas interesadas y son guardados en la siguiente carpeta de OneDrive Dominio Ecopetrol perteneciente al Lider Técnico Alexander Castro: https://ecopetrol-my.sharepoint.com/:f:/r/personal/alexander_castroch_ecopetrol_com_co/Documents/ALEX/Registros?csf=1&web=1&e=tP4gfr | H65: 30 | I65: 3 | J65: =IFERROR(I65/H65,0) -> 0.1 | K65: =I65+ENERO!K65 -> 5 | L65: =IFERROR(K65/H65,0) -> 0.16666667
B66: 5 | C66: 5.6 | D66: Generar los análisis asociados a candidatización de pozos para optimización de la producción empleando simulación numérica (análisis nodal) de productividad de pozos | F66: Base de Datos Informe de la Evaluación | G66: Todos los conceptos, interpretaciones, análisis y estudios son enviados a través de Correo electrónico a las diferentes áreas interesadas y son guardados en la siguiente carpeta de OneDrive Dominio Ecopetrol perteneciente al Lider Técnico Alexander Castro: https://ecopetrol-my.sharepoint.com/:f:/r/personal/alexander_castroch_ecopetrol_com_co/Documents/ALEX/Registros?csf=1&web=1&e=tP4gfr | H66: 35 | I66: 4 | J66: =IFERROR(I66/H66,0) -> 0.11428571 | K66: =I66+ENERO!K66 -> 7 | L66: =IFERROR(K66/H66,0) -> 0.2
B67: 5 | C67: 5.7 | D67: Generar reportes de soporte en la ejecución de trabajos ejecutados, tales como estimulaciones, fracturamientos hidráulicos, recañoneos, entre otros. | F67: Base de Datos, presentaciones, informes con conceptos técnicos | G67: Todos los conceptos, interpretaciones, análisis y estudios son enviados a través de Correo electrónico a las diferentes áreas interesadas y son guardados en la siguiente carpeta de OneDrive Dominio Ecopetrol perteneciente al Lider Técnico Alexander Castro: https://ecopetrol-my.sharepoint.com/:f:/r/personal/alexander_castroch_ecopetrol_com_co/Documents/ALEX/Registros?csf=1&web=1&e=tP4gfr | H67: 35 | I67: 4 | J67: =IFERROR(I67/H67,0) -> 0.11428571 | K67: =I67+ENERO!K67 -> 6 | L67: =IFERROR(K67/H67,0) -> 0.17142857
H68: =+CONCATENATE("TOTAL A ",D7) -> TOTAL A FEBRERO | K68: TOTAL ACUMULADO
H69: =+SUM(H13:H67) -> 1773 | I69: =+SUM(I13:I67) -> 228 | J69: =IFERROR(I69/H69,0) -> 0.1285956 | K69: =+SUM(K13:K67) -> 333 | L69: =IFERROR(K69/H69,0) -> 0.18781726
B71: Observaciones: | D71: 3,1 3,16 3,17 3,18 5,9 5,10 Junior (DM) * Actualización y seguimiento del sector model en REVEAL para escenarios de eficiencia de tratamientos de nano para control de arena en los pozos de Vigía sur (VGS-05). * Continuación de recopilación y organización de información para generar un sector model en REVEAL para generar un análisis del pozo K2 GC562_9_BP01, tuvo un problema de arenamiento y necesita comprensión del efecto de la generación y transporte de arena. * Soporte en reuniones sistemáticas multidisciplinarias jueves de piloto en el campo GCH y en la elaboración del sector model para en REVEAL para el pozo CHSW-80 incluido archivos prosper
D72: 3.17 5.2 5.5 5.6 5.7 5.8 5.9 Senior (MG): Se reportan 15 días del mes de enero, con incio de contrato el día 16 de enero de 2026 y # Contrato 90599924
D73: 5,1 5,2 5,3 5,4 5,5 5,6 5,7 5,8 5,9 5,1 5,11 7,1 7,2 7,3 8,4 Senior (JG):
D74: 3,10 3,16 3,17 3,18 5,9 5,1 Junior (DM):
D75: 3,10 3,16 3,17 3,18 5,9 5,1 Junior (AL):
D76: 3.10 3.17 5.1 5.7 5.11 Senior (LR): Los detalles son descritos en el documento GP-F-25 INFORME TÉCNICO. A partir del 13 de Febrero se generó cambio de cargo a Profesional Senior.
D77: 3.11 Junior (LC): Los detalles son descritos en el documento GP-F-25 INFORME TÉCNICO.
D78: 1.2 3.8 3.9 3.11 3.12 5.5 5.6 5.7 Senior (JC): * Se realizó evaluación de 9 registros de calidad de cemento, en diferentes campos de diferentes vicepresidencias (CASTILLA, CASABE, PIEDEMONTE, CHICHIMENE), usando el software Emeraude y aplicativo propio diseñado en Python. * Se realizó evaluación de 3 registros de ILT + FIUBRA OPTICA usando metodología de transientes creada en Python, para el análisis de perfiles de inyección e integridad. * Se realizó evaluación de 1 registro de correlación para posterior toma de decisiones, tras corte de tubería en pozo con BHA inteligente * Se discutió a través de reuniones virtuales las intervenciones a diferentes pozos, en los campos CASTILLA, CASABE, APIAY, CHICHIMENE entre otros. Se brindaron las recomendaciones técnicas pertinentes. * Se prestó apoyo en la realización de los Templates en el Software Emeraude versión 5.60.01, para agilizar el proceso de cargue de los pozos. Se logró una reducción significativa en los tiempos de respuesta gracias al uso de dichos templates. * La implementación de código de uso libre en Python permitió superar desafíos en el análisis de datos y la interpretación de registros, contribuyendo de manera clave al cumplimiento de los objetivos propuestos. * Todos los conceptos, interpretaciones, análisis y estudios son enviados a través de Correo electrónico a las diferentes áreas interesadas y son guardados en la siguiente carpeta de OneDrive Dominio Ecopetrol perteneciente al Líder Técnico Alexander Castro. En el formato GP-F-25 (Sección 2, descripción y/o resultados) se detalla pozo a pozo la ubicación de los archivos dentro de la nube: https://ecopetrol-my.sharepoint.com/:f:/r/personal/alexander_castroch_ecopetrol_com_co/Documents/ALEX/Registros?csf=1&web=1&e=tP4gfr
B79: ¿Se presentó algún aspecto o situación que afecte la ejecución y calidad de los entregables? (Marque con una X)
B81: PROFESIONAL
B82: SI | D82: Describa en este espacio su observación
B83: NO | C83: X
B84: ¿Se presentó algún aspecto o situación que afecte la ejecución y calidad de los entregables? (Marque con una X)
B86: INTERVENTOR O LIDER
B87: SI | D87: Describa en este espacio su observación
B88: NO
B91: Italo Bahamon
B92: Revisa: | H92: Interventor: | I92: Richard Disney Zabala Romero
A124: MES
A125: ENERO
A126: FEBRERO
A127: MARZO
A128: ABRIL
A129: MAYO
A130: JUNIO
A131: JULIO
A132: AGOSTO
A133: SEPTIEMBRE
A134: OCTUBRE
A135: NOVIEMBRE
A136: DICIEMBRE
