Workbook

Sheet ABRIL 2025
Q1: MES
B2: REPORTE DE AVANCE | Q2: ENERO
B3: Fecha: 29/06/2022 | F3: Version: 01 | J3: GP-F-23
Q4: FEBRERO
B5: Código Orden de servicio | D5: 90141005 | Q5: MARZO
Q6: JUNIO
B7: Mes a reportar | D7: ABRIL | Q7: JULIO
Q8: AGOSTO
B9: Fecha reporte | D9: 45777 | Q9: SEPTIEMBRE
Q10: OCTUBRE
B11: Clasificación del servicio | I11: Reporte mes por servicio | K11: Reporte acumulado por servicio | Q11: NOVIEMBRE
B12: Ítem general | C12: ítem actividad | D12: Descripción de la actividad | E12: Profesional a cargo | F12: Soporte | G12: Medio de entrega | H12: Días contratados | I12: Días | J12: % avance | K12: Días | L12: % avance | Q12: DICIEMBRE
B13: 3 | C13: 3.6 | D13: Generar Modelo analítico del yacimiento integrando la información disponible en un software específico | E13: Alejandro D López | F13: Cambio en los cronogramas y perfiles del modelo analítico en ARPS para los perfiles de producción para el campo Akasias en para las etapas de ANE y Tinamu | G13: ACCESS - PLP 2024 - Todos los documentos (sharepoint.com) | H13: 20 | I13: 7 | J13: =IFERROR(I13/H13,0) -> 0.35 | K13: =+I13 -> 7 | L13: =IFERROR(K13/H13,0) -> 0.35
B14: 3 | C14: 3.13 | D14: Generar base de datos de producción (OFM o la que se requiera) | F14: Generar archivos de carga de productores, inyectores y allocacion para el campo Tinamu. Se realizó control de calidad a los archivos que se subieron al ARPS | G14: https://ecopetrol.sharepoint.com/sites/EquipoDesarrolloCPO-9/Documentos%20compartidos/Forms/AllItems.aspx?id=%2Fsites%2FEquipoDesarrolloCPO%2D9%2FDocumentos%20compartidos%2FGeneral%2F04%2DExploratorio%2FExploratorios%20CPO%2D9&viewid=0e96c994%2D47e1%2D4e99%2D93c0%2D37826753815c | H14: 10 | I14: 8 | J14: =IFERROR(I14/H14,0) -> 0.8 | K14: =+I14 -> 8 | L14: =IFERROR(K14/H14,0) -> 0.8
B15: 3 | C15: 3.16 | D15: Análisis de Declinaciones por pozo y/o subunidad | F15: Se generó un establecio la configuracion de allocacion de primeras y segundas lineas por RWA para el campo Akacias en la etapa de desarrollo temprano | G15: ACCESS - PLP 2024 - Todos los documentos (sharepoint.com) | H15: 10 | I15: 2 | J15: =IFERROR(I15/H15,0) -> 0.2 | K15: =+I15 -> 2 | L15: =IFERROR(K15/H15,0) -> 0.2
B16: 3 | C16: 3.17 | D16: Analizar data histórica de producción, productividad y daño por pozo | F16: Base de Datos - Informe de la Evaluación | G16: ACCESS - PLP 2024 - Todos los documentos (sharepoint.com) | H16: 10 | I16: 4 | J16: =IFERROR(I16/H16,0) -> 0.4 | K16: =+I16 -> 4 | L16: =IFERROR(K16/H16,0) -> 0.4
B17: 3 | C17: 3.18 | D17: Generar perfiles de Producción por pozos para pozos existente en escenarios Bajo, Medio y Alto | F17: Se generó un archivo parcial de analisis de produccion de los pozos de cercanos y perforados del campo Tinamu para usar su produccion como referencia para los futuros pozos del campo | G17: ACCESS - PLP 2024 - Todos los documentos (sharepoint.com) | H17: 10 | I17: 2 | J17: =IFERROR(I17/H17,0) -> 0.2 | K17: =+I17 -> 2 | L17: =IFERROR(K17/H17,0) -> 0.2
B18: 5 | C18: 5.2 | D18: Generación de oportunidades de intervención a Pozos | F18: Base de Datos - Informe de la Evaluación | G18: ACCESS - Frontera - Todos los documentos | H18: 10 | I18: 3 | J18: =IFERROR(I18/H18,0) -> 0.3 | K18: =+I18 -> 3 | L18: =IFERROR(K18/H18,0) -> 0.3
B19: 5 | C19: 5.9 | D19: Realizar el seguimiento de producción/ inyección de pozos intervenidos con base en los comportamientos de producción previo y posterior a la intervención | F19: Entrega de perfiles de la etapa de Tinamu para proyectos | G19: ACCESS - Tinamu - Todos los documentos | H19: 10 | I19: 1 | J19: =IFERROR(I19/H19,0) -> 0.1 | K19: =+I19 -> 1 | L19: =IFERROR(K19/H19,0) -> 0.1
B20: 8 | C20: 8.2 | D20: Carga de datos, procesamiento de datos, Análisis Estadístico descriptivo considerando hipótesis desde la teoría, y análisis descriptivo considerando hipótesis generadas desde la misma data (pasos 1, 2 y 3 teoría CRISP-DM). | F20: Informe, con estadísticas descriptivas, histogramas, pruebas de ajuste, etc. | G20: Informe de reservas Campo Akacias 2022 - Inicio (sharepoint.com) | H20: 10 | I20: 3 | J20: =IFERROR(I20/H20,0) -> 0.3 | K20: =+I20 -> 3 | L20: =IFERROR(K20/H20,0) -> 0.3
B21: 3 | C21: 3.6 | D21: Generar Modelo analítico del yacimiento integrando la información disponible en un software específico | E21: Jhon H Carreño | F21: 1. Actualización semanal del modelo estático y dinámico del yacimiento y pozos del campo Akacias, mediante el proyecto Sahara Abr-2024 (Cargadores y modelo final) | G21: 1. X:\CHICHIMENE\INFORMACIÓN_CAMPO_CHICHIMENE\23.-Inyeccion de Agua\10. MONITOREO\09. Proyecto Sahara\2025\04. Abril 2. W:\2.- Ingeniería de Yacimientos\1.MONITOREO\1.Sahara\2025\4. Abril | H21: 10 | I21: 3 | J21: =IFERROR(I21/H21,0) -> 0.3 | K21: =+I21 -> 3 | L21: =IFERROR(K21/H21,0) -> 0.3
B22: 3 | C22: 3.13 | D22: Generar base de datos de producción (OFM o la que se requiera) | F22: 1. Actualización de la producción por proyecto y tipo de recobro en los Tableros 2.1 y las bases de datos de Molinos de viento de los pozos | G22: 1. https://ecopetrol.sharepoint.com/:f:/s/IAAKACIAS/EgCqFNT0rW9HqaUHUJ2Rl9QBCvS0kt0UAmo5iqfzicBI0Q?e=Qh9MOi 2. https://ecopetrol.sharepoint.com/:f:/s/IAAKACIAS/ErHM_OfTGKZLmCPrT3bK8O8BcnNF3UxaQIY023A7wFXXZg?e=2Qvz45 | H22: 10 | I22: 3 | J22: =IFERROR(I22/H22,0) -> 0.3 | K22: =+I22 -> 3 | L22: =IFERROR(K22/H22,0) -> 0.3
B23: 3 | C23: 3.14 | D23: Generar Distribución de Producción por sub- unidades (allocation) | F23: 1. Distribución de la producción asociada a la implementación del WF en los patrones de inyección del campo AK por medio del metodo RWA con la información a cierre de Mar-2025 | G23: 1. https://ecopetrol.sharepoint.com/:f:/s/IAAKACIAS/EtPNskxPDDlCgotsjtO3ZMgBdz_yBC_z0GJdAK8Dr4LYNA?e=M3WzO2 | H23: 10 | I23: 3 | J23: =IFERROR(I23/H23,0) -> 0.3 | K23: =+I23 -> 3 | L23: =IFERROR(K23/H23,0) -> 0.3
B24: 3 | C24: 3.16 | D24: Análisis de Declinaciones por pozo y/o subunidad | F24: 1. Elaboración y seguimiento a la estrategía de mitigación a la canalización presentada en los pozos AK-139 y AK-77 por el AK-26 2. Priorización de actividades para el POP del primer trimestre 2025 | G24: 1. https://ecopetrol.sharepoint.com/:p:/s/IAAKACIAS/EeE9kgAR8AxPn4UfJlXD_fAB2TJrx9FZPJU3F2Ddx2eXqQ?e=OQOaIb 2. https://ecopetrol.sharepoint.com/:x:/r/sites/IAAKACIAS/Documentos%20compartidos/34.%20POP%202024-2025/2025/ACT%20-%2011%2004%202025/POP_Vs_P50_RETO_11042025.xlsx?d=w0dc02f860ec24a6087e089a015726a66&csf=1&web=1&e=Z1XrGc | H24: 10 | I24: 4 | J24: =IFERROR(I24/H24,0) -> 0.4 | K24: =+I24 -> 4 | L24: =IFERROR(K24/H24,0) -> 0.4
B25: 3 | C25: 3.17 | D25: Analizar data histórica de producción, productividad y daño por pozo | F25: 1. Interpretación del PBU AK-156 2. Corrida de nodales para ver efecto de la petrofísica en la afectación de la productividad 3. Ajuste en la visualización de la pestaña de productividad en el tablero 2.6 para visualizar la data historica posterior a la entrada de la estación Orotoy | G25: 1. https://ecopetrol.sharepoint.com/:p:/s/IAAKACIAS/ETSl4EzNkxNCkKTkU5P7IlkBDiDfVPy--BoTL_sWcDdiPQ?e=SP4KAX 2. W:\2.- Ingeniería de Yacimientos\1.MONITOREO\3. Nodales\Analisis Nodal AK-153 3. https://ecopetrol.sharepoint.com/:u:/s/SeguimientoIAChichimeneECP/Ed09N9_VW1ZKvB1ao5Awy-gB2QfQA2HA2vexqLo-aLJh9g?e=nnAQQx | H25: 10 | I25: 3 | J25: =IFERROR(I25/H25,0) -> 0.3 | K25: =+I25 -> 3 | L25: =IFERROR(K25/H25,0) -> 0.3
B26: 3 | C26: 3.18 | D26: Generar perfiles de Producción por pozos para pozos existente en escenarios Bajo, Medio y Alto | F26: 1. Corrida del Resnode para el 2Q del 2025 | G26: 1. https://ecopetrol.sharepoint.com/:f:/s/IAAKACIAS/EqoG8uZYFsJNspSJS8-rSVwBZAlMrsbUA1Y20jTltnDz9g?e=OEg0Ft | H26: 10 | I26: 3 | J26: =IFERROR(I26/H26,0) -> 0.3 | K26: =+I26 -> 3 | L26: =IFERROR(K26/H26,0) -> 0.3
B27: 5 | C27: 5.2 | D27: Generación de oportunidades de intervención a Pozos | F27: 1. Intervención y análisis para reactivación de los pozos NE-3 y AK-153 2. Aplicación de la metodología planteada para selección de candidatos de CAF | G27: 1. https://ecopetrol.sharepoint.com/:p:/s/IAAKACIAS/EVyNiCrA7vJLvqXNF7yt4XUBTSxOfZlIpPCElt9CI5_Q4A?e=nxAcRe 2. https://ecopetrol.sharepoint.com/:p:/s/IAAKACIAS/EUKgWHePs4lCu3t20r0UTf8BODOHQh_ioXZYeBUMqFqrmw?e=jNtCfN 3. https://ecopetrol.sharepoint.com/:f:/s/IAAKACIAS/EkNgGC2v_1BCrY4XoGinTtkBsvHzYHtlrhuRMyD9NgJ5Jg?e=mvoKQM | H27: 10 | I27: 5 | J27: =IFERROR(I27/H27,0) -> 0.5 | K27: =+I27 -> 5 | L27: =IFERROR(K27/H27,0) -> 0.5
B28: 5 | C28: 5.9 | D28: Realizar el seguimiento de producción/ inyección de pozos intervenidos con base en los comportamientos de producción previo y posterior a la intervención | F28: 1. Definición y arranque del proyecto frontera ChiAk 2. Elaboración del docuemento para solicitud de producción temprana de los pozos Tejón-1 y Guamal profundo-1 | G28: 1. https://ecopetrol.sharepoint.com/:p:/r/sites/SeguimientoIAChichimeneECP/Documentos%20compartidos/36.%20Pozos%20Frontera/Protocolo%20Frontera.pptx?d=w93ed7554ac204e7e8a8bd69117896fad&csf=1&web=1&e=6JB57S 2. https://ecopetrol.sharepoint.com/:w:/s/IAAKACIAS/ESeATH2EI_xHiKHHxQYxEA0BmDMgLNeivKiYl9dRPYtigw?e=RqhYlH | H28: 10 | I28: 3 | J28: =IFERROR(I28/H28,0) -> 0.3 | K28: =+I28 -> 3 | L28: =IFERROR(K28/H28,0) -> 0.3
B29: 8 | C29: 8.2 | D29: Carga de datos, procesamiento de datos, Análisis Estadístico descriptivo considerando hipótesis desde la teoría, y análisis descriptivo considerando hipótesis generadas desde la misma data (pasos 1, 2 y 3 teoría CRISP-DM). | F29: 1/2/3. Soporte en la carga semanal y análisis de datos en repositorios de bases de datos correspondientes al campo Akacias (proyecto Sahara, AVM, tableros de producción, molinos de viento y control de proyectos, WellMeeting. | G29: 2. W:\2.- Ingeniería de Yacimientos\1.MONITOREO\22.Well Meeting\2025\4. Abril | H29: 10 | I29: 3 | J29: =IFERROR(I29/H29,0) -> 0.3 | K29: =+I29 -> 3 | L29: =IFERROR(K29/H29,0) -> 0.3
B30: 1 | C30: 1.2 | D30: Generación Bases de Datos de Pozos (Registros, Topes e información disponible) | E30: Julian A Hernández | F30: 1) Actualización con la base de datos con información final para los pozos CH-234, AK-145, CH-239. Planes direccionales pozos AK-214, CHSW94 y CH-236. | G30: \\10.100.25.35\pgtrabajodigital\JAH\Proyecto groups21\akacias\2.- Ingeniería de Yacimientos\1.MONITOREO | H30: 15 | I30: 4 | J30: =IFERROR(I30/H30,0) -> 0.26666667 | K30: =+I30 -> 4 | L30: =IFERROR(K30/H30,0) -> 0.26666667
B31: 1 | C31: 1.3 | D31: Interpretación Sísmica | F31: 1) Revisón de información sismica para los pozos pertencientes a los patrones de inyección para identificar estructuras y establecer conectividades en los patrones de inyección. En busqueda del mejoramiento del factor de conectividad geológico. 2) Revisión información sísmica para identificar fallas o estrucutras en los patrones de inyección en pro de actualziar el factor de conectividad geológica para el campo Akacias. 3) Revisión en conjunto con el área de geofísica de la informaicón sismica para los pozos nuevos a perforar en el campo Akacias. | G31: \\10.100.25.35\pgtrabajodigital\JAH\Proyecto Z:\akacias\2.- Ingeniería de Yacimientos\1.MONITOREO\19.Sistematica WF Akacias\2025\04.Abril | H31: 8 | I31: 2 | J31: =IFERROR(I31/H31,0) -> 0.25 | K31: =+I31 -> 2 | L31: =IFERROR(K31/H31,0) -> 0.25
B32: 1 | C32: 1.5 | D32: Digitalización, digitación y/o captura de información geológica (Mapas, Raw Data, topes, etc.) | F32: 1) Generación mapas, cortes y correalciones para hacer seguimiento a los patrones de inyección del campo y monitoreo a los pozos productores. 2) Cargue informaicón final de los pozos CH-234, AK-145, CH-23 (registros e interpretación petrofísica). 3) Actualización y cargue de los planes direccionales finales para los pozos AK-214, CHSW94 y CH-236. | G32: \\10.100.25.35\pgtrabajodigital\JAH\Proyecto | H32: 10 | I32: 2 | J32: =IFERROR(I32/H32,0) -> 0.2 | K32: =+I32 -> 2 | L32: =IFERROR(K32/H32,0) -> 0.2
B33: 1 | C33: 1.8 | D33: Balanceo de Secciones | F33: 1) Contrucción en petrel de secciones que permitan observar la continuidad horizontal de los ciclos estratigráficos en pro de establecer la conectividad geológica en los patrones de inyección, en el monitoreo del WF para el campo Akacias. 2) Generación de secciones estructurales que permitan observar el comportamiento areal del yacimiento para monitorear el comportamiento de pozos productores y conectividades en patrones de inyección. 3) Generación de secciones que permitan evaluar la continuidad lateral del yacimiento en el análisis de los pozos con baja inyectividad del campo Akacias. Adicionalmente, contrucción del material dentro del análisis de conectividad del patron del pozo AK-26 en el área de Nueva Esperanza. | G33: \\10.100.25.35\pgtrabajodigital\JAH\Proyecto | H33: 8 | I33: 3 | J33: =IFERROR(I33/H33,0) -> 0.375 | K33: =+I33 -> 3 | L33: =IFERROR(K33/H33,0) -> 0.375
B34: 1 | C34: 1.9 | D34: Análisis de sellos de fallas | F34: 1) Revisión del modelo estrucutural para el análisis de los patrones de inyección y así establecer la comunicación entre Inyec-produc durantes las sesiones de WF Akacias. 2) Revisión de los posibles sellos estructurales que condicionen el factor falla involucrado en la determinación del factor de conectividad geológico y continuar con la actualización de los tableros de conectividad geológica. 3) Análisis de las fallas dentro del estudio para identificar la influencia del acuífero en el campo a nivel CHIAK. 4) Actualziación de la interpretación estructural e inicio del análisis de conectividad en los patrones de inyección del campo. | G34: \\10.100.25.35\pgtrabajodigital\JAH\Proyecto Z:\akacias\2.- Ingeniería de Yacimientos\1.MONITOREO\19.Sistematica WF Akacias\2025\04.Abril | H34: 10 | I34: 5 | J34: =IFERROR(I34/H34,0) -> 0.5 | K34: =+I34 -> 5 | L34: =IFERROR(K34/H34,0) -> 0.5
B35: 1 | C35: 1.10 | D35: Amarre Sísmica Pozo | F35: 1) Revisión de la información sismíca con la trayectoria en las trayectorias entre pozos inyectores y porductores para identicar el Factor falla involucrado dentro del factor de conectividad geológica, insumo para actualizar el factor de conectividad geológico y el mapa de conectividad. 2) Revisión de las fallas interpretadas en las zonas de los pozos próximos a perforar para identificar los posibles riesgos geológicos y geofísicos. | G35: \\10.100.25.35\pgtrabajodigital\JAH\Proyecto groups21\akacias\5. Información de pozos | H35: 8 | I35: 3 | J35: =IFERROR(I35/H35,0) -> 0.375 | K35: =+I35 -> 3 | L35: =IFERROR(K35/H35,0) -> 0.375
B36: 1 | C36: 1.12 | D36: Generación de mapas de facies | F36: 1) Continua la elaboración de la base de datos para la actualización de los tableros G&G CHIAK. 2) Hacer seguimiento áreal de las facies para identificar los cambios laterales de facies que puedan indicar el comportamiento de arenas yto en los pozos productores. | G36: \\10.100.25.35\pgtrabajodigital\JAH\Proyecto | H36: 8 | I36: 2 | J36: =IFERROR(I36/H36,0) -> 0.25 | K36: =+I36 -> 2 | L36: =IFERROR(K36/H36,0) -> 0.25
B37: 1 | C37: 1.15 | D37: Carga de información para poblar el modelo geocelular (direccionales, coordenadas, surveys, topes, data de presión, estados mecánicos, evento de pozos, etc.) | F37: 1) Actualización final pozos CH-234, AK-145, CH-239 y actualización de los planes direccionales pozos AK-214, CHSW94 y CH-236. 2) Cargue de últimos planes direccionales aprobados para los pozos de la Etapa ANE y Frontera. | G37: ruta: \\10.100.25.35\pgtrabajodigital\JAH\Proyecto | H37: 15 | I37: 4 | J37: =IFERROR(I37/H37,0) -> 0.26666667 | K37: =+I37 -> 4 | L37: =IFERROR(K37/H37,0) -> 0.26666667
B38: 1 | C38: 1.25 | D38: Análisis geoquímicos de Fingerprinting | F38: 1) Continua: Análisis de la posible influencia del acuífero a nivel CHIAK actualización del mapa con datos a corte del segundo semestre de 2024, a partir de la integración de información de análisis fisicoquímicos, continuidad estratigráfica, rasgos estructurales, resultados de PLTs e ILTs, BSW y Ql en los pozos de los campos Chichimene y Akacias. | G38: ruta: \\10.100.25.35\pgtrabajodigital\JAH\Proyecto | H38: 8 | I38: 5 | J38: =IFERROR(I38/H38,0) -> 0.625 | K38: =+I38 -> 5 | L38: =IFERROR(K38/H38,0) -> 0.625
B39: 3 | C39: 3.6 | D39: Generar Modelo analítico del yacimiento integrando la información disponible en un software específico | E39: Milton J Gualteros | F39: Actualización modelo analítico de yacimientos ARPS (Frontera y Desarrollo Postrerios) | G39: Microsoft Teams, Email, Sharepoint Y:\akacias\37. Archivos | H39: 12 | I39: 3 | J39: =IFERROR(I39/H39,0) -> 0.25 | K39: =+I39 -> 3 | L39: =IFERROR(K39/H39,0) -> 0.25
B40: 3 | C40: 3.13 | D40: Generar base de datos de producción (OFM o la que se requiera) | F40: Generación base de datos y construcción perfiles de producción campaña WO | G40: Microsoft Teams, Email, Sharepoint Y:\akacias\37. Archivos | H40: 11 | I40: 3 | J40: =IFERROR(I40/H40,0) -> 0.27272727 | K40: =+I40 -> 3 | L40: =IFERROR(K40/H40,0) -> 0.27272727
B41: 3 | C41: 3.16 | D41: Análisis de Declinaciones por pozo y/o subunidad | F41: Análisis de declinación pozos asociados a patrones de inyección | G41: Microsoft Teams, Email, Sharepoint Y:\akacias\37. Archivos | H41: 11 | I41: 4 | J41: =IFERROR(I41/H41,0) -> 0.36363636 | K41: =+I41 -> 4 | L41: =IFERROR(K41/H41,0) -> 0.36363636
B42: 3 | C42: 3.17 | D42: Analizar data histórica de producción, productividad y daño por pozo | F42: Análisis de data histórica de producción para seguimiento proceso Waterflooding | G42: Microsoft Teams, Email, Sharepoint Y:\akacias\37. Archivos | H42: 11 | I42: 4 | J42: =IFERROR(I42/H42,0) -> 0.36363636 | K42: =+I42 -> 4 | L42: =IFERROR(K42/H42,0) -> 0.36363636
B43: 3 | C43: 3.18 | D43: Generar perfiles de Producción por pozos para pozos existente en escenarios Bajo, Medio y Alto | F43: Generación Perfiles escenarios bajo, medio, alto en ARPS y evaluar perfiles enviados por auditor | G43: Microsoft Teams, Email, Sharepoint Y:\akacias\37. Archivos | H43: 11 | I43: 4 | J43: =IFERROR(I43/H43,0) -> 0.36363636 | K43: =+I43 -> 4 | L43: =IFERROR(K43/H43,0) -> 0.36363636
B44: 5 | C44: 5.2 | D44: Generación de oportunidades de intervención a Pozos | F44: Definición oportunidades de intervención en reunión sistematica WF | G44: Microsoft Teams, Email, Sharepoint Y:\akacias\37. Archivos | H44: 11 | I44: 4 | J44: =IFERROR(I44/H44,0) -> 0.36363636 | K44: =+I44 -> 4 | L44: =IFERROR(K44/H44,0) -> 0.36363636
B45: 5 | C45: 5.9 | D45: Realizar el seguimiento de producción/ inyección de pozos intervenidos con base en los comportamientos de producción previo y posterior a la intervención | F45: Seguimiento de Producción e Inyección del proyecto de waterflooding del campo akacias | G45: Microsoft Teams, Email, Sharepoint Y:\akacias\37. Archivos | H45: 12 | I45: 4 | J45: =IFERROR(I45/H45,0) -> 0.33333333 | K45: =+I45 -> 4 | L45: =IFERROR(K45/H45,0) -> 0.33333333
B46: 8 | C46: 8.2 | D46: Carga de datos, procesamiento de datos, Análisis Estadístico descriptivo considerando hipótesis desde la teoría, y análisis descriptivo considerando hipótesis generadas desde la misma data (pasos 1, 2 y 3 teoría CRISP-DM). | F46: Cargue, análisis y procesamiento de los datos del modelo análitico de yacimientos. Analisis de datos en PowerBI | G46: Microsoft Teams, Email, Sharepoint Y:\akacias\37. Archivos | H46: 11 | I46: 4 | J46: =IFERROR(I46/H46,0) -> 0.36363636 | K46: =+I46 -> 4 | L46: =IFERROR(K46/H46,0) -> 0.36363636
B47: 3 | C47: 3.6 | D47: Generar Modelo analítico del yacimiento integrando la información disponible en un software específico | E47: Ana M Castellanos | F47: Modelo Analítico - Perfiles de Producción - Informe del modelo | G47: \\10.100.25.60\sya\gec | H47: 20 | I47: 3 | J47: =IFERROR(I47/H47,0) -> 0.15 | K47: =+I47 -> 3 | L47: =IFERROR(K47/H47,0) -> 0.15
B48: 3 | C48: 3.13 | D48: Generar base de datos de producción (OFM o la que se requiera) | F48: Base de Datos | G48: \\10.100.25.60\sya\gec | H48: 20 | I48: 3 | J48: =IFERROR(I48/H48,0) -> 0.15 | K48: =+I48 -> 3 | L48: =IFERROR(K48/H48,0) -> 0.15
B49: 3 | C49: 3.14 | D49: Generar Distribución de Producción por sub- unidades (allocation) | F49: Base de Datos | G49: \\10.100.25.60\sya\gec | H49: 20 | I49: 4 | J49: =IFERROR(I49/H49,0) -> 0.2 | K49: =+I49 -> 4 | L49: =IFERROR(K49/H49,0) -> 0.2
B50: 3 | C50: 3.16 | D50: Análisis de Declinaciones por pozo y/o subunidad | F50: Base de Datos - Perfiles Generados - Informe del análisis | G50: https://ecopetrol.sharepoint.com/sites/BDSaharaCastilla/Documentos%20compartidos/Forms/AllItems.aspx?id=%2Fsites%2FBDSaharaCastilla%2FDocumentos%20compartidos%2FBD%20Sahara&viewid=a035cf74%2D0100%2D4f66%2Da914%2D651dfeb02341 | H50: 20 | I50: 3 | J50: =IFERROR(I50/H50,0) -> 0.15 | K50: =+I50 -> 3 | L50: =IFERROR(K50/H50,0) -> 0.15
B51: 3 | C51: 3.17 | D51: Analizar data histórica de producción, productividad y daño por pozo | F51: Base de Datos - Informe de la Evaluación | G51: \\10.100.25.60\sya\gec | H51: 20 | I51: 4 | J51: =IFERROR(I51/H51,0) -> 0.2 | K51: =+I51 -> 4 | L51: =IFERROR(K51/H51,0) -> 0.2
B52: 3 | C52: 3.18 | D52: Generar perfiles de Producción por pozos para pozos existente en escenarios Bajo, Medio y Alto | F52: Base de Datos - Informe de la Evaluación | G52: \\10.100.25.60\sya\gec Sahara/ Tableros de diagnostico | H52: 20 | I52: 3 | J52: =IFERROR(I52/H52,0) -> 0.15 | K52: =+I52 -> 3 | L52: =IFERROR(K52/H52,0) -> 0.15
B53: 5 | C53: 5.2 | D53: Generación de oportunidades de intervención a Pozos | F53: Base de Datos - Informe de la Evaluación | G53: https://wellmeeting.ecopetrol.com.co/home https://ecopetrol.sharepoint.com/sites/CastillaWOs2022/Documentos%20compartidos/Forms/AllItems.aspx | H53: 20 | I53: 3 | J53: =IFERROR(I53/H53,0) -> 0.15 | K53: =+I53 -> 3 | L53: =IFERROR(K53/H53,0) -> 0.15
B54: 5 | C54: 5.9 | D54: Realizar el seguimiento de producción/ inyección de pozos intervenidos con base en los comportamientos de producción previo y posterior a la intervención | F54: Base de Datos - Informe de la Evaluación | G54: 2025-04-21 Sahara VyP Castilla.zip https://ecopetrol.sharepoint.com/sites/BDSaharaCastilla/Documentos%20compartidos/Forms/AllItems.aspx?id=%2Fsites%2FBDSaharaCastilla%2FDocumentos%20compartidos%2FPresentaciones%20soporte%20sesiones%2F2025&viewid=a035cf74%2D0100%2D4f66%2Da914%2D651dfeb02341 | H54: 20 | I54: 4 | J54: =IFERROR(I54/H54,0) -> 0.2 | K54: =+I54 -> 4 | L54: =IFERROR(K54/H54,0) -> 0.2
B55: 8 | C55: 8.2 | D55: Carga de datos, procesamiento de datos, Análisis Estadístico descriptivo considerando hipótesis desde la teoría, y análisis descriptivo considerando hipótesis generadas desde la misma data (pasos 1, 2 y 3 teoría CRISP-DM). | F55: Informe, con estadísticas descriptivas, histogramas, pruebas de ajuste, etc. | G55: https://app.powerbi.com/singleSignOn?ru=https%3A%2F%2Fapp.powerbi.com%2Fgroups%2Fe5641789-d59d-4f86-b857-9812c65a1a04%2Freports%2Fdff68870-b9fb-4308-960e-6c4f8c41c79d%2FReportSection974a4271511adef5c478%3FnoSignUpCheck%3D1 | H55: 20 | I55: 3 | J55: =IFERROR(I55/H55,0) -> 0.15 | K55: =+I55 -> 3 | L55: =IFERROR(K55/H55,0) -> 0.15
B56: 3 | C56: 3.6 | D56: Generar Modelo analítico del yacimiento integrando la información disponible en un software específico | E56: Paola Gomez | F56: Se realizó cargue de pruebas de produccion, tasas de inyección, pruebas de ILT en la BD de Sahara, adicionalmente se realiza el seguimiento a las optimizaciones, rediseños y WO a ejecutar. | G56: \\10.100.25.60\sya\gec\Castilla\39. Proyecto_Inyeccion_de_Agua\SAHARA) y en las notas de wellmeeting | H56: 18 | I56: 3 | J56: =IFERROR(I56/H56,0) -> 0.16666667 | K56: =+I56 -> 3 | L56: =IFERROR(K56/H56,0) -> 0.16666667
B57: 3 | C57: 3.13 | D57: Generar base de datos de producción (OFM o la que se requiera) | F57: Se realiza el reporte de producción a partir de correos y del tablero de producción prorrateada el cual es alimentado con base en la producción por formas y pruebas de producción de AVM. | G57: DTWF CASTILLA-Tablero Castilla y \\10.100.25.60\sya\gec\Castilla\39. Proyecto_Inyeccion_de_Agua\SAHARA | H57: 36 | I57: 6 | J57: =IFERROR(I57/H57,0) -> 0.16666667 | K57: =+I57 -> 6 | L57: =IFERROR(K57/H57,0) -> 0.16666667
B58: 3 | C58: 3.14 | D58: Generar Distribución de Producción por sub- unidades (allocation) | F58: Para esta actividad se genera distribución vertical por unidad para los inyectores asociados a la Zona Centro Norte. La distribución se encuentra actualizada a la fecha con los últimos valores de ILT para cada inyector. La evidencia se encuentra en la Base de Datos SAHARA. | G58: \\10.100.25.60\sya\gec\Castilla\39. Proyecto_Inyeccion_de_Agua\SAHARA | H58: 12 | I58: 2 | J58: =IFERROR(I58/H58,0) -> 0.16666667 | K58: =+I58 -> 2 | L58: =IFERROR(K58/H58,0) -> 0.16666667
B59: 3 | C59: 3.16 | D59: Análisis de Declinaciones por pozo y/o subunidad | F59: De acuerdo con el seguimiento a la producción e inyección, se realizó el seguimiento a los patrones CAN15, CAN22, CAN462, CAN700 y CAN450. | G59: TEAMS del equipo I&A Castilla (Revision y seguimiento pozos Sur) | H59: 36 | I59: 6 | J59: =IFERROR(I59/H59,0) -> 0.16666667 | K59: =+I59 -> 6 | L59: =IFERROR(K59/H59,0) -> 0.16666667
B60: 3 | C60: 3.17 | D60: Analizar data histórica de producción, productividad y daño por pozo | F60: se realiza relaciones y comparaciones con los datos de producción e inyección de la zona Centro Norte cargada en la base de datos de Sahara. Ver mayor ampliación en GP-F-25 | G60: \\10.100.25.60\sya\gec\Castilla\39. Proyecto_Inyeccion_de_Agua\SAHARA\BD Sahara | H60: 18 | I60: 3 | J60: =IFERROR(I60/H60,0) -> 0.16666667 | K60: =+I60 -> 3 | L60: =IFERROR(K60/H60,0) -> 0.16666667
B61: 3 | C61: 3.18 | D61: Generar perfiles de Producción por pozos para pozos existente en escenarios Bajo, Medio y Alto | F61: Para este ítem para el mes de abril se realizó los perfiles son generados para los pozos candidatos a (RDG) rediseño y Workover (WO) los cuales quedan registrados en la ruta del equipo de taller de producción GDT | G61: GDT Plus (El V.A.R.) - General - Todos los documentos y https://ecopetrol.sharepoint.com/sites/CastillaWOs2022/Documentos%20compartidos/Forms/AllItems.aspx | H61: 18 | I61: 3 | J61: =IFERROR(I61/H61,0) -> 0.16666667 | K61: =+I61 -> 3 | L61: =IFERROR(K61/H61,0) -> 0.16666667
B62: 5 | C62: 5.2 | D62: Generación de oportunidades de intervención a Pozos | F62: Con el equipo multidiciplinario se realiza un análisis de los pozos encontrando bajas eficiencias y declinaciones presentadas de los pozos de la zona Centro Norte concluyendo las oportunidades de intervención en la medida que se puedan realizar las oportunidades en los pozos candidatos, lo cual queda consignado en el WM | G62: https://wellmeeting.ecopetrol.com.co/home | H62: 12 | I62: 2 | J62: =IFERROR(I62/H62,0) -> 0.16666667 | K62: =+I62 -> 2 | L62: =IFERROR(K62/H62,0) -> 0.16666667
B63: 5 | C63: 5.9 | D63: Realizar el seguimiento de producción/ inyección de pozos intervenidos con base en los comportamientos de producción previo y posterior a la intervención | F63: Se realizo el seguimiento de producción/ inyección de pozos a cargo (23 patrones de inyección) con base en los comportamientos de producción e inyección | G63: TEAMS del equipo I&A Castilla (Revision Seguimiento de pozos productores inyectores - Zona Sur) | H63: 18 | I63: 3 | J63: =IFERROR(I63/H63,0) -> 0.16666667 | K63: =+I63 -> 3 | L63: =IFERROR(K63/H63,0) -> 0.16666667
B64: 8 | C64: 8.2 | D64: Carga de datos, procesamiento de datos, Análisis Estadístico descriptivo considerando hipótesis desde la teoría, y análisis descriptivo considerando hipótesis generadas desde la misma data (pasos 1, 2 y 3 teoría CRISP-DM). | F64: Para este ítem se realizó carga de datos de ILT en la BD de Sahara. Se realizó la actualización de volumetrías del pozo CAN454. | G64: \\10.100.25.60\sya\gec\Castilla\39. Proyecto_Inyeccion_de_Agua\SAHARA) y en las notas de wellmeeting | H64: 12 | I64: 2 | J64: =IFERROR(I64/H64,0) -> 0.16666667 | K64: =+I64 -> 2 | L64: =IFERROR(K64/H64,0) -> 0.16666667
B65: 3 | C65: 3.6 | D65: Generar Modelo analítico del yacimiento integrando la información disponible en un software específico | E65: Geisson Zafra | F65: Se lleva a cabo la distribución de la Básica de productores del campo a inyectores (RWA), para los Volúmenes proporcionados por el certificador 2024. | G65: https://ecopetrol-my.sharepoint.com/:p:/g/personal/fabian_torres_ecopetrol_com_co1/EVDU7dil0AZKuEEvwl_wYUMBz5-ITb1XKJgfJvcLtCKwyg?email=geisson.zafra%40ecopetrol.com.co&e=wAKzzZ&wdOrigin=TEAMS-MAGLEV.p2p_ns.rwc&wdExp=TEAMS-TREATMENT&wdhostclicktime=1741892843119&web=1&previoussessionid=2053db84-be0f-ec5a-3ed2-fe60df430c3f | H65: 30 | I65: 4 | J65: =IFERROR(I65/H65,0) -> 0.13333333 | K65: =+I65 -> 4 | L65: =IFERROR(K65/H65,0) -> 0.13333333
B66: 3 | C66: 3.13 | D66: Generar base de datos de producción (OFM o la que se requiera) | F66: Se actualizan periodicamente diferentes archivos que alimentan Tableros, como lo es el 2.6 Seguimiento de producción Chiak. Igualmente archivos de consulta como Real vs P50. | G66: C:\Users\c110096a\Ecopetrol S.A\Seguimiento I&A Chichimene ECP - Documentos\04. Pwf Chichimene | H66: 30 | I66: 4 | J66: =IFERROR(I66/H66,0) -> 0.13333333 | K66: =+I66 -> 4 | L66: =IFERROR(K66/H66,0) -> 0.13333333
B67: 3 | C67: 3.14 | D67: Generar Distribución de Producción por sub- unidades (allocation) | F67: Se generan cargadores IMR, primaria y Real_RWA para el mes de marzo. Lo anterior con el fin de ser cargados en el tablero de PDI como reales del mes. | G67: https://ecopetrol.sharepoint.com/sites/SeguimientoIAChichimeneECP/Documentos%20compartidos/Forms/AllItems.aspx?id=%2Fsites%2FSeguimientoIAChichimeneECP%2FDocumentos%20compartidos%2F17%2E%20IMR%2F2024%2F10%2E%20Octubre&viewid=72844968%2Df801%2D450d%2D81d2%2D32c578273e17 | H67: 30 | I67: 3 | J67: =IFERROR(I67/H67,0) -> 0.1 | K67: =+I67 -> 3 | L67: =IFERROR(K67/H67,0) -> 0.1
B68: 3 | C68: 3.16 | D68: Análisis de Declinaciones por pozo y/o subunidad | F68: Se mantienen sesiones con Alejandra del equipo del declinador automático DCA, se construye archivo de Líneas Base que es entregado al equipo del DCA y se inicia el cargue en el mismo. | G68: N/A | H68: 30 | I68: 4 | J68: =IFERROR(I68/H68,0) -> 0.13333333 | K68: =+I68 -> 4 | L68: =IFERROR(K68/H68,0) -> 0.13333333
B69: 3 | C69: 3.17 | D69: Analizar data histórica de producción, productividad y daño por pozo | F69: Se analizan los reales del mes de marzo luego de generados los archivos cargadores de formas, a fin de realizar comparaciones pozo a pozo y que se identifiquen las brechas en patrones de REAL frente a P50, CERT, GOP 1Q y PDI. | G69: https://ecopetrol.sharepoint.com/sites/SeguimientoIAChichimeneECP/Documentos%20compartidos/Forms/AllItems.aspx?id=%2Fsites%2FSeguimientoIAChichimeneECP%2FDocumentos%20compartidos%2F11%2E%20Desviaciones%20Prod%5FIny%20Real%20vs%20P50%20vs%20Auditoria%20vs%20PDI%20vs%20GOP%20vs%20POP%2F2025&viewid=72844968%2Df801%2D450d%2D81d2%2D32c578273e17 | H69: 30 | I69: 3 | J69: =IFERROR(I69/H69,0) -> 0.1 | K69: =+I69 -> 3 | L69: =IFERROR(K69/H69,0) -> 0.1
B70: 3 | C70: 3.18 | D70: Generar perfiles de Producción por pozos para pozos existente en escenarios Bajo, Medio y Alto | F70: Se proporciona información de perfiles y volúmenes de pronóstico de reservas PDI a diferentes equipos y profesionales por solicitud. | G70: N/A | H70: 30 | I70: 3 | J70: =IFERROR(I70/H70,0) -> 0.1 | K70: =+I70 -> 3 | L70: =IFERROR(K70/H70,0) -> 0.1
B71: 5 | C71: 5.2 | D71: Generación de oportunidades de intervención a Pozos | F71: Se lleva a cabo el seguimiento de la campaña de WO vigente 2024-2026, al igual que se sostiene reunión de seguimiento de Planes Operativos con proyectos para actualizar el archivo correspondiente. | G71: https://ecopetrol.sharepoint.com/sites/SeguimientoIAChichimeneECP/Documentos%20compartidos/Forms/AllItems.aspx?id=%2Fsites%2FSeguimientoIAChichimeneECP%2FDocumentos%20compartidos%2F45%2E%20WorkOvers%20GCH%202024%2D2026%2D2027&viewid=72844968%2Df801%2D450d%2D81d2%2D32c578273e17 | H71: 30 | I71: 3 | J71: =IFERROR(I71/H71,0) -> 0.1 | K71: =+I71 -> 3 | L71: =IFERROR(K71/H71,0) -> 0.1
B72: 5 | C72: 5.9 | D72: Realizar el seguimiento de producción/ inyección de pozos intervenidos con base en los comportamientos de producción previo y posterior a la intervención | F72: Se lleva a cabo actualización del escenario Forecast en el tablero de Molinos de Viento, donde se hace referencia a la visión ECP. Lo anterior, a fin de realizar los análisis correspondientes. | G72: https://ecopetrol.sharepoint.com/sites/gcres/conso/Forms/AllItems.aspx?id=%2Fsites%2Fgcres%2Fconso%2F02%2E%20Informaci%C3%B3n%20ANH%2F06%2E%20ANH%202024%2FVRO%2FCHICHIMENE%2FINFORME&viewid=d5d52ee2%2D5e05%2D45ee%2D9b29%2D8f34fb00a583 | H72: 30 | I72: 3 | J72: =IFERROR(I72/H72,0) -> 0.1 | K72: =+I72 -> 3 | L72: =IFERROR(K72/H72,0) -> 0.1
B73: 8 | C73: 8.2 | D73: Carga de datos, procesamiento de datos, Análisis Estadístico descriptivo considerando hipótesis desde la teoría, y análisis descriptivo considerando hipótesis generadas desde la misma data (pasos 1, 2 y 3 teoría CRISP-DM). | F73: Se atienden diferentes sesiones, talleres y sistemáticas, en orden de planear las actividades del plan de cierre de brechas, la planeación del año desde los diferentes equipos, al igual que la sistemática del proyecto Frontera a fin de definir metodologías para su gerenciamiento adecuado. | G73: N/A | H73: 30 | I73: 3 | J73: =IFERROR(I73/H73,0) -> 0.1 | K73: =+I73 -> 3 | L73: =IFERROR(K73/H73,0) -> 0.1
B74: 3 | C74: 3.6 | D74: Generar Modelo analítico del yacimiento integrando la información disponible en un software específico | E74: Cesar E Rodriguez | F74: Se realizó el seguimiento a las optimizaciones, rediseños y WO a ejecutar. La información quedó asegurada en el archivo “Matriz priorizacion incrementos“ y "Priorizacion de acciones GDT_RD-WO-WS" | G74: \\10.100.25.60\sya\gec\Castilla\39. Proyecto_Inyeccion_de_Agua\SAHARA) y en las notas de wellmeeting | H74: 20 | I74: 3 | J74: =IFERROR(I74/H74,0) -> 0.15 | K74: =+I74 -> 3 | L74: =IFERROR(K74/H74,0) -> 0.15
B75: 3 | C75: 3.13 | D75: Generar base de datos de producción (OFM o la que se requiera) | F75: En la herramienta Sahara oficial con corte a Mar/2025, se corrigió y actualizó estado de capa y factores de alocacion pozos CA20 y CA65. Cargue de data de producción y Presiones dinamicas actualizadas a Abr/25 de zona centro sur | G75: \\10.100.25.60\sya\gec\Castilla\39. Proyecto_Inyeccion_de_Agua\SAHARA | H75: 14 | I75: 2 | J75: =IFERROR(I75/H75,0) -> 0.14285714 | K75: =+I75 -> 2 | L75: =IFERROR(K75/H75,0) -> 0.14285714
B76: 3 | C76: 3.14 | D76: Generar Distribución de Producción por sub- unidades (allocation) | F76: Por solicitud de la líder, se diligenciaron los siguientes archivos con la información actualizada del estado de los pozos productores e inyectores del área que tengo en monitoreo: Candidatos rediseños, Rediseños Ejecutados en 2024-2025 por zona. actualización de EM, propiedades petrofísicas y factores de alocación para los diferentes pozos en la BD de SAHARA | G76: DTWF CASTILLA - Tablero Castilla Fan Edition - Todos los documentos \\10.100.25.60\sya\gec\Castilla\39. Proyecto_Inyeccion_de_Agua\SAHARA\BD Sahara | H76: 28 | I76: 5 | J76: =IFERROR(I76/H76,0) -> 0.17857143 | K76: =+I76 -> 5 | L76: =IFERROR(K76/H76,0) -> 0.17857143
B77: 3 | C77: 3.16 | D77: Análisis de Declinaciones por pozo y/o subunidad | F77: De acuerdo con el seguimiento a la producción e inyección, se realizó el seguimiento a las optimizaciones realizadas en el mes de enero, febrero y marzo, de acuerdo con el BSW, pruebas de producción y toma de niveles. | G77: \\10.100.25.60\sya\gec\Castilla\39. Proyecto_Inyeccion_de_Agua\SAHARA\BD Sahara | H77: 16 | I77: 3 | J77: =IFERROR(I77/H77,0) -> 0.1875 | K77: =+I77 -> 3 | L77: =IFERROR(K77/H77,0) -> 0.1875
B78: 3 | C78: 3.17 | D78: Analizar data histórica de producción, productividad y daño por pozo | F78: Se llevaron a mesa los pozos CA277 con la finalidad de aprobar oportunidades de WOP. Visualizados pozos con oportunidad de RDG: CA347, CA254H. Ver mayor ampliación en GP-F-25 | G78: https://wellmeeting.ecopetrol.com.co/login | H78: 16 | I78: 3 | J78: =IFERROR(I78/H78,0) -> 0.1875 | K78: =+I78 -> 3 | L78: =IFERROR(K78/H78,0) -> 0.1875
B79: 3 | C79: 3.18 | D79: Generar perfiles de Producción por pozos para pozos existente en escenarios Bajo, Medio y Alto | F79: Se aseguraron los diagnósticos y acciones en wellmeeting por motivos de las revisiones con el equipo multidisciplinario y revisión interna. Ver mayor ampliación en GP-F-25 | G79: https://wellmeeting.ecopetrol.com.co/login GDT Plus (El V.A.R.) - General - Todos los documentos | H79: 12 | I79: 2 | J79: =IFERROR(I79/H79,0) -> 0.16666667 | K79: =+I79 -> 2 | L79: =IFERROR(K79/H79,0) -> 0.16666667
B80: 5 | C80: 5.2 | D80: Generación de oportunidades de intervención a Pozos | F80: De acuerdo con los rediseños propuestos en el plan de cierre de brechas, se obtuvo una lista de 4 pozos que se requieren optimizar, se irán priorizando de acuerdo con el presupuesto aprobado: CA228, CA449, CA104 y CA105. | G80: teams (Sistemática WF y Gestión de la Básica y en la BD SAHARA (\\10.100.25.60\sya\gec\Castilla\39. Proyecto_Inyeccion_de_Agua\SAHARA) | H80: 24 | I80: 4 | J80: =IFERROR(I80/H80,0) -> 0.16666667 | K80: =+I80 -> 4 | L80: =IFERROR(K80/H80,0) -> 0.16666667
B81: 5 | C81: 5.9 | D81: Realizar el seguimiento de producción/ inyección de pozos intervenidos con base en los comportamientos de producción previo y posterior a la intervención | F81: Se realizo el seguimiento de producción/ inyección de pozos a cargo (13 patrones de inyección) con base en los comportamientos de producción e inyección | G81: TEAMS del equipo I&A Castilla (Sistemática WF): https://ecopetrol.sharepoint.com/sites/DTWFCASTILLA/Documentos%20compartidos/Forms/AllItems.aspx?OR=Teams%2DHL&CT=1722020892543&clickparams=eyJBcHBOYW1lIjoiVGVhbXMtRGVza3RvcCIsIkFwcFZlcnNpb24iOiI0OS8yNDA2MjcyNDgxNCIsIkhhc0ZlZGVyYXRlZFVzZXIiOmZhbHNlfQ%3D%3D&id=%2Fsites%2FDTWFCASTILLA%2FDocumentos%20compartidos%2FGeneral&viewid=9ba680aa%2D7c76%2D4823%2Dbaac%2Dba7ef8ef6f87 | H81: 26 | I81: 4 | J81: =IFERROR(I81/H81,0) -> 0.15384615 | K81: =+I81 -> 4 | L81: =IFERROR(K81/H81,0) -> 0.15384615
B82: 8 | C82: 8.2 | D82: Carga de datos, procesamiento de datos, Análisis Estadístico descriptivo considerando hipótesis desde la teoría, y análisis descriptivo considerando hipótesis generadas desde la misma data (pasos 1, 2 y 3 teoría CRISP-DM). | F82: En cuanto a la herramienta OFM se realizó el cargue de la producción, inyección y pruebas del mes de Marzo/2025. La información quedó asegurada en el proyecto 131. \\10.100.25.35\ofm\c110095a | G82: La información quedó asegurada en el proyecto 131. \\10.100.25.35\ofm\c106559s | H82: 24 | I82: 4 | J82: =IFERROR(I82/H82,0) -> 0.16666667 | K82: =+I82 -> 4 | L82: =IFERROR(K82/H82,0) -> 0.16666667
B83: 3 | C83: 3.6 | D83: Generar Modelo analítico del yacimiento integrando la información disponible en un software específico | E83: Diego F Galeano | F83: 1. Pronosticos de NUevos proyectos WOrkover secundaria y REdiseños. 2, DOcumento de soporte de reservas Word y Power point 3. Pronosticos de Proyecto Expansion de recobro Unidades T2 y K1 4. Memorando de modificacion del proyecto Expansion de recobro mejorado 5. Reuniones sistematicas de los proyetos Etapa 4 y Modulo integral Norte /sur 6. pozos inyectores de polímero proceso IDA- Explansion CEOR . | G83: Digital-1. \\10.100.25.60\sya\GEC\Castilla\Proyecto W.O 2024 2027 GDT\WORKOVER Y REDISEÑOS SECUNDARIA 2. \\10.100.25.60\sya\GEC\Castilla\20.Proyecto IOR K2\Expansión Recobro Mejorado GDT\reconfiguracion ERM junio 2024 3.\10.100.25.60\sya\GEC\Castilla\102.T2\Revision 2024 2. Presentación Semanal Sistemática Etapa 4 3.https://ecopetrol.sharepoint.com/sites/CastillaWOs2022/Documentos%20compartidos/Forms 4.20230921 Sistemática Semanal - Sur Norte .pptx 5. \\10.100.25.60\sya\GEC\Castilla\20.Proyecto IOR K2\Expansión Recobro Mejorado GDT\02. EXP REC MEJORADO FASE 1 | H83: 30 | I83: 3 | J83: =IFERROR(I83/H83,0) -> 0.1 | K83: =+I83 -> 3 | L83: =IFERROR(K83/H83,0) -> 0.1
B84: 3 | C84: 3.13 | D84: Generar base de datos de producción (OFM o la que se requiera) | F84: 1. Uso de base de datos (OFM & Sahara) para Generacion de Pronosticos de Nuevos proyectos Workover secundaria y Rediseños. 2. Pronosticos de Proyecto Expansion de recobro Unidades T2 y K1 | G84: Digital-1. \\10.100.25.60\sya\GEC\Castilla\Proyecto W.O 2024 2027 GDT\WORKOVER Y REDISEÑOS SECUNDARIA 2. \\10.100.25.60\sya\GEC\Castilla\20.Proyecto IOR K2\Expansión Recobro Mejorado GDT\reconfiguracion ERM junio 2024 3.\10.100.25.60\sya\GEC\Castilla\102.T2\Revision 2024 | H84: 30 | I84: 3 | J84: =IFERROR(I84/H84,0) -> 0.1 | K84: =+I84 -> 3 | L84: =IFERROR(K84/H84,0) -> 0.1
B85: 3 | C85: 3.14 | D85: Generar Distribución de Producción por sub- unidades (allocation) | F85: 1. Analisis de distribución de la produccion e inyeccion por Fomacion (T2,K1 &K2), para la generacion Pronosticos de Nuevos proyectos WOrkover secundaria y Rediseños & Pronosticos de Proyecto Expansion de recobro Unidades T2 y K1 | G85: Digital-1. \\10.100.25.60\sya\GEC\Castilla\Proyecto W.O 2024 2027 GDT\WORKOVER Y REDISEÑOS SECUNDARIA 2. \\10.100.25.60\sya\GEC\Castilla\20.Proyecto IOR K2\Expansión Recobro Mejorado GDT\reconfiguracion ERM junio 2024 3.\10.100.25.60\sya\GEC\Castilla\102.T2\Revision 2024 2. Presentación Semanal Sistemática Etapa 4 3.https://ecopetrol.sharepoint.com/sites/CastillaWOs2022/Documentos%20compartidos/Forms 4.20230921 Sistemática Semanal - Sur Norte .pptx 5. \\10.100.25.60\sya\GEC\Castilla\20.Proyecto IOR K2\Expansión Recobro Mejorado GDT\02. EXP REC MEJORADO FASE 1 | H85: 30 | I85: 3 | J85: =IFERROR(I85/H85,0) -> 0.1 | K85: =+I85 -> 3 | L85: =IFERROR(K85/H85,0) -> 0.1
B86: 3 | C86: 3.16 | D86: Análisis de Declinaciones por pozo y/o subunidad | F86: 1. Pronosticos de NUevos proyectos WOrkover secundaria y REdiseños. 2, DOcumento de soporte de reservas Word y Power point 3. Pronosticos de Proyecto Expansion de recobro Unidades T2 y K1 4. Memorando de modificacion del proyecto Expansion de recobro mejorado 5. Reuniones sistematicas de los proyetos Etapa 4 y Modulo integral Norte /sur 6. pozos inyectores de polímero proceso IDA- Explansion CEOR . | G86: Digital-1. \\10.100.25.60\sya\GEC\Castilla\Proyecto W.O 2024 2027 GDT\WORKOVER Y REDISEÑOS SECUNDARIA 2. \\10.100.25.60\sya\GEC\Castilla\20.Proyecto IOR K2\Expansión Recobro Mejorado GDT\reconfiguracion ERM junio 2024 3.\10.100.25.60\sya\GEC\Castilla\102.T2\Revision 2024 2. Presentación Semanal Sistemática Etapa 4 3.https://ecopetrol.sharepoint.com/sites/CastillaWOs2022/Documentos%20compartidos/Forms 4.20230921 Sistemática Semanal - Sur Norte .pptx 5. \\10.100.25.60\sya\GEC\Castilla\20.Proyecto IOR K2\Expansión Recobro Mejorado GDT\02. EXP REC MEJORADO FASE 1 | H86: 30 | I86: 3 | J86: =IFERROR(I86/H86,0) -> 0.1 | K86: =+I86 -> 3 | L86: =IFERROR(K86/H86,0) -> 0.1
B87: 3 | C87: 3.17 | D87: Analizar data histórica de producción, productividad y daño por pozo | F87: Generar declinaciones historicas para Pronosticos de NUevos proyectos WOrkover secundaria y REdiseños. Segimiento a la produccion e inyeccion y declinaciones de los pozos del proyecto etapa 4. . | G87: Digital-1. \\10.100.25.60\sya\GEC\Castilla\Proyecto W.O 2024 2027 GDT\WORKOVER Y REDISEÑOS SECUNDARIA 2,\\10.100.25.60\sya\GEC\Castilla\DFGB Etapa 4 | H87: 30 | I87: 3 | J87: =IFERROR(I87/H87,0) -> 0.1 | K87: =+I87 -> 3 | L87: =IFERROR(K87/H87,0) -> 0.1
B88: 3 | C88: 3.18 | D88: Generar perfiles de Producción por pozos para pozos existente en escenarios Bajo, Medio y Alto | F88: Perfiles de produccion e inyeccion para proyectos Workover secundario GDT, expnasion de recobro unidades T2 & K1, evaluacion de resultados de los pozos etapa 4, en escenarios Bajo, Medio y Alto . | G88: Digital-1. \\10.100.25.60\sya\GEC\Castilla\Proyecto W.O 2024 2027 GDT\WORKOVER Y REDISEÑOS SECUNDARIA 2. \\10.100.25.60\sya\GEC\Castilla\20.Proyecto IOR K2\Expansión Recobro Mejorado GDT\reconfiguracion ERM junio 2024 3.\10.100.25.60\sya\GEC\Castilla\102.T2\Revision 2024 2. Presentación Semanal Sistemática Etapa 4 3 5. \\10.100.25.60\sya\GEC\Castilla\20.Proyecto IOR K2\Expansión Recobro Mejorado GDT\02. EXP REC MEJORADO FASE 1 | H88: 30 | I88: 3 | J88: =IFERROR(I88/H88,0) -> 0.1 | K88: =+I88 -> 3 | L88: =IFERROR(K88/H88,0) -> 0.1
B89: 5 | C89: 5.2 | D89: Generación de oportunidades de intervención a Pozos | F89: Maduración del proyecto Intervension de pozos (Rediseños 40 trabajos 2025, 40 trabajos 2026) . | G89: Digital-1. \\10.100.25.60\sya\GEC\Castilla\Proyecto W.O 2024 2027 GDT\WORKOVER Y REDISEÑOS SECUNDARIA | H89: 30 | I89: 4 | J89: =IFERROR(I89/H89,0) -> 0.13333333 | K89: =+I89 -> 4 | L89: =IFERROR(K89/H89,0) -> 0.13333333
B90: 5 | C90: 5.9 | D90: Realizar el seguimiento de producción/ inyección de pozos intervenidos con base en los comportamientos de producción previo y posterior a la intervención | F90: Seguimiento a la campaña de Workover en ejecucion Workover 2024-2027 GDT (antes, despues, e incremental), 7 trabajos ejecutados durante al año 2024 | G90: \\10.100.25.60\sya\GEC\Castilla\Proyecto W.O 2024 2027 GDT | H90: 30 | I90: 4 | J90: =IFERROR(I90/H90,0) -> 0.13333333 | K90: =+I90 -> 4 | L90: =IFERROR(K90/H90,0) -> 0.13333333
B91: 8 | C91: 8.2 | D91: Carga de datos, procesamiento de datos, Análisis Estadístico descriptivo considerando hipótesis desde la teoría, y análisis descriptivo considerando hipótesis generadas desde la misma data (pasos 1, 2 y 3 teoría CRISP-DM). | F91: Actualizacion de informacion de yacimiento para el Proyecto futuro Expansion de recobro Unidades T2 y K1 | G91: 1. \\10.100.25.60\sya\GEC\Castilla\20.Proyecto IOR K2\Expansión Recobro Mejorado GDT\reconfiguracion ERM junio 2024 3.\10.100.25.60\sya\GEC\Castilla\102.T2\Revision 2024 | H91: 30 | I91: 4 | J91: =IFERROR(I91/H91,0) -> 0.13333333 | K91: =+I91 -> 4 | L91: =IFERROR(K91/H91,0) -> 0.13333333
B92: 3 | C92: 3.6 | D92: Generar Modelo analítico del yacimiento integrando la información disponible en un software específico | E92: Luis Monsalve | F92: Modelo Analítico - Perfiles de Producción - Informe del modelo | G92: Repositorio digital: N:\39. Proyecto_Inyeccion_de_Agua\SAHARA\BD Sahara\2024-09-23 Sahara VyP Castilla | H92: 18 | I92: 3 | J92: =IFERROR(I92/H92,0) -> 0.16666667 | K92: =+I92 -> 3 | L92: =IFERROR(K92/H92,0) -> 0.16666667
B93: 3 | C93: 3.13 | D93: Generar base de datos de producción (OFM o la que se requiera) | F93: Base de Datos | G93: OFM: \\10.100.25.35\ofm\C1118546 | H93: 16 | I93: 3 | J93: =IFERROR(I93/H93,0) -> 0.1875 | K93: =+I93 -> 3 | L93: =IFERROR(K93/H93,0) -> 0.1875
B94: 3 | C94: 3.14 | D94: Generar Distribución de Producción por sub- unidades (allocation) | F94: Base de Datos | G94: Repositorio digital: N:\39. Proyecto_Inyeccion_de_Agua\SAHARA\BD Sahara\2024-10-21 Sahara VyP Castilla | H94: 16 | I94: 2 | J94: =IFERROR(I94/H94,0) -> 0.125 | K94: =+I94 -> 2 | L94: =IFERROR(K94/H94,0) -> 0.125
B95: 3 | C95: 3.16 | D95: Análisis de Declinaciones por pozo y/o subunidad | F95: Base de Datos - Perfiles Generados - Informe del análisis | G95: Repositorio digital: N:\39. Proyecto_Inyeccion_de_Agua\SAHARA\BD Sahara\2024-10-21 Sahara VyP Castilla | H95: 16 | I95: 2 | J95: =IFERROR(I95/H95,0) -> 0.125 | K95: =+I95 -> 2 | L95: =IFERROR(K95/H95,0) -> 0.125
B96: 3 | C96: 3.17 | D96: Analizar data histórica de producción, productividad y daño por pozo | F96: Base de Datos - Informe de la Evaluación | G96: Sharepoint: https://ecopetrol.sharepoint.com/sites/BDSaharaCastilla/Documentos%20compartidos/Forms/AllItems.aspx?id=%2Fsites%2FBDSaharaCastilla%2FDocumentos%20compartidos%2FPresentaciones%20soporte%20sesiones%2F2024&viewid=a035cf74%2D0100%2D4f66%2Da914%2D651dfeb02341&noAuthRedirect=1&OR=Teams%2DHL&CT=1729284822343&clickparams=eyJBcHBOYW1lIjoiVGVhbXMtRGVza3RvcCIsIkFwcFZlcnNpb24iOiI0OS8yNDA5MTIyMTMxOCIsIkhhc0ZlZGVyYXRlZFVzZXIiOmZhbHNlfQ%3D%3D | H96: 16 | I96: 2 | J96: =IFERROR(I96/H96,0) -> 0.125 | K96: =+I96 -> 2 | L96: =IFERROR(K96/H96,0) -> 0.125
B97: 3 | C97: 3.18 | D97: Generar perfiles de Producción por pozos para pozos existente en escenarios Bajo, Medio y Alto | F97: Base de Datos - Informe de la Evaluación | G97: Sharepoint: https://ecopetrol.sharepoint.com/sites/CastillaWOs2022/Documentos%20compartidos/Forms/AllItems.aspx?id=%2Fsites%2FCastillaWOs2022%2FDocumentos%20compartidos%2FJustificaciones&viewid=9ecb22f4%2D2d68%2D4a78%2Db78d%2Df5ff342528b5 | H97: 16 | I97: 3 | J97: =IFERROR(I97/H97,0) -> 0.1875 | K97: =+I97 -> 3 | L97: =IFERROR(K97/H97,0) -> 0.1875
B98: 5 | C98: 5.2 | D98: Generación de oportunidades de intervención a Pozos | F98: Base de Datos - Informe de la Evaluación | G98: Sharepoint: https://ecopetrol.sharepoint.com/sites/CastillaWOs2022/Documentos%20compartidos/Forms/AllItems.aspx?id=%2Fsites%2FCastillaWOs2022%2FDocumentos%20compartidos%2FJustificaciones&viewid=9ecb22f4%2D2d68%2D4a78%2Db78d%2Df5ff342528b5 | H98: 16 | I98: 3 | J98: =IFERROR(I98/H98,0) -> 0.1875 | K98: =+I98 -> 3 | L98: =IFERROR(K98/H98,0) -> 0.1875
B99: 5 | C99: 5.3 | D99: Estimar restricciones de Presión y tasas para la generación de perfiles de producción | F99: Base de Datos - Informe de la Evaluación | G99: Repositorio digital: N:\39. Proyecto_Inyeccion_de_Agua\SAHARA\BD Sahara\2024-09-23 Sahara VyP Castilla | H99: 16 | I99: 3 | J99: =IFERROR(I99/H99,0) -> 0.1875 | K99: =+I99 -> 3 | L99: =IFERROR(K99/H99,0) -> 0.1875
B100: 5 | C100: 5.5 | D100: Adelantar la evaluación e interpretación de datos enfocada a candidatización de actividades de reacondicionamiento y optimización de productividad en los activos | F100: Base de Datos - Informe de la Evaluación | G100: Sharepoint: https://ecopetrol.sharepoint.com/:x:/r/sites/ZonaEsteCAE/Documentos%20compartidos/CAE/Bit%C3%A1cora%20Zona%20Este.xlsx?d=w7a348467c50040ec94ebcaffa475a9d1&csf=1&web=1&e=I8Rzqg | H100: 18 | I100: 3 | J100: =IFERROR(I100/H100,0) -> 0.16666667 | K100: =+I100 -> 3 | L100: =IFERROR(K100/H100,0) -> 0.16666667
...

Sheet MAYO 2025
Q1: MES
B2: REPORTE DE AVANCE | Q2: ENERO
B3: Fecha: 29/06/2022 | F3: Version: 01 | J3: GP-F-23
Q4: FEBRERO
B5: Código Orden de servicio | D5: 90141005 | Q5: MARZO
Q6: JUNIO
B7: Mes a reportar | D7: MAYO | Q7: JULIO
Q8: AGOSTO
B9: Fecha reporte | D9: 45808 | Q9: SEPTIEMBRE
Q10: OCTUBRE
B11: Clasificación del servicio | I11: Reporte mes por servicio | K11: Reporte acumulado por servicio | Q11: NOVIEMBRE
B12: Ítem general | C12: ítem actividad | D12: Descripción de la actividad | E12: Profesional a cargo | F12: Soporte | G12: Medio de entrega | H12: Días contratados | I12: Días | J12: % avance | K12: Días | L12: % avance | Q12: DICIEMBRE
B13: 3 | C13: 3.6 | D13: Generar Modelo analítico del yacimiento integrando la información disponible en un software específico | E13: Alejandro D López | F13: Cambio en los cronogramas y perfiles del modelo analítico en ARPS para los perfiles de producción para el campo Akasias en para las etapas de ANE y Tinamu | G13: ACCESS - PLP 2024 - Todos los documentos (sharepoint.com) | H13: 20 | I13: 7 | J13: =IFERROR(I13/H13,0) -> 0.35 | K13: =+I13+'ABRIL 2025'!K13 -> 14 | L13: =IFERROR(K13/H13,0) -> 0.7
B14: 3 | C14: 3.13 | D14: Generar base de datos de producción (OFM o la que se requiera) | F14: Generar archivos de carga de productores, inyectores y allocacion para el campo Tinamu. Se realizó control de calidad a los archivos que se subieron al ARPS | G14: https://ecopetrol.sharepoint.com/sites/EquipoDesarrolloCPO-9/Documentos%20compartidos/Forms/AllItems.aspx?id=%2Fsites%2FEquipoDesarrolloCPO%2D9%2FDocumentos%20compartidos%2FGeneral%2F04%2DExploratorio%2FExploratorios%20CPO%2D9&viewid=0e96c994%2D47e1%2D4e99%2D93c0%2D37826753815c | H14: 10 | I14: 2 | J14: =IFERROR(I14/H14,0) -> 0.2 | K14: =+I14+'ABRIL 2025'!K14 -> 10 | L14: =IFERROR(K14/H14,0) -> 1
B15: 3 | C15: 3.16 | D15: Análisis de Declinaciones por pozo y/o subunidad | F15: Se generó un establecio la configuracion de allocacion de primeras y segundas lineas por RWA para el campo Akacias en la etapa de desarrollo temprano | G15: ACCESS - PLP 2024 - Todos los documentos (sharepoint.com) | H15: 10 | I15: 2 | J15: =IFERROR(I15/H15,0) -> 0.2 | K15: =+I15+'ABRIL 2025'!K15 -> 4 | L15: =IFERROR(K15/H15,0) -> 0.4
B16: 3 | C16: 3.17 | D16: Analizar data histórica de producción, productividad y daño por pozo | F16: Base de Datos - Informe de la Evaluación | G16: ACCESS - PLP 2024 - Todos los documentos (sharepoint.com) | H16: 10 | I16: 4 | J16: =IFERROR(I16/H16,0) -> 0.4 | K16: =+I16+'ABRIL 2025'!K16 -> 8 | L16: =IFERROR(K16/H16,0) -> 0.8
B17: 3 | C17: 3.18 | D17: Generar perfiles de Producción por pozos para pozos existente en escenarios Bajo, Medio y Alto | F17: Se generó un archivo parcial de analisis de produccion de los pozos de cercanos y perforados del campo Tinamu para usar su produccion como referencia para los futuros pozos del campo | G17: ACCESS - PLP 2024 - Todos los documentos (sharepoint.com) | H17: 10 | I17: 2 | J17: =IFERROR(I17/H17,0) -> 0.2 | K17: =+I17+'ABRIL 2025'!K17 -> 4 | L17: =IFERROR(K17/H17,0) -> 0.4
B18: 5 | C18: 5.2 | D18: Generación de oportunidades de intervención a Pozos | F18: Base de Datos - Informe de la Evaluación | G18: ACCESS - Frontera - Todos los documentos | H18: 10 | I18: 3 | J18: =IFERROR(I18/H18,0) -> 0.3 | K18: =+I18+'ABRIL 2025'!K18 -> 6 | L18: =IFERROR(K18/H18,0) -> 0.6
B19: 5 | C19: 5.9 | D19: Realizar el seguimiento de producción/ inyección de pozos intervenidos con base en los comportamientos de producción previo y posterior a la intervención | F19: Entrega de perfiles de la etapa de Tinamu para proyectos | G19: ACCESS - Tinamu - Todos los documentos | H19: 10 | I19: 4 | J19: =IFERROR(I19/H19,0) -> 0.4 | K19: =+I19+'ABRIL 2025'!K19 -> 5 | L19: =IFERROR(K19/H19,0) -> 0.5
B20: 8 | C20: 8.2 | D20: Carga de datos, procesamiento de datos, Análisis Estadístico descriptivo considerando hipótesis desde la teoría, y análisis descriptivo considerando hipótesis generadas desde la misma data (pasos 1, 2 y 3 teoría CRISP-DM). | F20: Informe, con estadísticas descriptivas, histogramas, pruebas de ajuste, etc. | G20: Informe de reservas Campo Akacias 2022 - Inicio (sharepoint.com) | H20: 10 | I20: 6 | J20: =IFERROR(I20/H20,0) -> 0.6 | K20: =+I20+'ABRIL 2025'!K20 -> 9 | L20: =IFERROR(K20/H20,0) -> 0.9
B21: 3 | C21: 3.6 | D21: Generar Modelo analítico del yacimiento integrando la información disponible en un software específico | E21: Jhon H Carreño | F21: 1. Actualización semanal del modelo estático y dinámico del yacimiento y pozos del campo Akacias, mediante el proyecto Sahara Mayo-2025 (Cargadores y modelo final) | G21: 1. X:\CHICHIMENE\INFORMACIÓN_CAMPO_CHICHIMENE\23.-Inyeccion de Agua\10. MONITOREO\09. Proyecto Sahara\2025\05.Mayo 2. W:\2.- Ingeniería de Yacimientos\1.MONITOREO\1.Sahara\2025\5. Mayo | H21: 10 | I21: 4 | J21: =IFERROR(I21/H21,0) -> 0.4 | K21: =+I21+'ABRIL 2025'!K21 -> 7 | L21: =IFERROR(K21/H21,0) -> 0.7
B22: 3 | C22: 3.13 | D22: Generar base de datos de producción (OFM o la que se requiera) | F22: 1. Actualización de la producción por proyecto y tipo de recobro en los Tableros 2.1 y las bases de datos de Molinos de viento de los pozos con la información del mes de abril de 2025 | G22: 1. W:\2.- Ingeniería de Yacimientos\1.MONITOREO\9.Tablero Power BI 2.1\2025\4. Abril 2. W:\2.- Ingeniería de Yacimientos\1.MONITOREO\14.Molinos de Viento\Cargadores\Real\2025\04. Abril | H22: 10 | I22: 3 | J22: =IFERROR(I22/H22,0) -> 0.3 | K22: =+I22+'ABRIL 2025'!K22 -> 6 | L22: =IFERROR(K22/H22,0) -> 0.6
B23: 3 | C23: 3.14 | D23: Generar Distribución de Producción por sub- unidades (allocation) | F23: 1. Distribución de la producción asociada a la implementación del WF en los patrones de inyección del campo AK por medio del metodo RWA con la información a cierre de Abr-2025 | G23: 1. W:\2.- Ingeniería de Yacimientos\1.MONITOREO\16.RWA\AKACIAS\2025\4. Abril | H23: 10 | I23: 3 | J23: =IFERROR(I23/H23,0) -> 0.3 | K23: =+I23+'ABRIL 2025'!K23 -> 6 | L23: =IFERROR(K23/H23,0) -> 0.6
B24: 3 | C24: 3.16 | D24: Análisis de Declinaciones por pozo y/o subunidad | F24: 1. Participación en el taller plan cierre de brechas a fin de establecer las actividades aprobadas y definir las bases para el plan de inversiones | G24: 1. https://ecopetrol.sharepoint.com/:p:/s/IAAKACIAS/ERuRkXh3wQNPus0uGyB1N9UB7yXfOj7XEmce1gOnmCt4Cg?e=3IEjmr | H24: 10 | I24: 3 | J24: =IFERROR(I24/H24,0) -> 0.3 | K24: =+I24+'ABRIL 2025'!K24 -> 7 | L24: =IFERROR(K24/H24,0) -> 0.7
B25: 3 | C25: 3.17 | D25: Analizar data histórica de producción, productividad y daño por pozo | F25: 1. Presentación del efecto de la inyección en la zona NE, comportamiento de presiones | G25: 1. W:\2.- Ingeniería de Yacimientos\1.MONITOREO\7.Presiones\2025\1_Semestre | H25: 10 | I25: 3 | J25: =IFERROR(I25/H25,0) -> 0.3 | K25: =+I25+'ABRIL 2025'!K25 -> 6 | L25: =IFERROR(K25/H25,0) -> 0.6
B26: 3 | C26: 3.18 | D26: Generar perfiles de Producción por pozos para pozos existente en escenarios Bajo, Medio y Alto | F26: 1. Elaboración del programa de evaluación de los pozos Tejón-1 y Guamal profundo-1 bajo el esquema de producción temprana 2. Ajuste de declinación y PDI para corrida de RWA en la PDP | G26: 1. W:\34.- Exploratorios CPO-09\Producción temprana Guamal 2. https://ecopetrol.sharepoint.com/:x:/r/sites/IAAKACIAS/Documentos%20compartidos/21.%20Portafolio/2025/4.-%20PDI%202025/1.-%20B%C3%A1sica/DCA/AT%20Dnm%20Template.xlsx?d=w728cdf274b4946b9addc4b9b6feb6ec8&csf=1&web=1&e=1X7h1Y | H26: 10 | I26: 4 | J26: =IFERROR(I26/H26,0) -> 0.4 | K26: =+I26+'ABRIL 2025'!K26 -> 7 | L26: =IFERROR(K26/H26,0) -> 0.7
B27: 5 | C27: 5.2 | D27: Generación de oportunidades de intervención a Pozos | F27: 1. Análisis de información previa y necesidad de adquisición de presiones para el AK-153 a fin de verificar la conexión con el bloque principal. 2. Análisis en Saphir para realizar una prueba de interferencia entre el AK-139 y AK-153 | G27: 1. W:\2.- Ingeniería de Yacimientos\1.MONITOREO\19.Sistematica WF Akacias\2025\04. Abril 2. W:\2.- Ingeniería de Yacimientos\1.MONITOREO\19.Sistematica WF Akacias\2025\05. Mayo | H27: 10 | I27: 3 | J27: =IFERROR(I27/H27,0) -> 0.3 | K27: =+I27+'ABRIL 2025'!K27 -> 8 | L27: =IFERROR(K27/H27,0) -> 0.8
B28: 5 | C28: 5.9 | D28: Realizar el seguimiento de producción/ inyección de pozos intervenidos con base en los comportamientos de producción previo y posterior a la intervención | F28: 1. Estrategía y escenarios de perdida de producción durante apagados de los pozos del CL-NE para evitar afectación en los pozos del patrón AK-26 | G28: 1. https://ecopetrol.sharepoint.com/:p:/s/IAAKACIAS/Eb1baMERUeNEjoPL3ygdW7oBXSSC67Fti9iIakUSZ0N6tw?e=b0S10l 2. https://ecopetrol.sharepoint.com/:x:/s/IAAKACIAS/EZdMvxsKHBNHmGIiwYOoHYEBZrEZrqxKMrOkARzdtJNFCw?e=GehYyk | H28: 10 | I28: 3 | J28: =IFERROR(I28/H28,0) -> 0.3 | K28: =+I28+'ABRIL 2025'!K28 -> 6 | L28: =IFERROR(K28/H28,0) -> 0.6
B29: 8 | C29: 8.2 | D29: Carga de datos, procesamiento de datos, Análisis Estadístico descriptivo considerando hipótesis desde la teoría, y análisis descriptivo considerando hipótesis generadas desde la misma data (pasos 1, 2 y 3 teoría CRISP-DM). | F29: 1. Registro de las actividades pendientes para el inyector frontera AK-147 en Wellmeeting 2. Registro de acciones especificas para los pozos Akacias | G29: 1 y 2. W:\2.- Ingeniería de Yacimientos\1.MONITOREO\22.Well Meeting\2025\5. Mayo | H29: 10 | I29: 4 | J29: =IFERROR(I29/H29,0) -> 0.4 | K29: =+I29+'ABRIL 2025'!K29 -> 7 | L29: =IFERROR(K29/H29,0) -> 0.7
B30: 1 | C30: 1.2 | D30: Generación Bases de Datos de Pozos (Registros, Topes e información disponible) | E30: Julian A Hernández | F30: 1) Actualización con la base de datos con información final para el pozo AK-147 y AK-221. Planes direccionales pozos AK-150 y AK-158 | G30: \\10.100.25.35\pgtrabajodigital\JAH\Proyecto groups21\akacias\2.- Ingeniería de Yacimientos\1.MONITOREO | H30: 15 | I30: 5 | J30: =IFERROR(I30/H30,0) -> 0.33333333 | K30: =+I30+'ABRIL 2025'!K30 -> 9 | L30: =IFERROR(K30/H30,0) -> 0.6
B31: 1 | C31: 1.3 | D31: Interpretación Sísmica | F31: 1) Revisón de información sismica para los pozos pertencientes a los patrones de inyección para identificar estructuras y establecer conectividades en los patrones de inyección. En busqueda del mejoramiento del factor de conectividad geológico. 2) Revisión información sísmica para identificar fallas o estrucutras en los patrones de inyección en pro de actualziar el factor de conectividad geológica para el campo Akacias. 3) Revisión en conjunto con el área de geofísica de la informaicón sismica para los pozos nuevos a perforar en el campo Akacias. | G31: \\10.100.25.35\pgtrabajodigital\JAH\Proyecto Z:\akacias\2.- Ingeniería de Yacimientos\1.MONITOREO\19.Sistematica WF Akacias\2025\05.Mayo | H31: 8 | I31: 3 | J31: =IFERROR(I31/H31,0) -> 0.375 | K31: =+I31+'ABRIL 2025'!K31 -> 5 | L31: =IFERROR(K31/H31,0) -> 0.625
B32: 1 | C32: 1.5 | D32: Digitalización, digitación y/o captura de información geológica (Mapas, Raw Data, topes, etc.) | F32: 1) Generación mapas, cortes y correalciones para hacer seguimiento a los patrones de inyección del campo y monitoreo a los pozos productores. 2) Cargue informaicón final de los pozos AK-147 y AK-221 (registros e interpretación petrofísica). 3) Actualización y cargue de los planes direccionales finales para los pozos AK-150 y AK-158. | G32: \\10.100.25.35\pgtrabajodigital\JAH\Proyecto | H32: 10 | I32: 3 | J32: =IFERROR(I32/H32,0) -> 0.3 | K32: =+I32+'ABRIL 2025'!K32 -> 5 | L32: =IFERROR(K32/H32,0) -> 0.5
B33: 1 | C33: 1.8 | D33: Balanceo de Secciones | F33: 1) Contrucción en petrel de secciones que permitan observar la continuidad horizontal de los ciclos estratigráficos en pro de establecer la conectividad geológica en los patrones de inyección, en el monitoreo del WF para el campo Akacias. 2) Generación de secciones estructurales que permitan observar el comportamiento areal del yacimiento para monitorear el comportamiento de pozos productores y conectividades en patrones de inyección. | G33: \\10.100.25.35\pgtrabajodigital\JAH\Proyecto | H33: 8 | I33: 2 | J33: =IFERROR(I33/H33,0) -> 0.25 | K33: =+I33+'ABRIL 2025'!K33 -> 5 | L33: =IFERROR(K33/H33,0) -> 0.625
B34: 1 | C34: 1.9 | D34: Análisis de sellos de fallas | F34: 1) Revisión del modelo estrucutural para el análisis de los patrones de inyección y así establecer la comunicación entre Inyec-produc durantes las sesiones de WF Akacias. 2) Revisión de los posibles sellos estructurales que condicionen el factor falla involucrado en la determinación del factor de conectividad geológico y continuar con la actualización de los tableros de conectividad geológica. 3) Análisis de las fallas dentro del estudio para identificar la influencia del acuífero en el campo a nivel CHIAK. 4) Continua la actualziación de la interpretación estructural e inicio del análisis de conectividad en los patrones de inyección del campo. | G34: \\10.100.25.35\pgtrabajodigital\JAH\Proyecto Z:\akacias\2.- Ingeniería de Yacimientos\1.MONITOREO\19.Sistematica WF Akacias\2025\05.Mayo | H34: 10 | I34: 3 | J34: =IFERROR(I34/H34,0) -> 0.3 | K34: =+I34+'ABRIL 2025'!K34 -> 8 | L34: =IFERROR(K34/H34,0) -> 0.8
B35: 1 | C35: 1.10 | D35: Amarre Sísmica Pozo | F35: 1) Revisión de la información sismíca con la trayectoria en las trayectorias entre pozos inyectores y porductores para identicar el Factor falla involucrado dentro del factor de conectividad geológica, insumo para actualizar el factor de conectividad geológico y el mapa de conectividad. 2) Revisión de las fallas interpretadas en las zonas de los pozos próximos a perforar para identificar los posibles riesgos geológicos y geofísicos, incolucrando la nueva información estructural. | G35: \\10.100.25.35\pgtrabajodigital\JAH\Proyecto groups21\akacias\5. Información de pozos | H35: 8 | I35: 3 | J35: =IFERROR(I35/H35,0) -> 0.375 | K35: =+I35+'ABRIL 2025'!K35 -> 6 | L35: =IFERROR(K35/H35,0) -> 0.75
B36: 1 | C36: 1.12 | D36: Generación de mapas de facies | F36: 1) Continua la elaboración de la base de datos para la actualización de los tableros G&G CHIAK. 2) Hacer seguimiento áreal de las facies para identificar los cambios laterales de facies que puedan indicar el comportamiento de arenas yto en los pozos productores. | G36: \\10.100.25.35\pgtrabajodigital\JAH\Proyecto | H36: 8 | I36: 3 | J36: =IFERROR(I36/H36,0) -> 0.375 | K36: =+I36+'ABRIL 2025'!K36 -> 5 | L36: =IFERROR(K36/H36,0) -> 0.625
B37: 1 | C37: 1.15 | D37: Carga de información para poblar el modelo geocelular (direccionales, coordenadas, surveys, topes, data de presión, estados mecánicos, evento de pozos, etc.) | F37: 1) Actualización final pozos AK-147 y AK-221 y actualización de los planes direccionales pozos AK-150 y AK-158. 2) Continua cargue de últimos planes direccionales aprobados para los pozos de la Etapa ANE y Frontera para la elaboración de los archivos RMS. | G37: ruta: \\10.100.25.35\pgtrabajodigital\JAH\Proyecto | H37: 15 | I37: 5 | J37: =IFERROR(I37/H37,0) -> 0.33333333 | K37: =+I37+'ABRIL 2025'!K37 -> 9 | L37: =IFERROR(K37/H37,0) -> 0.6
B38: 1 | C38: 1.25 | D38: Análisis geoquímicos de Fingerprinting | F38: 1) Continua: Análisis de la posible influencia del acuífero a nivel CHIAK actualización del mapa con datos a corte del segundo semestre de 2024, a partir de la integración de información de análisis fisicoquímicos, continuidad estratigráfica, rasgos estructurales, resultados de PLTs e ILTs, BSW y Ql en los pozos de los campos Chichimene y Akacias. | G38: ruta: \\10.100.25.35\pgtrabajodigital\JAH\Proyecto | H38: 8 | I38: 3 | J38: =IFERROR(I38/H38,0) -> 0.375 | K38: =+I38+'ABRIL 2025'!K38 -> 8 | L38: =IFERROR(K38/H38,0) -> 1
B39: 3 | C39: 3.6 | D39: Generar Modelo analítico del yacimiento integrando la información disponible en un software específico | E39: Milton J Gualteros | F39: Actualización modelo analítico de yacimientos ARPS (Frontera, ANE, A3's) | G39: Microsoft Teams, Email, Sharepoint Y:\akacias\37. Archivos | H39: 12 | I39: 5 | J39: =IFERROR(I39/H39,0) -> 0.41666667 | K39: =+I39+'ABRIL 2025'!K39 -> 8 | L39: =IFERROR(K39/H39,0) -> 0.66666667
B40: 3 | C40: 3.13 | D40: Generar base de datos de producción (OFM o la que se requiera) | F40: Generación base de datos y construcción perfiles proyecto inyección norte CHIAK | G40: Microsoft Teams, Email, Sharepoint Y:\akacias\37. Archivos | H40: 11 | I40: 4 | J40: =IFERROR(I40/H40,0) -> 0.36363636 | K40: =+I40+'ABRIL 2025'!K40 -> 7 | L40: =IFERROR(K40/H40,0) -> 0.63636364
B41: 3 | C41: 3.16 | D41: Análisis de Declinaciones por pozo y/o subunidad | F41: Análisis de declinación pozos asociados a patrones de inyección | G41: Microsoft Teams, Email, Sharepoint Y:\akacias\37. Archivos | H41: 11 | I41: 3 | J41: =IFERROR(I41/H41,0) -> 0.27272727 | K41: =+I41+'ABRIL 2025'!K41 -> 7 | L41: =IFERROR(K41/H41,0) -> 0.63636364
B42: 3 | C42: 3.17 | D42: Analizar data histórica de producción, productividad y daño por pozo | F42: Análisis de data histórica de producción para seguimiento proceso Waterflooding | G42: Microsoft Teams, Email, Sharepoint Y:\akacias\37. Archivos | H42: 11 | I42: 4 | J42: =IFERROR(I42/H42,0) -> 0.36363636 | K42: =+I42+'ABRIL 2025'!K42 -> 8 | L42: =IFERROR(K42/H42,0) -> 0.72727273
B43: 3 | C43: 3.18 | D43: Generar perfiles de Producción por pozos para pozos existente en escenarios Bajo, Medio y Alto | F43: Generación perfiles de producción escenarios bajo, medio, alto en ARPS (PDI) | G43: Microsoft Teams, Email, Sharepoint Y:\akacias\37. Archivos | H43: 11 | I43: 3 | J43: =IFERROR(I43/H43,0) -> 0.27272727 | K43: =+I43+'ABRIL 2025'!K43 -> 7 | L43: =IFERROR(K43/H43,0) -> 0.63636364
B44: 5 | C44: 5.2 | D44: Generación de oportunidades de intervención a Pozos | F44: Definición oportunidades de intervención en reunión sistematica WF | G44: Microsoft Teams, Email, Sharepoint Y:\akacias\37. Archivos | H44: 11 | I44: 3 | J44: =IFERROR(I44/H44,0) -> 0.27272727 | K44: =+I44+'ABRIL 2025'!K44 -> 7 | L44: =IFERROR(K44/H44,0) -> 0.63636364
B45: 5 | C45: 5.9 | D45: Realizar el seguimiento de producción/ inyección de pozos intervenidos con base en los comportamientos de producción previo y posterior a la intervención | F45: Seguimiento de Producción e Inyección del proyecto de waterflooding del campo akacias | G45: Microsoft Teams, Email, Sharepoint Y:\akacias\37. Archivos | H45: 12 | I45: 4 | J45: =IFERROR(I45/H45,0) -> 0.33333333 | K45: =+I45+'ABRIL 2025'!K45 -> 8 | L45: =IFERROR(K45/H45,0) -> 0.66666667
B46: 8 | C46: 8.2 | D46: Carga de datos, procesamiento de datos, Análisis Estadístico descriptivo considerando hipótesis desde la teoría, y análisis descriptivo considerando hipótesis generadas desde la misma data (pasos 1, 2 y 3 teoría CRISP-DM). | F46: Cargue, análisis y procesamiento de los datos del modelo análitico de yacimientos. Analisis de datos en PowerBI | G46: Microsoft Teams, Email, Sharepoint Y:\akacias\37. Archivos | H46: 11 | I46: 4 | J46: =IFERROR(I46/H46,0) -> 0.36363636 | K46: =+I46+'ABRIL 2025'!K46 -> 8 | L46: =IFERROR(K46/H46,0) -> 0.72727273
B47: 3 | C47: 3.6 | D47: Generar Modelo analítico del yacimiento integrando la información disponible en un software específico | E47: Ana M Castellanos | F47: Modelo Analítico - Perfiles de Producción - Informe del modelo | G47: \\10.100.25.60\sya\gec | H47: 20 | I47: 3 | J47: =IFERROR(I47/H47,0) -> 0.15 | K47: =+I47+'ABRIL 2025'!K47 -> 6 | L47: =IFERROR(K47/H47,0) -> 0.3
B48: 3 | C48: 3.13 | D48: Generar base de datos de producción (OFM o la que se requiera) | F48: Base de Datos | G48: \\10.100.25.60\sya\gec | H48: 20 | I48: 3 | J48: =IFERROR(I48/H48,0) -> 0.15 | K48: =+I48+'ABRIL 2025'!K48 -> 6 | L48: =IFERROR(K48/H48,0) -> 0.3
B49: 3 | C49: 3.14 | D49: Generar Distribución de Producción por sub- unidades (allocation) | F49: Base de Datos | G49: \\10.100.25.60\sya\gec | H49: 20 | I49: 4 | J49: =IFERROR(I49/H49,0) -> 0.2 | K49: =+I49+'ABRIL 2025'!K49 -> 8 | L49: =IFERROR(K49/H49,0) -> 0.4
B50: 3 | C50: 3.16 | D50: Análisis de Declinaciones por pozo y/o subunidad | F50: Base de Datos - Perfiles Generados - Informe del análisis | G50: https://ecopetrol.sharepoint.com/sites/BDSaharaCastilla/Documentos%20compartidos/Forms/AllItems.aspx?id=%2Fsites%2FBDSaharaCastilla%2FDocumentos%20compartidos%2FBD%20Sahara&viewid=a035cf74%2D0100%2D4f66%2Da914%2D651dfeb02341 | H50: 20 | I50: 3 | J50: =IFERROR(I50/H50,0) -> 0.15 | K50: =+I50+'ABRIL 2025'!K50 -> 6 | L50: =IFERROR(K50/H50,0) -> 0.3
B51: 3 | C51: 3.17 | D51: Analizar data histórica de producción, productividad y daño por pozo | F51: Base de Datos - Informe de la Evaluación | G51: \\10.100.25.60\sya\gec | H51: 20 | I51: 4 | J51: =IFERROR(I51/H51,0) -> 0.2 | K51: =+I51+'ABRIL 2025'!K51 -> 8 | L51: =IFERROR(K51/H51,0) -> 0.4
B52: 3 | C52: 3.18 | D52: Generar perfiles de Producción por pozos para pozos existente en escenarios Bajo, Medio y Alto | F52: Base de Datos - Informe de la Evaluación | G52: \\10.100.25.60\sya\gec Sahara/ Tableros de diagnostico | H52: 20 | I52: 3 | J52: =IFERROR(I52/H52,0) -> 0.15 | K52: =+I52+'ABRIL 2025'!K52 -> 6 | L52: =IFERROR(K52/H52,0) -> 0.3
B53: 5 | C53: 5.2 | D53: Generación de oportunidades de intervención a Pozos | F53: Base de Datos - Informe de la Evaluación | G53: https://wellmeeting.ecopetrol.com.co/home https://ecopetrol.sharepoint.com/sites/CastillaWOs2022/Documentos%20compartidos/Forms/AllItems.aspx | H53: 20 | I53: 3 | J53: =IFERROR(I53/H53,0) -> 0.15 | K53: =+I53+'ABRIL 2025'!K53 -> 6 | L53: =IFERROR(K53/H53,0) -> 0.3
B54: 5 | C54: 5.9 | D54: Realizar el seguimiento de producción/ inyección de pozos intervenidos con base en los comportamientos de producción previo y posterior a la intervención | F54: Base de Datos - Informe de la Evaluación | G54: 2025-04-21 Sahara VyP Castilla.zip https://ecopetrol.sharepoint.com/sites/BDSaharaCastilla/Documentos%20compartidos/Forms/AllItems.aspx?id=%2Fsites%2FBDSaharaCastilla%2FDocumentos%20compartidos%2FPresentaciones%20soporte%20sesiones%2F2025&viewid=a035cf74%2D0100%2D4f66%2Da914%2D651dfeb02341 | H54: 20 | I54: 4 | J54: =IFERROR(I54/H54,0) -> 0.2 | K54: =+I54+'ABRIL 2025'!K54 -> 8 | L54: =IFERROR(K54/H54,0) -> 0.4
B55: 8 | C55: 8.2 | D55: Carga de datos, procesamiento de datos, Análisis Estadístico descriptivo considerando hipótesis desde la teoría, y análisis descriptivo considerando hipótesis generadas desde la misma data (pasos 1, 2 y 3 teoría CRISP-DM). | F55: Informe, con estadísticas descriptivas, histogramas, pruebas de ajuste, etc. | G55: https://app.powerbi.com/singleSignOn?ru=https%3A%2F%2Fapp.powerbi.com%2Fgroups%2Fe5641789-d59d-4f86-b857-9812c65a1a04%2Freports%2Fdff68870-b9fb-4308-960e-6c4f8c41c79d%2FReportSection974a4271511adef5c478%3FnoSignUpCheck%3D1 | H55: 20 | I55: 3 | J55: =IFERROR(I55/H55,0) -> 0.15 | K55: =+I55+'ABRIL 2025'!K55 -> 6 | L55: =IFERROR(K55/H55,0) -> 0.3
B56: 3 | C56: 3.6 | D56: Generar Modelo analítico del yacimiento integrando la información disponible en un software específico | E56: Paola Gomez | F56: Se realizó cargue de pruebas de produccion, tasas de inyección, pruebas de ILT en la BD de Sahara CA61, CAN20, CAN255, CaN450, CAN49 Y CAN57, adicionalmente se realiza el seguimiento a las 22 optimizaciones, 1 rediseños y 6 WO a ejecutar. | G56: \\10.100.25.60\sya\gec\Castilla\39. Proyecto_Inyeccion_de_Agua\SAHARA) y en las notas de wellmeeting | H56: 18 | I56: 3 | J56: =IFERROR(I56/H56,0) -> 0.16666667 | K56: =+I56+'ABRIL 2025'!K56 -> 6 | L56: =IFERROR(K56/H56,0) -> 0.33333333
B57: 3 | C57: 3.13 | D57: Generar base de datos de producción (OFM o la que se requiera) | F57: Se realiza el reporte de producción a partir de correos y del tablero de producción prorrateada el cual es alimentado con base en la producción por formas y pruebas de producción de AVM. | G57: DTWF CASTILLA-Tablero Castilla y \\10.100.25.60\sya\gec\Castilla\39. Proyecto_Inyeccion_de_Agua\SAHARA | H57: 36 | I57: 6 | J57: =IFERROR(I57/H57,0) -> 0.16666667 | K57: =+I57+'ABRIL 2025'!K57 -> 12 | L57: =IFERROR(K57/H57,0) -> 0.33333333
B58: 3 | C58: 3.14 | D58: Generar Distribución de Producción por sub- unidades (allocation) | F58: Para esta actividad se genera distribución vertical por unidad para los inyectores asociados a la Zona Centro Norte. La distribución se encuentra actualizada a la fecha con los últimos valores de ILT para cada inyector CA61, CAN20, CAN255, CaN450, CAN49 Y CAN57 . La evidencia se encuentra en la Base de Datos SAHARA. | G58: \\10.100.25.60\sya\gec\Castilla\39. Proyecto_Inyeccion_de_Agua\SAHARA | H58: 12 | I58: 2 | J58: =IFERROR(I58/H58,0) -> 0.16666667 | K58: =+I58+'ABRIL 2025'!K58 -> 4 | L58: =IFERROR(K58/H58,0) -> 0.33333333
B59: 3 | C59: 3.16 | D59: Análisis de Declinaciones por pozo y/o subunidad | F59: De acuerdo con el seguimiento a la producción e inyección, se realizó el seguimiento a los patrones CA61, CAN57, CAN56, CAN05 y CAN700. | G59: https://teams.microsoft.com/l/channel/19%3A0KSR0Sqd9sL27-AWAKb2UFAmZ-fupgWBuEQNEHUYOIY1%40thread.tacv2/Documentos?groupId=ba918c77-3768-4ebd-affe-4ef992094119&tenantId=a4305987-cf78-4f93-9d64-bf18af65397b | H59: 36 | I59: 6 | J59: =IFERROR(I59/H59,0) -> 0.16666667 | K59: =+I59+'ABRIL 2025'!K59 -> 12 | L59: =IFERROR(K59/H59,0) -> 0.33333333
B60: 3 | C60: 3.17 | D60: Analizar data histórica de producción, productividad y daño por pozo | F60: se realiza relaciones y comparaciones con los datos de producción e inyección de la zona Centro Norte cargada en la base de datos de Sahara. Ver mayor ampliación en GP-F-25 | G60: \\10.100.25.60\sya\gec\Castilla\39. Proyecto_Inyeccion_de_Agua\SAHARA\BD Sahara | H60: 18 | I60: 3 | J60: =IFERROR(I60/H60,0) -> 0.16666667 | K60: =+I60+'ABRIL 2025'!K60 -> 6 | L60: =IFERROR(K60/H60,0) -> 0.33333333
B61: 3 | C61: 3.18 | D61: Generar perfiles de Producción por pozos para pozos existente en escenarios Bajo, Medio y Alto | F61: Para este ítem para el mes de abril se realizó los perfiles generados para los pozos candidatos a (RDG) rediseño y Workover (WO) los cuales quedan registrados en la ruta del equipo de taller de producción GDT | G61: GDT Plus (El V.A.R.) - General - Todos los documentos y https://ecopetrol.sharepoint.com/sites/CastillaWOs2022/Documentos%20compartidos/Forms/AllItems.aspx | H61: 18 | I61: 3 | J61: =IFERROR(I61/H61,0) -> 0.16666667 | K61: =+I61+'ABRIL 2025'!K61 -> 6 | L61: =IFERROR(K61/H61,0) -> 0.33333333
B62: 5 | C62: 5.2 | D62: Generación de oportunidades de intervención a Pozos | F62: Con el equipo multidiciplinario se realiza un análisis de los pozos encontrando bajas eficiencias y declinaciones presentadas de los pozos de la zona Centro Norte concluyendo las oportunidades de intervención en la medida que se puedan realizar las oportunidades en los pozos candidatos, lo cual queda consignado en el WM. Se declaran los pozos CAN128 y CAN238 con el inyector CAN462 | G62: https://wellmeeting.ecopetrol.com.co/home | H62: 12 | I62: 2 | J62: =IFERROR(I62/H62,0) -> 0.16666667 | K62: =+I62+'ABRIL 2025'!K62 -> 4 | L62: =IFERROR(K62/H62,0) -> 0.33333333
B63: 5 | C63: 5.9 | D63: Realizar el seguimiento de producción/ inyección de pozos intervenidos con base en los comportamientos de producción previo y posterior a la intervención | F63: Se realizo el seguimiento de producción/ inyección de pozos a cargo (23 patrones de inyección) con base en los comportamientos de producción e inyección | G63: https://teams.microsoft.com/l/channel/19%3A0KSR0Sqd9sL27-AWAKb2UFAmZ-fupgWBuEQNEHUYOIY1%40thread.tacv2/Documentos?groupId=ba918c77-3768-4ebd-affe-4ef992094119&tenantId=a4305987-cf78-4f93-9d64-bf18af65397b | H63: 18 | I63: 3 | J63: =IFERROR(I63/H63,0) -> 0.16666667 | K63: =+I63+'ABRIL 2025'!K63 -> 6 | L63: =IFERROR(K63/H63,0) -> 0.33333333
B64: 8 | C64: 8.2 | D64: Carga de datos, procesamiento de datos, Análisis Estadístico descriptivo considerando hipótesis desde la teoría, y análisis descriptivo considerando hipótesis generadas desde la misma data (pasos 1, 2 y 3 teoría CRISP-DM). | F64: Para este ítem se realizó carga de datos de ILT en la BD de Sahara. Se realizó la actualización de volumetrías del pozo CAN450 y CAN56. | G64: \\10.100.25.60\sya\gec\Castilla\39. Proyecto_Inyeccion_de_Agua\SAHARA) y en las notas de wellmeeting | H64: 12 | I64: 2 | J64: =IFERROR(I64/H64,0) -> 0.16666667 | K64: =+I64+'ABRIL 2025'!K64 -> 4 | L64: =IFERROR(K64/H64,0) -> 0.33333333
B65: 3 | C65: 3.6 | D65: Generar Modelo analítico del yacimiento integrando la información disponible en un software específico | E65: Geisson Zafra | F65: Se inicia con el proceso de actualización de la básica para la corrida de plan de inversiones 2025, para lo cual se establecen las declinaciones y puntos de amarre de los pozos productores del campo para plantear el pronóstico de la PDP. Se deben asegurar cronogramas de WO, pozos inactivos y conversiones que se plasman en estos perfiles PDP. Acto seguido, se aseguran RWA historia y RWA PDP, a fin de ver el comportamiento de la secundaria. | G65: https://ecopetrol.sharepoint.com/sites/SeguimientoIAChichimeneECP/Documentos%20compartidos/Forms/AllItems.aspx?id=%2Fsites%2FSeguimientoIAChichimeneECP%2FDocumentos%20compartidos%2F20%2E%20Portafolio%2F2025%2FPlanInversiones052025&newTargetListUrl=%2Fsites%2FSeguimientoIAChichimeneECP%2FDocumentos%20compartidos&viewpath=%2Fsites%2FSeguimientoIAChichimeneECP%2FDocumentos%20compartidos%2FForms%2FAllItems%2Easpx | H65: 30 | I65: 5 | J65: =IFERROR(I65/H65,0) -> 0.16666667 | K65: =+I65+'ABRIL 2025'!K65 -> 9 | L65: =IFERROR(K65/H65,0) -> 0.3
B66: 3 | C66: 3.13 | D66: Generar base de datos de producción (OFM o la que se requiera) | F66: Posteriormente a asegurados los RWA, se ajustan en los archivos preproceso para la entrada de la información al archivo de Curvas Características. Se inicia el ajuste de CC y se concentra la información en un solo archivo. | G66: https://ecopetrol.sharepoint.com/sites/SeguimientoIAChichimeneECP/Documentos%20compartidos/Forms/AllItems.aspx?id=%2Fsites%2FSeguimientoIAChichimeneECP%2FDocumentos%20compartidos%2F20%2E%20Portafolio%2F2025%2FPlanInversiones052025&newTargetListUrl=%2Fsites%2FSeguimientoIAChichimeneECP%2FDocumentos%20compartidos&viewpath=%2Fsites%2FSeguimientoIAChichimeneECP%2FDocumentos%20compartidos%2FForms%2FAllItems%2Easpx | H66: 30 | I66: 4 | J66: =IFERROR(I66/H66,0) -> 0.13333333 | K66: =+I66+'ABRIL 2025'!K66 -> 8 | L66: =IFERROR(K66/H66,0) -> 0.26666667
B67: 3 | C67: 3.14 | D67: Generar Distribución de Producción por sub- unidades (allocation) | F67: Se distribuyen los volúmenes del auditor, se prepara el RWA CERT para que los volúmenes ingresen al archivo de Curvas Caracteríasticas al igual que los volúmenes Outside, a fin de que sirvan como guía en el ajuste de curvas características. | G67: https://ecopetrol.sharepoint.com/sites/SeguimientoIAChichimeneECP/Documentos%20compartidos/Forms/AllItems.aspx?id=%2Fsites%2FSeguimientoIAChichimeneECP%2FDocumentos%20compartidos%2F17%2E%20IMR%2F2024%2F10%2E%20Octubre&viewid=72844968%2Df801%2D450d%2D81d2%2D32c578273e17 | H67: 30 | I67: 4 | J67: =IFERROR(I67/H67,0) -> 0.13333333 | K67: =+I67+'ABRIL 2025'!K67 -> 7 | L67: =IFERROR(K67/H67,0) -> 0.23333333
B68: 3 | C68: 3.16 | D68: Análisis de Declinaciones por pozo y/o subunidad | F68: Se mantienen sesiones con Alejandra del equipo del declinador automático DCA, ya que es la herramienta usada para declinar los perfiles PDP y de donde se toma la información para los cargadores de RWA PDP. Se evidenciaron falencias que fueron reportadas a medida que surgían para el ajuste de la herramienta. | G68: N/A | H68: 30 | I68: 4 | J68: =IFERROR(I68/H68,0) -> 0.13333333 | K68: =+I68+'ABRIL 2025'!K68 -> 8 | L68: =IFERROR(K68/H68,0) -> 0.26666667
B69: 3 | C69: 3.17 | D69: Analizar data histórica de producción, productividad y daño por pozo | F69: Se analizan los reales del mes de abril luego de generados los archivos cargadores de formas, a fin de realizar comparaciones pozo a pozo y que se identifiquen las brechas en patrones de REAL frente a P50, CERT, GOP 1Q y PDI. | G69: https://ecopetrol.sharepoint.com/sites/SeguimientoIAChichimeneECP/Documentos%20compartidos/Forms/AllItems.aspx?id=%2Fsites%2FSeguimientoIAChichimeneECP%2FDocumentos%20compartidos%2F11%2E%20Desviaciones%20Prod%5FIny%20Real%20vs%20P50%20vs%20Auditoria%20vs%20PDI%20vs%20GOP%20vs%20POP%2F2025&viewid=72844968%2Df801%2D450d%2D81d2%2D32c578273e17 | H69: 30 | I69: 2 | J69: =IFERROR(I69/H69,0) -> 0.066666667 | K69: =+I69+'ABRIL 2025'!K69 -> 5 | L69: =IFERROR(K69/H69,0) -> 0.16666667
B70: 3 | C70: 3.18 | D70: Generar perfiles de Producción por pozos para pozos existente en escenarios Bajo, Medio y Alto | F70: Se proporciona información de perfiles y volúmenes de pronóstico de reservas PDI de la corrida 12-2024 a diferentes equipos y profesionales por solicitud. | G70: N/A | H70: 30 | I70: 2 | J70: =IFERROR(I70/H70,0) -> 0.066666667 | K70: =+I70+'ABRIL 2025'!K70 -> 5 | L70: =IFERROR(K70/H70,0) -> 0.16666667
B71: 5 | C71: 5.2 | D71: Generación de oportunidades de intervención a Pozos | F71: Se lleva a cabo el seguimiento de la campaña de WO vigente 2024-2026, al igual que se sostiene reunión de seguimiento de Planes Operativos con proyectos para actualizar el archivo correspondiente. | G71: https://ecopetrol.sharepoint.com/sites/SeguimientoIAChichimeneECP/Documentos%20compartidos/Forms/AllItems.aspx?id=%2Fsites%2FSeguimientoIAChichimeneECP%2FDocumentos%20compartidos%2F45%2E%20WorkOvers%20GCH%202024%2D2026%2D2027&viewid=72844968%2Df801%2D450d%2D81d2%2D32c578273e17 | H71: 30 | I71: 3 | J71: =IFERROR(I71/H71,0) -> 0.1 | K71: =+I71+'ABRIL 2025'!K71 -> 6 | L71: =IFERROR(K71/H71,0) -> 0.2
B72: 5 | C72: 5.9 | D72: Realizar el seguimiento de producción/ inyección de pozos intervenidos con base en los comportamientos de producción previo y posterior a la intervención | F72: Se mantienen sesiones con el equipo de inyección, planeación e ingeniería, para definir PDT de inyección, cronograma de pozos inactivos y conversiones, y cronograma de WO's. | G72: https://ecopetrol.sharepoint.com/sites/SeguimientoIAChichimeneECP/Documentos%20compartidos/Forms/AllItems.aspx?id=%2Fsites%2FSeguimientoIAChichimeneECP%2FDocumentos%20compartidos%2F20%2E%20Portafolio%2F2025%2FPlanInversiones052025&newTargetListUrl=%2Fsites%2FSeguimientoIAChichimeneECP%2FDocumentos%20compartidos&viewpath=%2Fsites%2FSeguimientoIAChichimeneECP%2FDocumentos%20compartidos%2FForms%2FAllItems%2Easpx | H72: 30 | I72: 4 | J72: =IFERROR(I72/H72,0) -> 0.13333333 | K72: =+I72+'ABRIL 2025'!K72 -> 7 | L72: =IFERROR(K72/H72,0) -> 0.23333333
B73: 8 | C73: 8.2 | D73: Carga de datos, procesamiento de datos, Análisis Estadístico descriptivo considerando hipótesis desde la teoría, y análisis descriptivo considerando hipótesis generadas desde la misma data (pasos 1, 2 y 3 teoría CRISP-DM). | F73: Se atienden diferentes sesiones, talleres y sistemáticas, en orden de planear las actividades del plan de cierre de brechas, la planeación del año desde los diferentes equipos, al igual que la sistemática del proyecto Frontera a fin de definir metodologías para su gerenciamiento adecuado. | G73: N/A | H73: 30 | I73: 2 | J73: =IFERROR(I73/H73,0) -> 0.066666667 | K73: =+I73+'ABRIL 2025'!K73 -> 5 | L73: =IFERROR(K73/H73,0) -> 0.16666667
B74: 3 | C74: 3.6 | D74: Generar Modelo analítico del yacimiento integrando la información disponible en un software específico | E74: Cesar E Rodriguez | F74: Se realizó el seguimiento a las optimizaciones, rediseños y WO a ejecutar. La información quedó asegurada en el archivo “Matriz priorizacion incrementos“ y "Priorizacion de acciones GDT_RD-WO-WS" | G74: \\10.100.25.60\sya\gec\Castilla\39. Proyecto_Inyeccion_de_Agua\SAHARA) y en las notas de wellmeeting | H74: 20 | I74: 4 | J74: =IFERROR(I74/H74,0) -> 0.2 | K74: =+I74+'ABRIL 2025'!K74 -> 7 | L74: =IFERROR(K74/H74,0) -> 0.35
B75: 3 | C75: 3.13 | D75: Generar base de datos de producción (OFM o la que se requiera) | F75: En la herramienta Sahara oficial con corte a Abr/2025, se corrigió y actualizó estado de capa y factores de alocacion pozos CA257. Cargue de data de producción y Presiones dinamicas actualizadas a Abr/25 de zona centro sur | G75: \\10.100.25.60\sya\gec\Castilla\39. Proyecto_Inyeccion_de_Agua\SAHARA | H75: 14 | I75: 3 | J75: =IFERROR(I75/H75,0) -> 0.21428571 | K75: =+I75+'ABRIL 2025'!K75 -> 5 | L75: =IFERROR(K75/H75,0) -> 0.35714286
B76: 3 | C76: 3.14 | D76: Generar Distribución de Producción por sub- unidades (allocation) | F76: Por solicitud de la líder, se diligenciaron los siguientes archivos con la información actualizada del estado de los pozos productores e inyectores del área que tengo en monitoreo: Candidatos rediseños, Rediseños Ejecutados en 2025 por zona. actualización de EM, propiedades petrofísicas y factores de alocación para los diferentes pozos en la BD de SAHARA | G76: DTWF CASTILLA - Tablero Castilla Fan Edition - Todos los documentos \\10.100.25.60\sya\gec\Castilla\39. Proyecto_Inyeccion_de_Agua\SAHARA\BD Sahara | H76: 28 | I76: 4 | J76: =IFERROR(I76/H76,0) -> 0.14285714 | K76: =+I76+'ABRIL 2025'!K76 -> 9 | L76: =IFERROR(K76/H76,0) -> 0.32142857
B77: 3 | C77: 3.16 | D77: Análisis de Declinaciones por pozo y/o subunidad | F77: De acuerdo con el seguimiento a la producción e inyección, se realizó el seguimiento a las optimizaciones realizadas en el mes de enero, febrero, marzo y abril, de acuerdo con el BSW, pruebas de producción y toma de niveles. | G77: \\10.100.25.60\sya\gec\Castilla\39. Proyecto_Inyeccion_de_Agua\SAHARA\BD Sahara | H77: 16 | I77: 3 | J77: =IFERROR(I77/H77,0) -> 0.1875 | K77: =+I77+'ABRIL 2025'!K77 -> 6 | L77: =IFERROR(K77/H77,0) -> 0.375
B78: 3 | C78: 3.17 | D78: Analizar data histórica de producción, productividad y daño por pozo | F78: Se llevaron a mesa los pozos CA41H con la finalidad de aprobar oportunidades de WOP. Visualizados pozos con oportunidad de RDG: CA347. Ver mayor ampliación en GP-F-25 | G78: https://wellmeeting.ecopetrol.com.co/login | H78: 16 | I78: 3 | J78: =IFERROR(I78/H78,0) -> 0.1875 | K78: =+I78+'ABRIL 2025'!K78 -> 6 | L78: =IFERROR(K78/H78,0) -> 0.375
B79: 3 | C79: 3.18 | D79: Generar perfiles de Producción por pozos para pozos existente en escenarios Bajo, Medio y Alto | F79: Se aseguraron los diagnósticos y acciones en wellmeeting por motivos de las revisiones con el equipo multidisciplinario y revisión interna. Ver mayor ampliación en GP-F-25 | G79: https://wellmeeting.ecopetrol.com.co/login GDT Plus (El V.A.R.) - General - Todos los documentos | H79: 12 | I79: 2 | J79: =IFERROR(I79/H79,0) -> 0.16666667 | K79: =+I79+'ABRIL 2025'!K79 -> 4 | L79: =IFERROR(K79/H79,0) -> 0.33333333
B80: 5 | C80: 5.2 | D80: Generación de oportunidades de intervención a Pozos | F80: De acuerdo con los rediseños propuestos en el plan de cierre de brechas, se obtuvo una lista de 12 pozos que se requieren optimizar, se irán priorizando de acuerdo con el presupuesto aprobado: CA228, CA37, CA449, CA104 y CA105. | G80: teams (Sistemática WF y Gestión de la Básica y en la BD SAHARA (\\10.100.25.60\sya\gec\Castilla\39. Proyecto_Inyeccion_de_Agua\SAHARA) | H80: 24 | I80: 3 | J80: =IFERROR(I80/H80,0) -> 0.125 | K80: =+I80+'ABRIL 2025'!K80 -> 7 | L80: =IFERROR(K80/H80,0) -> 0.29166667
B81: 5 | C81: 5.9 | D81: Realizar el seguimiento de producción/ inyección de pozos intervenidos con base en los comportamientos de producción previo y posterior a la intervención | F81: Se realizo el seguimiento de producción/ inyección de pozos a cargo (13 patrones de inyección) con base en los comportamientos de producción e inyección | G81: TEAMS del equipo I&A Castilla (Sistemática WF): https://ecopetrol.sharepoint.com/sites/DTWFCASTILLA/Documentos%20compartidos/Forms/AllItems.aspx?OR=Teams%2DHL&CT=1722020892543&clickparams=eyJBcHBOYW1lIjoiVGVhbXMtRGVza3RvcCIsIkFwcFZlcnNpb24iOiI0OS8yNDA2MjcyNDgxNCIsIkhhc0ZlZGVyYXRlZFVzZXIiOmZhbHNlfQ%3D%3D&id=%2Fsites%2FDTWFCASTILLA%2FDocumentos%20compartidos%2FGeneral&viewid=9ba680aa%2D7c76%2D4823%2Dbaac%2Dba7ef8ef6f87 | H81: 26 | I81: 4 | J81: =IFERROR(I81/H81,0) -> 0.15384615 | K81: =+I81+'ABRIL 2025'!K81 -> 8 | L81: =IFERROR(K81/H81,0) -> 0.30769231
B82: 8 | C82: 8.2 | D82: Carga de datos, procesamiento de datos, Análisis Estadístico descriptivo considerando hipótesis desde la teoría, y análisis descriptivo considerando hipótesis generadas desde la misma data (pasos 1, 2 y 3 teoría CRISP-DM). | F82: En cuanto a la herramienta OFM se realizó el cargue de la producción, inyección y pruebas del mes de Abril/2025. La información quedó asegurada en el proyecto 05. Proyecto OFM\Archivos Excel\Cargue OFM\2025 | G82: La información quedó asegurada en el proyecto 131. \\10.100.25.60\sya\gec\05. Proyecto OFM\Archivos Excel\Cargue OFM\2025 | H82: 24 | I82: 4 | J82: =IFERROR(I82/H82,0) -> 0.16666667 | K82: =+I82+'ABRIL 2025'!K82 -> 8 | L82: =IFERROR(K82/H82,0) -> 0.33333333
B83: 3 | C83: 3.6 | D83: Generar Modelo analítico del yacimiento integrando la información disponible en un software específico | E83: Diego F Galeano | F83: 1. Pronosticos de NUevos proyectos WOrkover secundaria y REdiseños. 2, DOcumento de soporte de reservas Word y Power point 3. Pronosticos de Proyecto Expansion de recobro Unidades T2 y K1 4. Memorando de modificacion del proyecto Expansion de recobro mejorado 5. Reuniones sistematicas de los proyetos Etapa 4 y Modulo integral Norte /sur 6. pozos inyectores de polímero proceso IDA- Explansion CEOR . | G83: Digital-1. \\10.100.25.60\sya\GEC\Castilla\Proyecto W.O 2024 2027 GDT\WORKOVER Y REDISEÑOS SECUNDARIA 2. \\10.100.25.60\sya\GEC\Castilla\20.Proyecto IOR K2\Expansión Recobro Mejorado GDT\reconfiguracion ERM junio 2024 3.\10.100.25.60\sya\GEC\Castilla\102.T2\Revision 2024 2. Presentación Semanal Sistemática Etapa 4 3.https://ecopetrol.sharepoint.com/sites/CastillaWOs2022/Documentos%20compartidos/Forms 4.20230921 Sistemática Semanal - Sur Norte .pptx 5. \\10.100.25.60\sya\GEC\Castilla\20.Proyecto IOR K2\Expansión Recobro Mejorado GDT\02. EXP REC MEJORADO FASE 1 | H83: 30 | I83: 3 | J83: =IFERROR(I83/H83,0) -> 0.1 | K83: =+I83+'ABRIL 2025'!K83 -> 6 | L83: =IFERROR(K83/H83,0) -> 0.2
B84: 3 | C84: 3.13 | D84: Generar base de datos de producción (OFM o la que se requiera) | F84: 1. Uso de base de datos (OFM & Sahara) para Generacion de Pronosticos de Nuevos proyectos Workover secundaria y Rediseños. 2. Pronosticos de Proyecto Expansion de recobro Unidades T2 y K1 | G84: Digital-1. \\10.100.25.60\sya\GEC\Castilla\Proyecto W.O 2024 2027 GDT\WORKOVER Y REDISEÑOS SECUNDARIA 2. \\10.100.25.60\sya\GEC\Castilla\20.Proyecto IOR K2\Expansión Recobro Mejorado GDT\reconfiguracion ERM junio 2024 3.\10.100.25.60\sya\GEC\Castilla\102.T2\Revision 2024 | H84: 30 | I84: 3 | J84: =IFERROR(I84/H84,0) -> 0.1 | K84: =+I84+'ABRIL 2025'!K84 -> 6 | L84: =IFERROR(K84/H84,0) -> 0.2
B85: 3 | C85: 3.14 | D85: Generar Distribución de Producción por sub- unidades (allocation) | F85: 1. Analisis de distribución de la produccion e inyeccion por Fomacion (T2,K1 &K2), para la generacion Pronosticos de Nuevos proyectos WOrkover secundaria y Rediseños & Pronosticos de Proyecto Expansion de recobro Unidades T2 y K1 | G85: Digital-1. \\10.100.25.60\sya\GEC\Castilla\Proyecto W.O 2024 2027 GDT\WORKOVER Y REDISEÑOS SECUNDARIA 2. \\10.100.25.60\sya\GEC\Castilla\20.Proyecto IOR K2\Expansión Recobro Mejorado GDT\reconfiguracion ERM junio 2024 3.\10.100.25.60\sya\GEC\Castilla\102.T2\Revision 2024 2. Presentación Semanal Sistemática Etapa 4 3.https://ecopetrol.sharepoint.com/sites/CastillaWOs2022/Documentos%20compartidos/Forms 4.20230921 Sistemática Semanal - Sur Norte .pptx 5. \\10.100.25.60\sya\GEC\Castilla\20.Proyecto IOR K2\Expansión Recobro Mejorado GDT\02. EXP REC MEJORADO FASE 1 | H85: 30 | I85: 3 | J85: =IFERROR(I85/H85,0) -> 0.1 | K85: =+I85+'ABRIL 2025'!K85 -> 6 | L85: =IFERROR(K85/H85,0) -> 0.2
B86: 3 | C86: 3.16 | D86: Análisis de Declinaciones por pozo y/o subunidad | F86: 1. Pronosticos de NUevos proyectos WOrkover secundaria y REdiseños. 2, DOcumento de soporte de reservas Word y Power point 3. Pronosticos de Proyecto Expansion de recobro Unidades T2 y K1 4. Memorando de modificacion del proyecto Expansion de recobro mejorado 5. Reuniones sistematicas de los proyetos Etapa 4 y Modulo integral Norte /sur 6. pozos inyectores de polímero proceso IDA- Explansion CEOR . | G86: Digital-1. \\10.100.25.60\sya\GEC\Castilla\Proyecto W.O 2024 2027 GDT\WORKOVER Y REDISEÑOS SECUNDARIA 2. \\10.100.25.60\sya\GEC\Castilla\20.Proyecto IOR K2\Expansión Recobro Mejorado GDT\reconfiguracion ERM junio 2024 3.\10.100.25.60\sya\GEC\Castilla\102.T2\Revision 2024 2. Presentación Semanal Sistemática Etapa 4 3.https://ecopetrol.sharepoint.com/sites/CastillaWOs2022/Documentos%20compartidos/Forms 4.20230921 Sistemática Semanal - Sur Norte .pptx 5. \\10.100.25.60\sya\GEC\Castilla\20.Proyecto IOR K2\Expansión Recobro Mejorado GDT\02. EXP REC MEJORADO FASE 1 | H86: 30 | I86: 3 | J86: =IFERROR(I86/H86,0) -> 0.1 | K86: =+I86+'ABRIL 2025'!K86 -> 6 | L86: =IFERROR(K86/H86,0) -> 0.2
B87: 3 | C87: 3.17 | D87: Analizar data histórica de producción, productividad y daño por pozo | F87: Generar declinaciones historicas para Pronosticos de NUevos proyectos WOrkover secundaria y REdiseños. Segimiento a la produccion e inyeccion y declinaciones de los pozos del proyecto etapa 4. . | G87: Digital-1. \\10.100.25.60\sya\GEC\Castilla\Proyecto W.O 2024 2027 GDT\WORKOVER Y REDISEÑOS SECUNDARIA 2,\\10.100.25.60\sya\GEC\Castilla\DFGB Etapa 4 | H87: 30 | I87: 3 | J87: =IFERROR(I87/H87,0) -> 0.1 | K87: =+I87+'ABRIL 2025'!K87 -> 6 | L87: =IFERROR(K87/H87,0) -> 0.2
B88: 3 | C88: 3.18 | D88: Generar perfiles de Producción por pozos para pozos existente en escenarios Bajo, Medio y Alto | F88: Perfiles de produccion e inyeccion para proyectos Workover secundario GDT, expnasion de recobro unidades T2 & K1, evaluacion de resultados de los pozos etapa 4, en escenarios Bajo, Medio y Alto . | G88: Digital-1. \\10.100.25.60\sya\GEC\Castilla\Proyecto W.O 2024 2027 GDT\WORKOVER Y REDISEÑOS SECUNDARIA 2. \\10.100.25.60\sya\GEC\Castilla\20.Proyecto IOR K2\Expansión Recobro Mejorado GDT\reconfiguracion ERM junio 2024 3.\10.100.25.60\sya\GEC\Castilla\102.T2\Revision 2024 2. Presentación Semanal Sistemática Etapa 4 3 5. \\10.100.25.60\sya\GEC\Castilla\20.Proyecto IOR K2\Expansión Recobro Mejorado GDT\02. EXP REC MEJORADO FASE 1 | H88: 30 | I88: 3 | J88: =IFERROR(I88/H88,0) -> 0.1 | K88: =+I88+'ABRIL 2025'!K88 -> 6 | L88: =IFERROR(K88/H88,0) -> 0.2
B89: 5 | C89: 5.2 | D89: Generación de oportunidades de intervención a Pozos | F89: Maduración del proyecto Intervension de pozos (Rediseños 40 trabajos 2025, 40 trabajos 2026) . | G89: Digital-1. \\10.100.25.60\sya\GEC\Castilla\Proyecto W.O 2024 2027 GDT\WORKOVER Y REDISEÑOS SECUNDARIA | H89: 30 | I89: 4 | J89: =IFERROR(I89/H89,0) -> 0.13333333 | K89: =+I89+'ABRIL 2025'!K89 -> 8 | L89: =IFERROR(K89/H89,0) -> 0.26666667
B90: 5 | C90: 5.9 | D90: Realizar el seguimiento de producción/ inyección de pozos intervenidos con base en los comportamientos de producción previo y posterior a la intervención | F90: Seguimiento a la campaña de Workover en ejecucion Workover 2024-2027 GDT (antes, despues, e incremental), 7 trabajos ejecutados durante al año 2024 | G90: \\10.100.25.60\sya\GEC\Castilla\Proyecto W.O 2024 2027 GDT | H90: 30 | I90: 4 | J90: =IFERROR(I90/H90,0) -> 0.13333333 | K90: =+I90+'ABRIL 2025'!K90 -> 8 | L90: =IFERROR(K90/H90,0) -> 0.26666667
B91: 8 | C91: 8.2 | D91: Carga de datos, procesamiento de datos, Análisis Estadístico descriptivo considerando hipótesis desde la teoría, y análisis descriptivo considerando hipótesis generadas desde la misma data (pasos 1, 2 y 3 teoría CRISP-DM). | F91: Actualizacion de informacion de yacimiento para el Proyecto futuro Expansion de recobro Unidades T2 y K1 | G91: 1. \\10.100.25.60\sya\GEC\Castilla\20.Proyecto IOR K2\Expansión Recobro Mejorado GDT\reconfiguracion ERM junio 2024 3.\10.100.25.60\sya\GEC\Castilla\102.T2\Revision 2024 | H91: 30 | I91: 4 | J91: =IFERROR(I91/H91,0) -> 0.13333333 | K91: =+I91+'ABRIL 2025'!K91 -> 8 | L91: =IFERROR(K91/H91,0) -> 0.26666667
B92: 3 | C92: 3.6 | D92: Generar Modelo analítico del yacimiento integrando la información disponible en un software específico | E92: Luis Monsalve | F92: Modelo Analítico - Perfiles de Producción - Informe del modelo | G92: Repositorio digital: N:\39. Proyecto_Inyeccion_de_Agua\SAHARA\BD Sahara\2024-09-23 Sahara VyP Castilla | H92: 18 | I92: 2 | J92: =IFERROR(I92/H92,0) -> 0.11111111 | K92: =+I92+'ABRIL 2025'!K92 -> 5 | L92: =IFERROR(K92/H92,0) -> 0.27777778
B93: 3 | C93: 3.13 | D93: Generar base de datos de producción (OFM o la que se requiera) | F93: Base de Datos | G93: OFM: \\10.100.25.35\ofm\C1118546 | H93: 16 | I93: 3 | J93: =IFERROR(I93/H93,0) -> 0.1875 | K93: =+I93+'ABRIL 2025'!K93 -> 6 | L93: =IFERROR(K93/H93,0) -> 0.375
B94: 3 | C94: 3.14 | D94: Generar Distribución de Producción por sub- unidades (allocation) | F94: Base de Datos | G94: Repositorio digital: N:\39. Proyecto_Inyeccion_de_Agua\SAHARA\BD Sahara\2024-10-21 Sahara VyP Castilla | H94: 16 | I94: 3 | J94: =IFERROR(I94/H94,0) -> 0.1875 | K94: =+I94+'ABRIL 2025'!K94 -> 5 | L94: =IFERROR(K94/H94,0) -> 0.3125
B95: 3 | C95: 3.16 | D95: Análisis de Declinaciones por pozo y/o subunidad | F95: Base de Datos - Perfiles Generados - Informe del análisis | G95: Repositorio digital: N:\39. Proyecto_Inyeccion_de_Agua\SAHARA\BD Sahara\2024-10-21 Sahara VyP Castilla | H95: 16 | I95: 3 | J95: =IFERROR(I95/H95,0) -> 0.1875 | K95: =+I95+'ABRIL 2025'!K95 -> 5 | L95: =IFERROR(K95/H95,0) -> 0.3125
B96: 3 | C96: 3.17 | D96: Analizar data histórica de producción, productividad y daño por pozo | F96: Base de Datos - Informe de la Evaluación | G96: Sharepoint: https://ecopetrol.sharepoint.com/sites/BDSaharaCastilla/Documentos%20compartidos/Forms/AllItems.aspx?id=%2Fsites%2FBDSaharaCastilla%2FDocumentos%20compartidos%2FPresentaciones%20soporte%20sesiones%2F2024&viewid=a035cf74%2D0100%2D4f66%2Da914%2D651dfeb02341&noAuthRedirect=1&OR=Teams%2DHL&CT=1729284822343&clickparams=eyJBcHBOYW1lIjoiVGVhbXMtRGVza3RvcCIsIkFwcFZlcnNpb24iOiI0OS8yNDA5MTIyMTMxOCIsIkhhc0ZlZGVyYXRlZFVzZXIiOmZhbHNlfQ%3D%3D | H96: 16 | I96: 3 | J96: =IFERROR(I96/H96,0) -> 0.1875 | K96: =+I96+'ABRIL 2025'!K96 -> 5 | L96: =IFERROR(K96/H96,0) -> 0.3125
B97: 3 | C97: 3.18 | D97: Generar perfiles de Producción por pozos para pozos existente en escenarios Bajo, Medio y Alto | F97: Base de Datos - Informe de la Evaluación | G97: Sharepoint: https://ecopetrol.sharepoint.com/sites/CastillaWOs2022/Documentos%20compartidos/Forms/AllItems.aspx?id=%2Fsites%2FCastillaWOs2022%2FDocumentos%20compartidos%2FJustificaciones&viewid=9ecb22f4%2D2d68%2D4a78%2Db78d%2Df5ff342528b5 | H97: 16 | I97: 3 | J97: =IFERROR(I97/H97,0) -> 0.1875 | K97: =+I97+'ABRIL 2025'!K97 -> 6 | L97: =IFERROR(K97/H97,0) -> 0.375
B98: 5 | C98: 5.2 | D98: Generación de oportunidades de intervención a Pozos | F98: Base de Datos - Informe de la Evaluación | G98: Sharepoint: https://ecopetrol.sharepoint.com/sites/CastillaWOs2022/Documentos%20compartidos/Forms/AllItems.aspx?id=%2Fsites%2FCastillaWOs2022%2FDocumentos%20compartidos%2FJustificaciones&viewid=9ecb22f4%2D2d68%2D4a78%2Db78d%2Df5ff342528b5 | H98: 16 | I98: 3 | J98: =IFERROR(I98/H98,0) -> 0.1875 | K98: =+I98+'ABRIL 2025'!K98 -> 6 | L98: =IFERROR(K98/H98,0) -> 0.375
B99: 5 | C99: 5.3 | D99: Estimar restricciones de Presión y tasas para la generación de perfiles de producción | F99: Base de Datos - Informe de la Evaluación | G99: Repositorio digital: N:\39. Proyecto_Inyeccion_de_Agua\SAHARA\BD Sahara\2024-09-23 Sahara VyP Castilla | H99: 16 | I99: 3 | J99: =IFERROR(I99/H99,0) -> 0.1875 | K99: =+I99+'ABRIL 2025'!K99 -> 6 | L99: =IFERROR(K99/H99,0) -> 0.375
B100: 5 | C100: 5.5 | D100: Adelantar la evaluación e interpretación de datos enfocada a candidatización de actividades de reacondicionamiento y optimización de productividad en los activos | F100: Base de Datos - Informe de la Evaluación | G100: Sharepoint: https://ecopetrol.sharepoint.com/:x:/r/sites/ZonaEsteCAE/Documentos%20compartidos/CAE/Bit%C3%A1cora%20Zona%20Este.xlsx?d=w7a348467c50040ec94ebcaffa475a9d1&csf=1&web=1&e=I8Rzqg | H100: 18 | I100: 3 | J100: =IFERROR(I100/H100,0) -> 0.16666667 | K100: =+I100+'ABRIL 2025'!K100 -> 6 | L100: =IFERROR(K100/H100,0) -> 0.33333333
...

Sheet JUNIO 2025
Q1: MES
B2: REPORTE DE AVANCE | Q2: ENERO
B3: Fecha: 29/06/2022 | F3: Version: 01 | J3: GP-F-23
Q4: FEBRERO
B5: Código Orden de servicio | D5: 90141005 | Q5: MARZO
Q6: JUNIO
B7: Mes a reportar | D7: JUNIO | Q7: JULIO
Q8: AGOSTO
B9: Fecha reporte | D9: 45838 | Q9: SEPTIEMBRE
Q10: OCTUBRE
B11: Clasificación del servicio | I11: Reporte mes por servicio | K11: Reporte acumulado por servicio | Q11: NOVIEMBRE
B12: Ítem general | C12: ítem actividad | D12: Descripción de la actividad | E12: Profesional a cargo | F12: Soporte | G12: Medio de entrega | H12: Días contratados | I12: Días | J12: % avance | K12: Días | L12: % avance | Q12: DICIEMBRE
B13: 3 | C13: 3.6 | D13: Generar Modelo analítico del yacimiento integrando la información disponible en un software específico | E13: Alejandro D López | F13: Cambio en los cronogramas y perfiles del modelo analítico en ARPS para los perfiles de producción para el campo Akasias en para las etapas de ANE y Tinamu | G13: ACCESS - PLP 2024 - Todos los documentos (sharepoint.com) | H13: 33 | I13: 6 | J13: =IFERROR(I13/H13,0) -> 0.18181818 | K13: =+I13+'MAYO 2025'!K13 -> 20 | L13: =IFERROR(K13/H13,0) -> 0.60606061
B14: 3 | C14: 3.13 | D14: Generar base de datos de producción (OFM o la que se requiera) | F14: - | G14: - | H14: 39 | I14: 0 | J14: =IFERROR(I14/H14,0) -> 0 | K14: =+I14+'MAYO 2025'!K14 -> 10 | L14: =IFERROR(K14/H14,0) -> 0.25641026
B15: 3 | C15: 3.16 | D15: Análisis de Declinaciones por pozo y/o subunidad | F15: Se generó un establecio la configuracion de allocacion de primeras y segundas lineas por RWA para el campo Akacias en la etapa de desarrollo temprano | G15: ACCESS - PLP 2024 - Todos los documentos (sharepoint.com) | H15: 33 | I15: 6 | J15: =IFERROR(I15/H15,0) -> 0.18181818 | K15: =+I15+'MAYO 2025'!K15 -> 10 | L15: =IFERROR(K15/H15,0) -> 0.3030303
B16: 3 | C16: 3.17 | D16: Analizar data histórica de producción, productividad y daño por pozo | F16: Base de Datos - Informe de la Evaluación | G16: ACCESS - PLP 2024 - Todos los documentos (sharepoint.com) | H16: 33 | I16: 2 | J16: =IFERROR(I16/H16,0) -> 0.060606061 | K16: =+I16+'MAYO 2025'!K16 -> 10 | L16: =IFERROR(K16/H16,0) -> 0.3030303
B17: 3 | C17: 3.18 | D17: Generar perfiles de Producción por pozos para pozos existente en escenarios Bajo, Medio y Alto | F17: Se generó un archivo parcial de analisis de produccion de los pozos de cercanos y perforados del campo Tinamu para usar su produccion como referencia para los futuros pozos del campo | G17: ACCESS - PLP 2024 - Todos los documentos (sharepoint.com) | H17: 33 | I17: 6 | J17: =IFERROR(I17/H17,0) -> 0.18181818 | K17: =+I17+'MAYO 2025'!K17 -> 10 | L17: =IFERROR(K17/H17,0) -> 0.3030303
B18: 5 | C18: 5.2 | D18: Generación de oportunidades de intervención a Pozos | F18: Base de Datos - Informe de la Evaluación | G18: ACCESS - Frontera - Todos los documentos | H18: 33 | I18: 4 | J18: =IFERROR(I18/H18,0) -> 0.12121212 | K18: =+I18+'MAYO 2025'!K18 -> 10 | L18: =IFERROR(K18/H18,0) -> 0.3030303
B19: 5 | C19: 5.9 | D19: Realizar el seguimiento de producción/ inyección de pozos intervenidos con base en los comportamientos de producción previo y posterior a la intervención | F19: Entrega de perfiles de la etapa de Tinamu para proyectos | G19: ACCESS - Tinamu - Todos los documentos | H19: 33 | I19: 5 | J19: =IFERROR(I19/H19,0) -> 0.15151515 | K19: =+I19+'MAYO 2025'!K19 -> 10 | L19: =IFERROR(K19/H19,0) -> 0.3030303
B20: 8 | C20: 8.2 | D20: Carga de datos, procesamiento de datos, Análisis Estadístico descriptivo considerando hipótesis desde la teoría, y análisis descriptivo considerando hipótesis generadas desde la misma data (pasos 1, 2 y 3 teoría CRISP-DM). | F20: Informe, con estadísticas descriptivas, histogramas, pruebas de ajuste, etc. | G20: Informe de reservas Campo Akacias 2022 - Inicio (sharepoint.com) | H20: 33 | I20: 1 | J20: =IFERROR(I20/H20,0) -> 0.03030303 | K20: =+I20+'MAYO 2025'!K20 -> 10 | L20: =IFERROR(K20/H20,0) -> 0.3030303
B21: 3 | C21: 3.6 | D21: Generar Modelo analítico del yacimiento integrando la información disponible en un software específico | E21: Jhon H Carreño | F21: 1. Actualización semanal del modelo estático y dinámico del yacimiento y pozos del campo Akacias, mediante el proyecto Sahara Junio-2025 (Cargadores y modelo final) | G21: X:\CHICHIMENE\INFORMACIÓN_CAMPO_CHICHIMENE\23.-Inyeccion de Agua\10. MONITOREO\09. Proyecto Sahara\2025\06. Junio W:\2.- Ingeniería de Yacimientos\1.MONITOREO\1.Sahara\2025\6. Junio | H21: 30 | I21: 3 | J21: =IFERROR(I21/H21,0) -> 0.1 | K21: =+I21+'MAYO 2025'!K21 -> 10 | L21: =IFERROR(K21/H21,0) -> 0.33333333
B22: 3 | C22: 3.13 | D22: Generar base de datos de producción (OFM o la que se requiera) | F22: 1. Actualización de la producción por proyecto y tipo de recobro en los Tableros 2.1 y los cargadores para la bases de datos de Molinos de viento de los pozos con la información del mes de mayo de 2025 | G22: W:\2.- Ingeniería de Yacimientos\1.MONITOREO\9.Tablero Power BI 2.1\2025 W:\2.- Ingeniería de Yacimientos\1.MONITOREO\14.Molinos de Viento\Cargadores\Real\2025 | H22: 30 | I22: 4 | J22: =IFERROR(I22/H22,0) -> 0.13333333 | K22: =+I22+'MAYO 2025'!K22 -> 10 | L22: =IFERROR(K22/H22,0) -> 0.33333333
B23: 3 | C23: 3.14 | D23: Generar Distribución de Producción por sub- unidades (allocation) | F23: 1. Distribución de la producción asociada a la implementación del WF en los patrones de inyección del campo AK por medio del metodo RWA con la información a cierre de May-2025 | G23: W:\2.- Ingeniería de Yacimientos\1.MONITOREO\16.RWA\AKACIAS\2025\5. Mayo | H23: 30 | I23: 4 | J23: =IFERROR(I23/H23,0) -> 0.13333333 | K23: =+I23+'MAYO 2025'!K23 -> 10 | L23: =IFERROR(K23/H23,0) -> 0.33333333
B24: 3 | C24: 3.16 | D24: Análisis de Declinaciones por pozo y/o subunidad | F24: 1. Análisis de la delcinación post BT en la generación de las curvas CC, distribución de la producción incremental para los trabajos de WO, OPT y OPEX bajo la metodología RWA para el plan de inversiones | G24: https://ecopetrol.sharepoint.com/:x:/s/IAAKACIAS/EXxBMXZqPrBMv9-HmsMp444BQgL9qkjBseaENWHbk4w31g?e=wfBNQM C:\Users\c109868u\Ecopetrol S.A\I&A AKACIAS - Documentos\21. Portafolio\2025\4.- PDI 2025\2. NPs\1. CCs\3. CCs | H24: 30 | I24: 3 | J24: =IFERROR(I24/H24,0) -> 0.1 | K24: =+I24+'MAYO 2025'!K24 -> 10 | L24: =IFERROR(K24/H24,0) -> 0.33333333
B25: 3 | C25: 3.17 | D25: Analizar data histórica de producción, productividad y daño por pozo | F25: 1. Interpretación y análisis de la influencia en inyección del productor de segunda línea AK-90ST con el inyector AK-135i por medio de presiones | G25: W:\2.- Ingeniería de Yacimientos\1.MONITOREO\7.Presiones\2025\1_Semestre\4. AK-90ST https://ecopetrol.sharepoint.com/:p:/r/sites/IAAKACIAS/Documentos%20compartidos/03.Sistem%C3%A1tica%20WF%20Akacias/2025/05.%20Mayo/Sistem%C3%A1tica%20WF-%20Akac%C3%ADas%2021.05.20251.pptx?d=wc1685bbd511144e38e83cbdf281d5bba&csf=1&web=1&e=w6J5DN | H25: 30 | I25: 4 | J25: =IFERROR(I25/H25,0) -> 0.13333333 | K25: =+I25+'MAYO 2025'!K25 -> 10 | L25: =IFERROR(K25/H25,0) -> 0.33333333
B26: 3 | C26: 3.18 | D26: Generar perfiles de Producción por pozos para pozos existente en escenarios Bajo, Medio y Alto | F26: 1. Construcción y arme de las curvas caracteristicas para los pozos de la zona NE y Frontera del campo Akacias incluyendo los escenarios de control de cambios A2.2 y modificación del VRR | G26: https://ecopetrol.sharepoint.com/:x:/s/IAAKACIAS/Eeu5b4fKMIRIn-TWjqiJSWIBlMASlQTwnfDNZqXLCPkh5w?e=0CfOjy | H26: 30 | I26: 3 | J26: =IFERROR(I26/H26,0) -> 0.1 | K26: =+I26+'MAYO 2025'!K26 -> 10 | L26: =IFERROR(K26/H26,0) -> 0.33333333
B27: 5 | C27: 5.2 | D27: Generación de oportunidades de intervención a Pozos | F27: 1. Diseño de caudales objetivos y estimación de propiedades por intervalo/zona para el pozo inyector AK-145i del proyecto frontera | G27: https://ecopetrol.sharepoint.com/:x:/s/IAAKACIAS/EVktu4yXZU9AoSJ9Rx6GnHMB_emfaXyqnG-lwIQPuxelWQ?e=2V1Hf5 | H27: 30 | I27: 2 | J27: =IFERROR(I27/H27,0) -> 0.066666667 | K27: =+I27+'MAYO 2025'!K27 -> 10 | L27: =IFERROR(K27/H27,0) -> 0.33333333
B28: 5 | C28: 5.9 | D28: Realizar el seguimiento de producción/ inyección de pozos intervenidos con base en los comportamientos de producción previo y posterior a la intervención | F28: 1. Descripción de causas en el seguimiento de los proyectos en ejecución para el campo Akacias | G28: https://ecopetrol.sharepoint.com/:x:/s/IAAKACIAS/Eeu5b4fKMIRIn-TWjqiJSWIBlMASlQTwnfDNZqXLCPkh5w?e=0CfOjy | H28: 30 | I28: 4 | J28: =IFERROR(I28/H28,0) -> 0.13333333 | K28: =+I28+'MAYO 2025'!K28 -> 10 | L28: =IFERROR(K28/H28,0) -> 0.33333333
B29: 8 | C29: 8.2 | D29: Carga de datos, procesamiento de datos, Análisis Estadístico descriptivo considerando hipótesis desde la teoría, y análisis descriptivo considerando hipótesis generadas desde la misma data (pasos 1, 2 y 3 teoría CRISP-DM). | F29: Actualización de las diferentes bases de datos para la actualización de tableros y distintas visuales | G29: https://ecopetrol.sharepoint.com/:f:/s/IAAKACIAS/EoI_hVXr9Q5FtD_ADjltMeYB1mxxF9WpklMtD9QXGgqRTA?e=FXnE5b | H29: 30 | I29: 3 | J29: =IFERROR(I29/H29,0) -> 0.1 | K29: =+I29+'MAYO 2025'!K29 -> 10 | L29: =IFERROR(K29/H29,0) -> 0.33333333
B30: 1 | C30: 1.2 | D30: Generación Bases de Datos de Pozos (Registros, Topes e información disponible) | E30: Julian A Hernández | F30: 1) Actualización con la base de datos con información preliminar para los pozos de la etapa ANE. | G30: \\10.100.25.35\pgtrabajodigital\JAH\Proyecto groups21\akacias\2.- Ingeniería de Yacimientos\1.MONITOREO | H30: 55 | I30: 6 | J30: =IFERROR(I30/H30,0) -> 0.10909091 | K30: =+I30+'MAYO 2025'!K30 -> 15 | L30: =IFERROR(K30/H30,0) -> 0.27272727
B31: 1 | C31: 1.3 | D31: Interpretación Sísmica | F31: 1) Revisón de información sismica para los pozos pertencientes a los patrones de inyección para identificar estructuras y establecer conectividades en los patrones de inyección. En busqueda del mejoramiento del factor de conectividad geológico. 2) Revisión información sísmica para identificar fallas o estrucutras en los patrones de inyección en pro de actualziar el factor de conectividad geológica para el campo Akacias. 3) Revisión en conjunto con el área de geofísica de la informaicón sismica para los pozos nuevos a perforar en el campo Akacias. | G31: \\10.100.25.35\pgtrabajodigital\JAH\Proyecto Z:\akacias\2.- Ingeniería de Yacimientos\1.MONITOREO\19.Sistematica WF Akacias\2025\06.Junio | H31: 20 | I31: 3 | J31: =IFERROR(I31/H31,0) -> 0.15 | K31: =+I31+'MAYO 2025'!K31 -> 8 | L31: =IFERROR(K31/H31,0) -> 0.4
B32: 1 | C32: 1.5 | D32: Digitalización, digitación y/o captura de información geológica (Mapas, Raw Data, topes, etc.) | F32: 1) Generación mapas, cortes y correalciones para hacer seguimiento a los patrones de inyección del campo y monitoreo a los pozos productores. 2) Cargue informaicón preliminar para los pozos de la etapa ANE. | G32: \\10.100.25.35\pgtrabajodigital\JAH\Proyecto | H32: 30 | I32: 5 | J32: =IFERROR(I32/H32,0) -> 0.16666667 | K32: =+I32+'MAYO 2025'!K32 -> 10 | L32: =IFERROR(K32/H32,0) -> 0.33333333
B33: 1 | C33: 1.8 | D33: Balanceo de Secciones | F33: 1) Contrucción en petrel de secciones que permitan observar la continuidad horizontal de los ciclos estratigráficos en pro de establecer la conectividad geológica en los patrones de inyección, en el monitoreo del WF para el campo Akacias. 2) Generación de secciones estructurales que permitan observar el comportamiento areal del yacimiento para monitorear el comportamiento de pozos productores y conectividades en patrones de inyección. | G33: \\10.100.25.35\pgtrabajodigital\JAH\Proyecto | H33: 25 | I33: 3 | J33: =IFERROR(I33/H33,0) -> 0.12 | K33: =+I33+'MAYO 2025'!K33 -> 8 | L33: =IFERROR(K33/H33,0) -> 0.32
B34: 1 | C34: 1.9 | D34: Análisis de sellos de fallas | F34: 1) Revisión del modelo estrucutural para el análisis de los patrones de inyección y así establecer la comunicación entre Inyec-produc durantes las sesiones de WF Akacias. 2) Revisión de los posibles sellos estructurales que condicionen el factor falla involucrado en la determinación del factor de conectividad geológico y continuar con la actualización de los tableros de conectividad geológica. 3) Análisis de las fallas dentro del estudio para identificar la influencia del acuífero en el campo a nivel CHIAK. 4) Continua la actualziación de la interpretación estructural e inicio del análisis de conectividad en los patrones de inyección del campo. | G34: \\10.100.25.35\pgtrabajodigital\JAH\Proyecto Z:\akacias\2.- Ingeniería de Yacimientos\1.MONITOREO\19.Sistematica WF Akacias\2025\06.Junio | H34: 30 | I34: 2 | J34: =IFERROR(I34/H34,0) -> 0.066666667 | K34: =+I34+'MAYO 2025'!K34 -> 10 | L34: =IFERROR(K34/H34,0) -> 0.33333333
B35: 1 | C35: 1.10 | D35: Amarre Sísmica Pozo | F35: 1) Revisión de la información sismíca con la trayectoria en las trayectorias entre pozos inyectores y porductores para identicar el Factor falla involucrado dentro del factor de conectividad geológica, insumo para actualizar el factor de conectividad geológico y el mapa de conectividad. 2) Revisión de las fallas interpretadas en las zonas de los pozos próximos a perforar para identificar los posibles riesgos geológicos y geofísicos, involucrando la nueva información estructural. Información que se usa como insumo para contrucción de los documentos RMS elaborados para los próximos pozos a perforar (etapas ANE y Frontera). | G35: \\10.100.25.35\pgtrabajodigital\JAH\Proyecto groups21\akacias\5. Información de pozos | H35: 20 | I35: 2 | J35: =IFERROR(I35/H35,0) -> 0.1 | K35: =+I35+'MAYO 2025'!K35 -> 8 | L35: =IFERROR(K35/H35,0) -> 0.4
B36: 1 | C36: 1.12 | D36: Generación de mapas de facies | F36: 1) Continua la elaboración de la base de datos para la actualización de los tableros G&G CHIAK. 2) Hacer seguimiento áreal de las facies para identificar los cambios laterales de facies que puedan indicar el comportamiento de arenas yto en los pozos productores. | G36: \\10.100.25.35\pgtrabajodigital\JAH\Proyecto | H36: 20 | I36: 3 | J36: =IFERROR(I36/H36,0) -> 0.15 | K36: =+I36+'MAYO 2025'!K36 -> 8 | L36: =IFERROR(K36/H36,0) -> 0.4
B37: 1 | C37: 1.15 | D37: Carga de información para poblar el modelo geocelular (direccionales, coordenadas, surveys, topes, data de presión, estados mecánicos, evento de pozos, etc.) | F37: 1) Actualización última información aprobada para los pozos de la etapa ANE y Frontera para la elaboración de los archivos RMS. | G37: ruta: \\10.100.25.35\pgtrabajodigital\JAH\Proyecto | H37: 50 | I37: 6 | J37: =IFERROR(I37/H37,0) -> 0.12 | K37: =+I37+'MAYO 2025'!K37 -> 15 | L37: =IFERROR(K37/H37,0) -> 0.3
B38: 1 | C38: 1.25 | D38: Análisis geoquímicos de Fingerprinting | F38: - | G38: - | H38: 20 | I38: 0 | J38: =IFERROR(I38/H38,0) -> 0 | K38: =+I38+'MAYO 2025'!K38 -> 8 | L38: =IFERROR(K38/H38,0) -> 0.4
B39: 3 | C39: 3.6 | D39: Generar Modelo analítico del yacimiento integrando la información disponible en un software específico | E39: Milton J Gualteros | F39: Actualización modelo analítico de yacimientos ARPS PDI2025 ESC3 - Frontera, ANE, Etapa 3, Inyección norte CHIAK | G39: Microsoft Teams, Email, Sharepoint Y:\akacias\37. Archivos | H39: 35 | I39: 4 | J39: =IFERROR(I39/H39,0) -> 0.11428571 | K39: =+I39+'MAYO 2025'!K39 -> 12 | L39: =IFERROR(K39/H39,0) -> 0.34285714
B40: 3 | C40: 3.13 | D40: Generar base de datos de producción (OFM o la que se requiera) | F40: Generación base de datos y construcción perfiles proyectos Desarrollo Posterior | G40: Microsoft Teams, Email, Sharepoint Y:\akacias\37. Archivos | H40: 33 | I40: 4 | J40: =IFERROR(I40/H40,0) -> 0.12121212 | K40: =+I40+'MAYO 2025'!K40 -> 11 | L40: =IFERROR(K40/H40,0) -> 0.33333333
B41: 3 | C41: 3.16 | D41: Análisis de Declinaciones por pozo y/o subunidad | F41: Análisis de declinación pozos asociados a patrones de inyección | G41: Microsoft Teams, Email, Sharepoint Y:\akacias\37. Archivos | H41: 33 | I41: 4 | J41: =IFERROR(I41/H41,0) -> 0.12121212 | K41: =+I41+'MAYO 2025'!K41 -> 11 | L41: =IFERROR(K41/H41,0) -> 0.33333333
B42: 3 | C42: 3.17 | D42: Analizar data histórica de producción, productividad y daño por pozo | F42: Análisis de data histórica de producción para seguimiento proceso Waterflooding | G42: Microsoft Teams, Email, Sharepoint Y:\akacias\37. Archivos | H42: 33 | I42: 3 | J42: =IFERROR(I42/H42,0) -> 0.090909091 | K42: =+I42+'MAYO 2025'!K42 -> 11 | L42: =IFERROR(K42/H42,0) -> 0.33333333
B43: 3 | C43: 3.18 | D43: Generar perfiles de Producción por pozos para pozos existente en escenarios Bajo, Medio y Alto | F43: Generación perfiles de producción escenarios bajo, medio, alto en ARPS (PDI2025 ESC3) | G43: Microsoft Teams, Email, Sharepoint Y:\akacias\37. Archivos | H43: 35 | I43: 4 | J43: =IFERROR(I43/H43,0) -> 0.11428571 | K43: =+I43+'MAYO 2025'!K43 -> 11 | L43: =IFERROR(K43/H43,0) -> 0.31428571
B44: 5 | C44: 5.2 | D44: Generación de oportunidades de intervención a Pozos | F44: Definición oportunidades de intervención en reunión sistematica WF | G44: Microsoft Teams, Email, Sharepoint Y:\akacias\37. Archivos | H44: 33 | I44: 4 | J44: =IFERROR(I44/H44,0) -> 0.12121212 | K44: =+I44+'MAYO 2025'!K44 -> 11 | L44: =IFERROR(K44/H44,0) -> 0.33333333
B45: 5 | C45: 5.9 | D45: Realizar el seguimiento de producción/ inyección de pozos intervenidos con base en los comportamientos de producción previo y posterior a la intervención | F45: Seguimiento de Producción e Inyección del proyecto de waterflooding del campo akacias | G45: Microsoft Teams, Email, Sharepoint Y:\akacias\37. Archivos | H45: 35 | I45: 4 | J45: =IFERROR(I45/H45,0) -> 0.11428571 | K45: =+I45+'MAYO 2025'!K45 -> 12 | L45: =IFERROR(K45/H45,0) -> 0.34285714
B46: 8 | C46: 8.2 | D46: Carga de datos, procesamiento de datos, Análisis Estadístico descriptivo considerando hipótesis desde la teoría, y análisis descriptivo considerando hipótesis generadas desde la misma data (pasos 1, 2 y 3 teoría CRISP-DM). | F46: Cargue, análisis y procesamiento de los datos del modelo análitico de yacimientos. Analisis de datos en PowerBI | G46: Microsoft Teams, Email, Sharepoint Y:\akacias\37. Archivos | H46: 33 | I46: 3 | J46: =IFERROR(I46/H46,0) -> 0.090909091 | K46: =+I46+'MAYO 2025'!K46 -> 11 | L46: =IFERROR(K46/H46,0) -> 0.33333333
B47: 3 | C47: 3.6 | D47: Generar Modelo analítico del yacimiento integrando la información disponible en un software específico | E47: Ana M Castellanos | F47: Modelo Analítico - Perfiles de Producción - Informe del modelo | G47: \\10.100.25.60\sya\gec | H47: 20 | I47: 3 | J47: =IFERROR(I47/H47,0) -> 0.15 | K47: =+I47+'MAYO 2025'!K47 -> 9 | L47: =IFERROR(K47/H47,0) -> 0.45
B48: 3 | C48: 3.13 | D48: Generar base de datos de producción (OFM o la que se requiera) | F48: Base de Datos | G48: \\10.100.25.60\sya\gec | H48: 20 | I48: 3 | J48: =IFERROR(I48/H48,0) -> 0.15 | K48: =+I48+'MAYO 2025'!K48 -> 9 | L48: =IFERROR(K48/H48,0) -> 0.45
B49: 3 | C49: 3.14 | D49: Generar Distribución de Producción por sub- unidades (allocation) | F49: Base de Datos | G49: \\10.100.25.60\sya\gec | H49: 20 | I49: 4 | J49: =IFERROR(I49/H49,0) -> 0.2 | K49: =+I49+'MAYO 2025'!K49 -> 12 | L49: =IFERROR(K49/H49,0) -> 0.6
B50: 3 | C50: 3.16 | D50: Análisis de Declinaciones por pozo y/o subunidad | F50: Base de Datos - Perfiles Generados - Informe del análisis | G50: https://ecopetrol.sharepoint.com/sites/BDSaharaCastilla/Documentos%20compartidos/Forms/AllItems.aspx?id=%2Fsites%2FBDSaharaCastilla%2FDocumentos%20compartidos%2FBD%20Sahara&viewid=a035cf74%2D0100%2D4f66%2Da914%2D651dfeb02341 | H50: 20 | I50: 3 | J50: =IFERROR(I50/H50,0) -> 0.15 | K50: =+I50+'MAYO 2025'!K50 -> 9 | L50: =IFERROR(K50/H50,0) -> 0.45
B51: 3 | C51: 3.17 | D51: Analizar data histórica de producción, productividad y daño por pozo | F51: Base de Datos - Informe de la Evaluación | G51: \\10.100.25.60\sya\gec | H51: 20 | I51: 4 | J51: =IFERROR(I51/H51,0) -> 0.2 | K51: =+I51+'MAYO 2025'!K51 -> 12 | L51: =IFERROR(K51/H51,0) -> 0.6
B52: 3 | C52: 3.18 | D52: Generar perfiles de Producción por pozos para pozos existente en escenarios Bajo, Medio y Alto | F52: Base de Datos - Informe de la Evaluación | G52: \\10.100.25.60\sya\gec Sahara/ Tableros de diagnostico | H52: 20 | I52: 3 | J52: =IFERROR(I52/H52,0) -> 0.15 | K52: =+I52+'MAYO 2025'!K52 -> 9 | L52: =IFERROR(K52/H52,0) -> 0.45
B53: 5 | C53: 5.2 | D53: Generación de oportunidades de intervención a Pozos | F53: Base de Datos - Informe de la Evaluación | G53: https://wellmeeting.ecopetrol.com.co/home https://ecopetrol.sharepoint.com/sites/CastillaWOs2022/Documentos%20compartidos/Forms/AllItems.aspx | H53: 20 | I53: 3 | J53: =IFERROR(I53/H53,0) -> 0.15 | K53: =+I53+'MAYO 2025'!K53 -> 9 | L53: =IFERROR(K53/H53,0) -> 0.45
B54: 5 | C54: 5.9 | D54: Realizar el seguimiento de producción/ inyección de pozos intervenidos con base en los comportamientos de producción previo y posterior a la intervención | F54: Base de Datos - Informe de la Evaluación | G54: 2025-04-21 Sahara VyP Castilla.zip https://ecopetrol.sharepoint.com/sites/BDSaharaCastilla/Documentos%20compartidos/Forms/AllItems.aspx?id=%2Fsites%2FBDSaharaCastilla%2FDocumentos%20compartidos%2FPresentaciones%20soporte%20sesiones%2F2025&viewid=a035cf74%2D0100%2D4f66%2Da914%2D651dfeb02341 | H54: 20 | I54: 4 | J54: =IFERROR(I54/H54,0) -> 0.2 | K54: =+I54+'MAYO 2025'!K54 -> 12 | L54: =IFERROR(K54/H54,0) -> 0.6
B55: 8 | C55: 8.2 | D55: Carga de datos, procesamiento de datos, Análisis Estadístico descriptivo considerando hipótesis desde la teoría, y análisis descriptivo considerando hipótesis generadas desde la misma data (pasos 1, 2 y 3 teoría CRISP-DM). | F55: Informe, con estadísticas descriptivas, histogramas, pruebas de ajuste, etc. | G55: https://app.powerbi.com/singleSignOn?ru=https%3A%2F%2Fapp.powerbi.com%2Fgroups%2Fe5641789-d59d-4f86-b857-9812c65a1a04%2Freports%2Fdff68870-b9fb-4308-960e-6c4f8c41c79d%2FReportSection974a4271511adef5c478%3FnoSignUpCheck%3D1 | H55: 20 | I55: 3 | J55: =IFERROR(I55/H55,0) -> 0.15 | K55: =+I55+'MAYO 2025'!K55 -> 9 | L55: =IFERROR(K55/H55,0) -> 0.45
B56: 3 | C56: 3.6 | D56: Generar Modelo analítico del yacimiento integrando la información disponible en un software específico | E56: Paola Gomez | F56: Se realizó cargue de pruebas de produccion, tasas de inyección, pruebas de ILT en la BD de Sahara CAN15, CAN57, y CAN462 adicionalmente se realiza el seguimiento a las 17 optimizaciones, 1 rediseños y 4 WO (2 en ejecucion y 2 a ejecutar). | G56: \\10.100.25.60\sya\gec\Castilla\39. Proyecto_Inyeccion_de_Agua\SAHARA) y en las notas de wellmeeting | H56: 18 | I56: 3 | J56: =IFERROR(I56/H56,0) -> 0.16666667 | K56: =+I56+'MAYO 2025'!K56 -> 9 | L56: =IFERROR(K56/H56,0) -> 0.5
B57: 3 | C57: 3.13 | D57: Generar base de datos de producción (OFM o la que se requiera) | F57: Se realizó la base de datos de seguimiento a patrones de Centro Norte con datos del tablero de producción prorrateada el cual es alimentado con base en la producción por formas y pruebas de producción de AVM. | G57: DTWF CASTILLA-Tablero Castilla y \\10.100.25.60\sya\gec\Castilla\39. Proyecto_Inyeccion_de_Agua\SAHARA | H57: 36 | I57: 6 | J57: =IFERROR(I57/H57,0) -> 0.16666667 | K57: =+I57+'MAYO 2025'!K57 -> 18 | L57: =IFERROR(K57/H57,0) -> 0.5
B58: 3 | C58: 3.14 | D58: Generar Distribución de Producción por sub- unidades (allocation) | F58: Para esta actividad se genera distribución vertical por unidad para los inyectores asociados a la Zona Centro Norte. La distribución se encuentra actualizada a la fecha con los últimos valores de ILT para cada inyector CAN15, CAN462, Y CAN57 . La evidencia se encuentra en la Base de Datos SAHARA. | G58: \\10.100.25.60\sya\gec\Castilla\39. Proyecto_Inyeccion_de_Agua\SAHARA | H58: 12 | I58: 2 | J58: =IFERROR(I58/H58,0) -> 0.16666667 | K58: =+I58+'MAYO 2025'!K58 -> 6 | L58: =IFERROR(K58/H58,0) -> 0.5
B59: 3 | C59: 3.16 | D59: Análisis de Declinaciones por pozo y/o subunidad | F59: De acuerdo con el seguimiento a la producción e inyección, se realizó el seguimiento a los patrones CA61, CAN255, CAN57, CAN56, CAN05 y CAN462. | G59: https://teams.microsoft.com/l/channel/19%3A0KSR0Sqd9sL27-AWAKb2UFAmZ-fupgWBuEQNEHUYOIY1%40thread.tacv2/Documentos?groupId=ba918c77-3768-4ebd-affe-4ef992094119&tenantId=a4305987-cf78-4f93-9d64-bf18af65397b | H59: 36 | I59: 6 | J59: =IFERROR(I59/H59,0) -> 0.16666667 | K59: =+I59+'MAYO 2025'!K59 -> 18 | L59: =IFERROR(K59/H59,0) -> 0.5
B60: 3 | C60: 3.17 | D60: Analizar data histórica de producción, productividad y daño por pozo | F60: se realiza relaciones y comparaciones con los datos de producción e inyección de la zona Centro Norte cargada en la base de datos de Sahara. Ver mayor ampliación en GP-F-25 | G60: \\10.100.25.60\sya\gec\Castilla\39. Proyecto_Inyeccion_de_Agua\SAHARA\BD Sahara | H60: 18 | I60: 3 | J60: =IFERROR(I60/H60,0) -> 0.16666667 | K60: =+I60+'MAYO 2025'!K60 -> 9 | L60: =IFERROR(K60/H60,0) -> 0.5
B61: 3 | C61: 3.18 | D61: Generar perfiles de Producción por pozos para pozos existente en escenarios Bajo, Medio y Alto | F61: Para este ítem para el mes de abril se realizó los perfiles generados para los pozos candidatos a (RDG) rediseño y Workover (WO) CAN376, CAN301, CAN102, CAN264 los cuales quedan registrados en la ruta del equipo de taller de producción GDT | G61: GDT Plus (El V.A.R.) - General - Todos los documentos y https://ecopetrol.sharepoint.com/sites/CastillaWOs2022/Documentos%20compartidos/Forms/AllItems.aspx | H61: 18 | I61: 3 | J61: =IFERROR(I61/H61,0) -> 0.16666667 | K61: =+I61+'MAYO 2025'!K61 -> 9 | L61: =IFERROR(K61/H61,0) -> 0.5
B62: 5 | C62: 5.2 | D62: Generación de oportunidades de intervención a Pozos | F62: Con el equipo multidiciplinario se realiza un análisis de los pozos encontrando bajas eficiencias y declinaciones presentadas de los pozos de la zona Centro Norte concluyendo las oportunidades de intervención en la medida que se puedan realizar las oportunidades en los pozos candidatos, lo cual queda consignado en el WM. Se declaran los pozos CAN403, CAN261 y CAN264 con el inyector CAN24 | G62: https://wellmeeting.ecopetrol.com.co/home | H62: 12 | I62: 2 | J62: =IFERROR(I62/H62,0) -> 0.16666667 | K62: =+I62+'MAYO 2025'!K62 -> 6 | L62: =IFERROR(K62/H62,0) -> 0.5
B63: 5 | C63: 5.9 | D63: Realizar el seguimiento de producción/ inyección de pozos intervenidos con base en los comportamientos de producción previo y posterior a la intervención | F63: Se realizo el seguimiento de producción/ inyección de pozos a cargo (22 patrones de inyección) con base en los comportamientos de producción e inyección | G63: https://teams.microsoft.com/l/channel/19%3A0KSR0Sqd9sL27-AWAKb2UFAmZ-fupgWBuEQNEHUYOIY1%40thread.tacv2/Documentos?groupId=ba918c77-3768-4ebd-affe-4ef992094119&tenantId=a4305987-cf78-4f93-9d64-bf18af65397b | H63: 18 | I63: 3 | J63: =IFERROR(I63/H63,0) -> 0.16666667 | K63: =+I63+'MAYO 2025'!K63 -> 9 | L63: =IFERROR(K63/H63,0) -> 0.5
B64: 8 | C64: 8.2 | D64: Carga de datos, procesamiento de datos, Análisis Estadístico descriptivo considerando hipótesis desde la teoría, y análisis descriptivo considerando hipótesis generadas desde la misma data (pasos 1, 2 y 3 teoría CRISP-DM). | F64: Para este ítem se realizó carga de datos de ILT en la BD de Sahara. Se realizó la actualización de volumetrías del pozo CAN255 y CA61. | G64: \\10.100.25.60\sya\gec\Castilla\39. Proyecto_Inyeccion_de_Agua\SAHARA) y en las notas de wellmeeting | H64: 12 | I64: 2 | J64: =IFERROR(I64/H64,0) -> 0.16666667 | K64: =+I64+'MAYO 2025'!K64 -> 6 | L64: =IFERROR(K64/H64,0) -> 0.5
B65: 3 | C65: 3.6 | D65: Generar Modelo analítico del yacimiento integrando la información disponible en un software específico | E65: Geisson Zafra | F65: Se continua con el proceso de actualización de la básica para la corrida de plan de inversiones 2025, para lo cual se hacen ajustes referentes a los perfiles de proyección dentro del archivo de Curvas Características, se imprimen los txt correspondientes para su cargue en la herramienta ARPS y así generar el archivo ARPS de la básica para ser exportada y cargada, primero a un tablero Power Bi para su revisión, con el objetivo de finalmente ser enviados los perfiles y volúmenes a Assembler. | G65: C:\Users\c110096a\OneDrive - Ecopetrol S.A\tablero\01_ECP\02_VIGENCIA\20250613\Entrega_Equipos\ESC_03 | H65: 30 | I65: 4 | J65: =IFERROR(I65/H65,0) -> 0.13333333 | K65: =+I65+'MAYO 2025'!K65 -> 13 | L65: =IFERROR(K65/H65,0) -> 0.43333333
B66: 3 | C66: 3.13 | D66: Generar base de datos de producción (OFM o la que se requiera) | F66: Se concentra la data de los diferentes proyectos y se inicia el balance de agua del campo. Para lo cual se llevan a cabo diferentes cambios en el archivo de la básica, como el cierre de pozos del norte que poseen altos BSW. | G66: C:\Users\c110096a\OneDrive - Ecopetrol S.A\tablero\01_ECP\02_VIGENCIA\20250613\Entrega_Equipos\ESC_03 | H66: 30 | I66: 4 | J66: =IFERROR(I66/H66,0) -> 0.13333333 | K66: =+I66+'MAYO 2025'!K66 -> 12 | L66: =IFERROR(K66/H66,0) -> 0.4
B67: 3 | C67: 3.14 | D67: Generar Distribución de Producción por sub- unidades (allocation) | F67: Se realiza revisión de las Ideas de los diferentes proyectos asociados a la básica, ajuste en nombre de pozos de acuerdo a la base de datos de la que se alimenta ARPS. | G67: C:\Users\c110096a\OneDrive - Ecopetrol S.A\tablero\01_ECP\02_VIGENCIA\20250613\Entrega_Equipos\ESC_03 | H67: 30 | I67: 4 | J67: =IFERROR(I67/H67,0) -> 0.13333333 | K67: =+I67+'MAYO 2025'!K67 -> 11 | L67: =IFERROR(K67/H67,0) -> 0.36666667
B68: 3 | C68: 3.16 | D68: Análisis de Declinaciones por pozo y/o subunidad | F68: Se sostienen sesiones con el desarrollador de la herramienta ARPS para implementar funciones en aras de ajustar los volúmenes a las necesidades previstas. Igualmente para subsanar fallas a la hora de exportar, conexión con base de datos, permisos para cargues en los campo contratos, permisos a assembler. | G68: N/A | H68: 30 | I68: 3 | J68: =IFERROR(I68/H68,0) -> 0.1 | K68: =+I68+'MAYO 2025'!K68 -> 11 | L68: =IFERROR(K68/H68,0) -> 0.36666667
B69: 3 | C69: 3.17 | D69: Analizar data histórica de producción, productividad y daño por pozo | F69: Se analizan los reales del mes de mayo luego de generados los archivos cargadores de formas, a fin de realizar comparaciones pozo a pozo y que se identifiquen las brechas en patrones de REAL frente a P50, CERT, GOP 1Q y PDI. | G69: https://ecopetrol.sharepoint.com/sites/SeguimientoIAChichimeneECP/Documentos%20compartidos/Forms/AllItems.aspx?id=%2Fsites%2FSeguimientoIAChichimeneECP%2FDocumentos%20compartidos%2F11%2E%20Desviaciones%20Prod%5FIny%20Real%20vs%20P50%20vs%20Auditoria%20vs%20PDI%20vs%20GOP%20vs%20POP%2F2025&viewid=72844968%2Df801%2D450d%2D81d2%2D32c578273e17 | H69: 30 | I69: 3 | J69: =IFERROR(I69/H69,0) -> 0.1 | K69: =+I69+'MAYO 2025'!K69 -> 8 | L69: =IFERROR(K69/H69,0) -> 0.26666667
B70: 3 | C70: 3.18 | D70: Generar perfiles de Producción por pozos para pozos existente en escenarios Bajo, Medio y Alto | F70: Se proporciona información de perfiles y volúmenes de pronóstico de reservas PDI de la corrida 12-2024 a diferentes equipos y profesionales por solicitud. | G70: N/A | H70: 30 | I70: 3 | J70: =IFERROR(I70/H70,0) -> 0.1 | K70: =+I70+'MAYO 2025'!K70 -> 8 | L70: =IFERROR(K70/H70,0) -> 0.26666667
B71: 5 | C71: 5.2 | D71: Generación de oportunidades de intervención a Pozos | F71: Se lleva a cabo el seguimiento de la campaña de WO vigente 2024-2026, al igual que se sostiene reunión de seguimiento de Planes Operativos con proyectos para actualizar el archivo correspondiente. | G71: https://ecopetrol.sharepoint.com/sites/SeguimientoIAChichimeneECP/Documentos%20compartidos/Forms/AllItems.aspx?id=%2Fsites%2FSeguimientoIAChichimeneECP%2FDocumentos%20compartidos%2F45%2E%20WorkOvers%20GCH%202024%2D2026%2D2027&viewid=72844968%2Df801%2D450d%2D81d2%2D32c578273e17 | H71: 30 | I71: 3 | J71: =IFERROR(I71/H71,0) -> 0.1 | K71: =+I71+'MAYO 2025'!K71 -> 9 | L71: =IFERROR(K71/H71,0) -> 0.3
B72: 5 | C72: 5.9 | D72: Realizar el seguimiento de producción/ inyección de pozos intervenidos con base en los comportamientos de producción previo y posterior a la intervención | F72: Se mantienen sesiones con el equipo de inyección, planeación e ingeniería, para definir PDT de inyección incrementos en T2, sincronización con POP, y cronograma de WO's. | G72: N/A | H72: 30 | I72: 3 | J72: =IFERROR(I72/H72,0) -> 0.1 | K72: =+I72+'MAYO 2025'!K72 -> 10 | L72: =IFERROR(K72/H72,0) -> 0.33333333
B73: 8 | C73: 8.2 | D73: Carga de datos, procesamiento de datos, Análisis Estadístico descriptivo considerando hipótesis desde la teoría, y análisis descriptivo considerando hipótesis generadas desde la misma data (pasos 1, 2 y 3 teoría CRISP-DM). | F73: Se atienden diferentes sesiones, talleres y sistemáticas, en orden de planear las actividades previstas para aumento de inyección en T2, al igual que la sistemática del proyecto Frontera a fin de definir metodologías para su gerenciamiento adecuado. | G73: N/A | H73: 30 | I73: 3 | J73: =IFERROR(I73/H73,0) -> 0.1 | K73: =+I73+'MAYO 2025'!K73 -> 8 | L73: =IFERROR(K73/H73,0) -> 0.26666667
B74: 3 | C74: 3.6 | D74: Generar Modelo analítico del yacimiento integrando la información disponible en un software específico | E74: Cesar E Rodriguez | F74: Se realizó el seguimiento a las optimizaciones, rediseños y WO a ejecutar. La información quedó asegurada en el archivo “Matriz priorizacion incrementos“ y "Priorizacion de acciones GDT_RD-WO-WS" | G74: \\10.100.25.60\sya\gec\Castilla\39. Proyecto_Inyeccion_de_Agua\SAHARA) y en las notas de wellmeeting | H74: 20 | I74: 3 | J74: =IFERROR(I74/H74,0) -> 0.15 | K74: =+I74+'MAYO 2025'!K74 -> 10 | L74: =IFERROR(K74/H74,0) -> 0.5
B75: 3 | C75: 3.13 | D75: Generar base de datos de producción (OFM o la que se requiera) | F75: En la herramienta Sahara oficial con corte a Jun/2025, se corrigió y actualizó estado de capa y factores de alocacion pozos CA73. Cargue de data de producción y Presiones dinamicas actualizadas a Jun/25 de zona centro sur | G75: \\10.100.25.60\sya\gec\Castilla\39. Proyecto_Inyeccion_de_Agua\SAHARA | H75: 14 | I75: 3 | J75: =IFERROR(I75/H75,0) -> 0.21428571 | K75: =+I75+'MAYO 2025'!K75 -> 8 | L75: =IFERROR(K75/H75,0) -> 0.57142857
B76: 3 | C76: 3.14 | D76: Generar Distribución de Producción por sub- unidades (allocation) | F76: Por solicitud de la líder, se diligenciaron los siguientes archivos con la información actualizada del estado de los pozos productores e inyectores del área que tengo en monitoreo: Candidatos rediseños, Rediseños Ejecutados en 2025 por zona. actualización de EM, propiedades petrofísicas y factores de alocación para los diferentes pozos en la BD de SAHARA | G76: DTWF CASTILLA - Tablero Castilla Fan Edition - Todos los documentos \\10.100.25.60\sya\gec\Castilla\39. Proyecto_Inyeccion_de_Agua\SAHARA\BD Sahara | H76: 28 | I76: 5 | J76: =IFERROR(I76/H76,0) -> 0.17857143 | K76: =+I76+'MAYO 2025'!K76 -> 14 | L76: =IFERROR(K76/H76,0) -> 0.5
B77: 3 | C77: 3.16 | D77: Análisis de Declinaciones por pozo y/o subunidad | F77: De acuerdo con el seguimiento a la producción e inyección, se realizó el seguimiento a las optimizaciones realizadas en el mes de enero, febrero, marzo y abril, de acuerdo con el BSW, pruebas de producción y toma de niveles. | G77: \\10.100.25.60\sya\gec\Castilla\39. Proyecto_Inyeccion_de_Agua\SAHARA\BD Sahara | H77: 16 | I77: 2 | J77: =IFERROR(I77/H77,0) -> 0.125 | K77: =+I77+'MAYO 2025'!K77 -> 8 | L77: =IFERROR(K77/H77,0) -> 0.5
B78: 3 | C78: 3.17 | D78: Analizar data histórica de producción, productividad y daño por pozo | F78: Se llevaron a mesa los pozos CA402st y CA21 con la finalidad de aprobar oportunidades de WOP. Visualizados pozos con oportunidad de RDG: CA347. Ver mayor ampliación en GP-F-25 | G78: https://wellmeeting.ecopetrol.com.co/login | H78: 16 | I78: 2 | J78: =IFERROR(I78/H78,0) -> 0.125 | K78: =+I78+'MAYO 2025'!K78 -> 8 | L78: =IFERROR(K78/H78,0) -> 0.5
B79: 3 | C79: 3.18 | D79: Generar perfiles de Producción por pozos para pozos existente en escenarios Bajo, Medio y Alto | F79: Se aseguraron los diagnósticos y acciones en wellmeeting por motivos de las revisiones con el equipo multidisciplinario y revisión interna. Ver mayor ampliación en GP-F-25 | G79: https://wellmeeting.ecopetrol.com.co/login GDT Plus (El V.A.R.) - General - Todos los documentos | H79: 12 | I79: 3 | J79: =IFERROR(I79/H79,0) -> 0.25 | K79: =+I79+'MAYO 2025'!K79 -> 7 | L79: =IFERROR(K79/H79,0) -> 0.58333333
B80: 5 | C80: 5.2 | D80: Generación de oportunidades de intervención a Pozos | F80: De acuerdo con los rediseños propuestos en el plan de cierre de brechas, se obtuvo una lista de 8 pozos que se requieren optimizar, se irán priorizando de acuerdo con el presupuesto aprobado: CA228, CA325, CA153H, CA155H, CA358, CA194, CA281H y CA105. | G80: teams (Sistemática WF y Gestión de la Básica y en la BD SAHARA (\\10.100.25.60\sya\gec\Castilla\39. Proyecto_Inyeccion_de_Agua\SAHARA) | H80: 24 | I80: 4 | J80: =IFERROR(I80/H80,0) -> 0.16666667 | K80: =+I80+'MAYO 2025'!K80 -> 11 | L80: =IFERROR(K80/H80,0) -> 0.45833333
B81: 5 | C81: 5.9 | D81: Realizar el seguimiento de producción/ inyección de pozos intervenidos con base en los comportamientos de producción previo y posterior a la intervención | F81: Se realizo el seguimiento de producción/ inyección de pozos a cargo (15 patrones de inyección) con base en los comportamientos de producción e inyección | G81: TEAMS del equipo I&A Castilla (Sistemática WF): https://ecopetrol.sharepoint.com/sites/DTWFCASTILLA/Documentos%20compartidos/Forms/AllItems.aspx?OR=Teams%2DHL&CT=1722020892543&clickparams=eyJBcHBOYW1lIjoiVGVhbXMtRGVza3RvcCIsIkFwcFZlcnNpb24iOiI0OS8yNDA2MjcyNDgxNCIsIkhhc0ZlZGVyYXRlZFVzZXIiOmZhbHNlfQ%3D%3D&id=%2Fsites%2FDTWFCASTILLA%2FDocumentos%20compartidos%2FGeneral&viewid=9ba680aa%2D7c76%2D4823%2Dbaac%2Dba7ef8ef6f87 | H81: 26 | I81: 4 | J81: =IFERROR(I81/H81,0) -> 0.15384615 | K81: =+I81+'MAYO 2025'!K81 -> 12 | L81: =IFERROR(K81/H81,0) -> 0.46153846
B82: 8 | C82: 8.2 | D82: Carga de datos, procesamiento de datos, Análisis Estadístico descriptivo considerando hipótesis desde la teoría, y análisis descriptivo considerando hipótesis generadas desde la misma data (pasos 1, 2 y 3 teoría CRISP-DM). | F82: En cuanto a la herramienta OFM se realizó el cargue de la producción, inyección y pruebas del mes deMayo/2025. La información quedó asegurada en el proyecto 05. Proyecto OFM\Archivos Excel\Cargue OFM\2025 | G82: La información quedó asegurada en el proyecto 131. \\10.100.25.60\sya\gec\05. Proyecto OFM\Archivos Excel\Cargue OFM\2025 | H82: 24 | I82: 4 | J82: =IFERROR(I82/H82,0) -> 0.16666667 | K82: =+I82+'MAYO 2025'!K82 -> 12 | L82: =IFERROR(K82/H82,0) -> 0.5
B83: 3 | C83: 3.6 | D83: Generar Modelo analítico del yacimiento integrando la información disponible en un software específico | E83: Diego F Galeano | F83: 1. Pronosticos de NUevos proyectos WOrkover secundaria y REdiseños. 2, DOcumento de soporte de reservas Word y Power point 3. Pronosticos de Proyecto Expansion de recobro Unidades T2 y K1 4. Memorando de modificacion del proyecto Expansion de recobro mejorado 5. Reuniones sistematicas de los proyetos Etapa 4 y Modulo integral Norte /sur 6. pozos inyectores de polímero proceso IDA- Explansion CEOR . | G83: Digital-1. \\10.100.25.60\sya\GEC\Castilla\Proyecto W.O 2024 2027 GDT\WORKOVER Y REDISEÑOS SECUNDARIA 2. \\10.100.25.60\sya\GEC\Castilla\20.Proyecto IOR K2\Expansión Recobro Mejorado GDT\reconfiguracion ERM junio 2024 3.\10.100.25.60\sya\GEC\Castilla\102.T2\Revision 2024 2. Presentación Semanal Sistemática Etapa 4 3.https://ecopetrol.sharepoint.com/sites/CastillaWOs2022/Documentos%20compartidos/Forms 4.20230921 Sistemática Semanal - Sur Norte .pptx 5. \\10.100.25.60\sya\GEC\Castilla\20.Proyecto IOR K2\Expansión Recobro Mejorado GDT\02. EXP REC MEJORADO FASE 1 | H83: 30 | I83: 3 | J83: =IFERROR(I83/H83,0) -> 0.1 | K83: =+I83+'MAYO 2025'!K83 -> 9 | L83: =IFERROR(K83/H83,0) -> 0.3
B84: 3 | C84: 3.13 | D84: Generar base de datos de producción (OFM o la que se requiera) | F84: 1. Uso de base de datos (OFM & Sahara) para Generacion de Pronosticos de Nuevos proyectos Workover secundaria y Rediseños. 2. Pronosticos de Proyecto Expansion de recobro Unidades T2 y K1 | G84: Digital-1. \\10.100.25.60\sya\GEC\Castilla\Proyecto W.O 2024 2027 GDT\WORKOVER Y REDISEÑOS SECUNDARIA 2. \\10.100.25.60\sya\GEC\Castilla\20.Proyecto IOR K2\Expansión Recobro Mejorado GDT\reconfiguracion ERM junio 2024 3.\10.100.25.60\sya\GEC\Castilla\102.T2\Revision 2024 | H84: 30 | I84: 3 | J84: =IFERROR(I84/H84,0) -> 0.1 | K84: =+I84+'MAYO 2025'!K84 -> 9 | L84: =IFERROR(K84/H84,0) -> 0.3
B85: 3 | C85: 3.14 | D85: Generar Distribución de Producción por sub- unidades (allocation) | F85: 1. Analisis de distribución de la produccion e inyeccion por Fomacion (T2,K1 &K2), para la generacion Pronosticos de Nuevos proyectos WOrkover secundaria y Rediseños & Pronosticos de Proyecto Expansion de recobro Unidades T2 y K1 | G85: Digital-1. \\10.100.25.60\sya\GEC\Castilla\Proyecto W.O 2024 2027 GDT\WORKOVER Y REDISEÑOS SECUNDARIA 2. \\10.100.25.60\sya\GEC\Castilla\20.Proyecto IOR K2\Expansión Recobro Mejorado GDT\reconfiguracion ERM junio 2024 3.\10.100.25.60\sya\GEC\Castilla\102.T2\Revision 2024 2. Presentación Semanal Sistemática Etapa 4 3.https://ecopetrol.sharepoint.com/sites/CastillaWOs2022/Documentos%20compartidos/Forms 4.20230921 Sistemática Semanal - Sur Norte .pptx 5. \\10.100.25.60\sya\GEC\Castilla\20.Proyecto IOR K2\Expansión Recobro Mejorado GDT\02. EXP REC MEJORADO FASE 1 | H85: 30 | I85: 3 | J85: =IFERROR(I85/H85,0) -> 0.1 | K85: =+I85+'MAYO 2025'!K85 -> 9 | L85: =IFERROR(K85/H85,0) -> 0.3
B86: 3 | C86: 3.16 | D86: Análisis de Declinaciones por pozo y/o subunidad | F86: 1. Pronosticos de NUevos proyectos WOrkover secundaria y REdiseños. 2, DOcumento de soporte de reservas Word y Power point 3. Pronosticos de Proyecto Expansion de recobro Unidades T2 y K1 4. Memorando de modificacion del proyecto Expansion de recobro mejorado 5. Reuniones sistematicas de los proyetos Etapa 4 y Modulo integral Norte /sur 6. pozos inyectores de polímero proceso IDA- Explansion CEOR . | G86: Digital-1. \\10.100.25.60\sya\GEC\Castilla\Proyecto W.O 2024 2027 GDT\WORKOVER Y REDISEÑOS SECUNDARIA 2. \\10.100.25.60\sya\GEC\Castilla\20.Proyecto IOR K2\Expansión Recobro Mejorado GDT\reconfiguracion ERM junio 2024 3.\10.100.25.60\sya\GEC\Castilla\102.T2\Revision 2024 2. Presentación Semanal Sistemática Etapa 4 3.https://ecopetrol.sharepoint.com/sites/CastillaWOs2022/Documentos%20compartidos/Forms 4.20230921 Sistemática Semanal - Sur Norte .pptx 5. \\10.100.25.60\sya\GEC\Castilla\20.Proyecto IOR K2\Expansión Recobro Mejorado GDT\02. EXP REC MEJORADO FASE 1 | H86: 30 | I86: 3 | J86: =IFERROR(I86/H86,0) -> 0.1 | K86: =+I86+'MAYO 2025'!K86 -> 9 | L86: =IFERROR(K86/H86,0) -> 0.3
B87: 3 | C87: 3.17 | D87: Analizar data histórica de producción, productividad y daño por pozo | F87: Generar declinaciones historicas para Pronosticos de NUevos proyectos WOrkover secundaria y REdiseños. Segimiento a la produccion e inyeccion y declinaciones de los pozos del proyecto etapa 4. . | G87: Digital-1. \\10.100.25.60\sya\GEC\Castilla\Proyecto W.O 2024 2027 GDT\WORKOVER Y REDISEÑOS SECUNDARIA 2,\\10.100.25.60\sya\GEC\Castilla\DFGB Etapa 4 | H87: 30 | I87: 3 | J87: =IFERROR(I87/H87,0) -> 0.1 | K87: =+I87+'MAYO 2025'!K87 -> 9 | L87: =IFERROR(K87/H87,0) -> 0.3
B88: 3 | C88: 3.18 | D88: Generar perfiles de Producción por pozos para pozos existente en escenarios Bajo, Medio y Alto | F88: Perfiles de produccion e inyeccion para proyectos Workover secundario GDT, expnasion de recobro unidades T2 & K1, evaluacion de resultados de los pozos etapa 4, en escenarios Bajo, Medio y Alto . | G88: Digital-1. \\10.100.25.60\sya\GEC\Castilla\Proyecto W.O 2024 2027 GDT\WORKOVER Y REDISEÑOS SECUNDARIA 2. \\10.100.25.60\sya\GEC\Castilla\20.Proyecto IOR K2\Expansión Recobro Mejorado GDT\reconfiguracion ERM junio 2024 3.\10.100.25.60\sya\GEC\Castilla\102.T2\Revision 2024 2. Presentación Semanal Sistemática Etapa 4 3 5. \\10.100.25.60\sya\GEC\Castilla\20.Proyecto IOR K2\Expansión Recobro Mejorado GDT\02. EXP REC MEJORADO FASE 1 | H88: 30 | I88: 3 | J88: =IFERROR(I88/H88,0) -> 0.1 | K88: =+I88+'MAYO 2025'!K88 -> 9 | L88: =IFERROR(K88/H88,0) -> 0.3
B89: 5 | C89: 5.2 | D89: Generación de oportunidades de intervención a Pozos | F89: Maduración del proyecto Intervension de pozos (Rediseños 40 trabajos 2025, 40 trabajos 2026) . | G89: Digital-1. \\10.100.25.60\sya\GEC\Castilla\Proyecto W.O 2024 2027 GDT\WORKOVER Y REDISEÑOS SECUNDARIA | H89: 30 | I89: 4 | J89: =IFERROR(I89/H89,0) -> 0.13333333 | K89: =+I89+'MAYO 2025'!K89 -> 12 | L89: =IFERROR(K89/H89,0) -> 0.4
B90: 5 | C90: 5.9 | D90: Realizar el seguimiento de producción/ inyección de pozos intervenidos con base en los comportamientos de producción previo y posterior a la intervención | F90: Seguimiento a la campaña de Workover en ejecucion Workover 2024-2027 GDT (antes, despues, e incremental), 7 trabajos ejecutados durante al año 2024 | G90: \\10.100.25.60\sya\GEC\Castilla\Proyecto W.O 2024 2027 GDT | H90: 30 | I90: 4 | J90: =IFERROR(I90/H90,0) -> 0.13333333 | K90: =+I90+'MAYO 2025'!K90 -> 12 | L90: =IFERROR(K90/H90,0) -> 0.4
B91: 8 | C91: 8.2 | D91: Carga de datos, procesamiento de datos, Análisis Estadístico descriptivo considerando hipótesis desde la teoría, y análisis descriptivo considerando hipótesis generadas desde la misma data (pasos 1, 2 y 3 teoría CRISP-DM). | F91: Actualizacion de informacion de yacimiento para el Proyecto futuro Expansion de recobro Unidades T2 y K1 | G91: 1. \\10.100.25.60\sya\GEC\Castilla\20.Proyecto IOR K2\Expansión Recobro Mejorado GDT\reconfiguracion ERM junio 2024 3.\10.100.25.60\sya\GEC\Castilla\102.T2\Revision 2024 | H91: 30 | I91: 4 | J91: =IFERROR(I91/H91,0) -> 0.13333333 | K91: =+I91+'MAYO 2025'!K91 -> 12 | L91: =IFERROR(K91/H91,0) -> 0.4
B92: 3 | C92: 3.6 | D92: Generar Modelo analítico del yacimiento integrando la información disponible en un software específico | E92: Luis Monsalve | F92: Modelo Analítico - Perfiles de Producción - Informe del modelo | G92: Repositorio digital: N:\39. Proyecto_Inyeccion_de_Agua\SAHARA\BD Sahara\2024-09-23 Sahara VyP Castilla | H92: 18 | I92: 2 | J92: =IFERROR(I92/H92,0) -> 0.11111111 | K92: =+I92+'MAYO 2025'!K92 -> 7 | L92: =IFERROR(K92/H92,0) -> 0.38888889
B93: 3 | C93: 3.13 | D93: Generar base de datos de producción (OFM o la que se requiera) | F93: Base de Datos | G93: OFM: \\10.100.25.35\ofm\C1118546 | H93: 16 | I93: 3 | J93: =IFERROR(I93/H93,0) -> 0.1875 | K93: =+I93+'MAYO 2025'!K93 -> 9 | L93: =IFERROR(K93/H93,0) -> 0.5625
B94: 3 | C94: 3.14 | D94: Generar Distribución de Producción por sub- unidades (allocation) | F94: Base de Datos | G94: Repositorio digital: N:\39. Proyecto_Inyeccion_de_Agua\SAHARA\BD Sahara\2024-10-21 Sahara VyP Castilla | H94: 16 | I94: 3 | J94: =IFERROR(I94/H94,0) -> 0.1875 | K94: =+I94+'MAYO 2025'!K94 -> 8 | L94: =IFERROR(K94/H94,0) -> 0.5
B95: 3 | C95: 3.16 | D95: Análisis de Declinaciones por pozo y/o subunidad | F95: Base de Datos - Perfiles Generados - Informe del análisis | G95: Repositorio digital: N:\39. Proyecto_Inyeccion_de_Agua\SAHARA\BD Sahara\2024-10-21 Sahara VyP Castilla | H95: 16 | I95: 3 | J95: =IFERROR(I95/H95,0) -> 0.1875 | K95: =+I95+'MAYO 2025'!K95 -> 8 | L95: =IFERROR(K95/H95,0) -> 0.5
B96: 3 | C96: 3.17 | D96: Analizar data histórica de producción, productividad y daño por pozo | F96: Base de Datos - Informe de la Evaluación | G96: Sharepoint: https://ecopetrol.sharepoint.com/sites/BDSaharaCastilla/Documentos%20compartidos/Forms/AllItems.aspx?id=%2Fsites%2FBDSaharaCastilla%2FDocumentos%20compartidos%2FPresentaciones%20soporte%20sesiones%2F2024&viewid=a035cf74%2D0100%2D4f66%2Da914%2D651dfeb02341&noAuthRedirect=1&OR=Teams%2DHL&CT=1729284822343&clickparams=eyJBcHBOYW1lIjoiVGVhbXMtRGVza3RvcCIsIkFwcFZlcnNpb24iOiI0OS8yNDA5MTIyMTMxOCIsIkhhc0ZlZGVyYXRlZFVzZXIiOmZhbHNlfQ%3D%3D | H96: 16 | I96: 3 | J96: =IFERROR(I96/H96,0) -> 0.1875 | K96: =+I96+'MAYO 2025'!K96 -> 8 | L96: =IFERROR(K96/H96,0) -> 0.5
B97: 3 | C97: 3.18 | D97: Generar perfiles de Producción por pozos para pozos existente en escenarios Bajo, Medio y Alto | F97: Base de Datos - Informe de la Evaluación | G97: Sharepoint: https://ecopetrol.sharepoint.com/sites/CastillaWOs2022/Documentos%20compartidos/Forms/AllItems.aspx?id=%2Fsites%2FCastillaWOs2022%2FDocumentos%20compartidos%2FJustificaciones&viewid=9ecb22f4%2D2d68%2D4a78%2Db78d%2Df5ff342528b5 | H97: 16 | I97: 3 | J97: =IFERROR(I97/H97,0) -> 0.1875 | K97: =+I97+'MAYO 2025'!K97 -> 9 | L97: =IFERROR(K97/H97,0) -> 0.5625
B98: 5 | C98: 5.2 | D98: Generación de oportunidades de intervención a Pozos | F98: Base de Datos - Informe de la Evaluación | G98: Sharepoint: https://ecopetrol.sharepoint.com/sites/CastillaWOs2022/Documentos%20compartidos/Forms/AllItems.aspx?id=%2Fsites%2FCastillaWOs2022%2FDocumentos%20compartidos%2FJustificaciones&viewid=9ecb22f4%2D2d68%2D4a78%2Db78d%2Df5ff342528b5 | H98: 16 | I98: 3 | J98: =IFERROR(I98/H98,0) -> 0.1875 | K98: =+I98+'MAYO 2025'!K98 -> 9 | L98: =IFERROR(K98/H98,0) -> 0.5625
B99: 5 | C99: 5.3 | D99: Estimar restricciones de Presión y tasas para la generación de perfiles de producción | F99: Base de Datos - Informe de la Evaluación | G99: Repositorio digital: N:\39. Proyecto_Inyeccion_de_Agua\SAHARA\BD Sahara\2024-09-23 Sahara VyP Castilla | H99: 16 | I99: 3 | J99: =IFERROR(I99/H99,0) -> 0.1875 | K99: =+I99+'MAYO 2025'!K99 -> 9 | L99: =IFERROR(K99/H99,0) -> 0.5625
B100: 5 | C100: 5.5 | D100: Adelantar la evaluación e interpretación de datos enfocada a candidatización de actividades de reacondicionamiento y optimización de productividad en los activos | F100: Base de Datos - Informe de la Evaluación | G100: Sharepoint: https://ecopetrol.sharepoint.com/:x:/r/sites/ZonaEsteCAE/Documentos%20compartidos/CAE/Bit%C3%A1cora%20Zona%20Este.xlsx?d=w7a348467c50040ec94ebcaffa475a9d1&csf=1&web=1&e=I8Rzqg | H100: 18 | I100: 3 | J100: =IFERROR(I100/H100,0) -> 0.16666667 | K100: =+I100+'MAYO 2025'!K100 -> 9 | L100: =IFERROR(K100/H100,0) -> 0.5
...

Sheet JULIO 2025
Q1: MES
B2: REPORTE DE AVANCE | Q2: ENERO
B3: Fecha: 29/06/2022 | F3: Version: 01 | J3: GP-F-23
Q4: FEBRERO
B5: Código Orden de servicio | D5: 90141005 | Q5: MARZO
Q6: JUNIO
B7: Mes a reportar | D7: JULIO | Q7: JULIO
Q8: AGOSTO
B9: Fecha reporte | D9: 45869 | Q9: SEPTIEMBRE
Q10: OCTUBRE
B11: Clasificación del servicio | I11: Reporte mes por servicio | K11: Reporte acumulado por servicio | Q11: NOVIEMBRE
B12: Ítem general | C12: ítem actividad | D12: Descripción de la actividad | E12: Profesional a cargo | F12: Soporte | G12: Medio de entrega | H12: Días contratados | I12: Días | J12: % avance | K12: Días | L12: % avance | Q12: DICIEMBRE
B13: 3 | C13: 3.6 | D13: Generar Modelo analítico del yacimiento integrando la información disponible en un software específico | E13: Alejandro D López | F13: Cambio en los cronogramas y perfiles del modelo analítico en ARPS para los perfiles de producción para el campo Akasias en para las etapas de ANE y Tinamu | G13: ACCESS - PLP 2024 - Todos los documentos (sharepoint.com) | H13: 33 | I13: 6 | J13: =IFERROR(I13/H13,0) -> 0.18181818 | K13: =+I13+'JUNIO 2025'!K13 -> 26 | L13: =IFERROR(K13/H13,0) -> 0.78787879
B14: 3 | C14: 3.13 | D14: Generar base de datos de producción (OFM o la que se requiera) | F14: Generar archivos de carga de productores, inyectores y allocacion para el campo Tinamu. Se realizó control de calidad a los archivos que se subieron al ARPS | G14: https://ecopetrol.sharepoint.com/sites/EquipoDesarrolloCPO-9/Documentos%20compartidos/Forms/AllItems.aspx?id=%2Fsites%2FEquipoDesarrolloCPO%2D9%2FDocumentos%20compartidos%2FGeneral%2F04%2DExploratorio%2FExploratorios%20CPO%2D9&viewid=0e96c994%2D47e1%2D4e99%2D93c0%2D37826753815c | H14: 39 | I14: 0 | J14: =IFERROR(I14/H14,0) -> 0 | K14: =+I14+'JUNIO 2025'!K14 -> 10 | L14: =IFERROR(K14/H14,0) -> 0.25641026
B15: 3 | C15: 3.16 | D15: Análisis de Declinaciones por pozo y/o subunidad | F15: Se generó un establecio la configuracion de allocacion de primeras y segundas lineas por RWA para el campo Akacias en la etapa de desarrollo temprano | G15: ACCESS - PLP 2024 - Todos los documentos (sharepoint.com) | H15: 33 | I15: 6 | J15: =IFERROR(I15/H15,0) -> 0.18181818 | K15: =+I15+'JUNIO 2025'!K15 -> 16 | L15: =IFERROR(K15/H15,0) -> 0.48484848
B16: 3 | C16: 3.17 | D16: Analizar data histórica de producción, productividad y daño por pozo | F16: Base de Datos - Informe de la Evaluación | G16: ACCESS - PLP 2024 - Todos los documentos (sharepoint.com) | H16: 33 | I16: 2 | J16: =IFERROR(I16/H16,0) -> 0.060606061 | K16: =+I16+'JUNIO 2025'!K16 -> 12 | L16: =IFERROR(K16/H16,0) -> 0.36363636
B17: 3 | C17: 3.18 | D17: Generar perfiles de Producción por pozos para pozos existente en escenarios Bajo, Medio y Alto | F17: Se generó un archivo parcial de analisis de produccion de los pozos de cercanos y perforados del campo Tinamu para usar su produccion como referencia para los futuros pozos del campo | G17: ACCESS - PLP 2024 - Todos los documentos (sharepoint.com) | H17: 33 | I17: 6 | J17: =IFERROR(I17/H17,0) -> 0.18181818 | K17: =+I17+'JUNIO 2025'!K17 -> 16 | L17: =IFERROR(K17/H17,0) -> 0.48484848
B18: 5 | C18: 5.2 | D18: Generación de oportunidades de intervención a Pozos | F18: Base de Datos - Informe de la Evaluación | G18: ACCESS - Frontera - Todos los documentos | H18: 33 | I18: 4 | J18: =IFERROR(I18/H18,0) -> 0.12121212 | K18: =+I18+'JUNIO 2025'!K18 -> 14 | L18: =IFERROR(K18/H18,0) -> 0.42424242
B19: 5 | C19: 5.9 | D19: Realizar el seguimiento de producción/ inyección de pozos intervenidos con base en los comportamientos de producción previo y posterior a la intervención | F19: Entrega de perfiles de la etapa de Tinamu para proyectos | G19: ACCESS - Tinamu - Todos los documentos | H19: 33 | I19: 5 | J19: =IFERROR(I19/H19,0) -> 0.15151515 | K19: =+I19+'JUNIO 2025'!K19 -> 15 | L19: =IFERROR(K19/H19,0) -> 0.45454545
B20: 8 | C20: 8.2 | D20: Carga de datos, procesamiento de datos, Análisis Estadístico descriptivo considerando hipótesis desde la teoría, y análisis descriptivo considerando hipótesis generadas desde la misma data (pasos 1, 2 y 3 teoría CRISP-DM). | F20: Informe, con estadísticas descriptivas, histogramas, pruebas de ajuste, etc. | G20: Informe de reservas Campo Akacias 2022 - Inicio (sharepoint.com) | H20: 33 | I20: 1 | J20: =IFERROR(I20/H20,0) -> 0.03030303 | K20: =+I20+'JUNIO 2025'!K20 -> 11 | L20: =IFERROR(K20/H20,0) -> 0.33333333
B21: 3 | C21: 3.6 | D21: Generar Modelo analítico del yacimiento integrando la información disponible en un software específico | E21: Jhon H Carreño | F21: Actualización semanal del modelo estático y dinámico del yacimiento y pozos del campo Akacias, mediante el proyecto Sahara Junio-2025 (Cargadores y modelo final) | G21: X:\CHICHIMENE\INFORMACIÓN_CAMPO_CHICHIMENE\23.-Inyeccion de Agua\10. MONITOREO\09. Proyecto Sahara\2025 W:\2.- Ingeniería de Yacimientos\1.MONITOREO\1.Sahara\2025\7. Julio | H21: 30 | I21: 3 | J21: =IFERROR(I21/H21,0) -> 0.1 | K21: =+I21+'JUNIO 2025'!K21 -> 13 | L21: =IFERROR(K21/H21,0) -> 0.43333333
B22: 3 | C22: 3.13 | D22: Generar base de datos de producción (OFM o la que se requiera) | F22: Actualización de la producción con base a la información de las formas ministeriales para las base de datos (molinos de viento) de producción mensual y cargue trimestral y seguimiento a proyectos en tableros de seguimiento | G22: W:\2.- Ingeniería de Yacimientos\1.MONITOREO\9.Tablero Power BI 2.1\2025 W:\2.- Ingeniería de Yacimientos\1.MONITOREO\14.Molinos de Viento\Cargadores\Real\2025 | H22: 30 | I22: 4 | J22: =IFERROR(I22/H22,0) -> 0.13333333 | K22: =+I22+'JUNIO 2025'!K22 -> 14 | L22: =IFERROR(K22/H22,0) -> 0.46666667
B23: 3 | C23: 3.14 | D23: Generar Distribución de Producción por sub- unidades (allocation) | F23: Distribución de la producción asociada a la implementación del WF en los patrones de inyección del campo AK por medio del metodo RWA con la información a cierre de Jun-2025 y distribución de la inyección de agua por medio de factores de alocación usando como información base los registros ILT adquiridos | G23: W:\2.- Ingeniería de Yacimientos\1.MONITOREO\9.Tablero Power BI 2.1\2025\6. Junio W:\2.- Ingeniería de Yacimientos\1.MONITOREO\14.Molinos de Viento\Cargadores\Real\2025\06. Junio | H23: 30 | I23: 4 | J23: =IFERROR(I23/H23,0) -> 0.13333333 | K23: =+I23+'JUNIO 2025'!K23 -> 14 | L23: =IFERROR(K23/H23,0) -> 0.46666667
B24: 3 | C24: 3.16 | D24: Análisis de Declinaciones por pozo y/o subunidad | F24: Definición del efecto de inyección del AK-135i sobre los productores AK-133 y 137. Construcción de líneas base en Sahara | G24: X:\CHICHIMENE\INFORMACIÓN_CAMPO_CHICHIMENE\23.-Inyeccion de Agua\10. MONITOREO\09. Proyecto Sahara\2025 | H24: 30 | I24: 3 | J24: =IFERROR(I24/H24,0) -> 0.1 | K24: =+I24+'JUNIO 2025'!K24 -> 13 | L24: =IFERROR(K24/H24,0) -> 0.43333333
B25: 3 | C25: 3.17 | D25: Analizar data histórica de producción, productividad y daño por pozo | F25: Interpretación del cierre para los pozos AK-79, AK-96, AK-127, AK-155 y AK-156 del sector Nueva Esperanza para determinar el grado de recuperación de presión por efecto de la inyección en el AK-26i, AK-147i y CH-235i del proyecto frontera | G25: W:\2.- Ingeniería de Yacimientos\1.MONITOREO\7.Presiones\2025\1_Semestre\Información de presión Jun2025 NE | H25: 30 | I25: 4 | J25: =IFERROR(I25/H25,0) -> 0.13333333 | K25: =+I25+'JUNIO 2025'!K25 -> 14 | L25: =IFERROR(K25/H25,0) -> 0.46666667
B26: 3 | C26: 3.18 | D26: Generar perfiles de Producción por pozos para pozos existente en escenarios Bajo, Medio y Alto | F26: Actualización del coeficiente de eficiencia veritical para seguimiento de los patrones de inyección del campo Akacias | G26: W:\2.- Ingeniería de Yacimientos\1.MONITOREO\37. Coeficientes de eficiencia vertical\2025\3. Junio | H26: 30 | I26: 3 | J26: =IFERROR(I26/H26,0) -> 0.1 | K26: =+I26+'JUNIO 2025'!K26 -> 13 | L26: =IFERROR(K26/H26,0) -> 0.43333333
B27: 5 | C27: 5.2 | D27: Generación de oportunidades de intervención a Pozos | F27: Interpretación del gradiente estático adquirido en el AK-153 del sector Nueva esperanza a fin de conocer el grado de conexión con los pozos del patrón, además de verificar el incremeto de presión en el tiempo | G27: W:\2.- Ingeniería de Yacimientos\1.MONITOREO\7.Presiones\2025\1_Semestre\5. AK-153 | H27: 30 | I27: 3 | J27: =IFERROR(I27/H27,0) -> 0.1 | K27: =+I27+'JUNIO 2025'!K27 -> 13 | L27: =IFERROR(K27/H27,0) -> 0.43333333
B28: 5 | C28: 5.9 | D28: Realizar el seguimiento de producción/ inyección de pozos intervenidos con base en los comportamientos de producción previo y posterior a la intervención | F28: Seguimiento a la intervención de WO de los pozos AK-35i, AK-33 y AK-05 | G28: W:\2.- Ingeniería de Yacimientos\1.MONITOREO\4. Inyectores\Etapa A2.2\AK-35\2025 https://ecopetrol.sharepoint.com/:p:/s/IAAKACIAS/EVKgMF0gGsVHtQBEs1cOyrwBuReCBoJh1yvlEMqX3lTqHw?e=79vEVM | H28: 30 | I28: 3 | J28: =IFERROR(I28/H28,0) -> 0.1 | K28: =+I28+'JUNIO 2025'!K28 -> 13 | L28: =IFERROR(K28/H28,0) -> 0.43333333
B29: 8 | C29: 8.2 | D29: Carga de datos, procesamiento de datos, Análisis Estadístico descriptivo considerando hipótesis desde la teoría, y análisis descriptivo considerando hipótesis generadas desde la misma data (pasos 1, 2 y 3 teoría CRISP-DM). | F29: Actualización de las diferentes bases de datos para la actualización de tableros y distintas visuales | G29: https://ecopetrol.sharepoint.com/:f:/s/IAAKACIAS/EoI_hVXr9Q5FtD_ADjltMeYB1mxxF9WpklMtD9QXGgqRTA?e=FXnE5b | H29: 30 | I29: 3 | J29: =IFERROR(I29/H29,0) -> 0.1 | K29: =+I29+'JUNIO 2025'!K29 -> 13 | L29: =IFERROR(K29/H29,0) -> 0.43333333
B30: 1 | C30: 1.2 | D30: Generación Bases de Datos de Pozos (Registros, Topes e información disponible) | E30: Julian A Hernández | F30: 1) Actualización con la base de datos con información de pozos inyectores del campo y la información preliminar aprobada para los pozos AK222 y AK99. | G30: \\10.100.25.35\pgtrabajodigital\JAH\Proyecto groups21\akacias\2.- Ingeniería de Yacimientos\1.MONITOREO | H30: 55 | I30: 7 | J30: =IFERROR(I30/H30,0) -> 0.12727273 | K30: =+I30+'JUNIO 2025'!K30 -> 22 | L30: =IFERROR(K30/H30,0) -> 0.4
B31: 1 | C31: 1.3 | D31: Interpretación Sísmica | F31: 1) Revisón de información sismica para los pozos pertencientes a los patrones de inyección para identificar estructuras y establecer conectividades en los patrones de inyección. En busqueda del mejoramiento del factor de conectividad geológico. 2) Revisión información sísmica para identificar fallas o estrucutras en los patrones de inyección en pro de actualziar el factor de conectividad geológica para el campo Akacias. 3) Revisión en conjunto con el área de geofísica de la informaicón sismica para los pozos nuevos a perforar en el campo Akacias (AK222) | G31: \\10.100.25.35\pgtrabajodigital\JAH\Proyecto Z:\akacias\2.- Ingeniería de Yacimientos\1.MONITOREO\19.Sistematica WF Akacias\2025\07.Julio | H31: 20 | I31: 1 | J31: =IFERROR(I31/H31,0) -> 0.05 | K31: =+I31+'JUNIO 2025'!K31 -> 9 | L31: =IFERROR(K31/H31,0) -> 0.45
B32: 1 | C32: 1.5 | D32: Digitalización, digitación y/o captura de información geológica (Mapas, Raw Data, topes, etc.) | F32: 1) Generación mapas, cortes y correalciones para hacer seguimiento a los patrones de inyección del campo y monitoreo a los pozos productores. 2) Cargue informaicón preliminar para el pozo dispositor AK222. | G32: \\10.100.25.35\pgtrabajodigital\JAH\Proyecto | H32: 30 | I32: 4 | J32: =IFERROR(I32/H32,0) -> 0.13333333 | K32: =+I32+'JUNIO 2025'!K32 -> 14 | L32: =IFERROR(K32/H32,0) -> 0.46666667
B33: 1 | C33: 1.8 | D33: Balanceo de Secciones | F33: 1) Contrucción en petrel de secciones que permitan observar la continuidad horizontal de los ciclos estratigráficos en pro de establecer la conectividad geológica en los patrones de inyección, en el monitoreo del WF para el campo Akacias. 2) Generación de secciones estructurales que permitan observar el comportamiento areal del yacimiento, enfocadas en monitorear el comportamiento de pozos productores y las conectividades en patrones de inyección en el campo Akacias. | G33: \\10.100.25.35\pgtrabajodigital\JAH\Proyecto | H33: 25 | I33: 4 | J33: =IFERROR(I33/H33,0) -> 0.16 | K33: =+I33+'JUNIO 2025'!K33 -> 12 | L33: =IFERROR(K33/H33,0) -> 0.48
B34: 1 | C34: 1.9 | D34: Análisis de sellos de fallas | F34: 1) Revisión del modelo estrucutural para el análisis de los patrones de inyección y así establecer la comunicación entre Inyec-produc durantes las sesiones de WF Akacias. 2) Revisión de los posibles sellos estructurales que condicionen el factor falla involucrado en la determinación del factor de conectividad geológico y continuar con la actualización de los tableros de conectividad geológica. 3) Análisis de las fallas dentro del estudio para identificar la influencia del acuífero en el campo a nivel CHIAK. | G34: \\10.100.25.35\pgtrabajodigital\JAH\Proyecto Z:\akacias\2.- Ingeniería de Yacimientos\1.MONITOREO\19.Sistematica WF Akacias\2025\07.Julio | H34: 30 | I34: 4 | J34: =IFERROR(I34/H34,0) -> 0.13333333 | K34: =+I34+'JUNIO 2025'!K34 -> 14 | L34: =IFERROR(K34/H34,0) -> 0.46666667
B35: 1 | C35: 1.10 | D35: Amarre Sísmica Pozo | F35: 1) Revisión de la información sismíca con la trayectoria en las trayectorias entre pozos inyectores y porductores para identicar el Factor falla involucrado dentro del factor de conectividad geológica, insumo para actualizar el factor de conectividad geológico y el mapa de conectividad. 2) Revisión de las fallas interpretadas en las zonas de los pozos próximos a perforar para identificar los posibles riesgos geológicos y geofísicos, involucrando la nueva información estructural. Información que se usa como insumo para contrucción de los documentos RMS elaborados para los próximos pozos a perforar (AK222). | G35: \\10.100.25.35\pgtrabajodigital\JAH\Proyecto groups21\akacias\5. Información de pozos | H35: 20 | I35: 1 | J35: =IFERROR(I35/H35,0) -> 0.05 | K35: =+I35+'JUNIO 2025'!K35 -> 9 | L35: =IFERROR(K35/H35,0) -> 0.45
B36: 1 | C36: 1.12 | D36: Generación de mapas de facies | F36: 1) Continua la elaboración de la base de datos para la actualización de los tableros G&G CHIAK. Actualización de mapas estructural, conectividad, cloruros, presiones y BSW 2) Hacer seguimiento áreal de las facies para identificar los cambios laterales de facies que puedan indicar el comportamiento de arenas yto en los pozos productores. | G36: \\10.100.25.35\pgtrabajodigital\JAH\Proyecto | H36: 20 | I36: 1 | J36: =IFERROR(I36/H36,0) -> 0.05 | K36: =+I36+'JUNIO 2025'!K36 -> 9 | L36: =IFERROR(K36/H36,0) -> 0.45
B37: 1 | C37: 1.15 | D37: Carga de información para poblar el modelo geocelular (direccionales, coordenadas, surveys, topes, data de presión, estados mecánicos, evento de pozos, etc.) | F37: 1) Actualización última información aprobada para la elaboración de los archivos RMS. | G37: ruta: \\10.100.25.35\pgtrabajodigital\JAH\Proyecto | H37: 50 | I37: 7 | J37: =IFERROR(I37/H37,0) -> 0.14 | K37: =+I37+'JUNIO 2025'!K37 -> 22 | L37: =IFERROR(K37/H37,0) -> 0.44
B38: 1 | C38: 1.25 | D38: Análisis geoquímicos de Fingerprinting | F38: 1) Continua: Análisis de la influencia del acuífero a nivel CHIAK actualización del mapa con datos a corte del primer semestre de 2025, a partir de la integración de información de análisis fisicoquímicos, continuidad estratigráfica, rasgos estructurales, resultados de PLTs e ILTs, BSW y Ql en los pozos de los campos Chichimene y Akacias. | G38: ruta: \\10.100.25.35\pgtrabajodigital\JAH\Proyecto | H38: 20 | I38: 1 | J38: =IFERROR(I38/H38,0) -> 0.05 | K38: =+I38+'JUNIO 2025'!K38 -> 9 | L38: =IFERROR(K38/H38,0) -> 0.45
B39: 3 | C39: 3.6 | D39: Generar Modelo analítico del yacimiento integrando la información disponible en un software específico | E39: Milton J Gualteros | F39: Actualización modelo analítico de yacimientos ARPS PDI2025 ESC3 - Frontera, ANE, Etapa 3, Inyección norte CHIAK | G39: Microsoft Teams, Email, Sharepoint Y:\akacias\37. Archivos | H39: 35 | I39: 4 | J39: =IFERROR(I39/H39,0) -> 0.11428571 | K39: =+I39+'JUNIO 2025'!K39 -> 16 | L39: =IFERROR(K39/H39,0) -> 0.45714286
B40: 3 | C40: 3.13 | D40: Generar base de datos de producción (OFM o la que se requiera) | F40: Generación base de datos y construcción perfiles proyectos Desarrollo Posterior | G40: Microsoft Teams, Email, Sharepoint Y:\akacias\37. Archivos | H40: 33 | I40: 4 | J40: =IFERROR(I40/H40,0) -> 0.12121212 | K40: =+I40+'JUNIO 2025'!K40 -> 15 | L40: =IFERROR(K40/H40,0) -> 0.45454545
B41: 3 | C41: 3.16 | D41: Análisis de Declinaciones por pozo y/o subunidad | F41: Análisis de declinación pozos asociados a patrones de inyección | G41: Microsoft Teams, Email, Sharepoint Y:\akacias\37. Archivos | H41: 33 | I41: 4 | J41: =IFERROR(I41/H41,0) -> 0.12121212 | K41: =+I41+'JUNIO 2025'!K41 -> 15 | L41: =IFERROR(K41/H41,0) -> 0.45454545
B42: 3 | C42: 3.17 | D42: Analizar data histórica de producción, productividad y daño por pozo | F42: Análisis de data histórica de producción para seguimiento proceso Waterflooding | G42: Microsoft Teams, Email, Sharepoint Y:\akacias\37. Archivos | H42: 33 | I42: 4 | J42: =IFERROR(I42/H42,0) -> 0.12121212 | K42: =+I42+'JUNIO 2025'!K42 -> 15 | L42: =IFERROR(K42/H42,0) -> 0.45454545
B43: 3 | C43: 3.18 | D43: Generar perfiles de Producción por pozos para pozos existente en escenarios Bajo, Medio y Alto | F43: Generación perfiles de producción escenarios bajo, medio, alto en ARPS (PDI2025 ESC3) | G43: Microsoft Teams, Email, Sharepoint Y:\akacias\37. Archivos | H43: 35 | I43: 4 | J43: =IFERROR(I43/H43,0) -> 0.11428571 | K43: =+I43+'JUNIO 2025'!K43 -> 15 | L43: =IFERROR(K43/H43,0) -> 0.42857143
B44: 5 | C44: 5.2 | D44: Generación de oportunidades de intervención a Pozos | F44: Definición oportunidades de intervención en reunión sistematica WF | G44: Microsoft Teams, Email, Sharepoint Y:\akacias\37. Archivos | H44: 33 | I44: 4 | J44: =IFERROR(I44/H44,0) -> 0.12121212 | K44: =+I44+'JUNIO 2025'!K44 -> 15 | L44: =IFERROR(K44/H44,0) -> 0.45454545
B45: 5 | C45: 5.9 | D45: Realizar el seguimiento de producción/ inyección de pozos intervenidos con base en los comportamientos de producción previo y posterior a la intervención | F45: Seguimiento de Producción e Inyección del proyecto de waterflooding del campo akacias | G45: Microsoft Teams, Email, Sharepoint Y:\akacias\37. Archivos | H45: 35 | I45: 3 | J45: =IFERROR(I45/H45,0) -> 0.085714286 | K45: =+I45+'JUNIO 2025'!K45 -> 15 | L45: =IFERROR(K45/H45,0) -> 0.42857143
B46: 8 | C46: 8.2 | D46: Carga de datos, procesamiento de datos, Análisis Estadístico descriptivo considerando hipótesis desde la teoría, y análisis descriptivo considerando hipótesis generadas desde la misma data (pasos 1, 2 y 3 teoría CRISP-DM). | F46: Cargue, análisis y procesamiento de los datos del modelo análitico de yacimientos. Analisis de datos en PowerBI | G46: Microsoft Teams, Email, Sharepoint Y:\akacias\37. Archivos | H46: 33 | I46: 3 | J46: =IFERROR(I46/H46,0) -> 0.090909091 | K46: =+I46+'JUNIO 2025'!K46 -> 14 | L46: =IFERROR(K46/H46,0) -> 0.42424242
B47: 3 | C47: 3.6 | D47: Generar Modelo analítico del yacimiento integrando la información disponible en un software específico | E47: Ana M Castellanos | F47: Modelo Analítico - Perfiles de Producción - Informe del modelo | G47: \\10.100.25.60\sya\gec | H47: 20 | I47: 3 | J47: =IFERROR(I47/H47,0) -> 0.15 | K47: =+I47+'JUNIO 2025'!K47 -> 12 | L47: =IFERROR(K47/H47,0) -> 0.6
B48: 3 | C48: 3.13 | D48: Generar base de datos de producción (OFM o la que se requiera) | F48: Base de Datos | G48: \\10.100.25.60\sya\gec | H48: 20 | I48: 3 | J48: =IFERROR(I48/H48,0) -> 0.15 | K48: =+I48+'JUNIO 2025'!K48 -> 12 | L48: =IFERROR(K48/H48,0) -> 0.6
B49: 3 | C49: 3.14 | D49: Generar Distribución de Producción por sub- unidades (allocation) | F49: Base de Datos | G49: \\10.100.25.60\sya\gec | H49: 20 | I49: 4 | J49: =IFERROR(I49/H49,0) -> 0.2 | K49: =+I49+'JUNIO 2025'!K49 -> 16 | L49: =IFERROR(K49/H49,0) -> 0.8
B50: 3 | C50: 3.16 | D50: Análisis de Declinaciones por pozo y/o subunidad | F50: Base de Datos - Perfiles Generados - Informe del análisis | G50: https://ecopetrol.sharepoint.com/sites/BDSaharaCastilla/Documentos%20compartidos/Forms/AllItems.aspx?id=%2Fsites%2FBDSaharaCastilla%2FDocumentos%20compartidos%2FBD%20Sahara&viewid=a035cf74%2D0100%2D4f66%2Da914%2D651dfeb02341 | H50: 20 | I50: 3 | J50: =IFERROR(I50/H50,0) -> 0.15 | K50: =+I50+'JUNIO 2025'!K50 -> 12 | L50: =IFERROR(K50/H50,0) -> 0.6
B51: 3 | C51: 3.17 | D51: Analizar data histórica de producción, productividad y daño por pozo | F51: Base de Datos - Informe de la Evaluación | G51: \\10.100.25.60\sya\gec | H51: 20 | I51: 4 | J51: =IFERROR(I51/H51,0) -> 0.2 | K51: =+I51+'JUNIO 2025'!K51 -> 16 | L51: =IFERROR(K51/H51,0) -> 0.8
B52: 3 | C52: 3.18 | D52: Generar perfiles de Producción por pozos para pozos existente en escenarios Bajo, Medio y Alto | F52: Base de Datos - Informe de la Evaluación | G52: \\10.100.25.60\sya\gec Sahara/ Tableros de diagnostico | H52: 20 | I52: 3 | J52: =IFERROR(I52/H52,0) -> 0.15 | K52: =+I52+'JUNIO 2025'!K52 -> 12 | L52: =IFERROR(K52/H52,0) -> 0.6
B53: 5 | C53: 5.2 | D53: Generación de oportunidades de intervención a Pozos | F53: Base de Datos - Informe de la Evaluación | G53: https://wellmeeting.ecopetrol.com.co/home https://ecopetrol.sharepoint.com/sites/CastillaWOs2022/Documentos%20compartidos/Forms/AllItems.aspx | H53: 20 | I53: 3 | J53: =IFERROR(I53/H53,0) -> 0.15 | K53: =+I53+'JUNIO 2025'!K53 -> 12 | L53: =IFERROR(K53/H53,0) -> 0.6
B54: 5 | C54: 5.9 | D54: Realizar el seguimiento de producción/ inyección de pozos intervenidos con base en los comportamientos de producción previo y posterior a la intervención | F54: Base de Datos - Informe de la Evaluación | G54: 2025-04-21 Sahara VyP Castilla.zip https://ecopetrol.sharepoint.com/sites/BDSaharaCastilla/Documentos%20compartidos/Forms/AllItems.aspx?id=%2Fsites%2FBDSaharaCastilla%2FDocumentos%20compartidos%2FPresentaciones%20soporte%20sesiones%2F2025&viewid=a035cf74%2D0100%2D4f66%2Da914%2D651dfeb02341 | H54: 20 | I54: 4 | J54: =IFERROR(I54/H54,0) -> 0.2 | K54: =+I54+'JUNIO 2025'!K54 -> 16 | L54: =IFERROR(K54/H54,0) -> 0.8
B55: 8 | C55: 8.2 | D55: Carga de datos, procesamiento de datos, Análisis Estadístico descriptivo considerando hipótesis desde la teoría, y análisis descriptivo considerando hipótesis generadas desde la misma data (pasos 1, 2 y 3 teoría CRISP-DM). | F55: Informe, con estadísticas descriptivas, histogramas, pruebas de ajuste, etc. | G55: https://app.powerbi.com/singleSignOn?ru=https%3A%2F%2Fapp.powerbi.com%2Fgroups%2Fe5641789-d59d-4f86-b857-9812c65a1a04%2Freports%2Fdff68870-b9fb-4308-960e-6c4f8c41c79d%2FReportSection974a4271511adef5c478%3FnoSignUpCheck%3D1 | H55: 20 | I55: 3 | J55: =IFERROR(I55/H55,0) -> 0.15 | K55: =+I55+'JUNIO 2025'!K55 -> 12 | L55: =IFERROR(K55/H55,0) -> 0.6
B56: 3 | C56: 3.6 | D56: Generar Modelo analítico del yacimiento integrando la información disponible en un software específico | E56: Paola Gomez | F56: Se realizó cargue de pruebas de produccion, tasas de inyección, pruebas de ILT en la BD de Sahara CAN22, CAN24, y CAN61 adicionalmente se realiza el seguimiento a las 20 optimizaciones, 1 rediseños y 2 WO (2 en ejecucion). | G56: \\10.100.25.60\sya\gec\Castilla\39. Proyecto_Inyeccion_de_Agua\SAHARA) y en las notas de wellmeeting | H56: 18 | I56: 3 | J56: =IFERROR(I56/H56,0) -> 0.16666667 | K56: =+I56+'JUNIO 2025'!K56 -> 12 | L56: =IFERROR(K56/H56,0) -> 0.66666667
B57: 3 | C57: 3.13 | D57: Generar base de datos de producción (OFM o la que se requiera) | F57: Se realizó la base de datos de seguimiento a patrones de Centro Norte con datos del tablero de producción prorrateada el cual es alimentado con base en la producción por formas y pruebas de producción de AVM. | G57: DTWF CASTILLA-Tablero Castilla y \\10.100.25.60\sya\gec\Castilla\39. Proyecto_Inyeccion_de_Agua\SAHARA | H57: 36 | I57: 6 | J57: =IFERROR(I57/H57,0) -> 0.16666667 | K57: =+I57+'JUNIO 2025'!K57 -> 24 | L57: =IFERROR(K57/H57,0) -> 0.66666667
B58: 3 | C58: 3.14 | D58: Generar Distribución de Producción por sub- unidades (allocation) | F58: Para esta actividad se genera distribución vertical por unidad para los inyectores asociados a la Zona Centro Norte. La distribución se encuentra actualizada a la fecha con los últimos valores de ILT para cada inyector CAN22, CAN24, y CAN617 . La evidencia se encuentra en la Base de Datos SAHARA. | G58: \\10.100.25.60\sya\gec\Castilla\39. Proyecto_Inyeccion_de_Agua\SAHARA | H58: 12 | I58: 2 | J58: =IFERROR(I58/H58,0) -> 0.16666667 | K58: =+I58+'JUNIO 2025'!K58 -> 8 | L58: =IFERROR(K58/H58,0) -> 0.66666667
B59: 3 | C59: 3.16 | D59: Análisis de Declinaciones por pozo y/o subunidad | F59: De acuerdo con el seguimiento a la producción e inyección, se realizó el seguimiento a los patrones CAN05, CAN450, CAN15, CAN01,y CAN57. | G59: https://teams.microsoft.com/l/channel/19%3A0KSR0Sqd9sL27-AWAKb2UFAmZ-fupgWBuEQNEHUYOIY1%40thread.tacv2/Documentos?groupId=ba918c77-3768-4ebd-affe-4ef992094119&tenantId=a4305987-cf78-4f93-9d64-bf18af65397b | H59: 36 | I59: 6 | J59: =IFERROR(I59/H59,0) -> 0.16666667 | K59: =+I59+'JUNIO 2025'!K59 -> 24 | L59: =IFERROR(K59/H59,0) -> 0.66666667
B60: 3 | C60: 3.17 | D60: Analizar data histórica de producción, productividad y daño por pozo | F60: se realiza relaciones y comparaciones con los datos de producción e inyección de la zona Centro Norte cargada en la base de datos de Sahara. Ver mayor ampliación en GP-F-25 | G60: \\10.100.25.60\sya\gec\Castilla\39. Proyecto_Inyeccion_de_Agua\SAHARA\BD Sahara | H60: 18 | I60: 3 | J60: =IFERROR(I60/H60,0) -> 0.16666667 | K60: =+I60+'JUNIO 2025'!K60 -> 12 | L60: =IFERROR(K60/H60,0) -> 0.66666667
B61: 3 | C61: 3.18 | D61: Generar perfiles de Producción por pozos para pozos existente en escenarios Bajo, Medio y Alto | F61: Para este ítem para el mes de abril se realizó los perfiles generados para los pozos candidatos a (RDG) rediseño y Workover (WO) los cuales quedan registrados en la ruta del equipo de taller de producción GDT | G61: GDT Plus (El V.A.R.) - General - Todos los documentos y https://ecopetrol.sharepoint.com/sites/CastillaWOs2022/Documentos%20compartidos/Forms/AllItems.aspx | H61: 18 | I61: 3 | J61: =IFERROR(I61/H61,0) -> 0.16666667 | K61: =+I61+'JUNIO 2025'!K61 -> 12 | L61: =IFERROR(K61/H61,0) -> 0.66666667
B62: 5 | C62: 5.2 | D62: Generación de oportunidades de intervención a Pozos | F62: Con el equipo multidiciplinario se realiza un análisis de los pozos encontrando bajas eficiencias y declinaciones presentadas de los pozos de la zona Centro Norte concluyendo las oportunidades de intervención en la medida que se puedan realizar las oportunidades en los pozos candidatos, lo cual queda consignado en el WM. Se realizo analisis de incremento de WOR de 47 pozos productores | G62: https://wellmeeting.ecopetrol.com.co/home | H62: 12 | I62: 2 | J62: =IFERROR(I62/H62,0) -> 0.16666667 | K62: =+I62+'JUNIO 2025'!K62 -> 8 | L62: =IFERROR(K62/H62,0) -> 0.66666667
B63: 5 | C63: 5.9 | D63: Realizar el seguimiento de producción/ inyección de pozos intervenidos con base en los comportamientos de producción previo y posterior a la intervención | F63: Se realizo el seguimiento de producción/ inyección de pozos a cargo (22 patrones de inyección) con base en los comportamientos de producción e inyección | G63: https://teams.microsoft.com/l/channel/19%3A0KSR0Sqd9sL27-AWAKb2UFAmZ-fupgWBuEQNEHUYOIY1%40thread.tacv2/Documentos?groupId=ba918c77-3768-4ebd-affe-4ef992094119&tenantId=a4305987-cf78-4f93-9d64-bf18af65397b | H63: 18 | I63: 3 | J63: =IFERROR(I63/H63,0) -> 0.16666667 | K63: =+I63+'JUNIO 2025'!K63 -> 12 | L63: =IFERROR(K63/H63,0) -> 0.66666667
B64: 8 | C64: 8.2 | D64: Carga de datos, procesamiento de datos, Análisis Estadístico descriptivo considerando hipótesis desde la teoría, y análisis descriptivo considerando hipótesis generadas desde la misma data (pasos 1, 2 y 3 teoría CRISP-DM). | F64: Para este ítem se realizó carga de datos de ILT en la BD de Sahara. Se realizó la actualización de volumetrías del pozo CAN22. | G64: \\10.100.25.60\sya\gec\Castilla\39. Proyecto_Inyeccion_de_Agua\SAHARA) y en las notas de wellmeeting | H64: 12 | I64: 2 | J64: =IFERROR(I64/H64,0) -> 0.16666667 | K64: =+I64+'JUNIO 2025'!K64 -> 8 | L64: =IFERROR(K64/H64,0) -> 0.66666667
B65: 3 | C65: 3.6 | D65: Generar Modelo analítico del yacimiento integrando la información disponible en un software específico | E65: Geisson Zafra | F65: Se generan los diferentes escenarios (3) de la básica en arps para su cargue en assembler, una vez se aseguró el balance de agua y se haya revisado el límite en capacidad. De igual forma, quedan pendientes ajustes a realizar cuando den la oportunidad de cambiar en asssembler. Adicionalmente, se generan los export de Access de los diferentes proyectos en el campo, para ser integrados con AK. | G65: C:\Users\c110096a\OneDrive - Ecopetrol S.A\tablero\01_ECP\02_VIGENCIA\20250613\Entrega_Equipos\ESC_03 | H65: 30 | I65: 3 | J65: =IFERROR(I65/H65,0) -> 0.1 | K65: =+I65+'JUNIO 2025'!K65 -> 16 | L65: =IFERROR(K65/H65,0) -> 0.53333333
B66: 3 | C66: 3.13 | D66: Generar base de datos de producción (OFM o la que se requiera) | F66: Se procede a realizar un análisis de reales vs Pronóstico para el mes de junio, con el fin de acercar el perfil de aceite al POP. Para lo anterior, se generaron archivos pareto que los compañeros de Corto Plazo han revisado para llegar a un ajuste más cercano al real. | G66: C:\Users\c110096a\OneDrive - Ecopetrol S.A\tablero\01_ECP\02_VIGENCIA\20250613\Entrega_Equipos\ESC_03 | H66: 30 | I66: 3 | J66: =IFERROR(I66/H66,0) -> 0.1 | K66: =+I66+'JUNIO 2025'!K66 -> 15 | L66: =IFERROR(K66/H66,0) -> 0.5
B67: 3 | C67: 3.14 | D67: Generar Distribución de Producción por sub- unidades (allocation) | F67: Se reciben las dudas por parte de Financiera y Proyectos sobre los perfiles cargados en assembler. Las cuales se han respondido con el apoyo de los diferentes equipos y resolución de ajustes en assembler, como el conteo de pozos o ideas no correctamente asociadas. | G67: C:\Users\c110096a\OneDrive - Ecopetrol S.A\tablero\01_ECP\02_VIGENCIA\20250613\Entrega_Equipos\ESC_03 | H67: 30 | I67: 3 | J67: =IFERROR(I67/H67,0) -> 0.1 | K67: =+I67+'JUNIO 2025'!K67 -> 14 | L67: =IFERROR(K67/H67,0) -> 0.46666667
B68: 3 | C68: 3.16 | D68: Análisis de Declinaciones por pozo y/o subunidad | F68: Se contruye presentación del proceso de PDI 2026 con sus resultados y premisas, para ser expuesto frente al comité de Desarrollo GDO. | G68: N/A | H68: 30 | I68: 3 | J68: =IFERROR(I68/H68,0) -> 0.1 | K68: =+I68+'JUNIO 2025'!K68 -> 14 | L68: =IFERROR(K68/H68,0) -> 0.46666667
B69: 3 | C69: 3.17 | D69: Analizar data histórica de producción, productividad y daño por pozo | F69: Se analizan los reales del mes de mayo luego de generados los archivos cargadores de formas, a fin de realizar comparaciones pozo a pozo y que se identifiquen las brechas en patrones de REAL frente a P50, CERT, GOP 1Q y PDI. | G69: https://ecopetrol-my.sharepoint.com/:p:/r/personal/leidyla_alvarez_ecopetrol_com_co/_layouts/15/Doc.aspx?sourcedoc=%7BBED50890-D34E-452E-9CF1-4EA9E7AC5B43%7D&file=Escenario%203.pptx&fromShare=true&action=edit&mobileredirect=true | H69: 30 | I69: 4 | J69: =IFERROR(I69/H69,0) -> 0.13333333 | K69: =+I69+'JUNIO 2025'!K69 -> 12 | L69: =IFERROR(K69/H69,0) -> 0.4
B70: 3 | C70: 3.18 | D70: Generar perfiles de Producción por pozos para pozos existente en escenarios Bajo, Medio y Alto | F70: Se proporciona información de perfiles y volúmenes de pronóstico de reservas PDI 2026 para diferentes equipos y profesionales por solicitud. | G70: N/A | H70: 30 | I70: 4 | J70: =IFERROR(I70/H70,0) -> 0.13333333 | K70: =+I70+'JUNIO 2025'!K70 -> 12 | L70: =IFERROR(K70/H70,0) -> 0.4
B71: 5 | C71: 5.2 | D71: Generación de oportunidades de intervención a Pozos | F71: Se lleva a cabo el seguimiento de la campaña de WO vigente 2024-2026, al igual que se sostiene reunión de seguimiento de Planes Operativos con proyectos para actualizar el archivo correspondiente. | G71: https://ecopetrol.sharepoint.com/sites/SeguimientoIAChichimeneECP/Documentos%20compartidos/Forms/AllItems.aspx?id=%2Fsites%2FSeguimientoIAChichimeneECP%2FDocumentos%20compartidos%2F45%2E%20WorkOvers%20GCH%202024%2D2026%2D2027&viewid=72844968%2Df801%2D450d%2D81d2%2D32c578273e17 | H71: 30 | I71: 3 | J71: =IFERROR(I71/H71,0) -> 0.1 | K71: =+I71+'JUNIO 2025'!K71 -> 12 | L71: =IFERROR(K71/H71,0) -> 0.4
B72: 5 | C72: 5.9 | D72: Realizar el seguimiento de producción/ inyección de pozos intervenidos con base en los comportamientos de producción previo y posterior a la intervención | F72: Se mantienen sesiones con el equipo de inyección, planeación e ingeniería, para definir PDT de inyección incrementos en T2, sincronización con POP, y cronograma de WO's. | G72: N/A | H72: 30 | I72: 3 | J72: =IFERROR(I72/H72,0) -> 0.1 | K72: =+I72+'JUNIO 2025'!K72 -> 13 | L72: =IFERROR(K72/H72,0) -> 0.43333333
B73: 8 | C73: 8.2 | D73: Carga de datos, procesamiento de datos, Análisis Estadístico descriptivo considerando hipótesis desde la teoría, y análisis descriptivo considerando hipótesis generadas desde la misma data (pasos 1, 2 y 3 teoría CRISP-DM). | F73: Se atienden diferentes sesiones, talleres y sistemáticas, en orden de planear las actividades previstas para aumento de inyección en T2, al igual que la sistemática del proyecto Frontera a fin de definir metodologías para su gerenciamiento adecuado. | G73: N/A | H73: 30 | I73: 4 | J73: =IFERROR(I73/H73,0) -> 0.13333333 | K73: =+I73+'JUNIO 2025'!K73 -> 12 | L73: =IFERROR(K73/H73,0) -> 0.4
B74: 3 | C74: 3.6 | D74: Generar Modelo analítico del yacimiento integrando la información disponible en un software específico | E74: Cesar E Rodriguez | F74: Se realizó el seguimiento a las optimizaciones, rediseños y WO a ejecutar. La información quedó asegurada en el archivo “Matriz priorizacion incrementos“ y "Priorizacion de acciones GDT_RD-WO-WS" | G74: \\10.100.25.60\sya\gec\Castilla\39. Proyecto_Inyeccion_de_Agua\SAHARA) y en las notas de wellmeeting | H74: 20 | I74: 4 | J74: =IFERROR(I74/H74,0) -> 0.2 | K74: =+I74+'JUNIO 2025'!K74 -> 14 | L74: =IFERROR(K74/H74,0) -> 0.7
B75: 3 | C75: 3.13 | D75: Generar base de datos de producción (OFM o la que se requiera) | F75: En la herramienta Sahara oficial con corte a Jul/2025, se corrigió y actualizó estado de capa y factores de alocacion pozos CA20, CA222st, CA300. Cargue de data de producción y Presiones dinamicas actualizadas a Jul/25 de zona centro sur | G75: \\10.100.25.60\sya\gec\Castilla\39. Proyecto_Inyeccion_de_Agua\SAHARA | H75: 14 | I75: 2 | J75: =IFERROR(I75/H75,0) -> 0.14285714 | K75: =+I75+'JUNIO 2025'!K75 -> 10 | L75: =IFERROR(K75/H75,0) -> 0.71428571
B76: 3 | C76: 3.14 | D76: Generar Distribución de Producción por sub- unidades (allocation) | F76: Por solicitud de la líder, se diligenciaron los siguientes archivos con la información actualizada del estado de los pozos productores e inyectores del área que tengo en monitoreo: Candidatos rediseños, Rediseños Ejecutados en 2025 por zona. actualización de EM, propiedades petrofísicas y factores de alocación para los diferentes pozos en la BD de SAHARA | G76: DTWF CASTILLA - Tablero Castilla Fan Edition - Todos los documentos \\10.100.25.60\sya\gec\Castilla\39. Proyecto_Inyeccion_de_Agua\SAHARA\BD Sahara | H76: 28 | I76: 6 | J76: =IFERROR(I76/H76,0) -> 0.21428571 | K76: =+I76+'JUNIO 2025'!K76 -> 20 | L76: =IFERROR(K76/H76,0) -> 0.71428571
B77: 3 | C77: 3.16 | D77: Análisis de Declinaciones por pozo y/o subunidad | F77: De acuerdo con el seguimiento a la producción e inyección, se realizó el seguimiento a las optimizaciones realizadas en el mes de febrero, marzo, abril, mayo y junio de acuerdo con el BSW, pruebas de producción y toma de niveles. | G77: \\10.100.25.60\sya\gec\Castilla\39. Proyecto_Inyeccion_de_Agua\SAHARA\BD Sahara | H77: 16 | I77: 2 | J77: =IFERROR(I77/H77,0) -> 0.125 | K77: =+I77+'JUNIO 2025'!K77 -> 10 | L77: =IFERROR(K77/H77,0) -> 0.625
B78: 3 | C78: 3.17 | D78: Analizar data histórica de producción, productividad y daño por pozo | F78: Se llevaron a mesa los pozos CA315 y CA371 con la finalidad de aprobar oportunidades de WOP. Visualizados pozos con oportunidad de RDG: CA146H. Ver mayor ampliación en GP-F-25 | G78: https://wellmeeting.ecopetrol.com.co/login | H78: 16 | I78: 2 | J78: =IFERROR(I78/H78,0) -> 0.125 | K78: =+I78+'JUNIO 2025'!K78 -> 10 | L78: =IFERROR(K78/H78,0) -> 0.625
B79: 3 | C79: 3.18 | D79: Generar perfiles de Producción por pozos para pozos existente en escenarios Bajo, Medio y Alto | F79: Se aseguraron los diagnósticos y acciones en wellmeeting por motivos de las revisiones con el equipo multidisciplinario y revisión interna. Ver mayor ampliación en GP-F-25 | G79: https://wellmeeting.ecopetrol.com.co/login GDT Plus (El V.A.R.) - General - Todos los documentos | H79: 12 | I79: 2 | J79: =IFERROR(I79/H79,0) -> 0.16666667 | K79: =+I79+'JUNIO 2025'!K79 -> 9 | L79: =IFERROR(K79/H79,0) -> 0.75
B80: 5 | C80: 5.2 | D80: Generación de oportunidades de intervención a Pozos | F80: De acuerdo con los rediseños propuestos en el plan de cierre de brechas, se obtuvo una lista de 12 pozos que se requieren optimizar, se irán priorizando de acuerdo con el presupuesto aprobado: CA40H, CA325, CA149H, CA155H, CA358, CA194, CA281H, CA105, CA70, CAN182, CAN63 y CA243H. | G80: teams (Sistemática WF y Gestión de la Básica y en la BD SAHARA (\\10.100.25.60\sya\gec\Castilla\39. Proyecto_Inyeccion_de_Agua\SAHARA) | H80: 24 | I80: 4 | J80: =IFERROR(I80/H80,0) -> 0.16666667 | K80: =+I80+'JUNIO 2025'!K80 -> 15 | L80: =IFERROR(K80/H80,0) -> 0.625
B81: 5 | C81: 5.9 | D81: Realizar el seguimiento de producción/ inyección de pozos intervenidos con base en los comportamientos de producción previo y posterior a la intervención | F81: Se realizo el seguimiento de producción/ inyección de pozos a cargo (13 patrones de inyección) con base en los comportamientos de producción e inyección | G81: TEAMS del equipo I&A Castilla (Sistemática WF): https://ecopetrol.sharepoint.com/sites/DTWFCASTILLA/Documentos%20compartidos/Forms/AllItems.aspx?OR=Teams%2DHL&CT=1722020892543&clickparams=eyJBcHBOYW1lIjoiVGVhbXMtRGVza3RvcCIsIkFwcFZlcnNpb24iOiI0OS8yNDA2MjcyNDgxNCIsIkhhc0ZlZGVyYXRlZFVzZXIiOmZhbHNlfQ%3D%3D&id=%2Fsites%2FDTWFCASTILLA%2FDocumentos%20compartidos%2FGeneral&viewid=9ba680aa%2D7c76%2D4823%2Dbaac%2Dba7ef8ef6f87 | H81: 26 | I81: 4 | J81: =IFERROR(I81/H81,0) -> 0.15384615 | K81: =+I81+'JUNIO 2025'!K81 -> 16 | L81: =IFERROR(K81/H81,0) -> 0.61538462
B82: 8 | C82: 8.2 | D82: Carga de datos, procesamiento de datos, Análisis Estadístico descriptivo considerando hipótesis desde la teoría, y análisis descriptivo considerando hipótesis generadas desde la misma data (pasos 1, 2 y 3 teoría CRISP-DM). | F82: En cuanto a la herramienta OFM se realizó el cargue de la producción, inyección y pruebas del mes de Junio/2025. La información quedó asegurada en el proyecto 05. Proyecto OFM\Archivos Excel\Cargue OFM\2025 | G82: La información quedó asegurada en el proyecto 131. \\10.100.25.60\sya\gec\05. Proyecto OFM\Archivos Excel\Cargue OFM\2025 | H82: 24 | I82: 4 | J82: =IFERROR(I82/H82,0) -> 0.16666667 | K82: =+I82+'JUNIO 2025'!K82 -> 16 | L82: =IFERROR(K82/H82,0) -> 0.66666667
B83: 3 | C83: 3.6 | D83: Generar Modelo analítico del yacimiento integrando la información disponible en un software específico | E83: Diego F Galeano | F83: 1. Pronosticos de NUevos proyectos WOrkover secundaria y REdiseños. 2, DOcumento de soporte de reservas Word y Power point 3. Pronosticos de Proyecto Expansion de recobro Unidades T2 y K1 4. Memorando de modificacion del proyecto Expansion de recobro mejorado 5. Reuniones sistematicas de los proyetos Etapa 4 y Modulo integral Norte /sur 6. pozos inyectores de polímero proceso IDA- Explansion CEOR . | G83: Digital-1. \\10.100.25.60\sya\GEC\Castilla\Proyecto W.O 2024 2027 GDT\WORKOVER Y REDISEÑOS SECUNDARIA 2. \\10.100.25.60\sya\GEC\Castilla\20.Proyecto IOR K2\Expansión Recobro Mejorado GDT\reconfiguracion ERM junio 2024 3.\10.100.25.60\sya\GEC\Castilla\102.T2\Revision 2024 2. Presentación Semanal Sistemática Etapa 4 3.https://ecopetrol.sharepoint.com/sites/CastillaWOs2022/Documentos%20compartidos/Forms 4.20230921 Sistemática Semanal - Sur Norte .pptx 5. \\10.100.25.60\sya\GEC\Castilla\20.Proyecto IOR K2\Expansión Recobro Mejorado GDT\02. EXP REC MEJORADO FASE 1 | H83: 30 | I83: 3 | J83: =IFERROR(I83/H83,0) -> 0.1 | K83: =+I83+'JUNIO 2025'!K83 -> 12 | L83: =IFERROR(K83/H83,0) -> 0.4
B84: 3 | C84: 3.13 | D84: Generar base de datos de producción (OFM o la que se requiera) | F84: 1. Uso de base de datos (OFM & Sahara) para Generacion de Pronosticos de Nuevos proyectos Workover secundaria y Rediseños. 2. Pronosticos de Proyecto Expansion de recobro Unidades T2 y K1 | G84: Digital-1. \\10.100.25.60\sya\GEC\Castilla\Proyecto W.O 2024 2027 GDT\WORKOVER Y REDISEÑOS SECUNDARIA 2. \\10.100.25.60\sya\GEC\Castilla\20.Proyecto IOR K2\Expansión Recobro Mejorado GDT\reconfiguracion ERM junio 2024 3.\10.100.25.60\sya\GEC\Castilla\102.T2\Revision 2024 | H84: 30 | I84: 3 | J84: =IFERROR(I84/H84,0) -> 0.1 | K84: =+I84+'JUNIO 2025'!K84 -> 12 | L84: =IFERROR(K84/H84,0) -> 0.4
B85: 3 | C85: 3.14 | D85: Generar Distribución de Producción por sub- unidades (allocation) | F85: 1. Analisis de distribución de la produccion e inyeccion por Fomacion (T2,K1 &K2), para la generacion Pronosticos de Nuevos proyectos WOrkover secundaria y Rediseños & Pronosticos de Proyecto Expansion de recobro Unidades T2 y K1 | G85: Digital-1. \\10.100.25.60\sya\GEC\Castilla\Proyecto W.O 2024 2027 GDT\WORKOVER Y REDISEÑOS SECUNDARIA 2. \\10.100.25.60\sya\GEC\Castilla\20.Proyecto IOR K2\Expansión Recobro Mejorado GDT\reconfiguracion ERM junio 2024 3.\10.100.25.60\sya\GEC\Castilla\102.T2\Revision 2024 2. Presentación Semanal Sistemática Etapa 4 3.https://ecopetrol.sharepoint.com/sites/CastillaWOs2022/Documentos%20compartidos/Forms 4.20230921 Sistemática Semanal - Sur Norte .pptx 5. \\10.100.25.60\sya\GEC\Castilla\20.Proyecto IOR K2\Expansión Recobro Mejorado GDT\02. EXP REC MEJORADO FASE 1 | H85: 30 | I85: 3 | J85: =IFERROR(I85/H85,0) -> 0.1 | K85: =+I85+'JUNIO 2025'!K85 -> 12 | L85: =IFERROR(K85/H85,0) -> 0.4
B86: 3 | C86: 3.16 | D86: Análisis de Declinaciones por pozo y/o subunidad | F86: 1. Pronosticos de NUevos proyectos WOrkover secundaria y REdiseños. 2, DOcumento de soporte de reservas Word y Power point 3. Pronosticos de Proyecto Expansion de recobro Unidades T2 y K1 4. Memorando de modificacion del proyecto Expansion de recobro mejorado 5. Reuniones sistematicas de los proyetos Etapa 4 y Modulo integral Norte /sur 6. pozos inyectores de polímero proceso IDA- Explansion CEOR . | G86: Digital-1. \\10.100.25.60\sya\GEC\Castilla\Proyecto W.O 2024 2027 GDT\WORKOVER Y REDISEÑOS SECUNDARIA 2. \\10.100.25.60\sya\GEC\Castilla\20.Proyecto IOR K2\Expansión Recobro Mejorado GDT\reconfiguracion ERM junio 2024 3.\10.100.25.60\sya\GEC\Castilla\102.T2\Revision 2024 2. Presentación Semanal Sistemática Etapa 4 3.https://ecopetrol.sharepoint.com/sites/CastillaWOs2022/Documentos%20compartidos/Forms 4.20230921 Sistemática Semanal - Sur Norte .pptx 5. \\10.100.25.60\sya\GEC\Castilla\20.Proyecto IOR K2\Expansión Recobro Mejorado GDT\02. EXP REC MEJORADO FASE 1 | H86: 30 | I86: 3 | J86: =IFERROR(I86/H86,0) -> 0.1 | K86: =+I86+'JUNIO 2025'!K86 -> 12 | L86: =IFERROR(K86/H86,0) -> 0.4
B87: 3 | C87: 3.17 | D87: Analizar data histórica de producción, productividad y daño por pozo | F87: Generar declinaciones historicas para Pronosticos de NUevos proyectos WOrkover secundaria y REdiseños. Segimiento a la produccion e inyeccion y declinaciones de los pozos del proyecto etapa 4. . | G87: Digital-1. \\10.100.25.60\sya\GEC\Castilla\Proyecto W.O 2024 2027 GDT\WORKOVER Y REDISEÑOS SECUNDARIA 2,\\10.100.25.60\sya\GEC\Castilla\DFGB Etapa 4 | H87: 30 | I87: 3 | J87: =IFERROR(I87/H87,0) -> 0.1 | K87: =+I87+'JUNIO 2025'!K87 -> 12 | L87: =IFERROR(K87/H87,0) -> 0.4
B88: 3 | C88: 3.18 | D88: Generar perfiles de Producción por pozos para pozos existente en escenarios Bajo, Medio y Alto | F88: Perfiles de produccion e inyeccion para proyectos Workover secundario GDT, expnasion de recobro unidades T2 & K1, evaluacion de resultados de los pozos etapa 4, en escenarios Bajo, Medio y Alto . | G88: Digital-1. \\10.100.25.60\sya\GEC\Castilla\Proyecto W.O 2024 2027 GDT\WORKOVER Y REDISEÑOS SECUNDARIA 2. \\10.100.25.60\sya\GEC\Castilla\20.Proyecto IOR K2\Expansión Recobro Mejorado GDT\reconfiguracion ERM junio 2024 3.\10.100.25.60\sya\GEC\Castilla\102.T2\Revision 2024 2. Presentación Semanal Sistemática Etapa 4 3 5. \\10.100.25.60\sya\GEC\Castilla\20.Proyecto IOR K2\Expansión Recobro Mejorado GDT\02. EXP REC MEJORADO FASE 1 | H88: 30 | I88: 3 | J88: =IFERROR(I88/H88,0) -> 0.1 | K88: =+I88+'JUNIO 2025'!K88 -> 12 | L88: =IFERROR(K88/H88,0) -> 0.4
B89: 5 | C89: 5.2 | D89: Generación de oportunidades de intervención a Pozos | F89: Maduración del proyecto Intervension de pozos (Rediseños 40 trabajos 2025, 40 trabajos 2026) . | G89: Digital-1. \\10.100.25.60\sya\GEC\Castilla\Proyecto W.O 2024 2027 GDT\WORKOVER Y REDISEÑOS SECUNDARIA | H89: 30 | I89: 4 | J89: =IFERROR(I89/H89,0) -> 0.13333333 | K89: =+I89+'JUNIO 2025'!K89 -> 16 | L89: =IFERROR(K89/H89,0) -> 0.53333333
B90: 5 | C90: 5.9 | D90: Realizar el seguimiento de producción/ inyección de pozos intervenidos con base en los comportamientos de producción previo y posterior a la intervención | F90: Seguimiento a la campaña de Workover en ejecucion Workover 2024-2027 GDT (antes, despues, e incremental), 7 trabajos ejecutados durante al año 2024 | G90: \\10.100.25.60\sya\GEC\Castilla\Proyecto W.O 2024 2027 GDT | H90: 30 | I90: 4 | J90: =IFERROR(I90/H90,0) -> 0.13333333 | K90: =+I90+'JUNIO 2025'!K90 -> 16 | L90: =IFERROR(K90/H90,0) -> 0.53333333
B91: 8 | C91: 8.2 | D91: Carga de datos, procesamiento de datos, Análisis Estadístico descriptivo considerando hipótesis desde la teoría, y análisis descriptivo considerando hipótesis generadas desde la misma data (pasos 1, 2 y 3 teoría CRISP-DM). | F91: Actualizacion de informacion de yacimiento para el Proyecto futuro Expansion de recobro Unidades T2 y K1 | G91: 1. \\10.100.25.60\sya\GEC\Castilla\20.Proyecto IOR K2\Expansión Recobro Mejorado GDT\reconfiguracion ERM junio 2024 3.\10.100.25.60\sya\GEC\Castilla\102.T2\Revision 2024 | H91: 30 | I91: 4 | J91: =IFERROR(I91/H91,0) -> 0.13333333 | K91: =+I91+'JUNIO 2025'!K91 -> 16 | L91: =IFERROR(K91/H91,0) -> 0.53333333
B92: 3 | C92: 3.6 | D92: Generar Modelo analítico del yacimiento integrando la información disponible en un software específico | E92: Luis Monsalve | F92: Modelo Analítico - Perfiles de Producción - Informe del modelo | G92: Repositorio digital: N:\39. Proyecto_Inyeccion_de_Agua\SAHARA\BD Sahara\2024-09-23 Sahara VyP Castilla | H92: 18 | I92: 2 | J92: =IFERROR(I92/H92,0) -> 0.11111111 | K92: =+I92+'JUNIO 2025'!K92 -> 9 | L92: =IFERROR(K92/H92,0) -> 0.5
B93: 3 | C93: 3.13 | D93: Generar base de datos de producción (OFM o la que se requiera) | F93: Base de Datos | G93: OFM: \\10.100.25.35\ofm\C1118546 | H93: 16 | I93: 3 | J93: =IFERROR(I93/H93,0) -> 0.1875 | K93: =+I93+'JUNIO 2025'!K93 -> 12 | L93: =IFERROR(K93/H93,0) -> 0.75
B94: 3 | C94: 3.14 | D94: Generar Distribución de Producción por sub- unidades (allocation) | F94: Base de Datos | G94: Repositorio digital: N:\39. Proyecto_Inyeccion_de_Agua\SAHARA\BD Sahara\2024-10-21 Sahara VyP Castilla | H94: 16 | I94: 3 | J94: =IFERROR(I94/H94,0) -> 0.1875 | K94: =+I94+'JUNIO 2025'!K94 -> 11 | L94: =IFERROR(K94/H94,0) -> 0.6875
