Workbook

Sheet ENERO 2026
Q1: MES
B2: REPORTE DE AVANCE | Q2: ENERO
B3: Fecha: 29/06/2022 | F3: Version: 01 | J3: GP-F-23
Q4: FEBRERO
B5: Código Orden de servicio | D5: 90577770 | Q5: MARZO
Q6: JUNIO
B7: Mes a reportar | D7: ENERO | Q7: JULIO
Q8: AGOSTO
B9: Fecha reporte | D9: 46053 | Q9: SEPTIEMBRE
Q10: OCTUBRE
B11: Clasificación del servicio | I11: Reporte mes por servicio | K11: Reporte acumulado por servicio | Q11: NOVIEMBRE
B12: Ítem general | C12: ítem actividad | D12: Descripción de la actividad | E12: Profesional a cargo | F12: Soporte | G12: Medio de entrega | H12: Días contratados Acta de Inicio | I12: Días | J12: % avance | K12: Días | L12: % avance | Q12: DICIEMBRE
B13: 1 | C13: 1.1 | D13: Generar Modelo Estático del yacimiento integrando la información disponible. | E13: Ximena Alejandra Rodriguez Florez | F13: Modelo Estático - Informe de Modelo - Cálculo de Volúmenes in Place | G13: Digital | H13: 60 | I13: 10 | J13: =IFERROR(I13/H13,0) -> 0.16666667 | K13: =I13 -> 10 | L13: =IFERROR(K13/H13,0) -> 0.16666667
B14: 1 | C14: 1.2 | D14: Generación de Bases de datos de Pozos (Registros, Topes e Información disponible) | F14: Bases de Datos | G14: Digital | H14: 20 | I14: 6 | J14: =IFERROR(I14/H14,0) -> 0.3 | K14: =I14 -> 6 | L14: =IFERROR(K14/H14,0) -> 0.3
B15: 1 | C15: 1.4 | D15: Generación Modelo estructural. | F15: Modelo estructural - Informe del Modelo | G15: Digital | H15: 45 | I15: 2 | J15: =IFERROR(I15/H15,0) -> 0.044444444 | K15: =I15 -> 2 | L15: =IFERROR(K15/H15,0) -> 0.044444444
B16: 1 | C16: 1.5 | D16: Digitalización, digitación y/o captura de información geológica (Mapas, Raw Data, topes, etc.) | F16: Mapas en formato digital | G16: Digital | H16: 20 | I16: 4 | J16: =IFERROR(I16/H16,0) -> 0.2 | K16: =I16 -> 4 | L16: =IFERROR(K16/H16,0) -> 0.2
B17: 1 | C17: 1.7 | D17: Generación Modelo Geocelular. | F17: Modelo Geocelular - Informe del Modelo | G17: Digital | H17: 30 | I17: 1 | J17: =IFERROR(I17/H17,0) -> 0.033333333 | K17: =I17 -> 1 | L17: =IFERROR(K17/H17,0) -> 0.033333333
B18: 1 | C18: 1.15 | D18: Carga de información para poblar el modelo geocelular (direccionales,coordenadas, surveys, topes, data de presión, estados mecánicos, evento de pozos, etc.) | F18: Modelo poblado | G18: Digital | H18: 20 | I18: 1 | J18: =IFERROR(I18/H18,0) -> 0.05 | K18: =I18 -> 1 | L18: =IFERROR(K18/H18,0) -> 0.05
B19: 1 | C19: 1.16 | D19: Georeferenciación de Mapas, pozos, Imágenes satélite, etc. y Definición de CRS (Cordinates Reference System) | F19: Información georeferenciada | G19: Digital | H19: 20 | I19: 2 | J19: =IFERROR(I19/H19,0) -> 0.1 | K19: =I19 -> 2 | L19: =IFERROR(K19/H19,0) -> 0.1
B20: 1 | C20: 1.17 | D20: Calculo probabilístico de Volúmenes In situ. | F20: - | G20: - | H20: 21 | I20: 0 | J20: =IFERROR(I20/H20,0) -> 0 | K20: =I20 -> 0 | L20: =IFERROR(K20/H20,0) -> 0
B21: 5 | C21: 5.1 | D21: Generar bases de datos de Eventos de pozos | E21: Jhon Abelardo Cuesta Asprilla | F21: Base de Datos | G21: Digital | H21: 30 | I21: 3 | J21: =IFERROR(I21/H21,0) -> 0.1 | K21: =I21 -> 3 | L21: =IFERROR(K21/H21,0) -> 0.1
B22: 5 | C22: 5.2 | D22: Generación de oportunidades de intervención a Pozos | F22: Base de Datos - Informe de la Evaluación | G22: Digital | H22: 30 | I22: 3 | J22: =IFERROR(I22/H22,0) -> 0.1 | K22: =I22 -> 3 | L22: =IFERROR(K22/H22,0) -> 0.1
B23: 5 | C23: 5.3 | D23: Estimar restricciones de Presión y tasas para la generación de perfiles de producción | F23: Base de Datos - Informe de la Evaluación | G23: Digital | H23: 30 | I23: 3 | J23: =IFERROR(I23/H23,0) -> 0.1 | K23: =I23 -> 3 | L23: =IFERROR(K23/H23,0) -> 0.1
B24: 5 | C24: 5.4 | D24: Generar modelo de Pozos | F24: Base de Datos - Informe de la Evaluación | G24: Digital | H24: 30 | I24: 3 | J24: =IFERROR(I24/H24,0) -> 0.1 | K24: =I24 -> 3 | L24: =IFERROR(K24/H24,0) -> 0.1
B25: 5 | C25: 5.5 | D25: Adelantar la evaluación e interpretación de datos enfocada a candidatización de actividades de reacondicionamiento y optimización de productividad en los activos | F25: Base de Datos - Informe de la Evaluación | G25: Digital | H25: 29 | I25: 4 | J25: =IFERROR(I25/H25,0) -> 0.13793103 | K25: =I25 -> 4 | L25: =IFERROR(K25/H25,0) -> 0.13793103
B26: 5 | C26: 5.6 | D26: Generar los análisis asociados a candidatización de pozos para optimización de la producción empleando simulación numérica (análisis nodal) de productividad de pozos | F26: Base de Datos - Informe de la Evaluación | G26: Digital | H26: 29 | I26: 4 | J26: =IFERROR(I26/H26,0) -> 0.13793103 | K26: =I26 -> 4 | L26: =IFERROR(K26/H26,0) -> 0.13793103
B27: 5 | C27: 5.9 | D27: Realizar el seguimiento de producción/ inyección de pozos intervenidos con base en los comportamientos de producción previo y posterior a la intervención | F27: Base de Datos - Informe de la Evaluación | G27: Digital | H27: 29 | I27: 3 | J27: =IFERROR(I27/H27,0) -> 0.10344828 | K27: =I27 -> 3 | L27: =IFERROR(K27/H27,0) -> 0.10344828
B28: 5 | C28: 5.10 | D28: Adelantar en análisis y evaluación de datos enfocada a la ejecución de estudios de daño de formación | F28: Base de Datos - Informe de la Evaluación | G28: Digital | H28: 29 | I28: 3 | J28: =IFERROR(I28/H28,0) -> 0.10344828 | K28: =I28 -> 3 | L28: =IFERROR(K28/H28,0) -> 0.10344828
B29: 5 | C29: 5.1 | D29: Generar bases de datos de Eventos de pozos | E29: Andres Fabian Amaya Hernandez | F29: Actualización de Tableros PBI con información de producción, inyección e intervenciones | G29: Sharepoint: https://ecopetrol.sharepoint.com/sites/TablerosdeSeguimientoYR-CG/Shared%20Documents/Forms/AllItems.aspx | H29: 30 | I29: 3.25 | J29: =IFERROR(I29/H29,0) -> 0.10833333 | K29: =I29 -> 3.25 | L29: =IFERROR(K29/H29,0) -> 0.10833333
B30: 5 | C30: 5.2 | D30: Generación de oportunidades de intervención a Pozos | F30: Reuniones sistemáticas para el seguimiento y monitoreo de la producción/inyección del Campo yariguí, y así identificar pozos candidatos para trabajos de WO y mejorar el índice de productividad e inyectividad | G30: Actas en medio digital: https://wellmeeting.ecopetrol.com.co/ | H30: 30 | I30: 3.25 | J30: =IFERROR(I30/H30,0) -> 0.10833333 | K30: =I30 -> 3.25 | L30: =IFERROR(K30/H30,0) -> 0.10833333
B31: 5 | C31: 5.3 | D31: Estimar restricciones de Presión y tasas para la generación de perfiles de producción | F31: Revisión de perfiles FID certificados y Flujos de Caja del campo yariguí-Cantagallo. Estimación de justificación de reservas 1P del Campo Yariguí | G31: Sharepoint: https://ecopetrol.sharepoint.com/sites/TablerosdeSeguimientoYR-CG/Shared%20Documents/Forms/AllItems.aspx Ruta compartida: \\10.11.46.150\groups07\01_YR-CG\04_PROYECTOS\26_PIC\2026 Ruta compartida: \\10.11.46.150\groups07\01_YR-CG\02_Modelo Dinámico\02_Yacimientos\07_Auditoria de Reservas | H31: 30 | I31: 3.25 | J31: =IFERROR(I31/H31,0) -> 0.10833333 | K31: =I31 -> 3.25 | L31: =IFERROR(K31/H31,0) -> 0.10833333
B32: 5 | C32: 5.4 | D32: Generar modelo de Pozos | F32: Base de Datos - Informe de la Evaluación | G32: Digital | H32: 30 | I32: 3.25 | J32: =IFERROR(I32/H32,0) -> 0.10833333 | K32: =I32 -> 3.25 | L32: =IFERROR(K32/H32,0) -> 0.10833333
B33: 5 | C33: 5.5 | D33: Adelantar la evaluación e interpretación de datos enfocada a candidatización de actividades de reacondicionamiento y optimización de productividad en los activos | F33: Actualización de Tableros PBI creados para el seguimiento de producción/inyección, gráficos de Lorenz de pozos inyectores, balance de presiones y revisión de reservas certificadas | G33: Sharepoint: https://ecopetrol.sharepoint.com/sites/TablerosdeSeguimientoYR-CG/Shared%20Documents/Forms/AllItems.aspx | H33: 30 | I33: 3.25 | J33: =IFERROR(I33/H33,0) -> 0.10833333 | K33: =I33 -> 3.25 | L33: =IFERROR(K33/H33,0) -> 0.10833333
B34: 5 | C34: 5.6 | D34: Generar los análisis asociados a candidatización de pozos para optimización de la producción empleando simulación numérica (análisis nodal) de productividad de pozos | F34: Reuniones sistemáticas para el seguimiento y monitoreo de la producción/inyección del Campo yariguí, y así identificar pozos con oportunidades de optimización de la presión de fondo manteniendo el balance de presiones del patrón | G34: Actas en medio digital: https://wellmeeting.ecopetrol.com.co/ Sharepoint: https://ecopetrol.sharepoint.com/sites/TablerosdeSeguimientoYR-CG/Shared%20Documents/Forms/AllItems.aspx | H34: 30 | I34: 3.25 | J34: =IFERROR(I34/H34,0) -> 0.10833333 | K34: =I34 -> 3.25 | L34: =IFERROR(K34/H34,0) -> 0.10833333
B35: 5 | C35: 5.9 | D35: Realizar el seguimiento de producción/ inyección de pozos intervenidos con base en los comportamientos de producción previo y posterior a la intervención | F35: Reuniones sistemáticas para el seguimiento y monitoreo de la producción/inyección del Campo yariguí | G35: Actas en medio digital: https://wellmeeting.ecopetrol.com.co/ | H35: 28 | I35: 3.25 | J35: =IFERROR(I35/H35,0) -> 0.11607143 | K35: =I35 -> 3.25 | L35: =IFERROR(K35/H35,0) -> 0.11607143
B36: 5 | C36: 5.10 | D36: Adelantar en análisis y evaluación de datos enfocada a la ejecución de estudios de daño de formación | F36: Actualización de Tableros PBI creados para el balance de presiones y poder identificar condiciones actuales de los pozos como Pwf actuales, Pwf límite, índice de productividad y condición de daño | G36: Sharepoint: https://ecopetrol.sharepoint.com/sites/TablerosdeSeguimientoYR-CG/Shared%20Documents/Forms/AllItems.aspx | H36: 28 | I36: 3.25 | J36: =IFERROR(I36/H36,0) -> 0.11607143 | K36: =I36 -> 3.25 | L36: =IFERROR(K36/H36,0) -> 0.11607143
B37: 3 | C37: 3.3 | D37: Realice el plan de desarrollo de campo y los pronósticos: realizando todos los pronósticos de escenarios de simulación para llevar a cabo la planificación del desarrollo de campo, esto incluye investigar y realizar análisis de sensibilidad e incertidumbre de los principales parámetros coincidentes de la historia y las incógnitas y su efecto en el pronóstico. La predicción se basaría en el plan de desarrollo de campo, las ubicaciones de perforación de relleno, el análisis de patrones, la optimización de la inyección de agua, la tasa de inyección óptima y el proceso de recuperación terciaria (química y térmica). Realizar evaluaciones económicas y evaluaciones de cada proceso y presentar la mejor solución óptima. Generar Modelo analítico del yacimiento integrando la información disponible en un software específico. | E37: Jose Carlos Garcia Rueda | F37: Modelo Dinámico -Perfiles de Producción -Informe. | G37: Digital | H37: 78 | I37: 14 | J37: =IFERROR(I37/H37,0) -> 0.17948718 | K37: =I37 -> 14 | L37: =IFERROR(K37/H37,0) -> 0.17948718
B38: 3 | C38: 3.13 | D38: Generar base de datos de producción (OFM o la que se requiera) | F38: Base de Datos | G38: Digital | H38: 34 | I38: 2 | J38: =IFERROR(I38/H38,0) -> 0.058823529 | K38: =I38 -> 2 | L38: =IFERROR(K38/H38,0) -> 0.058823529
B39: 3 | C39: 3.14 | D39: Generar Distribución de Producción por sub- unidades (allocation) | F39: - | G39: - | H39: 30 | I39: 0 | J39: =IFERROR(I39/H39,0) -> 0 | K39: =I39 -> 0 | L39: =IFERROR(K39/H39,0) -> 0
B40: 3 | C40: 3.16 | D40: Análisis de Declinaciones por pozo y/o subunidad | F40: - | G40: - | H40: 30 | I40: 0 | J40: =IFERROR(I40/H40,0) -> 0 | K40: =I40 -> 0 | L40: =IFERROR(K40/H40,0) -> 0
B41: 3 | C41: 3.17 | D41: Analizar data histórica de producción, productividad y daño por pozo | F41: Base de Datos - Informe de la Evaluación | G41: Digital | H41: 34 | I41: 10 | J41: =IFERROR(I41/H41,0) -> 0.29411765 | K41: =I41 -> 10 | L41: =IFERROR(K41/H41,0) -> 0.29411765
B42: 3 | C42: 3.18 | D42: Generar perfiles de Producción por pozos para pozos existente en escenarios Bajo, Medio y Alto | F42: - | G42: - | H42: 30 | I42: 0 | J42: =IFERROR(I42/H42,0) -> 0 | K42: =I42 -> 0 | L42: =IFERROR(K42/H42,0) -> 0
B43: 5 | C43: 5.1 | D43: Generar bases de datos de Eventos de pozos | E43: Maria Angelica Prada Fonseca | F43: Base de Datos | G43: Digital | H43: 30 | I43: 5 | J43: =IFERROR(I43/H43,0) -> 0.16666667 | K43: =I43 -> 5 | L43: =IFERROR(K43/H43,0) -> 0.16666667
B44: 5 | C44: 5.2 | D44: Generación de oportunidades de intervención a Pozos | F44: Base de Datos - Informe de la Evaluación | G44: Digital | H44: 27 | I44: 6 | J44: =IFERROR(I44/H44,0) -> 0.22222222 | K44: =I44 -> 6 | L44: =IFERROR(K44/H44,0) -> 0.22222222
B45: 5 | C45: 5.3 | D45: Estimar restricciones de Presión y tasas para la generación de perfiles de producción | F45: - | G45: - | H45: 35 | I45: 0 | J45: =IFERROR(I45/H45,0) -> 0 | K45: =I45 -> 0 | L45: =IFERROR(K45/H45,0) -> 0
B46: 5 | C46: 5.4 | D46: Generar modelo de Pozos | F46: - | G46: - | H46: 24 | I46: 0 | J46: =IFERROR(I46/H46,0) -> 0 | K46: =I46 -> 0 | L46: =IFERROR(K46/H46,0) -> 0
B47: 5 | C47: 5.5 | D47: Adelantar la evaluación e interpretación de datos enfocada a candidatización de actividades de reacondicionamiento y optimización de productividad en los activos | F47: Base de Datos - Informe de la Evaluación | G47: Digital | H47: 29 | I47: 5 | J47: =IFERROR(I47/H47,0) -> 0.17241379 | K47: =I47 -> 5 | L47: =IFERROR(K47/H47,0) -> 0.17241379
B48: 5 | C48: 5.6 | D48: Generar los análisis asociados a candidatización de pozos para optimización de la producción empleando simulación numérica (análisis nodal) de productividad de pozos | F48: - | G48: - | H48: 23 | I48: 0 | J48: =IFERROR(I48/H48,0) -> 0 | K48: =I48 -> 0 | L48: =IFERROR(K48/H48,0) -> 0
B49: 5 | C49: 5.10 | D49: Adelantar en análisis y evaluación de datos enfocada a la ejecución de estudios de daño de formación | F49: Base de Datos - Informe de la Evaluación | G49: Digital | H49: 19 | I49: 5 | J49: =IFERROR(I49/H49,0) -> 0.26315789 | K49: =I49 -> 5 | L49: =IFERROR(K49/H49,0) -> 0.26315789
B50: 5 | C50: 5.11 | D50: Generar los análisis asociados a la ejecución de estudios de daño de formación empleando simulación numérica (análisis nodal y single well model, análisis de aguas, análisis de crudos, entre otros) | F50: Base de Datos - Informe de la Evaluación | G50: Digital | H50: 19 | I50: 5 | J50: =IFERROR(I50/H50,0) -> 0.26315789 | K50: =I50 -> 5 | L50: =IFERROR(K50/H50,0) -> 0.26315789
B51: 1 | C51: 1.2 | D51: Generación de Bases de datos de Pozos (Registros, Topes e Información disponible) | E51: Estefany Lizeth Velandia Jaimes | F51: Bases de Datos | G51: Digital | H51: 59 | I51: 9 | J51: =IFERROR(I51/H51,0) -> 0.15254237 | K51: =I51 -> 9 | L51: =IFERROR(K51/H51,0) -> 0.15254237
B52: 1 | C52: 1.5 | D52: Digitalización, digitación y/o captura de información geológica (Mapas, Raw Data, topes, etc.) | F52: Mapas en formato digital | G52: Digital | H52: 59 | I52: 10 | J52: =IFERROR(I52/H52,0) -> 0.16949153 | K52: =I52 -> 10 | L52: =IFERROR(K52/H52,0) -> 0.16949153
B53: 1 | C53: 1.15 | D53: Carga de información para poblar el modelo geocelular (direccionales, coordenadas, surveys, topes, data de presión, estados mecánicos, evento de pozos, etc.) | F53: Modelo poblado | G53: Digital | H53: 59 | I53: 4 | J53: =IFERROR(I53/H53,0) -> 0.06779661 | K53: =I53 -> 4 | L53: =IFERROR(K53/H53,0) -> 0.06779661
B54: 1 | C54: 1.17 | D54: Calculo probabilístico de Volúmenes In situ. | F54: Calculo Volumétrico - Bases de Datos | G54: Digital | H54: 59 | I54: 3 | J54: =IFERROR(I54/H54,0) -> 0.050847458 | K54: =I54 -> 3 | L54: =IFERROR(K54/H54,0) -> 0.050847458
B55: 3 | C55: 3.3 | D55: Realizar el plan de desarrollo de campo y los pronósticos: realizando todos los pronósticos de escenarios de simulación para llevar a cabo la planificación del desarrollo de campo, esto incluye investigar y realizar análisis de sensibilidad e incertidumbre de los principales parámetros coincidentes de la historia y las incógnitas y su efecto en el pronóstico. La predicción se basaría en el plan de desarrollo de campo, las ubicaciones de perforación de relleno, el análisis de patrones, la optimización de la inyección de agua, la tasa de inyección óptima y el proceso de recuperación terciaria (química y térmica). Realizar evaluaciones económicas y evaluaciones de cada proceso y presentar la mejor solución óptima. | E55: Gustavo Andres Bautista Velandia | F55: - | G55: - | H55: 28 | I55: 0 | J55: =IFERROR(I55/H55,0) -> 0 | K55: =I55 -> 0 | L55: =IFERROR(K55/H55,0) -> 0
B56: 3 | C56: 3.4 | D56: Construya un estudio de modelos conceptuales y modelos de laboratorio: para construir un modelo conceptual que investigue temas específicos. Por ejemplo: tiempos y perfiles de ruptura del trazador, meseta de relación WOR de depósitos de múltiples capas, para investigar la aplicación de nueva tecnología (basada en polímeros o basada en térmicas). Problemas de conformance, aplicabilidad del polímero en un campo específico, investigar el efecto del espaciamiento de pozos y los tipos de patrones (5 puntos, 5 puntos invertidos, 7 puntos, unidad de línea) en proyectos EOR químicos. Un estudio conceptual para desarrollar una metodología práctica para tecnologías nuevas y actuales basadas en datos de campo y de laboratorio (metodología para modelar polímeros de preferencia cruzada, nano surfactante). Desarrollar una metodología para integrar y modelar pozos de múltiples segmentos y datos ILT. | F56: - | G56: - | H56: 29 | I56: 0 | J56: =IFERROR(I56/H56,0) -> 0 | K56: =I56 -> 0 | L56: =IFERROR(K56/H56,0) -> 0
B57: 3 | C57: 3.6 | D57: Generar Modelo analítico del yacimiento integrando la información disponible en un software específico. | F57: - | G57: - | H57: 29 | I57: 0 | J57: =IFERROR(I57/H57,0) -> 0 | K57: =I57 -> 0 | L57: =IFERROR(K57/H57,0) -> 0
B58: 3 | C58: 3.7 | D58: Inventario y acceso a raw data de puntos de presión (Pre-Test) tomados con probadores de formación (RDT (Halliburton), MDT (Schlumberger), MFT (Weatherford), etc.). La raw data debe contener por profundidad probada: valores de presión, temperatura, caudales inducidos (cc/seg) y volúmenes asociados de cámara pre-test (cc). | F58: Base de datos | G58: Digital | H58: 30 | I58: 8 | J58: =IFERROR(I58/H58,0) -> 0.26666667 | K58: =I58 -> 8 | L58: =IFERROR(K58/H58,0) -> 0.26666667
B59: 3 | C59: 3.12 | D59: Generar Modelo de Presiones partiendo de las pruebas previamente validadas e interpretadas | F59: Modelo del sector | G59: Digital | H59: 30 | I59: 5 | J59: =IFERROR(I59/H59,0) -> 0.16666667 | K59: =I59 -> 5 | L59: =IFERROR(K59/H59,0) -> 0.16666667
B60: 3 | C60: 3.16 | D60: Análisis de Declinaciones por pozo y/o subunidad | F60: Base de Datos - Perfiles Generados - Informe del análisis | G60: Digital | H60: 30 | I60: 2 | J60: =IFERROR(I60/H60,0) -> 0.066666667 | K60: =I60 -> 2 | L60: =IFERROR(K60/H60,0) -> 0.066666667
B61: 3 | C61: 3.17 | D61: Analizar data histórica de producción, productividad y daño por pozo | F61: Base de Datos - Informe de la Evaluación | G61: Digital | H61: 30 | I61: 5 | J61: =IFERROR(I61/H61,0) -> 0.16666667 | K61: =I61 -> 5 | L61: =IFERROR(K61/H61,0) -> 0.16666667
B62: 3 | C62: 3.18 | D62: Generar perfiles de Producción por pozos para pozos existente en escenarios Bajo, Medio y Alto | F62: Base de Datos - Informe de la Evaluación | G62: Digital | H62: 30 | I62: 6 | J62: =IFERROR(I62/H62,0) -> 0.2 | K62: =I62 -> 6 | L62: =IFERROR(K62/H62,0) -> 0.2
B63: 3 | C63: 3.3 | D63: Realice el plan de desarrollo de campo y los pronósticos: realizando todos los pronósticos de escenarios de simulación para llevar a cabo la planificación del desarrollo de campo, esto incluye investigar y realizar análisis de sensibilidad e incertidumbre de los principales parámetros coincidentes de la historia y las incógnitas y su efecto en el pronóstico. La predicción se basaría en el plan de desarrollo de campo, las ubicaciones de perforación de relleno, el análisis de patrones, la optimización de la inyección de agua, la tasa de inyección óptima y el proceso de recuperación terciaria (química y térmica). Realizar evaluaciones económicas y evaluaciones de cada proceso y presentar la mejor solución óptima. | E63: Emmanuel Robles Albarracin | F63: Modelo Dinámico -Perfiles de Producción -Informe. | G63: Digital | H63: 113 | I63: 11 | J63: =IFERROR(I63/H63,0) -> 0.097345133 | K63: =I63 -> 11 | L63: =IFERROR(K63/H63,0) -> 0.097345133
B64: 3 | C64: 3.5 | D64: Modelado sectorial cuando el modelo de simulación dinámica está disponible: modelado sectorial en el objetivo del estudio, modela adecuadamente y respeta las condiciones de frontera mediante el uso de límites de flujo o presión, realiza la planificación del desarrollo del campo, perforación de relleno, agotamiento primario, inyección de agua y térmica o química. Proceso de recuperación. Aumentar adecuadamente el resultado del modelo de sector al campo completo. Realizar la valuación económica del proceso. | F64: Modelo Dinámico con los archivos de entrada Perfiles de producción e inyección Informe | G64: Digital | H64: 48 | I64: 5 | J64: =IFERROR(I64/H64,0) -> 0.10416667 | K64: =I64 -> 5 | L64: =IFERROR(K64/H64,0) -> 0.10416667
B65: 3 | C65: 3.10 | D65: Control de calidad del dato adquirido para valorar representatividad de la prueba en cuestión. De ser válidas, levantamiento de información de entrada para análisis e interpretación (registros de desviación, estado mecánico de cada pozo, caliper/bit size ("), espesor neto (pies TVD), porosidad media (phi), Sw, PVT, producciones asociadas, corte de agua, salinidades, mapa estructural, etc. | F65: Inventario - Informe de Representatividad (Preliminar) | G65: Digital | H65: 15 | I65: 2 | J65: =IFERROR(I65/H65,0) -> 0.13333333 | K65: =I65 -> 2 | L65: =IFERROR(K65/H65,0) -> 0.13333333
B66: 3 | C66: 3.11 | D66: Análisis e interpretación de datos de pruebas de presión-producción (DSTs, PBU, Pruebas Extendidas Producción, Gradientes Estáticos- Dinámicos PT, etc.) o de presión inyección (Inyectividad, SRT, FOT) aplicadas ya sea en tiempo real, memorizadas o con sarta temporal DST. Integración Probador Formación - Registros Open Hole. | F66: Informe del análisis por pozo o prueba | G66: Digital | H66: 15 | I66: 2 | J66: =IFERROR(I66/H66,0) -> 0.13333333 | K66: =I66 -> 2 | L66: =IFERROR(K66/H66,0) -> 0.13333333
B67: 3 | C67: 3.16 | D67: Análisis de Declinaciones por pozo y/o subunidad | F67: Base de Datos - Perfiles Generados - Informe del análisis | G67: Digital | H67: 15 | I67: 2 | J67: =IFERROR(I67/H67,0) -> 0.13333333 | K67: =I67 -> 2 | L67: =IFERROR(K67/H67,0) -> 0.13333333
B68: 3 | C68: 3.17 | D68: Analizar data histórica de producción, productividad y daño por pozo | F68: Base de Datos - Informe de la Evaluación | G68: Digital | H68: 15 | I68: 2 | J68: =IFERROR(I68/H68,0) -> 0.13333333 | K68: =I68 -> 2 | L68: =IFERROR(K68/H68,0) -> 0.13333333
B69: 3 | C69: 3.18 | D69: Generar perfiles de Producción por pozos para pozos existente en escenarios Bajo, Medio y Alto | F69: Base de Datos - Informe de la Evaluación | G69: Digital | H69: 15 | I69: 2 | J69: =IFERROR(I69/H69,0) -> 0.13333333 | K69: =I69 -> 2 | L69: =IFERROR(K69/H69,0) -> 0.13333333
H70: TOTAL ACUMULADO
H71: =+SUM(H13:H69) -> 1858 | I71: =+SUM(I13:I69) -> 208 | J71: =IFERROR(I71/H71,0) -> 0.11194833 | K71: =+SUM(K13:K69) -> 208 | L71: =IFERROR(K71/H71,0) -> 0.11194833
B74: Observaciones | D74: 5.1 5.2 5.3 5.4 5.5 5.6 5.9 5.10 Junior (AM):
D75: 1.2 1.5 1.15 1.17 Junior (EV): * Apoyo integral en la actualización y consolidación de bases de datos, así como en la elaboración y validación de cartografía técnica, como parte de la entrega anual de los informes ITA – vigencia 2025, requeridos por la Agencia Nacional de Hidrocarburos (ANH). * Adicionalmente, gestión y atención de requerimientos operativos y técnicos del día a día, brindando soporte oportuno a los ingenieros del equipo para el apoyo en el desarrollo de sus actividades.
D76: 1.1 1.2 1.4 1.5 1.7 1.15 1.16 1.17 Senior (XR): * (1.1) mediante diagnósticos del modelo actual, reuniones de validación y elaboración de entregables; se consolidaron y revisaron los datos de pozos * (1.2) realizando QAQC y estudio de ensemble data; se ejecutaron tareas de digitalización y captura de información geológica * (1.5) con exportación de curvas y ajustes de mapas; se efectuó la georreferenciación y definición de CRS * (1.16) mediante corrección de mapas ITA Lisama; y de manera preliminar se realizaron actividades relacionadas con el modelo estructural * (1.4) y la preparación de datos para el modelo geocelular * (1.7, 1.15). Para detalles, revisar informe GP-F-25_Ximena A. Rodriguez.
B77: ¿Se presentó algún aspecto o situación que afecte la ejecución y calidad de los entregables? (Marque con una X)
B79: PROFESIONAL
B80: SI | D80: Describa en este espacio su observación
B81: NO
B82: ¿Se presentó algún aspecto o situación que afecte la ejecución y calidad de los entregables? (Marque con una X)
B84: INTERVENTOR O LIDER
B85: SI | D85: Describa en este espacio su observación
B86: NO
B90: Revisa: | I90: Heliodoro Cañarete Mejía
A117: MES
A118: ENERO
A119: FEBRERO
A120: MARZO
A121: ABRIL
A122: MAYO
A123: JUNIO
A124: JULIO
A125: AGOSTO
A126: SEPTIEMBRE
A127: OCTUBRE
A128: NOVIEMBRE
A129: DICIEMBRE

Sheet FEBRERO 2026
Q1: MES
B2: REPORTE DE AVANCE | Q2: ENERO
B3: Fecha: 29/06/2022 | F3: Version: 01 | J3: GP-F-23
Q4: FEBRERO
B5: Código Orden de servicio | D5: 90577770 | Q5: MARZO
Q6: JUNIO
B7: Mes a reportar | D7: FEBRERO | Q7: JULIO
Q8: AGOSTO
B9: Fecha reporte | D9: 46081 | Q9: SEPTIEMBRE
Q10: OCTUBRE
B11: Clasificación del servicio | I11: Reporte mes por servicio | K11: Reporte acumulado por servicio | Q11: NOVIEMBRE
B12: Ítem general | C12: ítem actividad | D12: Descripción de la actividad | E12: Profesional a cargo | F12: Soporte | G12: Medio de entrega | H12: Días contratados Acta de Inicio | I12: Días | J12: % avance | K12: Días | L12: % avance | Q12: DICIEMBRE
B13: 1 | C13: 1.1 | D13: Generar Modelo Estático del yacimiento integrando la información disponible. | E13: Ximena Alejandra Rodriguez Florez | F13: Modelo Estático - Informe de Modelo - Cálculo de Volúmenes in Place | G13: Digital | H13: 60 | I13: 5 | J13: =IFERROR(I13/H13,0) -> 0.083333333 | K13: =I13+'ENERO 2026'!K13 -> 15 | L13: =IFERROR(K13/H13,0) -> 0.25
B14: 1 | C14: 1.2 | D14: Generación de Bases de datos de Pozos (Registros, Topes e Información disponible) | F14: Bases de Datos | G14: Digital | H14: 20 | I14: 7 | J14: =IFERROR(I14/H14,0) -> 0.35 | K14: =I14+'ENERO 2026'!K14 -> 13 | L14: =IFERROR(K14/H14,0) -> 0.65
B15: 1 | C15: 1.4 | D15: Generación Modelo estructural. | F15: Modelo estructural - Informe del Modelo | G15: Digital | H15: 45 | I15: 3 | J15: =IFERROR(I15/H15,0) -> 0.066666667 | K15: =I15+'ENERO 2026'!K15 -> 5 | L15: =IFERROR(K15/H15,0) -> 0.11111111
B16: 1 | C16: 1.5 | D16: Digitalización, digitación y/o captura de información geológica (Mapas, Raw Data, topes, etc.) | F16: Mapas en formato digital | G16: Digital | H16: 20 | I16: 5 | J16: =IFERROR(I16/H16,0) -> 0.25 | K16: =I16+'ENERO 2026'!K16 -> 9 | L16: =IFERROR(K16/H16,0) -> 0.45
B17: 1 | C17: 1.7 | D17: Generación Modelo Geocelular. | F17: Modelo Geocelular - Informe del Modelo | G17: Digital | H17: 30 | I17: 0 | J17: =IFERROR(I17/H17,0) -> 0 | K17: =I17+'ENERO 2026'!K17 -> 1 | L17: =IFERROR(K17/H17,0) -> 0.033333333
B18: 1 | C18: 1.15 | D18: Carga de información para poblar el modelo geocelular (direccionales,coordenadas, surveys, topes, data de presión, estados mecánicos, evento de pozos, etc.) | F18: Modelo poblado | G18: Digital | H18: 20 | I18: 5 | J18: =IFERROR(I18/H18,0) -> 0.25 | K18: =I18+'ENERO 2026'!K18 -> 6 | L18: =IFERROR(K18/H18,0) -> 0.3
B19: 1 | C19: 1.16 | D19: Georeferenciación de Mapas, pozos, Imágenes satélite, etc. y Definición de CRS (Cordinates Reference System) | F19: Información georeferenciada | G19: Digital | H19: 20 | I19: 5 | J19: =IFERROR(I19/H19,0) -> 0.25 | K19: =I19+'ENERO 2026'!K19 -> 7 | L19: =IFERROR(K19/H19,0) -> 0.35
B20: 1 | C20: 1.17 | D20: Calculo probabilístico de Volúmenes In situ. | F20: Calculo Volumétrico - Bases de Datos | G20: Digital | H20: 21 | I20: 0 | J20: =IFERROR(I20/H20,0) -> 0 | K20: =I20+'ENERO 2026'!K20 -> 0 | L20: =IFERROR(K20/H20,0) -> 0
B21: 5 | C21: 5.1 | D21: Generar bases de datos de Eventos de pozos | E21: Jhon Abelardo Cuesta Asprilla | F21: Base de Datos | G21: Digital | H21: 30 | I21: 3 | J21: =IFERROR(I21/H21,0) -> 0.1 | K21: =I21+'ENERO 2026'!K21 -> 6 | L21: =IFERROR(K21/H21,0) -> 0.2
B22: 5 | C22: 5.2 | D22: Generación de oportunidades de intervención a Pozos | F22: Base de Datos - Informe de la Evaluación | G22: Digital | H22: 30 | I22: 4 | J22: =IFERROR(I22/H22,0) -> 0.13333333 | K22: =I22+'ENERO 2026'!K22 -> 7 | L22: =IFERROR(K22/H22,0) -> 0.23333333
B23: 5 | C23: 5.3 | D23: Estimar restricciones de Presión y tasas para la generación de perfiles de producción | F23: Base de Datos - Informe de la Evaluación | G23: Digital | H23: 30 | I23: 4 | J23: =IFERROR(I23/H23,0) -> 0.13333333 | K23: =I23+'ENERO 2026'!K23 -> 7 | L23: =IFERROR(K23/H23,0) -> 0.23333333
B24: 5 | C24: 5.4 | D24: Generar modelo de Pozos | F24: Base de Datos - Informe de la Evaluación | G24: Digital | H24: 30 | I24: 4 | J24: =IFERROR(I24/H24,0) -> 0.13333333 | K24: =I24+'ENERO 2026'!K24 -> 7 | L24: =IFERROR(K24/H24,0) -> 0.23333333
B25: 5 | C25: 5.5 | D25: Adelantar la evaluación e interpretación de datos enfocada a candidatización de actividades de reacondicionamiento y optimización de productividad en los activos | F25: Base de Datos - Informe de la Evaluación | G25: Digital | H25: 29 | I25: 4 | J25: =IFERROR(I25/H25,0) -> 0.13793103 | K25: =I25+'ENERO 2026'!K25 -> 8 | L25: =IFERROR(K25/H25,0) -> 0.27586207
B26: 5 | C26: 5.6 | D26: Generar los análisis asociados a candidatización de pozos para optimización de la producción empleando simulación numérica (análisis nodal) de productividad de pozos | F26: Base de Datos - Informe de la Evaluación | G26: Digital | H26: 29 | I26: 4 | J26: =IFERROR(I26/H26,0) -> 0.13793103 | K26: =I26+'ENERO 2026'!K26 -> 8 | L26: =IFERROR(K26/H26,0) -> 0.27586207
B27: 5 | C27: 5.9 | D27: Realizar el seguimiento de producción/ inyección de pozos intervenidos con base en los comportamientos de producción previo y posterior a la intervención | F27: Base de Datos - Informe de la Evaluación | G27: Digital | H27: 29 | I27: 4 | J27: =IFERROR(I27/H27,0) -> 0.13793103 | K27: =I27+'ENERO 2026'!K27 -> 7 | L27: =IFERROR(K27/H27,0) -> 0.24137931
B28: 5 | C28: 5.10 | D28: Adelantar en análisis y evaluación de datos enfocada a la ejecución de estudios de daño de formación | F28: Base de Datos - Informe de la Evaluación | G28: Digital | H28: 29 | I28: 3 | J28: =IFERROR(I28/H28,0) -> 0.10344828 | K28: =I28+'ENERO 2026'!K28 -> 6 | L28: =IFERROR(K28/H28,0) -> 0.20689655
B29: 5 | C29: 5.1 | D29: Generar bases de datos de Eventos de pozos | E29: Andres Fabian Amaya Hernandez | F29: Actualización de Tableros PBI con información de producción, inyección e intervenciones | G29: Sharepoint: https://ecopetrol.sharepoint.com/sites/TablerosdeSeguimientoYR-CG/Shared%20Documents/Forms/AllItems.aspx | H29: 30 | I29: 3.75 | J29: =IFERROR(I29/H29,0) -> 0.125 | K29: =I29+'ENERO 2026'!K29 -> 7 | L29: =IFERROR(K29/H29,0) -> 0.23333333
B30: 5 | C30: 5.2 | D30: Generación de oportunidades de intervención a Pozos | F30: Reuniones sistemáticas para el seguimiento y monitoreo de la producción/inyección del Campo yariguí, y así identificar pozos candidatos para trabajos de WO y mejorar el índice de productividad e inyectividad | G30: Actas en medio digital: https://wellmeeting.ecopetrol.com.co/ | H30: 30 | I30: 3.75 | J30: =IFERROR(I30/H30,0) -> 0.125 | K30: =I30+'ENERO 2026'!K30 -> 7 | L30: =IFERROR(K30/H30,0) -> 0.23333333
B31: 5 | C31: 5.3 | D31: Estimar restricciones de Presión y tasas para la generación de perfiles de producción | F31: Estimación de justificación de reservas 1P del Campo Yariguí. Diligenciamiento de Formato F20 sobre la conversión de reservas PND del Campo Yariguí-Cantagallo | G31: Sharepoint: https://ecopetrol.sharepoint.com/sites/TablerosdeSeguimientoYR-CG/Shared%20Documents/Forms/AllItems.aspx Ruta compartida: \\10.11.46.150\groups07\01_YR-CG\04_PROYECTOS\26_PIC\2026 Ruta compartida: \\10.11.46.150\groups07\01_YR-CG\02_Modelo Dinámico\02_Yacimientos\07_Auditoria de Reservas | H31: 30 | I31: 3.75 | J31: =IFERROR(I31/H31,0) -> 0.125 | K31: =I31+'ENERO 2026'!K31 -> 7 | L31: =IFERROR(K31/H31,0) -> 0.23333333
B32: 5 | C32: 5.4 | D32: Generar modelo de Pozos | F32: Base de Datos - Informe de la Evaluación | G32: Digital | H32: 30 | I32: 3.75 | J32: =IFERROR(I32/H32,0) -> 0.125 | K32: =I32+'ENERO 2026'!K32 -> 7 | L32: =IFERROR(K32/H32,0) -> 0.23333333
B33: 5 | C33: 5.5 | D33: Adelantar la evaluación e interpretación de datos enfocada a candidatización de actividades de reacondicionamiento y optimización de productividad en los activos | F33: Actualización de Tableros PBI creados para el seguimiento de producción/inyección, gráficos de Lorenz de pozos inyectores, balance de presiones y revisión de reservas certificadas | G33: Sharepoint: https://ecopetrol.sharepoint.com/sites/TablerosdeSeguimientoYR-CG/Shared%20Documents/Forms/AllItems.aspx | H33: 30 | I33: 3.75 | J33: =IFERROR(I33/H33,0) -> 0.125 | K33: =I33+'ENERO 2026'!K33 -> 7 | L33: =IFERROR(K33/H33,0) -> 0.23333333
B34: 5 | C34: 5.6 | D34: Generar los análisis asociados a candidatización de pozos para optimización de la producción empleando simulación numérica (análisis nodal) de productividad de pozos | F34: Reuniones sistemáticas para el seguimiento y monitoreo de la producción/inyección del Campo yariguí, y así identificar pozos con oportunidades de optimización de la presión de fondo manteniendo el balance de presiones del patrón | G34: Actas en medio digital: https://wellmeeting.ecopetrol.com.co/ Sharepoint: https://ecopetrol.sharepoint.com/sites/TablerosdeSeguimientoYR-CG/Shared%20Documents/Forms/AllItems.aspx | H34: 30 | I34: 3.75 | J34: =IFERROR(I34/H34,0) -> 0.125 | K34: =I34+'ENERO 2026'!K34 -> 7 | L34: =IFERROR(K34/H34,0) -> 0.23333333
B35: 5 | C35: 5.9 | D35: Realizar el seguimiento de producción/ inyección de pozos intervenidos con base en los comportamientos de producción previo y posterior a la intervención | F35: Reuniones sistemáticas para el seguimiento y monitoreo de la producción/inyección del Campo yariguí | G35: Actas en medio digital: https://wellmeeting.ecopetrol.com.co/ | H35: 28 | I35: 3.75 | J35: =IFERROR(I35/H35,0) -> 0.13392857 | K35: =I35+'ENERO 2026'!K35 -> 7 | L35: =IFERROR(K35/H35,0) -> 0.25
B36: 5 | C36: 5.10 | D36: Adelantar en análisis y evaluación de datos enfocada a la ejecución de estudios de daño de formación | F36: Actualización de Tableros PBI creados para el balance de presiones y poder identificar condiciones actuales de los pozos como Pwf actuales, Pwf límite, índice de productividad y condición de daño | G36: Sharepoint: https://ecopetrol.sharepoint.com/sites/TablerosdeSeguimientoYR-CG/Shared%20Documents/Forms/AllItems.aspx | H36: 28 | I36: 3.75 | J36: =IFERROR(I36/H36,0) -> 0.13392857 | K36: =I36+'ENERO 2026'!K36 -> 7 | L36: =IFERROR(K36/H36,0) -> 0.25
B37: 3 | C37: 3.3 | D37: Realice el plan de desarrollo de campo y los pronósticos: realizando todos los pronósticos de escenarios de simulación para llevar a cabo la planificación del desarrollo de campo, esto incluye investigar y realizar análisis de sensibilidad e incertidumbre de los principales parámetros coincidentes de la historia y las incógnitas y su efecto en el pronóstico. La predicción se basaría en el plan de desarrollo de campo, las ubicaciones de perforación de relleno, el análisis de patrones, la optimización de la inyección de agua, la tasa de inyección óptima y el proceso de recuperación terciaria (química y térmica). Realizar evaluaciones económicas y evaluaciones de cada proceso y presentar la mejor solución óptima. Generar Modelo analítico del yacimiento integrando la información disponible en un software específico. | E37: Jose Carlos Garcia Rueda | F37: Modelo Dinámico -Perfiles de Producción -Informe. | G37: Digital | H37: 78 | I37: 12 | J37: =IFERROR(I37/H37,0) -> 0.15384615 | K37: =I37+'ENERO 2026'!K37 -> 26 | L37: =IFERROR(K37/H37,0) -> 0.33333333
B38: 3 | C38: 3.13 | D38: Generar base de datos de producción (OFM o la que se requiera) | F38: Base de Datos | G38: Digital | H38: 34 | I38: 6 | J38: =IFERROR(I38/H38,0) -> 0.17647059 | K38: =I38+'ENERO 2026'!K38 -> 8 | L38: =IFERROR(K38/H38,0) -> 0.23529412
B39: 3 | C39: 3.14 | D39: Generar Distribución de Producción por sub- unidades (allocation) | F39: Base de Datos | G39: Digital | H39: 30 | I39: 6 | J39: =IFERROR(I39/H39,0) -> 0.2 | K39: =I39+'ENERO 2026'!K39 -> 6 | L39: =IFERROR(K39/H39,0) -> 0.2
B40: 3 | C40: 3.16 | D40: Análisis de Declinaciones por pozo y/o subunidad | F40: - | G40: - | H40: 30 | I40: 0 | J40: =IFERROR(I40/H40,0) -> 0 | K40: =I40+'ENERO 2026'!K40 -> 0 | L40: =IFERROR(K40/H40,0) -> 0
B41: 3 | C41: 3.17 | D41: Analizar data histórica de producción, productividad y daño por pozo | F41: - | G41: - | H41: 34 | I41: 0 | J41: =IFERROR(I41/H41,0) -> 0 | K41: =I41+'ENERO 2026'!K41 -> 10 | L41: =IFERROR(K41/H41,0) -> 0.29411765
B42: 3 | C42: 3.18 | D42: Generar perfiles de Producción por pozos para pozos existente en escenarios Bajo, Medio y Alto | F42: Base de Datos - Informe de la Evaluación | G42: Digital | H42: 30 | I42: 6 | J42: =IFERROR(I42/H42,0) -> 0.2 | K42: =I42+'ENERO 2026'!K42 -> 6 | L42: =IFERROR(K42/H42,0) -> 0.2
B43: 5 | C43: 5.1 | D43: Generar bases de datos de Eventos de pozos | E43: Maria Angelica Prada Fonseca | F43: Base de Datos | G43: Digital | H43: 30 | I43: 7 | J43: =IFERROR(I43/H43,0) -> 0.23333333 | K43: =I43+'ENERO 2026'!K43 -> 12 | L43: =IFERROR(K43/H43,0) -> 0.4
B44: 5 | C44: 5.2 | D44: Generación de oportunidades de intervención a Pozos | F44: Base de Datos - Informe de la Evaluación | G44: Digital | H44: 27 | I44: 7 | J44: =IFERROR(I44/H44,0) -> 0.25925926 | K44: =I44+'ENERO 2026'!K44 -> 13 | L44: =IFERROR(K44/H44,0) -> 0.48148148
B45: 5 | C45: 5.3 | D45: Estimar restricciones de Presión y tasas para la generación de perfiles de producción | F45: Base de Datos - Informe de la Evaluación | G45: Digital | H45: 35 | I45: 4 | J45: =IFERROR(I45/H45,0) -> 0.11428571 | K45: =I45+'ENERO 2026'!K45 -> 4 | L45: =IFERROR(K45/H45,0) -> 0.11428571
B46: 5 | C46: 5.4 | D46: Generar modelo de Pozos | F46: - | G46: - | H46: 24 | I46: 0 | J46: =IFERROR(I46/H46,0) -> 0 | K46: =I46+'ENERO 2026'!K46 -> 0 | L46: =IFERROR(K46/H46,0) -> 0
B47: 5 | C47: 5.5 | D47: Adelantar la evaluación e interpretación de datos enfocada a candidatización de actividades de reacondicionamiento y optimización de productividad en los activos | F47: Base de Datos - Informe de la Evaluación | G47: Digital | H47: 29 | I47: 6 | J47: =IFERROR(I47/H47,0) -> 0.20689655 | K47: =I47+'ENERO 2026'!K47 -> 11 | L47: =IFERROR(K47/H47,0) -> 0.37931034
B48: 5 | C48: 5.6 | D48: Generar los análisis asociados a candidatización de pozos para optimización de la producción empleando simulación numérica (análisis nodal) de productividad de pozos | F48: - | G48: - | H48: 23 | I48: 0 | J48: =IFERROR(I48/H48,0) -> 0 | K48: =I48+'ENERO 2026'!K48 -> 0 | L48: =IFERROR(K48/H48,0) -> 0
B49: 5 | C49: 5.10 | D49: Adelantar en análisis y evaluación de datos enfocada a la ejecución de estudios de daño de formación | F49: Base de Datos - Informe de la Evaluación | G49: Digital | H49: 19 | I49: 3 | J49: =IFERROR(I49/H49,0) -> 0.15789474 | K49: =I49+'ENERO 2026'!K49 -> 8 | L49: =IFERROR(K49/H49,0) -> 0.42105263
B50: 5 | C50: 5.11 | D50: Generar los análisis asociados a la ejecución de estudios de daño de formación empleando simulación numérica (análisis nodal y single well model, análisis de aguas, análisis de crudos, entre otros) | F50: Base de Datos - Informe de la Evaluación | G50: Digital | H50: 19 | I50: 3 | J50: =IFERROR(I50/H50,0) -> 0.15789474 | K50: =I50+'ENERO 2026'!K50 -> 8 | L50: =IFERROR(K50/H50,0) -> 0.42105263
B51: 1 | C51: 1.2 | D51: Generación de Bases de datos de Pozos (Registros, Topes e Información disponible) | E51: Estefany Lizeth Velandia Jaimes | F51: Bases de Datos | G51: Digital | H51: 59 | I51: 17 | J51: =IFERROR(I51/H51,0) -> 0.28813559 | K51: =I51+'ENERO 2026'!K51 -> 26 | L51: =IFERROR(K51/H51,0) -> 0.44067797
B52: 1 | C52: 1.5 | D52: Digitalización, digitación y/o captura de información geológica (Mapas, Raw Data, topes, etc.) | F52: Mapas en formato digital | G52: Digital | H52: 59 | I52: 5 | J52: =IFERROR(I52/H52,0) -> 0.084745763 | K52: =I52+'ENERO 2026'!K52 -> 15 | L52: =IFERROR(K52/H52,0) -> 0.25423729
B53: 1 | C53: 1.15 | D53: Carga de información para poblar el modelo geocelular (direccionales, coordenadas, surveys, topes, data de presión, estados mecánicos, evento de pozos, etc.) | F53: - | G53: - | H53: 59 | I53: 0 | J53: =IFERROR(I53/H53,0) -> 0 | K53: =I53+'ENERO 2026'!K53 -> 4 | L53: =IFERROR(K53/H53,0) -> 0.06779661
B54: 1 | C54: 1.17 | D54: Calculo probabilístico de Volúmenes In situ. | F54: Calculo Volumétrico - Bases de Datos | G54: Digital | H54: 59 | I54: 8 | J54: =IFERROR(I54/H54,0) -> 0.13559322 | K54: =I54+'ENERO 2026'!K54 -> 11 | L54: =IFERROR(K54/H54,0) -> 0.18644068
B55: 3 | C55: 3.3 | D55: Realizar el plan de desarrollo de campo y los pronósticos: realizando todos los pronósticos de escenarios de simulación para llevar a cabo la planificación del desarrollo de campo, esto incluye investigar y realizar análisis de sensibilidad e incertidumbre de los principales parámetros coincidentes de la historia y las incógnitas y su efecto en el pronóstico. La predicción se basaría en el plan de desarrollo de campo, las ubicaciones de perforación de relleno, el análisis de patrones, la optimización de la inyección de agua, la tasa de inyección óptima y el proceso de recuperación terciaria (química y térmica). Realizar evaluaciones económicas y evaluaciones de cada proceso y presentar la mejor solución óptima. | E55: Gustavo Andres Bautista Velandia | F55: - | G55: - | H55: 28 | I55: 0 | J55: =IFERROR(I55/H55,0) -> 0 | K55: =I55+'ENERO 2026'!K55 -> 0 | L55: =IFERROR(K55/H55,0) -> 0
B56: 3 | C56: 3.4 | D56: Construya un estudio de modelos conceptuales y modelos de laboratorio: para construir un modelo conceptual que investigue temas específicos. Por ejemplo: tiempos y perfiles de ruptura del trazador, meseta de relación WOR de depósitos de múltiples capas, para investigar la aplicación de nueva tecnología (basada en polímeros o basada en térmicas). Problemas de conformance, aplicabilidad del polímero en un campo específico, investigar el efecto del espaciamiento de pozos y los tipos de patrones (5 puntos, 5 puntos invertidos, 7 puntos, unidad de línea) en proyectos EOR químicos. Un estudio conceptual para desarrollar una metodología práctica para tecnologías nuevas y actuales basadas en datos de campo y de laboratorio (metodología para modelar polímeros de preferencia cruzada, nano surfactante). Desarrollar una metodología para integrar y modelar pozos de múltiples segmentos y datos ILT. | F56: Modelo Dinámico con los archivos de entrada Perfiles de producción e inyección Informe | G56: Digital | H56: 29 | I56: 5 | J56: =IFERROR(I56/H56,0) -> 0.17241379 | K56: =I56+'ENERO 2026'!K56 -> 5 | L56: =IFERROR(K56/H56,0) -> 0.17241379
B57: 3 | C57: 3.6 | D57: Generar Modelo analítico del yacimiento integrando la información disponible en un software específico. | F57: Modelo Analítico - Perfiles de Producción - Informe del modelo | G57: Digital | H57: 29 | I57: 5 | J57: =IFERROR(I57/H57,0) -> 0.17241379 | K57: =I57+'ENERO 2026'!K57 -> 5 | L57: =IFERROR(K57/H57,0) -> 0.17241379
B58: 3 | C58: 3.7 | D58: Inventario y acceso a raw data de puntos de presión (Pre-Test) tomados con probadores de formación (RDT (Halliburton), MDT (Schlumberger), MFT (Weatherford), etc.). La raw data debe contener por profundidad probada: valores de presión, temperatura, caudales inducidos (cc/seg) y volúmenes asociados de cámara pre-test (cc). | F58: Base de datos | G58: Digital | H58: 30 | I58: 8 | J58: =IFERROR(I58/H58,0) -> 0.26666667 | K58: =I58+'ENERO 2026'!K58 -> 16 | L58: =IFERROR(K58/H58,0) -> 0.53333333
B59: 3 | C59: 3.12 | D59: Generar Modelo de Presiones partiendo de las pruebas previamente validadas e interpretadas | F59: Modelo del sector | G59: Digital | H59: 30 | I59: 4 | J59: =IFERROR(I59/H59,0) -> 0.13333333 | K59: =I59+'ENERO 2026'!K59 -> 9 | L59: =IFERROR(K59/H59,0) -> 0.3
B60: 3 | C60: 3.16 | D60: Análisis de Declinaciones por pozo y/o subunidad | F60: - | G60: - | H60: 30 | I60: 0 | J60: =IFERROR(I60/H60,0) -> 0 | K60: =I60+'ENERO 2026'!K60 -> 2 | L60: =IFERROR(K60/H60,0) -> 0.066666667
B61: 3 | C61: 3.17 | D61: Analizar data histórica de producción, productividad y daño por pozo | F61: Base de Datos - Informe de la Evaluación | G61: Digital | H61: 30 | I61: 5 | J61: =IFERROR(I61/H61,0) -> 0.16666667 | K61: =I61+'ENERO 2026'!K61 -> 10 | L61: =IFERROR(K61/H61,0) -> 0.33333333
B62: 3 | C62: 3.18 | D62: Generar perfiles de Producción por pozos para pozos existente en escenarios Bajo, Medio y Alto | F62: Base de Datos - Informe de la Evaluación | G62: Digital | H62: 30 | I62: 3 | J62: =IFERROR(I62/H62,0) -> 0.1 | K62: =I62+'ENERO 2026'!K62 -> 9 | L62: =IFERROR(K62/H62,0) -> 0.3
B63: 3 | C63: 3.3 | D63: Realice el plan de desarrollo de campo y los pronósticos: realizando todos los pronósticos de escenarios de simulación para llevar a cabo la planificación del desarrollo de campo, esto incluye investigar y realizar análisis de sensibilidad e incertidumbre de los principales parámetros coincidentes de la historia y las incógnitas y su efecto en el pronóstico. La predicción se basaría en el plan de desarrollo de campo, las ubicaciones de perforación de relleno, el análisis de patrones, la optimización de la inyección de agua, la tasa de inyección óptima y el proceso de recuperación terciaria (química y térmica). Realizar evaluaciones económicas y evaluaciones de cada proceso y presentar la mejor solución óptima. | E63: Emmanuel Robles Albarracin | F63: Modelo Dinámico -Perfiles de Producción -Informe. | G63: Digital | H63: 113 | I63: 14 | J63: =IFERROR(I63/H63,0) -> 0.12389381 | K63: =I63+'ENERO 2026'!K63 -> 25 | L63: =IFERROR(K63/H63,0) -> 0.22123894
B64: 3 | C64: 3.5 | D64: Modelado sectorial cuando el modelo de simulación dinámica está disponible: modelado sectorial en el objetivo del estudio, modela adecuadamente y respeta las condiciones de frontera mediante el uso de límites de flujo o presión, realiza la planificación del desarrollo del campo, perforación de relleno, agotamiento primario, inyección de agua y térmica o química. Proceso de recuperación. Aumentar adecuadamente el resultado del modelo de sector al campo completo. Realizar la valuación económica del proceso. | F64: Modelo Dinámico con los archivos de entrada Perfiles de producción e inyección Informe | G64: Digital | H64: 48 | I64: 6 | J64: =IFERROR(I64/H64,0) -> 0.125 | K64: =I64+'ENERO 2026'!K64 -> 11 | L64: =IFERROR(K64/H64,0) -> 0.22916667
B65: 3 | C65: 3.10 | D65: Control de calidad del dato adquirido para valorar representatividad de la prueba en cuestión. De ser válidas, levantamiento de información de entrada para análisis e interpretación (registros de desviación, estado mecánico de cada pozo, caliper/bit size ("), espesor neto (pies TVD), porosidad media (phi), Sw, PVT, producciones asociadas, corte de agua, salinidades, mapa estructural, etc. | F65: Inventario - Informe de Representatividad (Preliminar) | G65: Digital | H65: 15 | I65: 2 | J65: =IFERROR(I65/H65,0) -> 0.13333333 | K65: =I65+'ENERO 2026'!K65 -> 4 | L65: =IFERROR(K65/H65,0) -> 0.26666667
B66: 3 | C66: 3.11 | D66: Análisis e interpretación de datos de pruebas de presión-producción (DSTs, PBU, Pruebas Extendidas Producción, Gradientes Estáticos- Dinámicos PT, etc.) o de presión inyección (Inyectividad, SRT, FOT) aplicadas ya sea en tiempo real, memorizadas o con sarta temporal DST. Integración Probador Formación - Registros Open Hole. | F66: Informe del análisis por pozo o prueba | G66: Digital | H66: 15 | I66: 2 | J66: =IFERROR(I66/H66,0) -> 0.13333333 | K66: =I66+'ENERO 2026'!K66 -> 4 | L66: =IFERROR(K66/H66,0) -> 0.26666667
B67: 3 | C67: 3.16 | D67: Análisis de Declinaciones por pozo y/o subunidad | F67: Base de Datos - Perfiles Generados - Informe del análisis | G67: Digital | H67: 15 | I67: 2 | J67: =IFERROR(I67/H67,0) -> 0.13333333 | K67: =I67+'ENERO 2026'!K67 -> 4 | L67: =IFERROR(K67/H67,0) -> 0.26666667
B68: 3 | C68: 3.17 | D68: Analizar data histórica de producción, productividad y daño por pozo | F68: Base de Datos - Informe de la Evaluación | G68: Digital | H68: 15 | I68: 2 | J68: =IFERROR(I68/H68,0) -> 0.13333333 | K68: =I68+'ENERO 2026'!K68 -> 4 | L68: =IFERROR(K68/H68,0) -> 0.26666667
B69: 3 | C69: 3.18 | D69: Generar perfiles de Producción por pozos para pozos existente en escenarios Bajo, Medio y Alto | F69: Base de Datos - Informe de la Evaluación | G69: Digital | H69: 15 | I69: 2 | J69: =IFERROR(I69/H69,0) -> 0.13333333 | K69: =I69+'ENERO 2026'!K69 -> 4 | L69: =IFERROR(K69/H69,0) -> 0.26666667
B70: 3 | C70: 3.3 | D70: Realice el plan de desarrollo de campo y los pronósticos: realizando todos los pronósticos de escenarios de simulación para llevar a cabo la planificación del desarrollo de campo, esto incluye investigar y realizar análisis de sensibilidad e incertidumbre de los principales parámetros coincidentes de la historia y las incógnitas y su efecto en el pronóstico. La predicción se basaría en el plan de desarrollo de campo, las ubicaciones de perforación de relleno, el análisis de patrones, la optimización de la inyección de agua, la tasa de inyección óptima y el proceso de recuperación terciaria (química y térmica). Realizar evaluaciones económicas y evaluaciones de cada proceso y presentar la mejor solución óptima. | E70: Hugo Quiroga Cruz | F70: Modelo Dinámico -Perfiles de Producción -Informe. | G70: Digital | H70: 180 | I70: 29 | J70: =IFERROR(I70/H70,0) -> 0.16111111 | K70: =+I70 -> 29 | L70: =IFERROR(K70/H70,0) -> 0.16111111
H71: TOTAL ACUMULADO
H72: =+SUM(H13:H70) -> 2038 | I72: =+SUM(I13:I70) -> 269 | J72: =IFERROR(I72/H72,0) -> 0.13199215 | K72: =+SUM(K13:K70) -> 477 | L72: =IFERROR(K72/H72,0) -> 0.23405299
B75: Observaciones | D75: 5.1 5.2 5.3 5.4 5.5 5.6 5.9 5.10 Junior (AM):
D76: 1.2 1.5 1.15 1.17 Junior (EV): Se dio inicio al análisis de propiedades petrofísicas en los intervalos previamente propuestos para cañoneo, correspondientes a 18 de los 24 pozos candidatos a Open Zone del Campo Nare Unificado. Participación en la elaboración de informes y mapas IRR vigencia 2025. Adicionalmente participación en el primer día técnico de la comunidad de práctica disciplina de geomodelamiento y en el taller de fluidos Teca Nare.
D77: 1.1 1.2 1.4 1.5 1.7 1.15 1.16 1.17 Senior (XR):
B78: ¿Se presentó algún aspecto o situación que afecte la ejecución y calidad de los entregables? (Marque con una X)
B80: PROFESIONAL
B81: SI | D81: Describa en este espacio su observación
B82: NO
B83: ¿Se presentó algún aspecto o situación que afecte la ejecución y calidad de los entregables? (Marque con una X)
B85: INTERVENTOR O LIDER
B86: SI | D86: Describa en este espacio su observación
B87: NO
B91: Revisa: | I91: Heliodoro Cañarete Mejía
A118: MES
A119: ENERO
A120: FEBRERO
A121: MARZO
A122: ABRIL
A123: MAYO
A124: JUNIO
A125: JULIO
A126: AGOSTO
A127: SEPTIEMBRE
A128: OCTUBRE
A129: NOVIEMBRE
A130: DICIEMBRE
